{
  "type": "Feature",
  "properties": {
    "gn:admin1_code":"39.0",
    "gn:asciiname":"Mechta Ouled Bou Abdallah",
    "gn:country_code":"DZ",
    "gn:dem":961,
    "gn:feature_class":"P",
    "gn:feature_code":"PPL",
    "gn:name":"Mechta Ouled Bou Abdallah",
    "gn:population":0,
    "gn:timezone":"Africa/Algiers",
    "iso:country":"DZ",
    "name:und_x_variant":[
        "Mechtat Ouled Bou Abdallah",
        "Mechta Ouled Bou Abdallah"
    ],
    "wof:name":"Mechta Ouled Bou Abdallah",
    "wof:placetype":"locality"
},
  "geometry": {"coordinates":[4.60402,36.03996],"type":"Point"}
}