{
  "type": "Feature",
  "properties": {
    "gn:admin1_code":"27.0",
    "gn:asciiname":"Mechta Ben Mehdi",
    "gn:country_code":"DZ",
    "gn:dem":467,
    "gn:feature_class":"P",
    "gn:feature_code":"PPL",
    "gn:name":"Mechta Ben Mehdi",
    "gn:population":0,
    "gn:timezone":"Africa/Algiers",
    "iso:country":"DZ",
    "name:und_x_variant":[
        "Mechtat Ben Mehdi",
        "Mechta Ben Mehdi"
    ],
    "wof:name":"Mechta Ben Mehdi",
    "wof:placetype":"locality"
},
  "geometry": {"coordinates":[4.78088,35.64084000000001],"type":"Point"}
}