{
  "type": "Feature",
  "properties": {
    "gn:admin1_code":"27.0",
    "gn:asciiname":"El Outa Sbeirath",
    "gn:country_code":"DZ",
    "gn:dem":765,
    "gn:feature_class":"P",
    "gn:feature_code":"PPLL",
    "gn:name":"El Outa Sbe\u00efrath",
    "gn:population":0,
    "gn:timezone":"Africa/Algiers",
    "iso:country":"DZ",
    "wof:name":"El Outa Sbeirath",
    "wof:placetype":"locality"
},
  "geometry": {"coordinates":[3.59196,35.1627],"type":"Point"}
}