{
  "type": "Feature",
  "properties": {
    "gn:admin1_code":"26.0",
    "gn:asciiname":"Nessissa",
    "gn:country_code":"DZ",
    "gn:dem":687,
    "gn:feature_class":"P",
    "gn:feature_code":"PPL",
    "gn:name":"Nessissa",
    "gn:population":0,
    "gn:timezone":"Africa/Algiers",
    "iso:country":"DZ",
    "wof:name":"Nessissa",
    "wof:placetype":"locality"
},
  "geometry": {"coordinates":[0.22361,35.12972],"type":"Point"}
}