{
  "type": "Feature",
  "properties": {
    "gn:admin1_code":"47.0",
    "gn:asciiname":"Aslellef",
    "gn:country_code":"DZ",
    "gn:dem":1332,
    "gn:feature_class":"P",
    "gn:feature_code":"PPL",
    "gn:name":"Aslellef",
    "gn:population":0,
    "gn:timezone":"Africa/Algiers",
    "iso:country":"DZ",
    "wof:name":"Aslellef",
    "wof:placetype":"locality"
},
  "geometry": {"coordinates":[6.94252,35.05193],"type":"Point"}
}