{
  "type": "Feature",
  "properties": {
    "gn:admin1_code":"23.0",
    "gn:asciiname":"Mechta Satha",
    "gn:country_code":"DZ",
    "gn:dem":429,
    "gn:feature_class":"P",
    "gn:feature_code":"PPL",
    "gn:name":"Mechta Satha",
    "gn:population":0,
    "gn:timezone":"Africa/Algiers",
    "iso:country":"DZ",
    "name:und_x_variant":[
        "Mechtat Satha",
        "Mechta Satha"
    ],
    "wof:name":"Mechta Satha",
    "wof:placetype":"locality"
},
  "geometry": {"coordinates":[7.22444,36.5125],"type":"Point"}
}