{
  "type": "Feature",
  "properties": {
    "gn:admin1_code":"34.0",
    "gn:asciiname":"Akbour",
    "gn:country_code":"DZ",
    "gn:dem":298,
    "gn:feature_class":"P",
    "gn:feature_code":"PPL",
    "gn:name":"Akbour",
    "gn:population":0,
    "gn:timezone":"Africa/Algiers",
    "iso:country":"DZ",
    "wof:name":"Akbour",
    "wof:placetype":"locality"
},
  "geometry": {"coordinates":[0.32637,28.72739],"type":"Point"}
}