{
  "type": "Feature",
  "properties": {
    "gn:admin1_code":"24.0",
    "gn:asciiname":"Henchia",
    "gn:country_code":"DZ",
    "gn:dem":390,
    "gn:feature_class":"P",
    "gn:feature_code":"PPL",
    "gn:name":"Henchia",
    "gn:population":0,
    "gn:timezone":"Africa/Algiers",
    "iso:country":"DZ",
    "name:und_x_variant":[
        "Hennchia",
        "Henchia"
    ],
    "wof:name":"Henchia",
    "wof:placetype":"locality"
},
  "geometry": {"coordinates":[5.56042,36.67154],"type":"Point"}
}