{
  "type": "Feature",
  "properties": {
    "gn:country":"DZ",
    "gn:fcode":"PPL",
    "gn:pop":33611,
    "iso:country":"DZ",
    "name:ara_x_preferred":[
        "\u0628\u0646\u064a \u062f\u0648\u0627\u0644\u0629"
    ],
    "name:dut_x_preferred":[
        "Beni Douala"
    ],
    "name:eng_x_preferred":[
        "Beni Douala"
    ],
    "name:fre_x_preferred":[
        "Beni Douala"
    ],
    "name:ita_x_preferred":[
        "Beni Douala"
    ],
    "name:kab_x_preferred":[
        "Ta \u0263iwant n At Dwala"
    ],
    "name:may_x_preferred":[
        "Beni Douala"
    ],
    "name:per_x_preferred":[
        "\u0628\u0646\u06cc \u062f\u0648\u0627\u0644\u0647"
    ],
    "name:por_x_preferred":[
        "B\u00e9ni Douala"
    ],
    "name:rum_x_preferred":[
        "Beni Douala"
    ],
    "name:swe_x_preferred":[
        "Beni Douala"
    ],
    "name:unk_x_variant":[
        "Beni Doula"
    ],
    "name:vie_x_preferred":[
        "Beni-Douala"
    ],
    "qs:name":"Beni Douala",
    "qs:photos_9r":0,
    "qs:photos_sr":0,
    "qs:pop_sr":"7",
    "wd:wordcount":57,
    "wof:name":"Beni Douala",
    "wof:placetype":"locality",
    "wof:population":33611
},
  "geometry": {"coordinates":[4.08282,36.61954],"type":"Point"}
}