{
  "type": "Feature",
  "properties": {
    "gn:admin1_code":"23.0",
    "gn:asciiname":"Bouati Mahmoud",
    "gn:country_code":"DZ",
    "gn:dem":173,
    "gn:feature_class":"P",
    "gn:feature_code":"PPL",
    "gn:name":"Bouati Mahmoud",
    "gn:population":0,
    "gn:timezone":"Africa/Algiers",
    "iso:country":"DZ",
    "name:ara_x_preferred":[
        "\u0628\u0648\u0639\u0627\u0637\u064a \u0645\u062d\u0645\u0648\u062f"
    ],
    "name:azb_x_preferred":[
        "\u0628\u0648\u0639\u0627\u0637\u06cc \u0645\u062d\u0645\u0648\u062f"
    ],
    "name:deu_x_preferred":[
        "Bouati Mahmoud"
    ],
    "name:fas_x_preferred":[
        "\u0628\u0648\u0639\u0627\u0637\u06cc \u0645\u062d\u0645\u0648\u062f"
    ],
    "name:fra_x_preferred":[
        "Bouati Mahmoud"
    ],
    "name:ita_x_preferred":[
        "Bouati Mahmoud"
    ],
    "name:msa_x_preferred":[
        "Bouati Mahmoud"
    ],
    "name:por_x_preferred":[
        "Bouati Mahmoud"
    ],
    "name:ron_x_preferred":[
        "Bouati Mahmoud"
    ],
    "name:spa_x_preferred":[
        "Bouati Mahmoud"
    ],
    "name:und_x_variant":[
        "Galli\u00e9ni",
        "Bou-Aci",
        "Hennchir Sa\u00efd",
        "Enchir Sa\u00efd"
    ],
    "name:vie_x_preferred":[
        "Bouati Mahmoud"
    ],
    "wof:name":"Bouati Mahmoud",
    "wof:placetype":"locality"
},
  "geometry": {"coordinates":[7.32694,36.59083],"type":"Point"}
}