{
  "type": "Feature",
  "properties": {
    "gn:admin1_code":"26.0",
    "gn:asciiname":"Douar Oulad Ahmed Ben Aissa",
    "gn:country_code":"DZ",
    "gn:dem":598,
    "gn:feature_class":"P",
    "gn:feature_code":"PPL",
    "gn:name":"Douar Oulad Ahmed Ben A\u00efssa",
    "gn:population":0,
    "gn:timezone":"Africa/Algiers",
    "iso:country":"DZ",
    "wof:name":"Douar Oulad Ahmed Ben Aissa",
    "wof:placetype":"locality"
},
  "geometry": {"coordinates":[0.73667,35.37167],"type":"Point"}
}