{
  "type": "Feature",
  "properties": {
    "gn:admin1_code":"40.0",
    "gn:asciiname":"Ighoumrassen",
    "gn:country_code":"DZ",
    "gn:dem":203,
    "gn:feature_class":"P",
    "gn:feature_code":"PPLS",
    "gn:name":"Ighoumrassen",
    "gn:population":0,
    "gn:timezone":"Africa/Algiers",
    "iso:country":"DZ",
    "wof:name":"Ighoumrassen",
    "wof:placetype":"locality"
},
  "geometry": {"coordinates":[3.75571,36.69294],"type":"Point"}
}