{
  "type": "Feature",
  "properties": {
    "gn:admin1_code":"34.0",
    "gn:asciiname":"Ouinna",
    "gn:country_code":"DZ",
    "gn:dem":242,
    "gn:feature_class":"P",
    "gn:feature_code":"PPL",
    "gn:name":"Ouinna",
    "gn:population":0,
    "gn:timezone":"Africa/Algiers",
    "iso:country":"DZ",
    "wof:name":"Ouinna",
    "wof:placetype":"locality"
},
  "geometry": {"coordinates":[-0.36024,27.89344],"type":"Point"}
}