{
  "type": "Feature",
  "properties": {
    "gn:admin1_code":"12.0",
    "gn:asciiname":"'Ain Trick",
    "gn:country_code":"DZ",
    "gn:dem":1017,
    "gn:feature_class":"P",
    "gn:feature_code":"PPL",
    "gn:name":"\u2019A\u00efn Trick",
    "gn:population":0,
    "gn:timezone":"Africa/Algiers",
    "iso:country":"DZ",
    "name:und_x_variant":[
        "A\u00efne Trick",
        "A\u00efn Trik",
        "\u2019A\u00efn Trick"
    ],
    "wof:name":"'Ain Trick",
    "wof:placetype":"locality"
},
  "geometry": {"coordinates":[5.44306,36.14781],"type":"Point"}
}