{
  "type": "Feature",
  "properties": {
    "gn:admin1_code":"13.0",
    "gn:asciiname":"Bordj Bou Harket",
    "gn:country_code":"DZ",
    "gn:dem":990,
    "gn:feature_class":"P",
    "gn:feature_code":"PPL",
    "gn:name":"Bordj Bou Harket",
    "gn:population":0,
    "gn:timezone":"Africa/Algiers",
    "iso:country":"DZ",
    "name:und_x_variant":[
        "Bordj Bou Harkett",
        "Bordj Bou Harket"
    ],
    "wof:name":"Bordj Bou Harket",
    "wof:placetype":"locality"
},
  "geometry": {"coordinates":[0.96546,34.84578],"type":"Point"}
}