{
  "type": "Feature",
  "properties": {
    "gn:admin1_code":"31.0",
    "gn:asciiname":"Ras el Ma",
    "gn:country_code":"DZ",
    "gn:dem":176,
    "gn:feature_class":"P",
    "gn:feature_code":"PPL",
    "gn:name":"R\u00e2s el Ma",
    "gn:population":0,
    "gn:timezone":"Africa/Algiers",
    "iso:country":"DZ",
    "name:und_x_variant":[
        "Rass el Ma",
        "R\u00e2s el Ma"
    ],
    "wof:name":"Ras el Ma",
    "wof:placetype":"locality"
},
  "geometry": {"coordinates":[7.01104,36.69689],"type":"Point"}
}