{
  "type": "Feature",
  "properties": {
    "gn:admin1_code":"7.0",
    "gn:asciiname":"Douar Ouled Attia",
    "gn:country_code":"DZ",
    "gn:dem":40,
    "gn:feature_class":"P",
    "gn:feature_code":"PPL",
    "gn:name":"Douar Ouled Attia",
    "gn:population":0,
    "gn:timezone":"Africa/Algiers",
    "iso:country":"DZ",
    "name:und_x_variant":[
        "Mechta Oulad Attia"
    ],
    "wof:name":"Douar Ouled Attia",
    "wof:placetype":"locality"
},
  "geometry": {"coordinates":[0.64824,35.97353],"type":"Point"}
}