{
  "type": "Feature",
  "properties": {
    "gn:admin1_code":"51.0",
    "gn:asciiname":"Douar Rahlia",
    "gn:country_code":"DZ",
    "gn:dem":460,
    "gn:feature_class":"P",
    "gn:feature_code":"PPL",
    "gn:name":"Douar Rahlia",
    "gn:population":0,
    "gn:timezone":"Africa/Algiers",
    "iso:country":"DZ",
    "wof:name":"Douar Rahlia",
    "wof:placetype":"locality"
},
  "geometry": {"coordinates":[0.69444,35.53417],"type":"Point"}
}