{
  "type": "Feature",
  "properties": {
    "gn:admin1_code":"53.0",
    "gn:asciiname":"Teghenanet",
    "gn:country_code":"DZ",
    "gn:dem":1844,
    "gn:feature_class":"P",
    "gn:feature_code":"PPL",
    "gn:name":"Teghen\u00e2net",
    "gn:population":0,
    "gn:timezone":"Africa/Algiers",
    "iso:country":"DZ",
    "name:und_x_variant":[
        "Tarhananet",
        "Terhen\u00e2net",
        "Teghen\u00e2net"
    ],
    "wof:name":"Teghenanet",
    "wof:placetype":"locality"
},
  "geometry": {"coordinates":[5.42311,23.16433],"type":"Point"}
}