{
  "type": "Feature",
  "properties": {
    "gn:admin1_code":"31.0",
    "gn:asciiname":"Mrabai",
    "gn:country_code":"DZ",
    "gn:dem":577,
    "gn:feature_class":"P",
    "gn:feature_code":"PPL",
    "gn:name":"Mraba\u00ef",
    "gn:population":0,
    "gn:timezone":"Africa/Algiers",
    "iso:country":"DZ",
    "wof:name":"Mrabai",
    "wof:placetype":"locality"
},
  "geometry": {"coordinates":[6.37944,37.05194],"type":"Point"}
}