{
  "type": "Feature",
  "properties": {
    "gn:admin1_code":"40.0",
    "gn:asciiname":"Tazerart",
    "gn:country_code":"DZ",
    "gn:dem":391,
    "gn:feature_class":"P",
    "gn:feature_code":"PPL",
    "gn:name":"Tazerart",
    "gn:population":0,
    "gn:timezone":"Africa/Algiers",
    "iso:country":"DZ",
    "wof:name":"Tazerart",
    "wof:placetype":"locality"
},
  "geometry": {"coordinates":[4.05127,36.80926],"type":"Point"}
}