{
  "type": "Feature",
  "properties": {
    "gn:admin1_code":"51.0",
    "gn:asciiname":"Douar ez Zhairia",
    "gn:country_code":"DZ",
    "gn:dem":401,
    "gn:feature_class":"P",
    "gn:feature_code":"PPL",
    "gn:name":"Douar ez Zha\u00efria",
    "gn:population":0,
    "gn:timezone":"Africa/Algiers",
    "iso:country":"DZ",
    "wof:name":"Douar ez Zhairia",
    "wof:placetype":"locality"
},
  "geometry": {"coordinates":[0.71271,35.64033],"type":"Point"}
}