{
  "type": "Feature",
  "properties": {
    "gn:admin1_code":"4.0",
    "gn:asciiname":"Mechta Zehana",
    "gn:country_code":"DZ",
    "gn:dem":792,
    "gn:feature_class":"P",
    "gn:feature_code":"PPL",
    "gn:name":"Mechta Zehana",
    "gn:population":0,
    "gn:timezone":"Africa/Algiers",
    "iso:country":"DZ",
    "wof:name":"Mechta Zehana",
    "wof:placetype":"locality"
},
  "geometry": {"coordinates":[7.02296,36.23463],"type":"Point"}
}