{
  "type": "Feature",
  "properties": {
    "gn:admin1_code":"34.0",
    "gn:asciiname":"Oulad Antar",
    "gn:country_code":"DZ",
    "gn:dem":226,
    "gn:feature_class":"P",
    "gn:feature_code":"PPL",
    "gn:name":"Oulad Antar",
    "gn:population":0,
    "gn:timezone":"Africa/Algiers",
    "iso:country":"DZ",
    "wof:name":"Oulad Antar",
    "wof:placetype":"locality"
},
  "geometry": {"coordinates":[-0.26745,27.44711],"type":"Point"}
}