{
  "type": "Feature",
  "properties": {
    "gn:admin1_code":"40.0",
    "gn:asciiname":"Ibouharene",
    "gn:country_code":"DZ",
    "gn:dem":429,
    "gn:feature_class":"P",
    "gn:feature_code":"PPL",
    "gn:name":"Ibouharene",
    "gn:population":0,
    "gn:timezone":"Africa/Algiers",
    "iso:country":"DZ",
    "wof:name":"Ibouharene",
    "wof:placetype":"locality"
},
  "geometry": {"coordinates":[3.87371,36.66754],"type":"Point"}
}