{
  "type": "Feature",
  "properties": {
    "gn:admin1_code":"51.0",
    "gn:asciiname":"El Khdaidia",
    "gn:country_code":"DZ",
    "gn:dem":235,
    "gn:feature_class":"P",
    "gn:feature_code":"PPL",
    "gn:name":"El Khda\u00efdia",
    "gn:population":0,
    "gn:timezone":"Africa/Algiers",
    "iso:country":"DZ",
    "name:und_x_variant":[
        "Mechta Kreda\u00efdia",
        "El Khda\u00efdia",
        "Mechta Kheda\u00efdia"
    ],
    "wof:name":"El Khdaidia",
    "wof:placetype":"locality"
},
  "geometry": {"coordinates":[0.79597,35.77978],"type":"Point"}
}