{
  "type": "Feature",
  "properties": {
    "gn:admin1_code":"12.0",
    "gn:asciiname":"Mechta Bel Ouachoun",
    "gn:country_code":"DZ",
    "gn:dem":844,
    "gn:feature_class":"P",
    "gn:feature_code":"PPL",
    "gn:name":"Mechta Bel Ouachoun",
    "gn:population":0,
    "gn:timezone":"Africa/Algiers",
    "iso:country":"DZ",
    "name:und_x_variant":[
        "Mechtat Bel Ouachoune",
        "Mechta Bel Ouachoun"
    ],
    "wof:name":"Mechta Bel Ouachoun",
    "wof:placetype":"locality"
},
  "geometry": {"coordinates":[5.77653,36.34774],"type":"Point"}
}