{
  "type": "Feature",
  "properties": {
    "gn:admin1_code":"19.0",
    "gn:asciiname":"Oum el Habel",
    "gn:country_code":"DZ",
    "gn:dem":868,
    "gn:feature_class":"P",
    "gn:feature_code":"PPL",
    "gn:name":"Oum el Habel",
    "gn:population":0,
    "gn:timezone":"Africa/Algiers",
    "iso:country":"DZ",
    "wof:name":"Oum el Habel",
    "wof:placetype":"locality"
},
  "geometry": {"coordinates":[6.3843,34.95021],"type":"Point"}
}