{
  "type": "Feature",
  "properties": {
    "gn:admin1_code":"6.0",
    "gn:asciiname":"Boghar",
    "gn:country_code":"DZ",
    "gn:dem":906,
    "gn:feature_class":"P",
    "gn:feature_code":"PPL",
    "gn:name":"Boghar",
    "gn:population":0,
    "gn:timezone":"Africa/Algiers",
    "iso:country":"DZ",
    "wof:name":"Boghar",
    "wof:placetype":"locality"
},
  "geometry": {"coordinates":[2.71667,35.91139000000001],"type":"Point"}
}