{
  "type": "Feature",
  "properties": {
    "gn:admin1_code":"6.0",
    "gn:asciiname":"Boghar",
    "gn:country_code":"DZ",
    "gn:dem":906,
    "gn:feature_class":"P",
    "gn:feature_code":"PPL",
    "gn:name":"Boghar",
    "gn:population":0,
    "gn:timezone":"Africa/Algiers",
    "iso:country":"DZ",
    "name:ara_x_preferred":[
        "\u0628\u0648\u063a\u0627\u0631"
    ],
    "name:azb_x_preferred":[
        "\u0628\u0648\u063a\u0627\u0631"
    ],
    "name:fas_x_preferred":[
        "\u0628\u0648\u063a\u0627\u0631"
    ],
    "name:fra_x_preferred":[
        "Boghar"
    ],
    "name:ita_x_preferred":[
        "Boghar"
    ],
    "name:msa_x_preferred":[
        "Boghar"
    ],
    "name:por_x_preferred":[
        "Boghar"
    ],
    "name:ron_x_preferred":[
        "Boghar"
    ],
    "name:spa_x_preferred":[
        "Boghar"
    ],
    "name:vie_x_preferred":[
        "Boghar"
    ],
    "name:zho_x_preferred":[
        "\u5e03\u52a0\u723e"
    ],
    "wof:name":"Boghar",
    "wof:placetype":"locality"
},
  "geometry": {"coordinates":[2.71667,35.91139000000001],"type":"Point"}
}