{
  "type": "Feature",
  "properties": {
    "gn:admin1_code":"39.0",
    "gn:asciiname":"Mechtat el Aouinat",
    "gn:country_code":"DZ",
    "gn:dem":919,
    "gn:feature_class":"P",
    "gn:feature_code":"PPL",
    "gn:name":"Mechtat el Aouinat",
    "gn:population":0,
    "gn:timezone":"Africa/Algiers",
    "iso:country":"DZ",
    "wof:name":"Mechtat el Aouinat",
    "wof:placetype":"locality"
},
  "geometry": {"coordinates":[5.1106,36.16042],"type":"Point"}
}