{
  "type": "Feature",
  "properties": {
    "gn:admin1_code":"41.0",
    "gn:asciiname":"Bou Yaghad",
    "gn:country_code":"DZ",
    "gn:dem":162,
    "gn:feature_class":"P",
    "gn:feature_code":"PPL",
    "gn:name":"Bou Yaghad",
    "gn:population":0,
    "gn:timezone":"Africa/Algiers",
    "iso:country":"DZ",
    "wof:name":"Bou Yaghad",
    "wof:placetype":"locality"
},
  "geometry": {"coordinates":[1.6563,36.5117],"type":"Point"}
}