{
  "type": "Feature",
  "properties": {
    "gn:admin1_code":"41.0",
    "gn:asciiname":"Ameraoua",
    "gn:country_code":"DZ",
    "gn:dem":412,
    "gn:feature_class":"P",
    "gn:feature_code":"PPL",
    "gn:name":"Ameraoua",
    "gn:population":0,
    "gn:timezone":"Africa/Algiers",
    "iso:country":"DZ",
    "wof:name":"Ameraoua",
    "wof:placetype":"locality"
},
  "geometry": {"coordinates":[1.38099,36.4427],"type":"Point"}
}