{
  "type": "Feature",
  "properties": {
    "gn:admin1_code":"23.0",
    "gn:asciiname":"Mechroha",
    "gn:country_code":"DZ",
    "gn:dem":749,
    "gn:feature_class":"P",
    "gn:feature_code":"PPL",
    "gn:name":"Mechroha",
    "gn:population":0,
    "gn:timezone":"Africa/Algiers",
    "iso:country":"DZ",
    "name:und_x_variant":[
        "Merahna",
        "Laverdure",
        "Mechroha"
    ],
    "wof:name":"Mechroha",
    "wof:placetype":"locality"
},
  "geometry": {"coordinates":[7.83754,36.35718],"type":"Point"}
}