{
  "type": "Feature",
  "properties": {
    "gn:admin1_code":"23.0",
    "gn:asciiname":"Mechtat et Toubaga",
    "gn:country_code":"DZ",
    "gn:dem":793,
    "gn:feature_class":"P",
    "gn:feature_code":"PPL",
    "gn:name":"Mechtat et Toubaga",
    "gn:population":0,
    "gn:timezone":"Africa/Algiers",
    "iso:country":"DZ",
    "wof:name":"Mechtat et Toubaga",
    "wof:placetype":"locality"
},
  "geometry": {"coordinates":[7.36741,36.25718],"type":"Point"}
}