{
  "type": "Feature",
  "properties": {
    "gn:admin1_code":"35.0",
    "gn:asciiname":"Abdallah Ben Mohammed",
    "gn:country_code":"DZ",
    "gn:dem":378,
    "gn:feature_class":"P",
    "gn:feature_code":"PPL",
    "gn:name":"Abdallah Ben Mohammed",
    "gn:population":0,
    "gn:timezone":"Africa/Algiers",
    "iso:country":"DZ",
    "wof:name":"Abdallah Ben Mohammed",
    "wof:placetype":"locality"
},
  "geometry": {"coordinates":[2.19913,36.14257],"type":"Point"}
}