{
  "type": "Feature",
  "properties": {
    "gn:admin1_code":"33.0",
    "gn:asciiname":"Mechtat Torrich",
    "gn:country_code":"DZ",
    "gn:dem":772,
    "gn:feature_class":"P",
    "gn:feature_code":"PPL",
    "gn:name":"Mechtat Torrich",
    "gn:population":0,
    "gn:timezone":"Africa/Algiers",
    "iso:country":"DZ",
    "name:und_x_variant":[
        "Mechta Torrich",
        "Mechtat Torricha",
        "Mechtat Torrich"
    ],
    "wof:name":"Mechtat Torrich",
    "wof:placetype":"locality"
},
  "geometry": {"coordinates":[8.04733,35.62623],"type":"Point"}
}