{
  "type": "Feature",
  "properties": {
    "gn:admin1_code":"27.0",
    "gn:asciiname":"Souala",
    "gn:country_code":"DZ",
    "gn:dem":473,
    "gn:feature_class":"P",
    "gn:feature_code":"PPL",
    "gn:name":"Souala",
    "gn:population":0,
    "gn:timezone":"Africa/Algiers",
    "iso:country":"DZ",
    "wof:name":"Souala",
    "wof:placetype":"locality"
},
  "geometry": {"coordinates":[5.00338,35.57018],"type":"Point"}
}