{
  "type": "Feature",
  "properties": {
    "gn:admin1_code":"33.0",
    "gn:asciiname":"Ferkane",
    "gn:country_code":"DZ",
    "gn:dem":308,
    "gn:feature_class":"P",
    "gn:feature_code":"PPL",
    "gn:name":"Ferkane",
    "gn:population":0,
    "gn:timezone":"Africa/Algiers",
    "iso:country":"DZ",
    "name:ara_x_preferred":[
        "\u0641\u0631\u0643\u0627\u0646"
    ],
    "name:fra_x_preferred":[
        "Ferkane"
    ],
    "name:ita_x_preferred":[
        "Ferkane"
    ],
    "name:msa_x_preferred":[
        "Ferkane"
    ],
    "name:por_x_preferred":[
        "Ferkane"
    ],
    "name:ron_x_preferred":[
        "Ferkane"
    ],
    "name:spa_x_preferred":[
        "Ferkane"
    ],
    "name:vie_x_preferred":[
        "Ferkane"
    ],
    "name:zho_x_preferred":[
        "\u8cbb\u723e\u574e"
    ],
    "wof:name":"Ferkane",
    "wof:placetype":"locality"
},
  "geometry": {"coordinates":[7.40375,34.56233],"type":"Point"}
}