{
  "type": "Feature",
  "properties": {
    "gn:admin1_code":"13.0",
    "gn:asciiname":"Moussa el Ghaoui",
    "gn:country_code":"DZ",
    "gn:dem":826,
    "gn:feature_class":"P",
    "gn:feature_code":"PPL",
    "gn:name":"Moussa el Ghaoui",
    "gn:population":0,
    "gn:timezone":"Africa/Algiers",
    "iso:country":"DZ",
    "wof:name":"Moussa el Ghaoui",
    "wof:placetype":"locality"
},
  "geometry": {"coordinates":[1.00188,35.07680999999999],"type":"Point"}
}