{
  "type": "Feature",
  "properties": {
    "gn:admin1_code":"38.0",
    "gn:asciiname":"Bechir",
    "gn:country_code":"DZ",
    "gn:dem":439,
    "gn:feature_class":"P",
    "gn:feature_code":"PPL",
    "gn:name":"Bechir",
    "gn:population":0,
    "gn:timezone":"Africa/Algiers",
    "iso:country":"DZ",
    "name:por_x_preferred":[
        "B\u00e9chir"
    ],
    "wof:name":"Bechir",
    "wof:placetype":"locality"
},
  "geometry": {"coordinates":[-1.97452,29.94347],"type":"Point"}
}