{
  "type": "Feature",
  "properties": {
    "gn:admin1_code":"19.0",
    "gn:asciiname":"Seriana",
    "gn:country_code":"DZ",
    "gn:dem":106,
    "gn:feature_class":"P",
    "gn:feature_code":"PPL",
    "gn:name":"Seriana",
    "gn:population":0,
    "gn:timezone":"Africa/Algiers",
    "iso:country":"DZ",
    "wof:name":"Seriana",
    "wof:placetype":"locality"
},
  "geometry": {"coordinates":[5.91272,34.81871],"type":"Point"}
}