{
  "type": "Feature",
  "properties": {
    "gn:admin1_code":"14.0",
    "gn:asciiname":"Iferhounene",
    "gn:country_code":"DZ",
    "gn:dem":782,
    "gn:feature_class":"P",
    "gn:feature_code":"PPL",
    "gn:name":"Iferhounene",
    "gn:population":0,
    "gn:timezone":"Africa/Algiers",
    "iso:country":"DZ",
    "name:ara_x_preferred":[
        "\u0625\u064a\u0641\u0631\u062d\u0648\u0646\u0646"
    ],
    "name:azb_x_preferred":[
        "\u0627\u06cc\u0641\u0631\u062d\u0648\u0646\u0646"
    ],
    "name:fas_x_preferred":[
        "\u0627\u06cc\u0641\u0631\u062d\u0648\u0646\u0646"
    ],
    "name:fra_x_preferred":[
        "Iferhoun\u00e8ne"
    ],
    "name:ita_x_preferred":[
        "Iferhoun\u00e8ne"
    ],
    "name:kab_x_preferred":[
        "Ifer\u1e25unen"
    ],
    "name:msa_x_preferred":[
        "Iferhounene"
    ],
    "name:por_x_preferred":[
        "Iferhoun\u00e8ne"
    ],
    "name:ron_x_preferred":[
        "Iferhoun\u00e8ne"
    ],
    "name:spa_x_preferred":[
        "Iferhoun\u00e8ne"
    ],
    "name:und_x_variant":[
        "Iferhouene",
        "Iferouene"
    ],
    "name:vie_x_preferred":[
        "Iferhoun\u00e8ne"
    ],
    "name:zho_x_preferred":[
        "\u4f0a\u8cbb\u723e\u80e1\u5357"
    ],
    "wof:name":"Iferhounene",
    "wof:placetype":"locality"
},
  "geometry": {"coordinates":[4.38333,36.51667],"type":"Point"}
}