{
  "type": "Feature",
  "properties": {
    "gn:admin1_code":"14.0",
    "gn:asciiname":"Iferhounene",
    "gn:country_code":"DZ",
    "gn:dem":782,
    "gn:feature_class":"P",
    "gn:feature_code":"PPL",
    "gn:name":"Iferhounene",
    "gn:population":0,
    "gn:timezone":"Africa/Algiers",
    "iso:country":"DZ",
    "name:und_x_variant":[
        "Iferhouene",
        "Iferouene",
        "Iferhounene"
    ],
    "wof:name":"Iferhounene",
    "wof:placetype":"locality"
},
  "geometry": {"coordinates":[4.38333,36.51667],"type":"Point"}
}