{
  "type": "Feature",
  "properties": {
    "gn:admin1_code":"48.0",
    "gn:asciiname":"Tiberguent",
    "gn:country_code":"DZ",
    "gn:dem":430,
    "gn:feature_class":"P",
    "gn:feature_code":"PPL",
    "gn:name":"Tiberguent",
    "gn:population":0,
    "gn:timezone":"Africa/Algiers",
    "iso:country":"DZ",
    "wof:name":"Tiberguent",
    "wof:placetype":"locality"
},
  "geometry": {"coordinates":[6.04,36.40917],"type":"Point"}
}