{
  "type": "Feature",
  "properties": {
    "gn:admin1_code":"48.0",
    "gn:asciiname":"Tiberguent",
    "gn:country_code":"DZ",
    "gn:dem":430,
    "gn:feature_class":"P",
    "gn:feature_code":"PPL",
    "gn:name":"Tiberguent",
    "gn:population":0,
    "gn:timezone":"Africa/Algiers",
    "iso:country":"DZ",
    "name:ara_x_preferred":[
        "\u062a\u0628\u0631\u0642\u0646\u062a"
    ],
    "name:azb_x_preferred":[
        "\u062a\u0628\u0631\u0642\u0646\u062a"
    ],
    "name:fas_x_preferred":[
        "\u062a\u0628\u0631\u0642\u0646\u062a"
    ],
    "name:fra_x_preferred":[
        "Tiberguent"
    ],
    "name:ita_x_preferred":[
        "Tiberguent"
    ],
    "name:kab_x_preferred":[
        "Tibergent"
    ],
    "name:msa_x_preferred":[
        "Tiberguent"
    ],
    "name:por_x_preferred":[
        "Tiberguent"
    ],
    "name:ron_x_preferred":[
        "Tiberguent"
    ],
    "name:spa_x_preferred":[
        "Tiberguent"
    ],
    "name:vie_x_preferred":[
        "Tiberguent"
    ],
    "wof:name":"Tiberguent",
    "wof:placetype":"locality"
},
  "geometry": {"coordinates":[6.04,36.40917],"type":"Point"}
}