{
  "type": "Feature",
  "properties": {
    "gn:admin1_code":"18.0",
    "gn:asciiname":"Affirou",
    "gn:country_code":"DZ",
    "gn:dem":1049,
    "gn:feature_class":"P",
    "gn:feature_code":"PPL",
    "gn:name":"Affirou",
    "gn:population":0,
    "gn:timezone":"Africa/Algiers",
    "iso:country":"DZ",
    "wof:name":"Affirou",
    "wof:placetype":"locality"
},
  "geometry": {"coordinates":[4.62536,36.24923],"type":"Point"}
}