{
  "type": "Feature",
  "properties": {
    "gn:admin1_code":"26.0",
    "gn:asciiname":"El Allalcha",
    "gn:country_code":"DZ",
    "gn:dem":683,
    "gn:feature_class":"P",
    "gn:feature_code":"PPL",
    "gn:name":"El Allalcha",
    "gn:population":0,
    "gn:timezone":"Africa/Algiers",
    "iso:country":"DZ",
    "wof:name":"El Allalcha",
    "wof:placetype":"locality"
},
  "geometry": {"coordinates":[0.51811,35.14502],"type":"Point"}
}