{
  "type": "Feature",
  "properties": {
    "gn:admin1_code":"26.0",
    "gn:asciiname":"Douar Brourate",
    "gn:country_code":"DZ",
    "gn:dem":304,
    "gn:feature_class":"P",
    "gn:feature_code":"PPL",
    "gn:name":"Douar Brourate",
    "gn:population":0,
    "gn:timezone":"Africa/Algiers",
    "iso:country":"DZ",
    "wof:name":"Douar Brourate",
    "wof:placetype":"locality"
},
  "geometry": {"coordinates":[0.04437,35.43982000000001],"type":"Point"}
}