{
  "type": "Feature",
  "properties": {
    "gn:admin1_code":"27.0",
    "gn:asciiname":"Mechta Ouled Mbarek",
    "gn:country_code":"DZ",
    "gn:dem":561,
    "gn:feature_class":"P",
    "gn:feature_code":"PPL",
    "gn:name":"Mechta Ouled Mbarek",
    "gn:population":0,
    "gn:timezone":"Africa/Algiers",
    "iso:country":"DZ",
    "name:und_x_variant":[
        "Mechta Ouled Embarek",
        "Mechta Ouled Mbarek"
    ],
    "wof:name":"Mechta Ouled Mbarek",
    "wof:placetype":"locality"
},
  "geometry": {"coordinates":[5.00368,35.6241],"type":"Point"}
}