{
  "type": "Feature",
  "properties": {
    "gn:admin1_code":"3.0",
    "gn:asciiname":"Dermoun",
    "gn:country_code":"DZ",
    "gn:dem":246,
    "gn:feature_class":"P",
    "gn:feature_code":"PPL",
    "gn:name":"Dermoun",
    "gn:population":0,
    "gn:timezone":"Africa/Algiers",
    "iso:country":"DZ",
    "name:und_x_variant":[
        "Dermoune",
        "Dermoun"
    ],
    "wof:name":"Dermoun",
    "wof:placetype":"locality"
},
  "geometry": {"coordinates":[6.5219,34.8609],"type":"Point"}
}