{
  "type": "Feature",
  "properties": {
    "gn:admin1_code":"51.0",
    "gn:asciiname":"Douar Laarahba",
    "gn:country_code":"DZ",
    "gn:dem":545,
    "gn:feature_class":"P",
    "gn:feature_code":"PPL",
    "gn:name":"Douar La\u00e2rahba",
    "gn:population":0,
    "gn:timezone":"Africa/Algiers",
    "iso:country":"DZ",
    "name:und_x_variant":[
        "Douar La\u00e2rahba",
        "Douar Araba"
    ],
    "wof:name":"Douar Laarahba",
    "wof:placetype":"locality"
},
  "geometry": {"coordinates":[0.86807,35.60129000000001],"type":"Point"}
}