{
  "type": "Feature",
  "properties": {
    "gn:admin1_code":"36.0",
    "gn:asciiname":"Mezraet ech Chahid Maatallah",
    "gn:country_code":"DZ",
    "gn:dem":198,
    "gn:feature_class":"P",
    "gn:feature_code":"PPL",
    "gn:name":"Mezraet ech Chahid Maatallah",
    "gn:population":0,
    "gn:timezone":"Africa/Algiers",
    "iso:country":"DZ",
    "name:und_x_variant":[
        "Domaine du Keroulis",
        "Mezraet ech Chahid Maatallah"
    ],
    "wof:name":"Mezraet ech Chahid Maatallah",
    "wof:placetype":"locality"
},
  "geometry": {"coordinates":[-1.01228,35.29939],"type":"Point"}
}