{
  "type": "Feature",
  "properties": {
    "gn:admin1_code":"12.0",
    "gn:asciiname":"Mechtet Ouled Si Ahmed",
    "gn:country_code":"DZ",
    "gn:dem":931,
    "gn:feature_class":"P",
    "gn:feature_code":"PPL",
    "gn:name":"Mechtet Ouled Si Ahmed",
    "gn:population":0,
    "gn:timezone":"Africa/Algiers",
    "iso:country":"DZ",
    "name:und_x_variant":[
        "Oulad Si Ahmed",
        "Oulad Sidi Ahmed",
        "Mechtet Ouled Si Ahmed"
    ],
    "wof:name":"Mechtet Ouled Si Ahmed",
    "wof:placetype":"locality"
},
  "geometry": {"coordinates":[5.39306,35.96282],"type":"Point"}
}