{
  "type": "Feature",
  "properties": {
    "gn:admin1_code":"51.0",
    "gn:asciiname":"Khechab",
    "gn:country_code":"DZ",
    "gn:dem":126,
    "gn:feature_class":"P",
    "gn:feature_code":"PPL",
    "gn:name":"Khechab",
    "gn:population":0,
    "gn:timezone":"Africa/Algiers",
    "iso:country":"DZ",
    "wof:name":"Khechab",
    "wof:placetype":"locality"
},
  "geometry": {"coordinates":[0.54998,35.63323],"type":"Point"}
}