{
  "type": "Feature",
  "properties": {
    "gn:admin1_code":"18.0",
    "gn:asciiname":"Bel Ayel",
    "gn:country_code":"DZ",
    "gn:dem":905,
    "gn:feature_class":"P",
    "gn:feature_code":"PPL",
    "gn:name":"Bel Ayel",
    "gn:population":0,
    "gn:timezone":"Africa/Algiers",
    "iso:country":"DZ",
    "wof:name":"Bel Ayel",
    "wof:placetype":"locality"
},
  "geometry": {"coordinates":[4.55529,36.32537],"type":"Point"}
}