{
  "type": "Feature",
  "properties": {
    "gn:admin1_code":"13.0",
    "gn:asciiname":"Serget Lihoudi",
    "gn:country_code":"DZ",
    "gn:dem":1059,
    "gn:feature_class":"P",
    "gn:feature_code":"PPL",
    "gn:name":"Serget Lihoudi",
    "gn:population":0,
    "gn:timezone":"Africa/Algiers",
    "iso:country":"DZ",
    "wof:name":"Serget Lihoudi",
    "wof:placetype":"locality"
},
  "geometry": {"coordinates":[1.01765,35.19390999999999],"type":"Point"}
}