{
  "type": "Feature",
  "properties": {
    "gn:admin1_code":"27.0",
    "gn:asciiname":"Ouled Salah",
    "gn:country_code":"DZ",
    "gn:dem":618,
    "gn:feature_class":"P",
    "gn:feature_code":"PPL",
    "gn:name":"Ouled Salah",
    "gn:population":0,
    "gn:timezone":"Africa/Algiers",
    "iso:country":"DZ",
    "wof:name":"Ouled Salah",
    "wof:placetype":"locality"
},
  "geometry": {"coordinates":[4.79667,35.72472],"type":"Point"}
}