{
  "type": "Feature",
  "properties": {
    "gn:admin1_code":"3.0",
    "gn:asciiname":"Mechta Ain el Beida",
    "gn:country_code":"DZ",
    "gn:dem":817,
    "gn:feature_class":"P",
    "gn:feature_code":"PPL",
    "gn:name":"Mechta A\u00efn el Be\u00efda",
    "gn:population":0,
    "gn:timezone":"Africa/Algiers",
    "iso:country":"DZ",
    "wof:name":"Mechta Ain el Beida",
    "wof:placetype":"locality"
},
  "geometry": {"coordinates":[6.15096,35.8075],"type":"Point"}
}