{
  "type": "Feature",
  "properties": {
    "gn:admin1_code":"15.0",
    "gn:asciiname":"Ouzidane",
    "gn:country_code":"DZ",
    "gn:dem":514,
    "gn:feature_class":"P",
    "gn:feature_code":"PPL",
    "gn:name":"Ouzidane",
    "gn:population":0,
    "gn:timezone":"Africa/Algiers",
    "iso:country":"DZ",
    "wof:name":"Ouzidane",
    "wof:placetype":"locality"
},
  "geometry": {"coordinates":[-1.28262,34.94211],"type":"Point"}
}