{
  "type": "Feature",
  "properties": {
    "gn:admin1_code":"40.0",
    "gn:asciiname":"Takdempt",
    "gn:country_code":"DZ",
    "gn:dem":42,
    "gn:feature_class":"P",
    "gn:feature_code":"PPL",
    "gn:name":"Takdempt",
    "gn:population":0,
    "gn:timezone":"Africa/Algiers",
    "iso:country":"DZ",
    "wof:name":"Takdempt",
    "wof:placetype":"locality"
},
  "geometry": {"coordinates":[3.84441,36.90476],"type":"Point"}
}