{
  "type": "Feature",
  "properties": {
    "iso:country":"DZ",
    "name:ara_x_preferred":[
        "\u0648\u0644\u0627\u064a\u0629 \u0628\u0631\u062c \u0628\u0648\u0639\u0631\u064a\u0631\u064a\u062c"
    ],
    "name:eng_x_preferred":[
        "Bordj Bou Arreidj Province"
    ],
    "qs:gn_pop":0,
    "qs:name":"\u0648\u0644\u0627\u064a\u0629 \u0628\u0631\u062c \u0628\u0648\u0639\u0631\u064a\u0631\u064a\u062c",
    "qs:name_adm0":"\u0627\u0644\u062c\u0632\u0627\u0626\u0631",
    "qs:name_adm1":"Bordj Bou Arreridj",
    "qs:photos":45,
    "qs:photos_1k":9,
    "qs:photos_9k":1,
    "qs:photos_9r":2,
    "qs:photos_all":45,
    "qs:photos_sr":2,
    "qs:placetype":"Town",
    "qs:pop_sr":"0",
    "qs:woe_adm0":23424740,
    "wof:name":"Bordj Bou Arreidj Province",
    "wof:placetype":"locality"
},
  "geometry": {"coordinates":[4.817504,36.065543],"type":"Point"}
}