{
  "type": "Feature",
  "properties": {
    "gn:admin1_code":"6.0",
    "gn:asciiname":"El Mahdi",
    "gn:country_code":"DZ",
    "gn:dem":647,
    "gn:feature_class":"P",
    "gn:feature_code":"PPL",
    "gn:name":"El Mahdi",
    "gn:population":0,
    "gn:timezone":"Africa/Algiers",
    "iso:country":"DZ",
    "wof:name":"El Mahdi",
    "wof:placetype":"locality"
},
  "geometry": {"coordinates":[2.6273,36.19183],"type":"Point"}
}