{
  "type": "Feature",
  "properties": {
    "gn:admin1_code":"7.0",
    "gn:asciiname":"Oulad Sidi Ahmar",
    "gn:country_code":"DZ",
    "gn:dem":33,
    "gn:feature_class":"P",
    "gn:feature_code":"PPL",
    "gn:name":"Oulad Sidi Ahmar",
    "gn:population":0,
    "gn:timezone":"Africa/Algiers",
    "iso:country":"DZ",
    "wof:name":"Oulad Sidi Ahmar",
    "wof:placetype":"locality"
},
  "geometry": {"coordinates":[0.2005,36.03557],"type":"Point"}
}