{
  "type": "Feature",
  "properties": {
    "gn:admin1_code":"51.0",
    "gn:asciiname":"Cherarka",
    "gn:country_code":"DZ",
    "gn:dem":137,
    "gn:feature_class":"P",
    "gn:feature_code":"PPL",
    "gn:name":"Cherarka",
    "gn:population":0,
    "gn:timezone":"Africa/Algiers",
    "iso:country":"DZ",
    "name:und_x_variant":[
        "Douar Cherarka",
        "Cherarka"
    ],
    "wof:name":"Cherarka",
    "wof:placetype":"locality"
},
  "geometry": {"coordinates":[0.91116,35.84384],"type":"Point"}
}