{
  "type": "Feature",
  "properties": {
    "gn:admin1_code":"37.0",
    "gn:asciiname":"Bordjel El Hassane",
    "gn:country_code":"DZ",
    "gn:dem":174,
    "gn:feature_class":"P",
    "gn:feature_code":"PPL",
    "gn:name":"Bordjel El Hassane",
    "gn:population":0,
    "gn:timezone":"Africa/Algiers",
    "iso:country":"DZ",
    "wof:name":"Bordjel El Hassane",
    "wof:placetype":"locality"
},
  "geometry": {"coordinates":[7.69167,36.60278],"type":"Point"}
}