{
  "type": "Feature",
  "properties": {
    "gn:admin1_code":"35.0",
    "gn:asciiname":"Douar el Hadj Ben Slimane",
    "gn:country_code":"DZ",
    "gn:dem":273,
    "gn:feature_class":"P",
    "gn:feature_code":"PPL",
    "gn:name":"Douar el Hadj Ben Slimane",
    "gn:population":0,
    "gn:timezone":"Africa/Algiers",
    "iso:country":"DZ",
    "name:und_x_variant":[
        "Es Slimane"
    ],
    "wof:name":"Douar el Hadj Ben Slimane",
    "wof:placetype":"locality"
},
  "geometry": {"coordinates":[2.10462,36.20759],"type":"Point"}
}