{
  "type": "Feature",
  "properties": {
    "gn:admin1_code":"41.0",
    "gn:asciiname":"Menasria",
    "gn:country_code":"DZ",
    "gn:dem":256,
    "gn:feature_class":"P",
    "gn:feature_code":"PPL",
    "gn:name":"Menasria",
    "gn:population":0,
    "gn:timezone":"Africa/Algiers",
    "iso:country":"DZ",
    "name:und_x_variant":[
        "Menasrya",
        "Menasria"
    ],
    "wof:name":"Menasria",
    "wof:placetype":"locality"
},
  "geometry": {"coordinates":[1.44178,36.17547],"type":"Point"}
}