{
  "type": "Feature",
  "properties": {
    "gn:admin1_code":"9.0",
    "gn:asciiname":"Douar Bel Hadef",
    "gn:country_code":"DZ",
    "gn:dem":117,
    "gn:feature_class":"P",
    "gn:feature_code":"PPL",
    "gn:name":"Douar Bel Hadef",
    "gn:population":0,
    "gn:timezone":"Africa/Algiers",
    "iso:country":"DZ",
    "name:und_x_variant":[
        "Bel Hadef",
        "Douar Bel Hadef"
    ],
    "wof:name":"Douar Bel Hadef",
    "wof:placetype":"locality"
},
  "geometry": {"coordinates":[-0.53464,35.52650999999999],"type":"Point"}
}