{
  "type": "Feature",
  "properties": {
    "gn:admin1_code":"7.0",
    "gn:asciiname":"Beni Yahi",
    "gn:country_code":"DZ",
    "gn:dem":16,
    "gn:feature_class":"P",
    "gn:feature_code":"PPL",
    "gn:name":"Beni Yahi",
    "gn:population":0,
    "gn:timezone":"Africa/Algiers",
    "iso:country":"DZ",
    "name:und_x_variant":[
        "Benihi",
        "Douar Beni Yahi",
        "Beni Yahi",
        "Douar Benihi"
    ],
    "wof:name":"Beni Yahi",
    "wof:placetype":"locality"
},
  "geometry": {"coordinates":[0.03378,35.76741],"type":"Point"}
}