{
  "type": "Feature",
  "properties": {
    "gn:admin1_code":"0.0",
    "gn:asciiname":"Douar Bredeah",
    "gn:country_code":"DZ",
    "gn:dem":133,
    "gn:feature_class":"P",
    "gn:feature_code":"PPL",
    "gn:name":"Douar Bredeah",
    "gn:population":0,
    "gn:timezone":"Africa/Algiers",
    "iso:country":"DZ",
    "wof:name":"Douar Bredeah",
    "wof:placetype":"locality"
},
  "geometry": {"coordinates":[-0.85,35.58333],"type":"Point"}
}