{
  "type": "Feature",
  "properties": {
    "gn:admin1_code":"39.0",
    "gn:asciiname":"Mechta Rhoder",
    "gn:country_code":"DZ",
    "gn:dem":1310,
    "gn:feature_class":"P",
    "gn:feature_code":"PPL",
    "gn:name":"Mechta Rhoder",
    "gn:population":0,
    "gn:timezone":"Africa/Algiers",
    "iso:country":"DZ",
    "name:und_x_variant":[
        "Mechtat Rhoder",
        "Mechta Rhoder"
    ],
    "wof:name":"Mechta Rhoder",
    "wof:placetype":"locality"
},
  "geometry": {"coordinates":[4.93104,35.86245],"type":"Point"}
}