{
  "type": "Feature",
  "properties": {
    "gn:admin1_code":"41.0",
    "gn:asciiname":"Douar Zemala",
    "gn:country_code":"DZ",
    "gn:dem":345,
    "gn:feature_class":"P",
    "gn:feature_code":"PPL",
    "gn:name":"Douar Zemala",
    "gn:population":0,
    "gn:timezone":"Africa/Algiers",
    "iso:country":"DZ",
    "wof:name":"Douar Zemala",
    "wof:placetype":"locality"
},
  "geometry": {"coordinates":[1.10685,36.27845],"type":"Point"}
}