{
  "type": "Feature",
  "properties": {
    "gn:admin1_code":"51.0",
    "gn:asciiname":"Souk el Djemaa",
    "gn:country_code":"DZ",
    "gn:dem":56,
    "gn:feature_class":"P",
    "gn:feature_code":"PPL",
    "gn:name":"Souk el Djem\u00e2a",
    "gn:population":0,
    "gn:timezone":"Africa/Algiers",
    "iso:country":"DZ",
    "wof:name":"Souk el Djemaa",
    "wof:placetype":"locality"
},
  "geometry": {"coordinates":[0.87778,35.99861],"type":"Point"}
}