{
  "type": "Feature",
  "properties": {
    "gn:admin1_code":"20.0",
    "gn:asciiname":"Tachert",
    "gn:country_code":"DZ",
    "gn:dem":699,
    "gn:feature_class":"P",
    "gn:feature_code":"PPL",
    "gn:name":"Tachert",
    "gn:population":0,
    "gn:timezone":"Africa/Algiers",
    "iso:country":"DZ",
    "name:und_x_variant":[
        "Tacherte",
        "Tachert"
    ],
    "wof:name":"Tachert",
    "wof:placetype":"locality"
},
  "geometry": {"coordinates":[3.06133,36.44764],"type":"Point"}
}