{
  "type": "Feature",
  "properties": {
    "gn:admin1_code":"41.0",
    "gn:asciiname":"Ech Chelh",
    "gn:country_code":"DZ",
    "gn:dem":77,
    "gn:feature_class":"P",
    "gn:feature_code":"PPL",
    "gn:name":"Ech Chelh",
    "gn:population":0,
    "gn:timezone":"Africa/Algiers",
    "iso:country":"DZ",
    "wof:name":"Ech Chelh",
    "wof:placetype":"locality"
},
  "geometry": {"coordinates":[1.46261,36.53248],"type":"Point"}
}