{
  "type": "Feature",
  "properties": {
    "gn:admin1_code":"3.0",
    "gn:asciiname":"Tletz",
    "gn:country_code":"DZ",
    "gn:dem":1416,
    "gn:feature_class":"P",
    "gn:feature_code":"PPL",
    "gn:name":"Tletz",
    "gn:population":0,
    "gn:timezone":"Africa/Algiers",
    "iso:country":"DZ",
    "wof:name":"Tletz",
    "wof:placetype":"locality"
},
  "geometry": {"coordinates":[6.25056,35.28444000000001],"type":"Point"}
}