{
  "type": "Feature",
  "properties": {
    "gn:admin1_code":"6.0",
    "gn:asciiname":"Ouled Sidi Abdelaziz",
    "gn:country_code":"DZ",
    "gn:dem":576,
    "gn:feature_class":"P",
    "gn:feature_code":"PPL",
    "gn:name":"Ouled Sidi Abdelaziz",
    "gn:population":0,
    "gn:timezone":"Africa/Algiers",
    "iso:country":"DZ",
    "wof:name":"Ouled Sidi Abdelaziz",
    "wof:placetype":"locality"
},
  "geometry": {"coordinates":[3.3337,36.24953],"type":"Point"}
}