{
  "type": "Feature",
  "properties": {
    "gn:admin1_code":"7.0",
    "gn:asciiname":"Douar Ouled Bou Ali",
    "gn:country_code":"DZ",
    "gn:dem":35,
    "gn:feature_class":"P",
    "gn:feature_code":"PPL",
    "gn:name":"Douar Ouled Bou Ali",
    "gn:population":0,
    "gn:timezone":"Africa/Algiers",
    "iso:country":"DZ",
    "wof:name":"Douar Ouled Bou Ali",
    "wof:placetype":"locality"
},
  "geometry": {"coordinates":[0.41306,36.00806],"type":"Point"}
}