{
  "type": "Feature",
  "properties": {
    "gn:admin1_code":"36.0",
    "gn:asciiname":"Lahsaina",
    "gn:country_code":"DZ",
    "gn:dem":303,
    "gn:feature_class":"P",
    "gn:feature_code":"PPL",
    "gn:name":"Lahsa\u00efna",
    "gn:population":0,
    "gn:timezone":"Africa/Algiers",
    "iso:country":"DZ",
    "name:und_x_variant":[
        "Ouled Sidi Madani",
        "Lahsa\u00efna"
    ],
    "wof:name":"Lahsaina",
    "wof:placetype":"locality"
},
  "geometry": {"coordinates":[-1.54936,35.24688],"type":"Point"}
}