{
  "type": "Feature",
  "properties": {
    "gn:admin1_code":"30.0",
    "gn:asciiname":"Lamtar",
    "gn:country_code":"DZ",
    "gn:dem":578,
    "gn:feature_class":"P",
    "gn:feature_code":"PPL",
    "gn:name":"Lamt\u00e2r",
    "gn:population":0,
    "gn:timezone":"Africa/Algiers",
    "iso:country":"DZ",
    "name:ara_x_preferred":[
        "\u0644\u0645\u0637\u0627\u0631"
    ],
    "name:azb_x_preferred":[
        "\u0644\u0645\u0637\u0627\u0631"
    ],
    "name:fas_x_preferred":[
        "\u0644\u0645\u0637\u0627\u0631"
    ],
    "name:fra_x_preferred":[
        "Lamtar"
    ],
    "name:ita_x_preferred":[
        "Lamtar"
    ],
    "name:kab_x_preferred":[
        "Lem\u1e6dar"
    ],
    "name:msa_x_preferred":[
        "Lamtar"
    ],
    "name:pol_x_preferred":[
        "Lamtar"
    ],
    "name:por_x_preferred":[
        "Lamtar"
    ],
    "name:ron_x_preferred":[
        "Lamtar"
    ],
    "name:spa_x_preferred":[
        "Lamtar"
    ],
    "name:und_x_variant":[
        "Lamt\u00e2r"
    ],
    "name:urd_x_preferred":[
        "\u0644\u0627\u0645\u0679\u0627\u0631"
    ],
    "name:vie_x_preferred":[
        "Lamtar"
    ],
    "wof:name":"Lamtar",
    "wof:placetype":"locality"
},
  "geometry": {"coordinates":[-0.79851,35.07104],"type":"Point"}
}