{
  "type": "Feature",
  "properties": {
    "gn:admin1_code":"33.0",
    "gn:asciiname":"Mechtat er Rouis",
    "gn:country_code":"DZ",
    "gn:dem":1135,
    "gn:feature_class":"P",
    "gn:feature_code":"PPLL",
    "gn:name":"Mechtat er Rouis",
    "gn:population":0,
    "gn:timezone":"Africa/Algiers",
    "iso:country":"DZ",
    "name:und_x_variant":[
        "Mechtet er Rouis",
        "Mechtat er Rouiss",
        "Mechtat er Rouis"
    ],
    "wof:name":"Mechtat er Rouis",
    "wof:placetype":"locality"
},
  "geometry": {"coordinates":[7.9525,35.21083],"type":"Point"}
}