{
  "type": "Feature",
  "properties": {
    "gn:admin1_code":"31.0",
    "gn:asciiname":"Azakour",
    "gn:country_code":"DZ",
    "gn:dem":530,
    "gn:feature_class":"P",
    "gn:feature_code":"PPL",
    "gn:name":"Azakour",
    "gn:population":0,
    "gn:timezone":"Africa/Algiers",
    "iso:country":"DZ",
    "wof:name":"Azakour",
    "wof:placetype":"locality"
},
  "geometry": {"coordinates":[6.34417,37.00639],"type":"Point"}
}