{
  "type": "Feature",
  "properties": {
    "gn:admin1_code":"51.0",
    "gn:asciiname":"Douar el H'djaidjia",
    "gn:country_code":"DZ",
    "gn:dem":162,
    "gn:feature_class":"P",
    "gn:feature_code":"PPL",
    "gn:name":"Douar el H\u2019djaidjia",
    "gn:population":0,
    "gn:timezone":"Africa/Algiers",
    "iso:country":"DZ",
    "name:und_x_variant":[
        "Douar Hadi Ha\u00efdjia",
        "Douar el Hadja\u00efdjiya",
        "Douar el H\u2019djaidjia",
        "Hadi Ha\u00efdjia"
    ],
    "wof:name":"Douar el H'djaidjia",
    "wof:placetype":"locality"
},
  "geometry": {"coordinates":[0.31735,35.6976],"type":"Point"}
}