{
  "type": "Feature",
  "properties": {
    "gn:admin1_code":"41.0",
    "gn:asciiname":"Ouled el Hadj Abbed",
    "gn:country_code":"DZ",
    "gn:dem":81,
    "gn:feature_class":"P",
    "gn:feature_code":"PPLL",
    "gn:name":"Ouled el Hadj Abbed",
    "gn:population":0,
    "gn:timezone":"Africa/Algiers",
    "iso:country":"DZ",
    "name:und_x_variant":[
        "Ouled el Hadj \u2019Abed"
    ],
    "wof:name":"Ouled el Hadj Abbed",
    "wof:placetype":"locality"
},
  "geometry": {"coordinates":[1.16904,36.10926],"type":"Point"}
}