{
  "type": "Feature",
  "properties": {
    "gn:admin1_code":"41.0",
    "gn:asciiname":"El Arabat",
    "gn:country_code":"DZ",
    "gn:dem":88,
    "gn:feature_class":"P",
    "gn:feature_code":"PPL",
    "gn:name":"El Arabat",
    "gn:population":0,
    "gn:timezone":"Africa/Algiers",
    "iso:country":"DZ",
    "wof:name":"El Arabat",
    "wof:placetype":"locality"
},
  "geometry": {"coordinates":[1.25765,36.15854],"type":"Point"}
}