{
  "type": "Feature",
  "properties": {
    "gn:admin1_code":"51.0",
    "gn:asciiname":"Douar Ouled Djelloul",
    "gn:country_code":"DZ",
    "gn:dem":389,
    "gn:feature_class":"P",
    "gn:feature_code":"PPL",
    "gn:name":"Douar Ouled Djelloul",
    "gn:population":0,
    "gn:timezone":"Africa/Algiers",
    "iso:country":"DZ",
    "wof:name":"Douar Ouled Djelloul",
    "wof:placetype":"locality"
},
  "geometry": {"coordinates":[0.72965,35.62564000000001],"type":"Point"}
}