{
  "type": "Feature",
  "properties": {
    "gn:admin1_code":"41.0",
    "gn:asciiname":"Ouled Boukria",
    "gn:country_code":"DZ",
    "gn:dem":405,
    "gn:feature_class":"P",
    "gn:feature_code":"PPL",
    "gn:name":"Ouled Boukria",
    "gn:population":0,
    "gn:timezone":"Africa/Algiers",
    "iso:country":"DZ",
    "wof:name":"Ouled Boukria",
    "wof:placetype":"locality"
},
  "geometry": {"coordinates":[1.02955,36.33305],"type":"Point"}
}