{
  "type": "Feature",
  "properties": {
    "gn:admin1_code":"55.0",
    "gn:asciiname":"Boumenzou",
    "gn:country_code":"DZ",
    "gn:dem":875,
    "gn:feature_class":"P",
    "gn:feature_code":"PPLL",
    "gn:name":"Boumenzou",
    "gn:population":0,
    "gn:timezone":"Africa/Algiers",
    "iso:country":"DZ",
    "wof:name":"Boumenzou",
    "wof:placetype":"locality"
},
  "geometry": {"coordinates":[1.90148,36.40498],"type":"Point"}
}