{
  "type": "Feature",
  "properties": {
    "gn:admin1_code":"26.0",
    "gn:asciiname":"Douar Ouled M'barek",
    "gn:country_code":"DZ",
    "gn:dem":595,
    "gn:feature_class":"P",
    "gn:feature_code":"PPL",
    "gn:name":"Douar Ouled M\u2019barek",
    "gn:population":0,
    "gn:timezone":"Africa/Algiers",
    "iso:country":"DZ",
    "wof:name":"Douar Ouled M'barek",
    "wof:placetype":"locality"
},
  "geometry": {"coordinates":[0.26133,35.45422],"type":"Point"}
}