{
  "type": "Feature",
  "properties": {
    "gn:admin1_code":"51.0",
    "gn:asciiname":"Keracha",
    "gn:country_code":"DZ",
    "gn:dem":191,
    "gn:feature_class":"P",
    "gn:feature_code":"PPL",
    "gn:name":"Keracha",
    "gn:population":0,
    "gn:timezone":"Africa/Algiers",
    "iso:country":"DZ",
    "wof:name":"Keracha",
    "wof:placetype":"locality"
},
  "geometry": {"coordinates":[0.64272,35.51364],"type":"Point"}
}