{
  "type": "Feature",
  "properties": {
    "gn:admin1_code":"7.0",
    "gn:asciiname":"Plage Abd el Malek Ramdane",
    "gn:country_code":"DZ",
    "gn:dem":9,
    "gn:feature_class":"P",
    "gn:feature_code":"PPL",
    "gn:name":"Plage Abd el Malek Ramdane",
    "gn:population":0,
    "gn:timezone":"Africa/Algiers",
    "iso:country":"DZ",
    "name:und_x_variant":[
        "Ouillis-Plage",
        "Abd el-Malek Ramdane Plage",
        "Plage de Ramdan",
        "Plage Abd el Malek Ramdane"
    ],
    "wof:name":"Plage Abd el Malek Ramdane",
    "wof:placetype":"locality"
},
  "geometry": {"coordinates":[0.26282,36.12546],"type":"Point"}
}