{
  "type": "Feature",
  "properties": {
    "gn:admin1_code":"19.0",
    "gn:asciiname":"Bigou",
    "gn:country_code":"DZ",
    "gn:dem":81,
    "gn:feature_class":"P",
    "gn:feature_code":"PPL",
    "gn:name":"Bigou",
    "gn:population":0,
    "gn:timezone":"Africa/Algiers",
    "iso:country":"DZ",
    "wof:name":"Bigou",
    "wof:placetype":"locality"
},
  "geometry": {"coordinates":[5.53947,34.66229000000001],"type":"Point"}
}