{
  "type": "Feature",
  "properties": {
    "gn:admin1_code":"3.0",
    "gn:asciiname":"Mechta Bou Assida",
    "gn:country_code":"DZ",
    "gn:dem":860,
    "gn:feature_class":"P",
    "gn:feature_code":"PPL",
    "gn:name":"Mechta Bou Assida",
    "gn:population":0,
    "gn:timezone":"Africa/Algiers",
    "iso:country":"DZ",
    "wof:name":"Mechta Bou Assida",
    "wof:placetype":"locality"
},
  "geometry": {"coordinates":[6.37394,35.77057],"type":"Point"}
}