{
  "type": "Feature",
  "properties": {
    "gn:admin1_code":"18.0",
    "gn:asciiname":"Bouridene",
    "gn:country_code":"DZ",
    "gn:dem":410,
    "gn:feature_class":"P",
    "gn:feature_code":"PPL",
    "gn:name":"Bouridene",
    "gn:population":0,
    "gn:timezone":"Africa/Algiers",
    "iso:country":"DZ",
    "wof:name":"Bouridene",
    "wof:placetype":"locality"
},
  "geometry": {"coordinates":[4.94719,36.59759],"type":"Point"}
}