{
  "type": "Feature",
  "properties": {
    "gn:admin1_code":"24.0",
    "gn:asciiname":"Mechta Oulad Sa'id",
    "gn:country_code":"DZ",
    "gn:dem":63,
    "gn:feature_class":"P",
    "gn:feature_code":"PPL",
    "gn:name":"Mechta Oulad Sa\u2019\u00eed",
    "gn:population":0,
    "gn:timezone":"Africa/Algiers",
    "iso:country":"DZ",
    "name:und_x_variant":[
        "Mechtat Oulad Sa\u00efd",
        "Mechta Oulad Sa\u2019\u00eed"
    ],
    "wof:name":"Mechta Oulad Sa'id",
    "wof:placetype":"locality"
},
  "geometry": {"coordinates":[5.95335,36.73293],"type":"Point"}
}