{
  "type": "Feature",
  "properties": {
    "gn:admin1_code":"14.0",
    "gn:asciiname":"Irtabene",
    "gn:country_code":"DZ",
    "gn:dem":447,
    "gn:feature_class":"P",
    "gn:feature_code":"PPL",
    "gn:name":"Irtabene",
    "gn:population":0,
    "gn:timezone":"Africa/Algiers",
    "iso:country":"DZ",
    "wof:name":"Irtabene",
    "wof:placetype":"locality"
},
  "geometry": {"coordinates":[4.66238,36.76418],"type":"Point"}
}