{
  "type": "Feature",
  "properties": {
    "gn:admin1_code":"33.0",
    "gn:asciiname":"Mechtat Torchane",
    "gn:country_code":"DZ",
    "gn:dem":785,
    "gn:feature_class":"P",
    "gn:feature_code":"PPL",
    "gn:name":"Mechtat Torchane",
    "gn:population":0,
    "gn:timezone":"Africa/Algiers",
    "iso:country":"DZ",
    "name:und_x_variant":[
        "Mechta Torchane",
        "Mechtat Torchane"
    ],
    "wof:name":"Mechtat Torchane",
    "wof:placetype":"locality"
},
  "geometry": {"coordinates":[7.94489,35.60429],"type":"Point"}
}