{
  "type": "Feature",
  "properties": {
    "gn:admin1_code":"6.0",
    "gn:asciiname":"Dar el Hachemi",
    "gn:country_code":"DZ",
    "gn:dem":700,
    "gn:feature_class":"P",
    "gn:feature_code":"PPL",
    "gn:name":"Dar el Hachemi",
    "gn:population":0,
    "gn:timezone":"Africa/Algiers",
    "iso:country":"DZ",
    "wof:name":"Dar el Hachemi",
    "wof:placetype":"locality"
},
  "geometry": {"coordinates":[2.41135,35.60482000000001],"type":"Point"}
}