{
  "type": "Feature",
  "properties": {
    "gn:admin1_code":"51.0",
    "gn:asciiname":"Temzida",
    "gn:country_code":"DZ",
    "gn:dem":561,
    "gn:feature_class":"P",
    "gn:feature_code":"PPL",
    "gn:name":"Temzida",
    "gn:population":0,
    "gn:timezone":"Africa/Algiers",
    "iso:country":"DZ",
    "wof:name":"Temzida",
    "wof:placetype":"locality"
},
  "geometry": {"coordinates":[1.25787,35.91005999999999],"type":"Point"}
}