{
  "type": "Feature",
  "properties": {
    "gn:admin1_code":"36.0",
    "gn:asciiname":"Chaabat el Leham",
    "gn:country_code":"DZ",
    "gn:dem":168,
    "gn:feature_class":"P",
    "gn:feature_code":"PPL",
    "gn:name":"Chaabat el Leham",
    "gn:population":0,
    "gn:timezone":"Africa/Algiers",
    "iso:country":"DZ",
    "name:ara_x_preferred":[
        "\u0634\u0639\u0628\u0629 \u0627\u0644\u0644\u062d\u0645"
    ],
    "name:azb_x_preferred":[
        "\u0634\u0639\u0628\u0647 \u0644\u062d\u0645"
    ],
    "name:fas_x_preferred":[
        "\u0634\u0639\u0628\u0647 \u0644\u062d\u0645"
    ],
    "name:fra_x_preferred":[
        "Chaabat El Leham"
    ],
    "name:ita_x_preferred":[
        "Chaabet El Ham"
    ],
    "name:kab_x_preferred":[
        "Ce\u025bbet Ll\u1e25em"
    ],
    "name:msa_x_preferred":[
        "Chaabet El Ham"
    ],
    "name:por_x_preferred":[
        "Chaabet El Ham"
    ],
    "name:ron_x_preferred":[
        "Chaabat El Leham"
    ],
    "name:spa_x_preferred":[
        "Chaabat El Leham"
    ],
    "name:und_x_variant":[
        "Laferri\u00e8re",
        "Chabet el Leham",
        "Chahat el Leham",
        "Chabaat El Leham",
        "Chaabat el Leham"
    ],
    "name:vie_x_preferred":[
        "Chaabet El Ham"
    ],
    "name:zho_x_preferred":[
        "\u6c99\u62dc\u7279\u54c8\u59c6"
    ],
    "wof:name":"Chaabat el Leham",
    "wof:placetype":"locality"
},
  "geometry": {"coordinates":[-1.10145,35.33619],"type":"Point"}
}