{
  "type": "Feature",
  "properties": {
    "gn:admin1_code":"36.0",
    "gn:asciiname":"Chaabat el Leham",
    "gn:country_code":"DZ",
    "gn:dem":168,
    "gn:feature_class":"P",
    "gn:feature_code":"PPL",
    "gn:name":"Chaabat el Leham",
    "gn:population":0,
    "gn:timezone":"Africa/Algiers",
    "iso:country":"DZ",
    "name:und_x_variant":[
        "Laferri\u00e8re",
        "Chabet el Leham",
        "Chahat el Leham",
        "Chabaat El Leham",
        "Chaabat el Leham"
    ],
    "wof:name":"Chaabat el Leham",
    "wof:placetype":"locality"
},
  "geometry": {"coordinates":[-1.10145,35.33619],"type":"Point"}
}