{
  "type": "Feature",
  "properties": {
    "gn:admin1_code":"3.0",
    "gn:asciiname":"Mechta Gabel Azem",
    "gn:country_code":"DZ",
    "gn:dem":938,
    "gn:feature_class":"P",
    "gn:feature_code":"PPL",
    "gn:name":"Mechta Gabel Azem",
    "gn:population":0,
    "gn:timezone":"Africa/Algiers",
    "iso:country":"DZ",
    "wof:name":"Mechta Gabel Azem",
    "wof:placetype":"locality"
},
  "geometry": {"coordinates":[6.4452,35.71992],"type":"Point"}
}