{
  "type": "Feature",
  "properties": {
    "gn:admin1_code":"51.0",
    "gn:asciiname":"Douar Toueitia",
    "gn:country_code":"DZ",
    "gn:dem":587,
    "gn:feature_class":"P",
    "gn:feature_code":"PPL",
    "gn:name":"Douar Toueitia",
    "gn:population":0,
    "gn:timezone":"Africa/Algiers",
    "iso:country":"DZ",
    "wof:name":"Douar Toueitia",
    "wof:placetype":"locality"
},
  "geometry": {"coordinates":[0.91889,35.62389],"type":"Point"}
}