{
  "type": "Feature",
  "properties": {
    "iso:country":"DZ",
    "qs:gn_pop":0,
    "qs:name":"Saint-Cloud-d'Algerie",
    "qs:name_adm0":"\u0627\u0644\u062c\u0632\u0627\u0626\u0631",
    "qs:name_adm1":"\u0648\u0644\u0627\u064a\u0629 \u0648\u0647\u0631\u0627\u0646",
    "qs:photos":7,
    "qs:photos_1k":1,
    "qs:photos_9k":1,
    "qs:photos_9r":1,
    "qs:photos_all":7,
    "qs:photos_sr":1,
    "qs:placetype":"Town",
    "qs:pop_sr":"0",
    "qs:woe_adm0":23424740,
    "wof:name":"Saint-Cloud-d'Algerie",
    "wof:placetype":"locality"
},
  "geometry": {"coordinates":[-0.389416,35.793972],"type":"Point"}
}