{
  "type": "Feature",
  "properties": {
    "gn:admin1_code":"26.0",
    "gn:asciiname":"Ouled Boudjahnit",
    "gn:country_code":"DZ",
    "gn:dem":467,
    "gn:feature_class":"P",
    "gn:feature_code":"PPL",
    "gn:name":"Ouled Boudjahnit",
    "gn:population":0,
    "gn:timezone":"Africa/Algiers",
    "iso:country":"DZ",
    "wof:name":"Ouled Boudjahnit",
    "wof:placetype":"locality"
},
  "geometry": {"coordinates":[0.15892,35.31763],"type":"Point"}
}