{
  "type": "Feature",
  "properties": {
    "gn:admin1_code":"21.0",
    "gn:asciiname":"El Hachimia",
    "gn:country_code":"DZ",
    "gn:dem":719,
    "gn:feature_class":"P",
    "gn:feature_code":"PPL",
    "gn:name":"El Hachimia",
    "gn:population":0,
    "gn:timezone":"Africa/Algiers",
    "iso:country":"DZ",
    "name:ara_x_preferred":[
        "\u0627\u0644\u0647\u0627\u0634\u0645\u064a\u0629"
    ],
    "name:azb_x_preferred":[
        "\u0647\u0627\u0634\u0645\u06cc\u0647"
    ],
    "name:fas_x_preferred":[
        "\u0647\u0627\u0634\u0645\u06cc\u0647"
    ],
    "name:fra_x_preferred":[
        "El Hachimia"
    ],
    "name:ita_x_preferred":[
        "El Hachimia"
    ],
    "name:kab_x_preferred":[
        "Lhacmiyya"
    ],
    "name:msa_x_preferred":[
        "El Hachimia"
    ],
    "name:por_x_preferred":[
        "El Hachimia"
    ],
    "name:ron_x_preferred":[
        "El Hachimia"
    ],
    "name:spa_x_preferred":[
        "El Hachimia"
    ],
    "name:und_x_variant":[
        "Al Hachimia",
        "Baraque",
        "La Baraque"
    ],
    "name:urd_x_preferred":[
        "\u0627\u0644\u06c1\u0627\u0634\u0645\u06cc\u06c1"
    ],
    "name:vie_x_preferred":[
        "El Hachimia"
    ],
    "wof:name":"El Hachimia",
    "wof:placetype":"locality"
},
  "geometry": {"coordinates":[3.83714,36.24071],"type":"Point"}
}