{
  "type": "Feature",
  "properties": {
    "gn:admin1_code":"21.0",
    "gn:asciiname":"El Hachimia",
    "gn:country_code":"DZ",
    "gn:dem":719,
    "gn:feature_class":"P",
    "gn:feature_code":"PPL",
    "gn:name":"El Hachimia",
    "gn:population":0,
    "gn:timezone":"Africa/Algiers",
    "iso:country":"DZ",
    "name:und_x_variant":[
        "Al Hachimia",
        "Baraque",
        "La Baraque",
        "El Hachimia"
    ],
    "wof:name":"El Hachimia",
    "wof:placetype":"locality"
},
  "geometry": {"coordinates":[3.83714,36.24071],"type":"Point"}
}