{
  "type": "Feature",
  "properties": {
    "gn:admin1_code":"18.0",
    "gn:asciiname":"Bou Msedene",
    "gn:country_code":"DZ",
    "gn:dem":888,
    "gn:feature_class":"P",
    "gn:feature_code":"PPL",
    "gn:name":"Bou Msedene",
    "gn:population":0,
    "gn:timezone":"Africa/Algiers",
    "iso:country":"DZ",
    "name:und_x_variant":[
        "Bou Msedena",
        "Bou Msedene"
    ],
    "wof:name":"Bou Msedene",
    "wof:placetype":"locality"
},
  "geometry": {"coordinates":[5.26135,36.39538],"type":"Point"}
}