{
  "type": "Feature",
  "properties": {
    "gn:admin1_code":"18.0",
    "gn:asciiname":"Irhzer Abbas",
    "gn:country_code":"DZ",
    "gn:dem":560,
    "gn:feature_class":"P",
    "gn:feature_code":"PPL",
    "gn:name":"Irhzer Abbas",
    "gn:population":0,
    "gn:timezone":"Africa/Algiers",
    "iso:country":"DZ",
    "wof:name":"Irhzer Abbas",
    "wof:placetype":"locality"
},
  "geometry": {"coordinates":[4.72223,36.77842],"type":"Point"}
}