{
  "type": "Feature",
  "properties": {
    "gn:admin1_code":"9.0",
    "gn:asciiname":"Douar er Rehamna",
    "gn:country_code":"DZ",
    "gn:dem":163,
    "gn:feature_class":"P",
    "gn:feature_code":"PPL",
    "gn:name":"Douar er Rehamna",
    "gn:population":0,
    "gn:timezone":"Africa/Algiers",
    "iso:country":"DZ",
    "name:und_x_variant":[
        "Er Ramena",
        "Douar er Ramena",
        "Douar er Rehamna"
    ],
    "wof:name":"Douar er Rehamna",
    "wof:placetype":"locality"
},
  "geometry": {"coordinates":[-0.25771,35.71922],"type":"Point"}
}