{
  "type": "Feature",
  "properties": {
    "gn:admin1_code":"51.0",
    "gn:asciiname":"El Mekkaidia",
    "gn:country_code":"DZ",
    "gn:dem":44,
    "gn:feature_class":"P",
    "gn:feature_code":"PPL",
    "gn:name":"El Mekka\u00efdia",
    "gn:population":0,
    "gn:timezone":"Africa/Algiers",
    "iso:country":"DZ",
    "wof:name":"El Mekkaidia",
    "wof:placetype":"locality"
},
  "geometry": {"coordinates":[0.60812,35.83271],"type":"Point"}
}