{
  "type": "Feature",
  "properties": {
    "gn:admin1_code":"51.0",
    "gn:asciiname":"Douar el Aaza",
    "gn:country_code":"DZ",
    "gn:dem":45,
    "gn:feature_class":"P",
    "gn:feature_code":"PPL",
    "gn:name":"Douar el Aaza",
    "gn:population":0,
    "gn:timezone":"Africa/Algiers",
    "iso:country":"DZ",
    "wof:name":"Douar el Aaza",
    "wof:placetype":"locality"
},
  "geometry": {"coordinates":[0.72924,35.9897],"type":"Point"}
}