{
  "type": "Feature",
  "properties": {
    "gn:admin1_code":"13.0",
    "gn:asciiname":"Bounoual",
    "gn:country_code":"DZ",
    "gn:dem":531,
    "gn:feature_class":"P",
    "gn:feature_code":"PPL",
    "gn:name":"Bounoual",
    "gn:population":0,
    "gn:timezone":"Africa/Algiers",
    "iso:country":"DZ",
    "name:und_x_variant":[
        "Bou Noual"
    ],
    "wof:name":"Bounoual",
    "wof:placetype":"locality"
},
  "geometry": {"coordinates":[0.65259,35.21133],"type":"Point"}
}