{
  "type": "Feature",
  "properties": {
    "gn:admin1_code":"29.0",
    "gn:asciiname":"M'Chira",
    "gn:country_code":"DZ",
    "gn:dem":856,
    "gn:feature_class":"P",
    "gn:feature_code":"PPL",
    "gn:name":"M\u2019Chira",
    "gn:population":0,
    "gn:timezone":"Africa/Algiers",
    "iso:country":"DZ",
    "name:und_x_variant":[
        "M\u2019Chira"
    ],
    "wof:name":"M'Chira",
    "wof:placetype":"locality"
},
  "geometry": {"coordinates":[6.23085,36.01266],"type":"Point"}
}