{
  "type": "Feature",
  "properties": {
    "gn:admin1_code":"39.0",
    "gn:asciiname":"Mechta Cherchar",
    "gn:country_code":"DZ",
    "gn:dem":943,
    "gn:feature_class":"P",
    "gn:feature_code":"PPL",
    "gn:name":"Mechta Cherchar",
    "gn:population":0,
    "gn:timezone":"Africa/Algiers",
    "iso:country":"DZ",
    "name:und_x_variant":[
        "Mechtat Cherchar",
        "Mechta Cherchar"
    ],
    "wof:name":"Mechta Cherchar",
    "wof:placetype":"locality"
},
  "geometry": {"coordinates":[5.08805,36.17972],"type":"Point"}
}