{
  "type": "Feature",
  "properties": {
    "gn:admin1_code":"6.0",
    "gn:asciiname":"Ouled Saoula",
    "gn:country_code":"DZ",
    "gn:dem":731,
    "gn:feature_class":"P",
    "gn:feature_code":"PPL",
    "gn:name":"Ouled Saoula",
    "gn:population":0,
    "gn:timezone":"Africa/Algiers",
    "iso:country":"DZ",
    "wof:name":"Ouled Saoula",
    "wof:placetype":"locality"
},
  "geometry": {"coordinates":[2.36948,35.61172],"type":"Point"}
}