{
  "type": "Feature",
  "properties": {
    "gn:admin1_code":"41.0",
    "gn:asciiname":"Boukaat es Sadnia",
    "gn:country_code":"DZ",
    "gn:dem":158,
    "gn:feature_class":"P",
    "gn:feature_code":"PPL",
    "gn:name":"Boukaat es Sadnia",
    "gn:population":0,
    "gn:timezone":"Africa/Algiers",
    "iso:country":"DZ",
    "name:und_x_variant":[
        "Boka\u2019et es Sa\u2019d\u00eania"
    ],
    "wof:name":"Boukaat es Sadnia",
    "wof:placetype":"locality"
},
  "geometry": {"coordinates":[1.22706,36.23967],"type":"Point"}
}