{
  "type": "Feature",
  "properties": {
    "iso:country":"DZ",
    "name:ara_x_preferred":[
        "\u0628\u0648\u0642\u0627\u0639\u0629"
    ],
    "name:ceb_x_preferred":[
        "Bougaa"
    ],
    "name:eng_x_preferred":[
        "Bougaa"
    ],
    "name:fas_x_preferred":[
        "\u0628\u0648\u0642\u0627\u0639\u0647"
    ],
    "name:fra_x_preferred":[
        "Bougaa"
    ],
    "name:ita_x_preferred":[
        "Bougaa"
    ],
    "name:kab_x_preferred":[
        "Buge\u025b\u025ba"
    ],
    "name:nld_x_preferred":[
        "Bougaa"
    ],
    "name:por_x_preferred":[
        "Bougaa"
    ],
    "name:ron_x_preferred":[
        "Bougaa"
    ],
    "name:swe_x_preferred":[
        "Bougaa"
    ],
    "name:unk_x_variant":[
        "Lafayette"
    ],
    "name:vie_x_preferred":[
        "Bougaa"
    ],
    "name:zho_min_nan_x_preferred":[
        "Bougaa"
    ],
    "qs:gn_country":"DZ",
    "qs:gn_fcode":"PPL",
    "qs:gn_pop":38597,
    "qs:name":"Bougaa",
    "qs:name_adm0":"\u0627\u0644\u062c\u0632\u0627\u0626\u0631",
    "qs:name_adm1":"Setif",
    "qs:photos":0,
    "qs:photos_1k":0,
    "qs:photos_9k":1,
    "qs:photos_9r":1,
    "qs:photos_all":1,
    "qs:photos_sr":0,
    "qs:placetype":"Town",
    "qs:pop_sr":"7",
    "qs:woe_adm0":23424740,
    "wd:wordcount":38,
    "wof:name":"Bougaa",
    "wof:placetype":"locality",
    "wof:population":38597
},
  "geometry": {"coordinates":[5.08843,36.33293],"type":"Point"}
}