{
  "type": "Feature",
  "properties": {
    "gn:admin1_code":"24.0",
    "gn:asciiname":"Zra el Mial",
    "gn:country_code":"DZ",
    "gn:dem":896,
    "gn:feature_class":"P",
    "gn:feature_code":"PPL",
    "gn:name":"Zra el Mial",
    "gn:population":0,
    "gn:timezone":"Africa/Algiers",
    "iso:country":"DZ",
    "wof:name":"Zra el Mial",
    "wof:placetype":"locality"
},
  "geometry": {"coordinates":[5.58844,36.56059000000001],"type":"Point"}
}