{
  "type": "Feature",
  "properties": {
    "gn:admin1_code":"14.0",
    "gn:asciiname":"Kelaa",
    "gn:country_code":"DZ",
    "gn:dem":715,
    "gn:feature_class":"P",
    "gn:feature_code":"PPL",
    "gn:name":"Kelaa",
    "gn:population":0,
    "gn:timezone":"Africa/Algiers",
    "iso:country":"DZ",
    "name:und_x_variant":[
        "Kella",
        "Kelaa"
    ],
    "wof:name":"Kelaa",
    "wof:placetype":"locality"
},
  "geometry": {"coordinates":[4.43328,36.8401],"type":"Point"}
}