{
  "type": "Feature",
  "properties": {
    "gn:admin1_code":"34.0",
    "gn:asciiname":"Zaouia",
    "gn:country_code":"DZ",
    "gn:dem":298,
    "gn:feature_class":"P",
    "gn:feature_code":"PPL",
    "gn:name":"Zaouia",
    "gn:population":0,
    "gn:timezone":"Africa/Algiers",
    "iso:country":"DZ",
    "wof:name":"Zaouia",
    "wof:placetype":"locality"
},
  "geometry": {"coordinates":[0.32258,28.73314],"type":"Point"}
}