{
  "type": "Feature",
  "properties": {
    "gn:country":"DZ",
    "gn:fcode":"PPL",
    "gn:population":39744,
    "iso:country":"DZ",
    "name:ara_x_preferred":[
        "\u0627\u0644\u062d\u062c\u064a\u0631\u0629"
    ],
    "name:arz_x_preferred":[
        "\u0627\u0644\u062d\u062c\u064a\u0631\u0647"
    ],
    "name:azb_x_preferred":[
        "\u062d\u062c\u06cc\u0631\u0647"
    ],
    "name:ceb_x_preferred":[
        "El Hadjira"
    ],
    "name:eng_x_preferred":[
        "El Hadjira"
    ],
    "name:fas_x_preferred":[
        "\u062d\u062c\u06cc\u0631\u0647"
    ],
    "name:fra_x_preferred":[
        "El Hadjira"
    ],
    "name:ita_x_preferred":[
        "El Hadjira"
    ],
    "name:msa_x_preferred":[
        "El Hadjira"
    ],
    "name:nan_x_preferred":[
        "El Hadjira"
    ],
    "name:nld_x_preferred":[
        "El Hadjira"
    ],
    "name:por_x_preferred":[
        "El Hadjira"
    ],
    "name:ron_x_preferred":[
        "El Hadjira"
    ],
    "name:rus_x_preferred":[
        "\u042d\u043b\u044c-\u0425\u0430\u0434\u0436\u0438\u0440\u0430"
    ],
    "name:spa_x_preferred":[
        "El Hadjira"
    ],
    "name:swe_x_preferred":[
        "El Hadjira"
    ],
    "name:vie_x_preferred":[
        "El Hadjira"
    ],
    "name:zho_x_preferred":[
        "\u54c8\u5409\u62c9"
    ],
    "qs:name":"El Hadjira",
    "qs:photos_9r":0,
    "qs:photos_sr":0,
    "qs:pop_sr":"7",
    "wd:wordcount":476,
    "wof:name":"El Hadjira",
    "wof:placetype":"locality",
    "wof:population":39744
},
  "geometry": {"coordinates":[5.51259,32.61336],"type":"Point"}
}