{
  "type": "Feature",
  "properties": {
    "gn:country":"DZ",
    "gn:fcode":"PPL",
    "gn:pop":39744,
    "iso:country":"DZ",
    "name:ara_x_preferred":[
        "\u0627\u0644\u062d\u062c\u064a\u0631\u0629"
    ],
    "name:eng_x_preferred":[
        "El Hadjira"
    ],
    "name:fas_x_preferred":[
        "\u062d\u062c\u06cc\u0631\u0647"
    ],
    "name:fra_x_preferred":[
        "El Hadjira"
    ],
    "name:ita_x_preferred":[
        "El Hadjira"
    ],
    "name:msa_x_preferred":[
        "El Hadjira"
    ],
    "name:nld_x_preferred":[
        "El Hadjira"
    ],
    "name:por_x_preferred":[
        "El Hadjira"
    ],
    "name:ron_x_preferred":[
        "El Hadjira"
    ],
    "name:swe_x_preferred":[
        "El Hadjira"
    ],
    "name:vie_x_preferred":[
        "El Hadjira"
    ],
    "qs:name":"El Hadjira",
    "qs:photos_9r":0,
    "qs:photos_sr":0,
    "qs:pop_sr":"7",
    "wd:wordcount":476,
    "wof:name":"El Hadjira",
    "wof:placetype":"locality",
    "wof:population":39744
},
  "geometry": {"coordinates":[5.51259,32.61336],"type":"Point"}
}