{
  "type": "Feature",
  "properties": {
    "gn:admin1_code":"51.0",
    "gn:asciiname":"Ramka",
    "gn:country_code":"DZ",
    "gn:dem":391,
    "gn:feature_class":"P",
    "gn:feature_code":"PPL",
    "gn:name":"Ramka",
    "gn:population":0,
    "gn:timezone":"Africa/Algiers",
    "iso:country":"DZ",
    "name:und_x_variant":[
        "A\u00efn Ramka",
        "Ramka"
    ],
    "wof:name":"Ramka",
    "wof:placetype":"locality"
},
  "geometry": {"coordinates":[1.33229,35.8555],"type":"Point"}
}