{
  "type": "Feature",
  "properties": {
    "gn:admin1_code":"13.0",
    "gn:asciiname":"Ouled Attia",
    "gn:country_code":"DZ",
    "gn:dem":818,
    "gn:feature_class":"P",
    "gn:feature_code":"PPL",
    "gn:name":"Ouled Attia",
    "gn:population":0,
    "gn:timezone":"Africa/Algiers",
    "iso:country":"DZ",
    "wof:name":"Ouled Attia",
    "wof:placetype":"locality"
},
  "geometry": {"coordinates":[2.16067,35.52800999999999],"type":"Point"}
}