{
  "type": "Feature",
  "properties": {
    "gn:admin1_code":"13.0",
    "gn:asciiname":"Ouled Attia",
    "gn:country_code":"DZ",
    "gn:dem":818,
    "gn:feature_class":"P",
    "gn:feature_code":"PPL",
    "gn:name":"Ouled Attia",
    "gn:population":0,
    "gn:timezone":"Africa/Algiers",
    "iso:country":"DZ",
    "name:ara_x_preferred":[
        "\u0623\u0648\u0644\u0627\u062f \u0639\u0637\u064a\u0629"
    ],
    "name:azb_x_preferred":[
        "\u0627\u0648\u0644\u0627\u062f \u0639\u0637\u06cc\u0647"
    ],
    "name:fas_x_preferred":[
        "\u0627\u0648\u0644\u0627\u062f \u0639\u0637\u06cc\u0647"
    ],
    "name:fra_x_preferred":[
        "Ouled Attia"
    ],
    "name:ita_x_preferred":[
        "Ouled Attia"
    ],
    "name:kab_x_preferred":[
        "Wlad \u0190\u1e6deya"
    ],
    "name:msa_x_preferred":[
        "Ouled Attia"
    ],
    "name:por_x_preferred":[
        "Ouled Attia"
    ],
    "name:ron_x_preferred":[
        "Ouled Attia"
    ],
    "name:spa_x_preferred":[
        "Ouled Attia"
    ],
    "name:vie_x_preferred":[
        "Ouled Attia"
    ],
    "name:zho_x_preferred":[
        "\u5967\u62c9\u5fb7\u963f\u63d0\u8036"
    ],
    "wof:name":"Ouled Attia",
    "wof:placetype":"locality"
},
  "geometry": {"coordinates":[2.16067,35.52800999999999],"type":"Point"}
}