{
  "type": "Feature",
  "properties": {
    "gn:admin1_code":"9.0",
    "gn:asciiname":"Mers el Hadjad",
    "gn:country_code":"DZ",
    "gn:dem":3,
    "gn:feature_class":"P",
    "gn:feature_code":"PPL",
    "gn:name":"Mers el Hadjad",
    "gn:population":0,
    "gn:timezone":"Africa/Algiers",
    "iso:country":"DZ",
    "name:und_x_variant":[
        "Port-aux-Poules",
        "Mers el Hadjat",
        "Mers el Hadjad"
    ],
    "wof:name":"Mers el Hadjad",
    "wof:placetype":"locality"
},
  "geometry": {"coordinates":[-0.16432,35.79787],"type":"Point"}
}