{
  "type": "Feature",
  "properties": {
    "gn:admin1_code":"12.0",
    "gn:asciiname":"Mechtet Lablalit",
    "gn:country_code":"DZ",
    "gn:dem":915,
    "gn:feature_class":"P",
    "gn:feature_code":"PPL",
    "gn:name":"Mechtet Lablalit",
    "gn:population":0,
    "gn:timezone":"Africa/Algiers",
    "iso:country":"DZ",
    "name:und_x_variant":[
        "Mechta Lablalit",
        "Mechtet Lablalit"
    ],
    "wof:name":"Mechtet Lablalit",
    "wof:placetype":"locality"
},
  "geometry": {"coordinates":[5.35621,35.94648],"type":"Point"}
}