{
  "type": "Feature",
  "properties": {
    "gn:admin1_code":"14.0",
    "gn:asciiname":"Akerroui",
    "gn:country_code":"DZ",
    "gn:dem":576,
    "gn:feature_class":"P",
    "gn:feature_code":"PPL",
    "gn:name":"Akerroui",
    "gn:population":0,
    "gn:timezone":"Africa/Algiers",
    "iso:country":"DZ",
    "wof:name":"Akerroui",
    "wof:placetype":"locality"
},
  "geometry": {"coordinates":[4.31367,36.66311],"type":"Point"}
}