{
  "type": "Feature",
  "properties": {
    "iso:country":"DZ",
    "name:ara_x_preferred":[
        "\u0633\u064a\u062f\u064a \u0645\u0631\u0648\u0627\u0646"
    ],
    "name:azb_x_preferred":[
        "\u0633\u06cc\u062f\u06cc \u0645\u0631\u0648\u0627\u0646"
    ],
    "name:ceb_x_preferred":[
        "Sidi M\u00e9rouane"
    ],
    "name:eng_x_preferred":[
        "Sidi Merouane"
    ],
    "name:fas_x_preferred":[
        "\u0633\u06cc\u062f\u06cc \u0645\u0631\u0648\u0627\u0646"
    ],
    "name:fra_x_preferred":[
        "Sidi M\u00e9rouane"
    ],
    "name:ita_x_preferred":[
        "Sidi M\u00e9rouane"
    ],
    "name:msa_x_preferred":[
        "Sidi Merouane"
    ],
    "name:nan_x_preferred":[
        "Sidi M\u00e9rouane"
    ],
    "name:nld_x_preferred":[
        "Sidi Merouane"
    ],
    "name:por_x_preferred":[
        "Sidi Merouane"
    ],
    "name:ron_x_preferred":[
        "Sidi M\u00e9rouane"
    ],
    "name:spa_x_preferred":[
        "Sidi M\u00e9rouane"
    ],
    "name:swe_x_preferred":[
        "Sidi M\u00e9rouane"
    ],
    "name:und_x_variant":[
        "Sidi Merouan"
    ],
    "name:vie_x_preferred":[
        "Sidi Merouane"
    ],
    "qs:gn_country":"DZ",
    "qs:gn_fcode":"PPL",
    "qs:gn_pop":25129,
    "qs:name":"Sidi Merouane",
    "qs:name_adm0":"\u0627\u0644\u062c\u0632\u0627\u0626\u0631",
    "qs:name_adm1":"\u0648\u0644\u0627\u064a\u0629 \u0645\u064a\u0644\u0629",
    "qs:photos":0,
    "qs:photos_1k":0,
    "qs:photos_9k":0,
    "qs:photos_9r":0,
    "qs:photos_all":0,
    "qs:photos_sr":0,
    "qs:placetype":"Town",
    "qs:pop_sr":"7",
    "qs:woe_adm0":23424740,
    "wd:wordcount":39,
    "wof:name":"Sidi Merouane",
    "wof:placetype":"locality",
    "wof:population":25129
},
  "geometry": {"coordinates":[6.26111,36.52056],"type":"Point"}
}