{
  "type": "Feature",
  "properties": {
    "gn:admin1_code":"29.0",
    "gn:asciiname":"Mechtat el Gouissa",
    "gn:country_code":"DZ",
    "gn:dem":821,
    "gn:feature_class":"P",
    "gn:feature_code":"PPL",
    "gn:name":"Mechtat el Gouissa",
    "gn:population":0,
    "gn:timezone":"Africa/Algiers",
    "iso:country":"DZ",
    "wof:name":"Mechtat el Gouissa",
    "wof:placetype":"locality"
},
  "geometry": {"coordinates":[7.36542,36.0301],"type":"Point"}
}