{
  "type": "Feature",
  "properties": {
    "gn:admin1_code":"48.0",
    "gn:asciiname":"Mechta Kermouda",
    "gn:country_code":"DZ",
    "gn:dem":402,
    "gn:feature_class":"P",
    "gn:feature_code":"PPL",
    "gn:name":"Mechta Kermouda",
    "gn:population":0,
    "gn:timezone":"Africa/Algiers",
    "iso:country":"DZ",
    "name:und_x_variant":[
        "Mechtat Kermouda",
        "Mechta Kermouda"
    ],
    "wof:name":"Mechta Kermouda",
    "wof:placetype":"locality"
},
  "geometry": {"coordinates":[6.15392,36.46405],"type":"Point"}
}