{
  "type": "Feature",
  "properties": {
    "gn:admin1_code":"41.0",
    "gn:asciiname":"Bordi el Mathen",
    "gn:country_code":"DZ",
    "gn:dem":602,
    "gn:feature_class":"P",
    "gn:feature_code":"PPL",
    "gn:name":"Bordi el Mathen",
    "gn:population":0,
    "gn:timezone":"Africa/Algiers",
    "iso:country":"DZ",
    "wof:name":"Bordi el Mathen",
    "wof:placetype":"locality"
},
  "geometry": {"coordinates":[1.38349,36.40377],"type":"Point"}
}