{
  "type": "Feature",
  "properties": {
    "gn:admin1_code":"41.0",
    "gn:asciiname":"El Abadlia",
    "gn:country_code":"DZ",
    "gn:dem":296,
    "gn:feature_class":"P",
    "gn:feature_code":"PPL",
    "gn:name":"El Abadlia",
    "gn:population":0,
    "gn:timezone":"Africa/Algiers",
    "iso:country":"DZ",
    "wof:name":"El Abadlia",
    "wof:placetype":"locality"
},
  "geometry": {"coordinates":[1.24731,36.33468],"type":"Point"}
}