{
  "type": "Feature",
  "properties": {
    "gn:admin1_code":"41.0",
    "gn:asciiname":"Douar el M'Den",
    "gn:country_code":"DZ",
    "gn:dem":532,
    "gn:feature_class":"P",
    "gn:feature_code":"PPL",
    "gn:name":"Douar el M\u2019Den",
    "gn:population":0,
    "gn:timezone":"Africa/Algiers",
    "iso:country":"DZ",
    "wof:name":"Douar el M'Den",
    "wof:placetype":"locality"
},
  "geometry": {"coordinates":[1.36806,36.27074],"type":"Point"}
}