{
  "type": "Feature",
  "properties": {
    "gn:admin1_code":"24.0",
    "gn:asciiname":"Dar el Hammoud",
    "gn:country_code":"DZ",
    "gn:dem":521,
    "gn:feature_class":"P",
    "gn:feature_code":"PPL",
    "gn:name":"D\u00e2r el Hammoud",
    "gn:population":0,
    "gn:timezone":"Africa/Algiers",
    "iso:country":"DZ",
    "name:und_x_variant":[
        "Mechtat Dar el Hanout",
        "D\u00e2r el Hammoud"
    ],
    "wof:name":"Dar el Hammoud",
    "wof:placetype":"locality"
},
  "geometry": {"coordinates":[5.7844,36.69083],"type":"Point"}
}