{
  "type": "Feature",
  "properties": {
    "gn:admin1_code":"4.0",
    "gn:asciiname":"Mechta Sidi Embarek",
    "gn:country_code":"DZ",
    "gn:dem":866,
    "gn:feature_class":"P",
    "gn:feature_code":"PPL",
    "gn:name":"Mechta Sidi Embarek",
    "gn:population":0,
    "gn:timezone":"Africa/Algiers",
    "iso:country":"DZ",
    "name:und_x_variant":[
        "Mechtat Sidi Embarek",
        "Mechta Sidi Embarek"
    ],
    "wof:name":"Mechta Sidi Embarek",
    "wof:placetype":"locality"
},
  "geometry": {"coordinates":[6.88507,36.19699],"type":"Point"}
}