{
  "type": "Feature",
  "properties": {
    "gn:admin1_code":"48.0",
    "gn:asciiname":"Mechta Safsafa",
    "gn:country_code":"DZ",
    "gn:dem":1024,
    "gn:feature_class":"P",
    "gn:feature_code":"PPL",
    "gn:name":"Mechta Safsafa",
    "gn:population":0,
    "gn:timezone":"Africa/Algiers",
    "iso:country":"DZ",
    "name:und_x_variant":[
        "Mechtat Safsafa",
        "Mechta Safsafa"
    ],
    "wof:name":"Mechta Safsafa",
    "wof:placetype":"locality"
},
  "geometry": {"coordinates":[6.05543,36.34035],"type":"Point"}
}