{
  "type": "Feature",
  "properties": {
    "gn:admin1_code":"29.0",
    "gn:asciiname":"Mesloula",
    "gn:country_code":"DZ",
    "gn:dem":698,
    "gn:feature_class":"P",
    "gn:feature_code":"PPL",
    "gn:name":"Meslo\u00fbla",
    "gn:population":0,
    "gn:timezone":"Africa/Algiers",
    "iso:country":"DZ",
    "wof:name":"Mesloula",
    "wof:placetype":"locality"
},
  "geometry": {"coordinates":[7.83679,35.87027],"type":"Point"}
}