{
  "type": "Feature",
  "properties": {
    "gn:admin1_code":"21.0",
    "gn:asciiname":"Allessa",
    "gn:country_code":"DZ",
    "gn:dem":872,
    "gn:feature_class":"P",
    "gn:feature_code":"PPL",
    "gn:name":"Allessa",
    "gn:population":0,
    "gn:timezone":"Africa/Algiers",
    "iso:country":"DZ",
    "name:und_x_variant":[
        "Alle\u00e7a",
        "Allessa"
    ],
    "wof:name":"Allessa",
    "wof:placetype":"locality"
},
  "geometry": {"coordinates":[4.04323,36.19087],"type":"Point"}
}