{
  "type": "Feature",
  "properties": {
    "gn:admin1_code":"56.0",
    "gn:asciiname":"Hardy",
    "gn:country_code":"DZ",
    "gn:dem":815,
    "gn:feature_class":"P",
    "gn:feature_code":"PPL",
    "gn:name":"Hardy",
    "gn:population":0,
    "gn:timezone":"Africa/Algiers",
    "iso:country":"DZ",
    "name:bul_x_preferred":[
        "\u0425\u0430\u0440\u0434\u0438"
    ],
    "name:cat_x_preferred":[
        "Hardy"
    ],
    "name:ceb_x_preferred":[
        "Hardy"
    ],
    "name:ces_x_preferred":[
        "Hardy"
    ],
    "name:deu_x_preferred":[
        "Hardy"
    ],
    "name:fas_x_preferred":[
        "\u0647\u0627\u0631\u062f\u06cc"
    ],
    "name:fin_x_preferred":[
        "Hardy"
    ],
    "name:fra_x_preferred":[
        "Hardy"
    ],
    "name:heb_x_preferred":[
        "\u05d4\u05d0\u05e8\u05d3\u05d9"
    ],
    "name:ita_x_preferred":[
        "Hardy"
    ],
    "name:jpn_x_preferred":[
        "\u30cf\u30fc\u30c7\u30a3"
    ],
    "name:lav_x_preferred":[
        "H\u0101rdijs"
    ],
    "name:lit_x_preferred":[
        "Hardy"
    ],
    "name:nld_x_preferred":[
        "Hardy"
    ],
    "name:pol_x_preferred":[
        "Hardy"
    ],
    "name:por_x_preferred":[
        "Hardy"
    ],
    "name:rus_x_preferred":[
        "\u0425\u0430\u0440\u0434\u0438"
    ],
    "name:spa_x_preferred":[
        "Hardy"
    ],
    "name:srp_x_preferred":[
        "\u0425\u0430\u0440\u0434\u0438"
    ],
    "name:swe_x_preferred":[
        "Hardy"
    ],
    "name:ukr_x_preferred":[
        "\u0413\u0430\u0440\u0434\u0456"
    ],
    "name:und_x_variant":[
        "Hamadia",
        "A\u00efn el Ba\u00efda"
    ],
    "name:vol_x_preferred":[
        "Hardy"
    ],
    "wof:name":"Hardy",
    "wof:placetype":"locality"
},
  "geometry": {"coordinates":[1.96082,35.55736],"type":"Point"}
}