{
  "type": "Feature",
  "properties": {
    "gn:admin1_code":"56.0",
    "gn:asciiname":"Hardy",
    "gn:country_code":"DZ",
    "gn:dem":815,
    "gn:feature_class":"P",
    "gn:feature_code":"PPL",
    "gn:name":"Hardy",
    "gn:population":0,
    "gn:timezone":"Africa/Algiers",
    "iso:country":"DZ",
    "name:und_x_variant":[
        "Hamadia",
        "A\u00efn el Ba\u00efda",
        "Hardy"
    ],
    "wof:name":"Hardy",
    "wof:placetype":"locality"
},
  "geometry": {"coordinates":[1.96082,35.55736],"type":"Point"}
}