{
  "type": "Feature",
  "properties": {
    "gn:admin1_code":"20.0",
    "gn:asciiname":"Oulad 'Ayyach",
    "gn:country_code":"DZ",
    "gn:dem":294,
    "gn:feature_class":"P",
    "gn:feature_code":"PPL",
    "gn:name":"Oulad \u2019Ayy\u00e2ch",
    "gn:population":0,
    "gn:timezone":"Africa/Algiers",
    "iso:country":"DZ",
    "name:und_x_variant":[
        "Oulad Ayach",
        "Oulad \u2019Ayy\u00e2ch"
    ],
    "wof:name":"Oulad 'Ayyach",
    "wof:placetype":"locality"
},
  "geometry": {"coordinates":[2.71165,36.42066],"type":"Point"}
}