{
  "type": "Feature",
  "properties": {
    "gn:admin1_code":"13.0",
    "gn:asciiname":"El Matmour",
    "gn:country_code":"DZ",
    "gn:dem":652,
    "gn:feature_class":"P",
    "gn:feature_code":"PPL",
    "gn:name":"El Matmour",
    "gn:population":0,
    "gn:timezone":"Africa/Algiers",
    "iso:country":"DZ",
    "name:und_x_variant":[
        "Metameur ed Darou",
        "Ed Darou",
        "El Matmour"
    ],
    "wof:name":"El Matmour",
    "wof:placetype":"locality"
},
  "geometry": {"coordinates":[0.86682,35.19864000000001],"type":"Point"}
}