{
  "type": "Feature",
  "properties": {
    "gn:admin1_code":"26.0",
    "gn:asciiname":"Sidi Ameur el Kbar",
    "gn:country_code":"DZ",
    "gn:dem":496,
    "gn:feature_class":"P",
    "gn:feature_code":"PPL",
    "gn:name":"Sidi Ameur el Kbar",
    "gn:population":0,
    "gn:timezone":"Africa/Algiers",
    "iso:country":"DZ",
    "wof:name":"Sidi Ameur el Kbar",
    "wof:placetype":"locality"
},
  "geometry": {"coordinates":[-0.34104,35.42296],"type":"Point"}
}