{
  "type": "Feature",
  "properties": {
    "gn:admin1_code":"41.0",
    "gn:asciiname":"El Ababsa",
    "gn:country_code":"DZ",
    "gn:dem":182,
    "gn:feature_class":"P",
    "gn:feature_code":"PPL",
    "gn:name":"El Ababsa",
    "gn:population":0,
    "gn:timezone":"Africa/Algiers",
    "iso:country":"DZ",
    "name:und_x_variant":[
        "Ababessa",
        "El Ababsa"
    ],
    "wof:name":"El Ababsa",
    "wof:placetype":"locality"
},
  "geometry": {"coordinates":[1.61194,36.2584],"type":"Point"}
}