{
  "type": "Feature",
  "properties": {
    "gn:admin1_code":"24.0",
    "gn:asciiname":"Oulad Ayad",
    "gn:country_code":"DZ",
    "gn:dem":264,
    "gn:feature_class":"P",
    "gn:feature_code":"PPL",
    "gn:name":"Oulad Ayad",
    "gn:population":0,
    "gn:timezone":"Africa/Algiers",
    "iso:country":"DZ",
    "name:ara_x_preferred":[
        "\u0623\u0648\u0644\u0627\u062f \u0639\u064a\u0627\u062f"
    ],
    "name:azb_x_preferred":[
        "\u0627\u0648\u0644\u0627\u062f \u0639\u06cc\u0627\u062f"
    ],
    "name:cat_x_preferred":[
        "Oulad Ayad"
    ],
    "name:fas_x_preferred":[
        "\u0627\u0648\u0644\u0627\u062f \u0639\u06cc\u0627\u062f"
    ],
    "name:fra_x_preferred":[
        "Oulad Ayad"
    ],
    "name:ita_x_preferred":[
        "Oulad Ayad"
    ],
    "wof:name":"Oulad Ayad",
    "wof:placetype":"locality"
},
  "geometry": {"coordinates":[5.59524,36.63957],"type":"Point"}
}