{
  "type": "Feature",
  "properties": {
    "gn:admin1_code":"6.0",
    "gn:asciiname":"Et Tnine",
    "gn:country_code":"DZ",
    "gn:dem":717,
    "gn:feature_class":"P",
    "gn:feature_code":"PPL",
    "gn:name":"Et Tnine",
    "gn:population":0,
    "gn:timezone":"Africa/Algiers",
    "iso:country":"DZ",
    "wof:name":"Et Tnine",
    "wof:placetype":"locality"
},
  "geometry": {"coordinates":[3.23667,36.19139000000001],"type":"Point"}
}