{
  "type": "Feature",
  "properties": {
    "gn:admin1_code":"25.0",
    "gn:asciiname":"Ennfouss",
    "gn:country_code":"DZ",
    "gn:dem":1345,
    "gn:feature_class":"P",
    "gn:feature_code":"PPL",
    "gn:name":"Ennfouss",
    "gn:population":0,
    "gn:timezone":"Africa/Algiers",
    "iso:country":"DZ",
    "wof:name":"Ennfouss",
    "wof:placetype":"locality"
},
  "geometry": {"coordinates":[2.12138,33.97372],"type":"Point"}
}