{
  "type": "Feature",
  "properties": {
    "gn:country":"DZ",
    "gn:fcode":"PPL",
    "gn:pop":59990,
    "iso:country":"DZ",
    "name:ara_x_preferred":[
        "\u0645\u0641\u062a\u0627\u062d"
    ],
    "name:dut_x_preferred":[
        "Meftah"
    ],
    "name:eng_x_preferred":[
        "Meftah"
    ],
    "name:fre_x_preferred":[
        "Meftah"
    ],
    "name:ita_x_preferred":[
        "Meftah"
    ],
    "name:kab_x_preferred":[
        "Mefta\u1e25"
    ],
    "name:may_x_preferred":[
        "Meftah"
    ],
    "name:per_x_preferred":[
        "\u0645\u0641\u062a\u0627\u062d"
    ],
    "name:por_x_preferred":[
        "Meftah"
    ],
    "name:rum_x_preferred":[
        "Meftah"
    ],
    "name:rus_x_preferred":[
        "\u041c\u0435\u0444\u0442\u0430\u0445"
    ],
    "name:swe_x_preferred":[
        "Meftah"
    ],
    "name:unk_x_variant":[
        "Rivet"
    ],
    "name:urd_x_preferred":[
        "\u0645\u0641\u062a\u0627\u062d"
    ],
    "name:vie_x_preferred":[
        "Meftah"
    ],
    "qs:name":"Meftah",
    "qs:photos_9r":0,
    "qs:photos_sr":0,
    "qs:pop_sr":"8",
    "wd:wordcount":85,
    "wof:name":"Meftah",
    "wof:placetype":"locality",
    "wof:population":59990
},
  "geometry": {"coordinates":[3.22248,36.6204],"type":"Point"}
}