{
  "type": "Feature",
  "properties": {
    "gn:admin1_code":"12.0",
    "gn:asciiname":"Bourhzel",
    "gn:country_code":"DZ",
    "gn:dem":871,
    "gn:feature_class":"P",
    "gn:feature_code":"PPL",
    "gn:name":"Bourhzel",
    "gn:population":0,
    "gn:timezone":"Africa/Algiers",
    "iso:country":"DZ",
    "name:und_x_variant":[
        "\u2019A\u00efn Djasser",
        "Bourhzel"
    ],
    "wof:name":"Bourhzel",
    "wof:placetype":"locality"
},
  "geometry": {"coordinates":[6.00175,35.85994],"type":"Point"}
}