{
  "type": "Feature",
  "properties": {
    "gn:admin1_code":"39.0",
    "gn:asciiname":"'Ain Bourdeche",
    "gn:country_code":"DZ",
    "gn:dem":1272,
    "gn:feature_class":"P",
    "gn:feature_code":"PPL",
    "gn:name":"\u2019A\u00efn Bourdeche",
    "gn:population":0,
    "gn:timezone":"Africa/Algiers",
    "iso:country":"DZ",
    "wof:name":"'Ain Bourdeche",
    "wof:placetype":"locality"
},
  "geometry": {"coordinates":[5.08495,35.86263],"type":"Point"}
}