{
  "type": "Feature",
  "properties": {
    "gn:admin1_code":"26.0",
    "gn:asciiname":"Khalouia",
    "gn:country_code":"DZ",
    "gn:dem":558,
    "gn:feature_class":"P",
    "gn:feature_code":"PPL",
    "gn:name":"Khalouia",
    "gn:population":0,
    "gn:timezone":"Africa/Algiers",
    "iso:country":"DZ",
    "name:und_x_variant":[
        "Ha\u00eftia",
        "Sonis",
        "Khelouia",
        "Khalouia"
    ],
    "wof:name":"Khalouia",
    "wof:placetype":"locality"
},
  "geometry": {"coordinates":[0.29762,35.46298],"type":"Point"}
}