{
  "type": "Feature",
  "properties": {
    "gn:admin1_code":"26.0",
    "gn:asciiname":"Khalouia",
    "gn:country_code":"DZ",
    "gn:dem":558,
    "gn:feature_class":"P",
    "gn:feature_code":"PPL",
    "gn:name":"Khalouia",
    "gn:population":0,
    "gn:timezone":"Africa/Algiers",
    "iso:country":"DZ",
    "name:ara_x_preferred":[
        "\u062e\u0644\u0648\u064a\u0629"
    ],
    "name:azb_x_preferred":[
        "\u062e\u0644\u0648\u06cc\u0647"
    ],
    "name:fas_x_preferred":[
        "\u062e\u0644\u0648\u06cc\u0647"
    ],
    "name:fra_x_preferred":[
        "Khalouia"
    ],
    "name:ita_x_preferred":[
        "Khalouia"
    ],
    "name:kab_x_preferred":[
        "Xalweyya"
    ],
    "name:msa_x_preferred":[
        "Khalouia"
    ],
    "name:por_x_preferred":[
        "Khalouia"
    ],
    "name:ron_x_preferred":[
        "Khalouia"
    ],
    "name:spa_x_preferred":[
        "Khalouia"
    ],
    "name:und_x_variant":[
        "Ha\u00eftia",
        "Sonis",
        "Khelouia"
    ],
    "name:vie_x_preferred":[
        "Khalouia"
    ],
    "wof:name":"Khalouia",
    "wof:placetype":"locality"
},
  "geometry": {"coordinates":[0.29762,35.46298],"type":"Point"}
}