{
  "type": "Feature",
  "properties": {
    "gn:admin1_code":"26.0",
    "gn:asciiname":"Douar Ouled Ababou",
    "gn:country_code":"DZ",
    "gn:dem":353,
    "gn:feature_class":"P",
    "gn:feature_code":"PPL",
    "gn:name":"Douar Ouled Ababou",
    "gn:population":0,
    "gn:timezone":"Africa/Algiers",
    "iso:country":"DZ",
    "name:und_x_variant":[
        "Abba Bou",
        "Douar Ouled Ababou"
    ],
    "wof:name":"Douar Ouled Ababou",
    "wof:placetype":"locality"
},
  "geometry": {"coordinates":[-0.31461,35.4689],"type":"Point"}
}