{
  "type": "Feature",
  "properties": {
    "gn:admin1_code":"35.0",
    "gn:asciiname":"Ouamri",
    "gn:country_code":"DZ",
    "gn:dem":718,
    "gn:feature_class":"P",
    "gn:feature_code":"PPL",
    "gn:name":"Ouamri",
    "gn:population":0,
    "gn:timezone":"Africa/Algiers",
    "iso:country":"DZ",
    "name:und_x_variant":[
        "Bor\u00e9ly-la-Sapie",
        "Ouamria",
        "Ouamri"
    ],
    "wof:name":"Ouamri",
    "wof:placetype":"locality"
},
  "geometry": {"coordinates":[2.5637,36.23196],"type":"Point"}
}