{
  "type": "Feature",
  "properties": {
    "gn:admin1_code":"35.0",
    "gn:asciiname":"Ouamri",
    "gn:country_code":"DZ",
    "gn:dem":718,
    "gn:feature_class":"P",
    "gn:feature_code":"PPL",
    "gn:name":"Ouamri",
    "gn:population":0,
    "gn:timezone":"Africa/Algiers",
    "iso:country":"DZ",
    "name:ara_x_preferred":[
        "\u0648\u0627\u0645\u0631\u064a"
    ],
    "name:azb_x_preferred":[
        "\u0648\u0627\u0645\u0631\u06cc"
    ],
    "name:fas_x_preferred":[
        "\u0648\u0627\u0645\u0631\u06cc"
    ],
    "name:fra_x_preferred":[
        "Ouamri"
    ],
    "name:ita_x_preferred":[
        "Ouamri"
    ],
    "name:kab_x_preferred":[
        "\u0190wamreyya"
    ],
    "name:msa_x_preferred":[
        "Ouamri"
    ],
    "name:por_x_preferred":[
        "Ouamri"
    ],
    "name:ron_x_preferred":[
        "Ouamri"
    ],
    "name:spa_x_preferred":[
        "Ouamri"
    ],
    "name:und_x_variant":[
        "Bor\u00e9ly-la-Sapie",
        "Ouamria",
        "Ouamri"
    ],
    "name:vie_x_preferred":[
        "Ouamri"
    ],
    "name:zho_x_preferred":[
        "\u74e6\u59c6\u91cc"
    ],
    "wof:name":"Ouamri",
    "wof:placetype":"locality"
},
  "geometry": {"coordinates":[2.5637,36.23196],"type":"Point"}
}