{
  "type": "Feature",
  "properties": {
    "gn:admin1_code":"26.0",
    "gn:asciiname":"Douar Ouled el Khamsa",
    "gn:country_code":"DZ",
    "gn:dem":520,
    "gn:feature_class":"P",
    "gn:feature_code":"PPLL",
    "gn:name":"Douar Ouled el Khamsa",
    "gn:population":0,
    "gn:timezone":"Africa/Algiers",
    "iso:country":"DZ",
    "wof:name":"Douar Ouled el Khamsa",
    "wof:placetype":"locality"
},
  "geometry": {"coordinates":[0.27892,35.41615],"type":"Point"}
}