{
  "type": "Feature",
  "properties": {
    "gn:admin1_code":"14.0",
    "gn:asciiname":"Tidmimine",
    "gn:country_code":"DZ",
    "gn:dem":643,
    "gn:feature_class":"P",
    "gn:feature_code":"PPL",
    "gn:name":"Tidmimine",
    "gn:population":0,
    "gn:timezone":"Africa/Algiers",
    "iso:country":"DZ",
    "wof:name":"Tidmimine",
    "wof:placetype":"locality"
},
  "geometry": {"coordinates":[4.44149,36.84774],"type":"Point"}
}