{
  "type": "Feature",
  "properties": {
    "gn:admin1_code":"7.0",
    "gn:asciiname":"Oulad Sidi Ahmed Cheikh",
    "gn:country_code":"DZ",
    "gn:dem":286,
    "gn:feature_class":"P",
    "gn:feature_code":"PPL",
    "gn:name":"Oulad Sidi Ahmed Cheikh",
    "gn:population":0,
    "gn:timezone":"Africa/Algiers",
    "iso:country":"DZ",
    "name:und_x_variant":[
        "Douar Oulad Sidi Ahmed Cheikh",
        "Oulad Sidi Ahmed Cheikh"
    ],
    "wof:name":"Oulad Sidi Ahmed Cheikh",
    "wof:placetype":"locality"
},
  "geometry": {"coordinates":[0.50975,36.16786],"type":"Point"}
}