{
  "type": "Feature",
  "properties": {
    "gn:admin1_code":"23.0",
    "gn:asciiname":"Mechta Ras el Ma",
    "gn:country_code":"DZ",
    "gn:dem":1048,
    "gn:feature_class":"P",
    "gn:feature_code":"PPL",
    "gn:name":"Mechta R\u00e2s el Ma",
    "gn:population":0,
    "gn:timezone":"Africa/Algiers",
    "iso:country":"DZ",
    "name:und_x_variant":[
        "Mechta Ras et Ma",
        "Mechta R\u00e2s el Ma"
    ],
    "wof:name":"Mechta Ras el Ma",
    "wof:placetype":"locality"
},
  "geometry": {"coordinates":[7.49678,36.26104],"type":"Point"}
}