{
  "type": "Feature",
  "properties": {
    "gn:admin1_code":"27.0",
    "gn:asciiname":"Bou Rebza",
    "gn:country_code":"DZ",
    "gn:dem":501,
    "gn:feature_class":"P",
    "gn:feature_code":"PPL",
    "gn:name":"Bou Rebza",
    "gn:population":0,
    "gn:timezone":"Africa/Algiers",
    "iso:country":"DZ",
    "wof:name":"Bou Rebza",
    "wof:placetype":"locality"
},
  "geometry": {"coordinates":[5.08678,35.56679000000001],"type":"Point"}
}