{
  "type": "Feature",
  "properties": {
    "gn:admin1_code":"12.0",
    "gn:asciiname":"Arbaoun",
    "gn:cc2":"DZ",
    "gn:country_code":"DZ",
    "gn:dem":713,
    "gn:feature_class":"P",
    "gn:feature_code":"PPL",
    "gn:name":"Arbaoun",
    "gn:population":0,
    "gn:timezone":"Africa/Algiers",
    "iso:country":"DZ",
    "name:ara_x_preferred":[
        "\u0628\u0646\u064a \u0639\u0632\u064a\u0632"
    ],
    "name:azb_x_preferred":[
        "\u0628\u0646\u06cc \u0639\u0632\u06cc\u0632"
    ],
    "name:fas_x_preferred":[
        "\u0628\u0646\u06cc \u0639\u0632\u06cc\u0632"
    ],
    "name:fra_x_preferred":[
        "Beni Aziz"
    ],
    "name:ita_x_preferred":[
        "Beni Aziz"
    ],
    "name:kab_x_preferred":[
        "Bni \u0190ziz"
    ],
    "name:por_x_preferred":[
        "Beni Aziz"
    ],
    "name:ron_x_preferred":[
        "Beni Aziz"
    ],
    "name:spa_x_preferred":[
        "Beni Aziz"
    ],
    "name:szl_x_preferred":[
        "Beni Aziz"
    ],
    "name:ukr_x_preferred":[
        "\u0411\u0435\u043d\u0456-\u0410\u0437\u0456\u0437"
    ],
    "name:und_x_variant":[
        "Chevreul",
        "Ben Aziz",
        "Arbaoun"
    ],
    "name:vie_x_preferred":[
        "Beni Aziz"
    ],
    "wof:name":"Arbaoun",
    "wof:placetype":"locality"
},
  "geometry": {"coordinates":[5.64806,36.46278],"type":"Point"}
}