{
  "type": "Feature",
  "properties": {
    "gn:admin1_code":"12.0",
    "gn:asciiname":"Arbaoun",
    "gn:cc2":"DZ",
    "gn:country_code":"DZ",
    "gn:dem":713,
    "gn:feature_class":"P",
    "gn:feature_code":"PPL",
    "gn:name":"Arbaoun",
    "gn:population":0,
    "gn:timezone":"Africa/Algiers",
    "iso:country":"DZ",
    "name:und_x_variant":[
        "Chevreul",
        "Ben Aziz",
        "Beni Aziz",
        "Arbaoun"
    ],
    "wof:name":"Arbaoun",
    "wof:placetype":"locality"
},
  "geometry": {"coordinates":[5.64806,36.46278],"type":"Point"}
}