{
  "type": "Feature",
  "properties": {
    "gn:admin1_code":"18.0",
    "gn:asciiname":"Akbouch",
    "gn:country_code":"DZ",
    "gn:dem":391,
    "gn:feature_class":"P",
    "gn:feature_code":"PPL",
    "gn:name":"Akbouch",
    "gn:population":0,
    "gn:timezone":"Africa/Algiers",
    "iso:country":"DZ",
    "wof:name":"Akbouch",
    "wof:placetype":"locality"
},
  "geometry": {"coordinates":[5.21667,36.61667],"type":"Point"}
}