{
  "type": "Feature",
  "properties": {
    "gn:admin1_code":"34.0",
    "gn:asciiname":"Sidi Ben Hadj",
    "gn:country_code":"DZ",
    "gn:dem":233,
    "gn:feature_class":"P",
    "gn:feature_code":"PPL",
    "gn:name":"Sidi Ben Hadj",
    "gn:population":0,
    "gn:timezone":"Africa/Algiers",
    "iso:country":"DZ",
    "wof:name":"Sidi Ben Hadj",
    "wof:placetype":"locality"
},
  "geometry": {"coordinates":[-0.27576,27.73365],"type":"Point"}
}