{
  "type": "Feature",
  "properties": {
    "gn:admin1_code":"34.0",
    "gn:asciiname":"Rharmianou",
    "gn:country_code":"DZ",
    "gn:dem":248,
    "gn:feature_class":"P",
    "gn:feature_code":"PPL",
    "gn:name":"Rharmianou",
    "gn:population":0,
    "gn:timezone":"Africa/Algiers",
    "iso:country":"DZ",
    "wof:name":"Rharmianou",
    "wof:placetype":"locality"
},
  "geometry": {"coordinates":[-0.18465,27.37624000000001],"type":"Point"}
}