{
  "type": "Feature",
  "properties": {
    "gn:admin1_code":"26.0",
    "gn:asciiname":"Douar el Araissia",
    "gn:country_code":"DZ",
    "gn:dem":567,
    "gn:feature_class":"P",
    "gn:feature_code":"PPL",
    "gn:name":"Douar el Ara\u00efssia",
    "gn:population":0,
    "gn:timezone":"Africa/Algiers",
    "iso:country":"DZ",
    "wof:name":"Douar el Araissia",
    "wof:placetype":"locality"
},
  "geometry": {"coordinates":[0.26181,35.44096],"type":"Point"}
}