{
  "type": "Feature",
  "properties": {
    "gn:admin1_code":"51.0",
    "gn:asciiname":"Douar ez Zerraoula",
    "gn:country_code":"DZ",
    "gn:dem":149,
    "gn:feature_class":"P",
    "gn:feature_code":"PPL",
    "gn:name":"Douar ez Zerraoula",
    "gn:population":0,
    "gn:timezone":"Africa/Algiers",
    "iso:country":"DZ",
    "name:und_x_variant":[
        "Douar ez Zeraoula",
        "Douar ez Zerraoula",
        "Ez Zeraoula"
    ],
    "wof:name":"Douar ez Zerraoula",
    "wof:placetype":"locality"
},
  "geometry": {"coordinates":[0.50447,35.63561],"type":"Point"}
}