{
  "type": "Feature",
  "properties": {
    "gn:admin1_code":"7.0",
    "gn:asciiname":"Douar Ouled Abbas",
    "gn:country_code":"DZ",
    "gn:dem":207,
    "gn:feature_class":"P",
    "gn:feature_code":"PPLL",
    "gn:name":"Douar Ouled Abbas",
    "gn:population":0,
    "gn:timezone":"Africa/Algiers",
    "iso:country":"DZ",
    "wof:name":"Douar Ouled Abbas",
    "wof:placetype":"locality"
},
  "geometry": {"coordinates":[0.13795,35.85538],"type":"Point"}
}