{
  "type": "Feature",
  "properties": {
    "gn:admin1_code":"35.0",
    "gn:asciiname":"Ouled Moussa",
    "gn:country_code":"DZ",
    "gn:dem":193,
    "gn:feature_class":"P",
    "gn:feature_code":"PPL",
    "gn:name":"Ouled Moussa",
    "gn:population":0,
    "gn:timezone":"Africa/Algiers",
    "iso:country":"DZ",
    "name:und_x_variant":[
        "Oulad Moussa",
        "Ouled Moussa"
    ],
    "wof:name":"Ouled Moussa",
    "wof:placetype":"locality"
},
  "geometry": {"coordinates":[1.68271,36.21309],"type":"Point"}
}