{
  "type": "Feature",
  "properties": {
    "gn:admin1_code":"37.0",
    "gn:asciiname":"Sainte-Croix de l'Edough",
    "gn:country_code":"DZ",
    "gn:dem":740,
    "gn:feature_class":"P",
    "gn:feature_code":"PPL",
    "gn:name":"Sainte-Croix de l\u2019Edough",
    "gn:population":0,
    "gn:timezone":"Africa/Algiers",
    "iso:country":"DZ",
    "name:und_x_variant":[
        "Sainte-Croix de l\u2019Edourh",
        "Sainte-Croix de l\u2019Edough"
    ],
    "wof:name":"Sainte-Croix de l'Edough",
    "wof:placetype":"locality"
},
  "geometry": {"coordinates":[7.66279,36.90653],"type":"Point"}
}