{
  "type": "Feature",
  "properties": {
    "gn:admin1_code":"7.0",
    "gn:asciiname":"Douar M'raniz",
    "gn:country_code":"DZ",
    "gn:dem":124,
    "gn:feature_class":"P",
    "gn:feature_code":"PPL",
    "gn:name":"Douar M\u2019raniz",
    "gn:population":0,
    "gn:timezone":"Africa/Algiers",
    "iso:country":"DZ",
    "wof:name":"Douar M'raniz",
    "wof:placetype":"locality"
},
  "geometry": {"coordinates":[0.37778,36.14472],"type":"Point"}
}