{
  "type": "Feature",
  "properties": {
    "gn:admin1_code":"41.0",
    "gn:asciiname":"Douar Houmdia",
    "gn:country_code":"DZ",
    "gn:dem":284,
    "gn:feature_class":"P",
    "gn:feature_code":"PPL",
    "gn:name":"Douar Houmdia",
    "gn:population":0,
    "gn:timezone":"Africa/Algiers",
    "iso:country":"DZ",
    "wof:name":"Douar Houmdia",
    "wof:placetype":"locality"
},
  "geometry": {"coordinates":[1.27893,36.38303],"type":"Point"}
}