{
  "type": "Feature",
  "properties": {
    "gn:admin1_code":"34.0",
    "gn:asciiname":"Oulad Noun",
    "gn:country_code":"DZ",
    "gn:dem":269,
    "gn:feature_class":"P",
    "gn:feature_code":"PPL",
    "gn:name":"Oulad Noun",
    "gn:population":0,
    "gn:timezone":"Africa/Algiers",
    "iso:country":"DZ",
    "wof:name":"Oulad Noun",
    "wof:placetype":"locality"
},
  "geometry": {"coordinates":[0.21628,29.25136],"type":"Point"}
}