{
  "type": "Feature",
  "properties": {
    "gn:admin1_code":"6.0",
    "gn:asciiname":"Oulad Sidi Aissa",
    "gn:country_code":"DZ",
    "gn:dem":919,
    "gn:feature_class":"P",
    "gn:feature_code":"PPL",
    "gn:name":"Oulad Sidi A\u00efssa",
    "gn:population":0,
    "gn:timezone":"Africa/Algiers",
    "iso:country":"DZ",
    "wof:name":"Oulad Sidi Aissa",
    "wof:placetype":"locality"
},
  "geometry": {"coordinates":[3.36736,36.46096],"type":"Point"}
}