{
  "type": "Feature",
  "properties": {
    "gn:admin1_code":"13.0",
    "gn:asciiname":"Moulguelouane",
    "gn:country_code":"DZ",
    "gn:dem":1118,
    "gn:feature_class":"P",
    "gn:feature_code":"PPL",
    "gn:name":"Moulguelouane",
    "gn:population":0,
    "gn:timezone":"Africa/Algiers",
    "iso:country":"DZ",
    "name:und_x_variant":[
        "Ain Moulgelouane",
        "Moulgelouane",
        "Moulguelouane"
    ],
    "wof:name":"Moulguelouane",
    "wof:placetype":"locality"
},
  "geometry": {"coordinates":[1.42132,34.9137],"type":"Point"}
}