{
  "type": "Feature",
  "properties": {
    "gn:admin1_code":"18.0",
    "gn:asciiname":"Aguemoun-n-Ait Aissa",
    "gn:country_code":"DZ",
    "gn:dem":753,
    "gn:feature_class":"P",
    "gn:feature_code":"PPL",
    "gn:name":"Aguemoun-n-A\u00eft A\u00efssa",
    "gn:population":0,
    "gn:timezone":"Africa/Algiers",
    "iso:country":"DZ",
    "name:und_x_variant":[
        "Aguemonne Na\u00eft A\u00efssa",
        "Aguemoun-n-A\u00eft A\u00efssa"
    ],
    "wof:name":"Aguemoun-n-Ait Aissa",
    "wof:placetype":"locality"
},
  "geometry": {"coordinates":[4.77709,36.41336],"type":"Point"}
}