{
  "type": "Feature",
  "properties": {
    "gn:admin1_code":"6.0",
    "gn:asciiname":"El Ababsa",
    "gn:country_code":"DZ",
    "gn:dem":656,
    "gn:feature_class":"P",
    "gn:feature_code":"PPL",
    "gn:name":"El Ababsa",
    "gn:population":0,
    "gn:timezone":"Africa/Algiers",
    "iso:country":"DZ",
    "wof:name":"El Ababsa",
    "wof:placetype":"locality"
},
  "geometry": {"coordinates":[2.70409,35.86043],"type":"Point"}
}