{
  "type": "Feature",
  "properties": {
    "gn:admin1_code":"31.0",
    "gn:asciiname":"Ain Zeroula",
    "gn:country_code":"DZ",
    "gn:dem":186,
    "gn:feature_class":"P",
    "gn:feature_code":"PPL",
    "gn:name":"A\u00efn Zeroula",
    "gn:population":0,
    "gn:timezone":"Africa/Algiers",
    "iso:country":"DZ",
    "name:und_x_variant":[
        "Mechou\u00e2r el \u2019Arab",
        "A\u00efne Zeroula",
        "A\u00efn Zeroula"
    ],
    "wof:name":"Ain Zeroula",
    "wof:placetype":"locality"
},
  "geometry": {"coordinates":[7.39375,37.02041],"type":"Point"}
}