{
  "type": "Feature",
  "properties": {
    "gn:admin1_code":"7.0",
    "gn:asciiname":"Douar Chailia",
    "gn:country_code":"DZ",
    "gn:dem":236,
    "gn:feature_class":"P",
    "gn:feature_code":"PPL",
    "gn:name":"Douar Chailia",
    "gn:population":0,
    "gn:timezone":"Africa/Algiers",
    "iso:country":"DZ",
    "wof:name":"Douar Chailia",
    "wof:placetype":"locality"
},
  "geometry": {"coordinates":[0.26922,35.91847999999999],"type":"Point"}
}