{
  "type": "Feature",
  "properties": {
    "gn:admin1_code":"6.0",
    "gn:asciiname":"Ouled Znine",
    "gn:country_code":"DZ",
    "gn:dem":894,
    "gn:feature_class":"P",
    "gn:feature_code":"PPL",
    "gn:name":"Ouled Znine",
    "gn:population":0,
    "gn:timezone":"Africa/Algiers",
    "iso:country":"DZ",
    "wof:name":"Ouled Znine",
    "wof:placetype":"locality"
},
  "geometry": {"coordinates":[3.37739,36.04991],"type":"Point"}
}