{
  "type": "Feature",
  "properties": {
    "iso:country":"DZ",
    "name:ara_x_preferred":[
        "\u0627\u0644\u0634\u0641\u0629"
    ],
    "name:ceb_x_preferred":[
        "Chiffa"
    ],
    "name:eng_x_preferred":[
        "Chiffa"
    ],
    "name:fra_x_preferred":[
        "Chiffa"
    ],
    "name:ita_x_preferred":[
        "Chiffa"
    ],
    "name:msa_x_preferred":[
        "Chiffa"
    ],
    "name:nan_x_preferred":[
        "Chiffa"
    ],
    "name:nld_x_preferred":[
        "Chiffa"
    ],
    "name:por_x_preferred":[
        "Chiffa"
    ],
    "name:ron_x_preferred":[
        "Chiffa"
    ],
    "name:spa_x_preferred":[
        "Chiffa"
    ],
    "name:swe_x_preferred":[
        "Chiffa"
    ],
    "name:unk_x_variant":[
        "La Chiffa"
    ],
    "name:urd_x_preferred":[
        "\u0634\u0641\u06c1"
    ],
    "name:vie_x_preferred":[
        "Chiffa"
    ],
    "name:zho_min_nan_x_preferred":[
        "Chiffa"
    ],
    "qs:gn_country":"DZ",
    "qs:gn_fcode":"PPL",
    "qs:gn_pop":23218,
    "qs:name":"Chiffa",
    "qs:name_adm0":"\u0627\u0644\u062c\u0632\u0627\u0626\u0631",
    "qs:name_adm1":"\u0648\u0644\u0627\u064a\u0629 \u0627\u0644\u0628\u0644\u064a\u062f\u0629",
    "qs:photos":0,
    "qs:photos_1k":0,
    "qs:photos_9k":1,
    "qs:photos_9r":1,
    "qs:photos_all":1,
    "qs:photos_sr":0,
    "qs:placetype":"Town",
    "qs:pop_sr":"7",
    "qs:woe_adm0":23424740,
    "wd:wordcount":94,
    "wof:name":"Chiffa",
    "wof:placetype":"locality",
    "wof:population":23218
},
  "geometry": {"coordinates":[2.73873,36.46293],"type":"Point"}
}