{
  "type": "Feature",
  "properties": {
    "gn:admin1_code":"3.0",
    "gn:asciiname":"Metkaouak",
    "gn:country_code":"DZ",
    "gn:dem":412,
    "gn:feature_class":"P",
    "gn:feature_code":"PPL",
    "gn:name":"Metkaouak",
    "gn:population":0,
    "gn:timezone":"Africa/Algiers",
    "iso:country":"DZ",
    "name:und_x_variant":[
        "Metgaouak",
        "Metkaouak"
    ],
    "wof:name":"Metkaouak",
    "wof:placetype":"locality"
},
  "geometry": {"coordinates":[5.17806,35.36872],"type":"Point"}
}