{
  "type": "Feature",
  "properties": {
    "gn:admin1_code":"26.0",
    "gn:asciiname":"Hadj Djilali",
    "gn:country_code":"DZ",
    "gn:dem":175,
    "gn:feature_class":"P",
    "gn:feature_code":"PPLL",
    "gn:name":"Hadj Djilali",
    "gn:population":0,
    "gn:timezone":"Africa/Algiers",
    "iso:country":"DZ",
    "name:und_x_variant":[
        "Douar Hadj Djilali",
        "Hadj Djilali"
    ],
    "wof:name":"Hadj Djilali",
    "wof:placetype":"locality"
},
  "geometry": {"coordinates":[0.22231,35.6613],"type":"Point"}
}