{
  "type": "Feature",
  "properties": {
    "gn:admin1_code":"35.0",
    "gn:asciiname":"Ouled Moussa",
    "gn:country_code":"DZ",
    "gn:dem":404,
    "gn:feature_class":"P",
    "gn:feature_code":"PPL",
    "gn:name":"Ouled Moussa",
    "gn:population":0,
    "gn:timezone":"Africa/Algiers",
    "iso:country":"DZ",
    "name:ara_x_preferred":[
        "\u0623\u0648\u0644\u0627\u062f \u0645\u0648\u0633\u0649"
    ],
    "name:ceb_x_preferred":[
        "Ouled Moussa"
    ],
    "name:fra_x_preferred":[
        "Ouled Moussa"
    ],
    "name:ita_x_preferred":[
        "Ouled Moussa"
    ],
    "name:msa_x_preferred":[
        "Ouled Moussa"
    ],
    "name:por_x_preferred":[
        "Ouled Moussa"
    ],
    "name:ron_x_preferred":[
        "Ouled Moussa"
    ],
    "name:rus_x_preferred":[
        "\u0423\u043b\u0430\u0434-\u041c\u0443\u0441\u0430"
    ],
    "name:spa_x_preferred":[
        "Ouled Moussa"
    ],
    "name:vie_x_preferred":[
        "Ouled Moussa"
    ],
    "wof:name":"Ouled Moussa",
    "wof:placetype":"locality"
},
  "geometry": {"coordinates":[1.92377,36.16797],"type":"Point"}
}