{
  "type": "Feature",
  "properties": {
    "gn:admin1_code":"18.0",
    "gn:asciiname":"Mechta Ouled Ahmar",
    "gn:country_code":"DZ",
    "gn:dem":1088,
    "gn:feature_class":"P",
    "gn:feature_code":"PPL",
    "gn:name":"Mechta Ouled Ahmar",
    "gn:population":0,
    "gn:timezone":"Africa/Algiers",
    "iso:country":"DZ",
    "name:und_x_variant":[
        "Mechtat Ouled Ahmar",
        "Mechta Ouled Ahmar"
    ],
    "wof:name":"Mechta Ouled Ahmar",
    "wof:placetype":"locality"
},
  "geometry": {"coordinates":[5.35,36.36667],"type":"Point"}
}