{
  "type": "Feature",
  "properties": {
    "gn:admin1_code":"51.0",
    "gn:asciiname":"Sidi el Bachir",
    "gn:country_code":"DZ",
    "gn:dem":49,
    "gn:feature_class":"P",
    "gn:feature_code":"PPL",
    "gn:name":"Sidi el Bachir",
    "gn:population":0,
    "gn:timezone":"Africa/Algiers",
    "iso:country":"DZ",
    "wof:name":"Sidi el Bachir",
    "wof:placetype":"locality"
},
  "geometry": {"coordinates":[0.77972,35.96611],"type":"Point"}
}