{
  "type": "Feature",
  "properties": {
    "gn:admin1_code":"51.0",
    "gn:asciiname":"Douar el Guradib",
    "gn:country_code":"DZ",
    "gn:dem":371,
    "gn:feature_class":"P",
    "gn:feature_code":"PPL",
    "gn:name":"Douar el Guradib",
    "gn:population":0,
    "gn:timezone":"Africa/Algiers",
    "iso:country":"DZ",
    "name:und_x_variant":[
        "El Gueradib",
        "Douars el Gueradib",
        "Douar el Guradib"
    ],
    "wof:name":"Douar el Guradib",
    "wof:placetype":"locality"
},
  "geometry": {"coordinates":[0.71029,35.64817],"type":"Point"}
}