{
  "type": "Feature",
  "properties": {
    "gn:admin1_code":"27.0",
    "gn:asciiname":"Mechta Louzazna",
    "gn:country_code":"DZ",
    "gn:dem":423,
    "gn:feature_class":"P",
    "gn:feature_code":"PPL",
    "gn:name":"Mechta Louzazna",
    "gn:population":0,
    "gn:timezone":"Africa/Algiers",
    "iso:country":"DZ",
    "name:und_x_variant":[
        "Mechtat Louzazna",
        "Mechta Louzazna"
    ],
    "wof:name":"Mechta Louzazna",
    "wof:placetype":"locality"
},
  "geometry": {"coordinates":[4.51312,35.60563],"type":"Point"}
}