{
  "type": "Feature",
  "properties": {
    "gn:admin1_code":"6.0",
    "gn:asciiname":"Zerouki",
    "gn:country_code":"DZ",
    "gn:dem":755,
    "gn:feature_class":"P",
    "gn:feature_code":"PPL",
    "gn:name":"Zerouki",
    "gn:population":0,
    "gn:timezone":"Africa/Algiers",
    "iso:country":"DZ",
    "wof:name":"Zerouki",
    "wof:placetype":"locality"
},
  "geometry": {"coordinates":[2.43406,35.64765999999999],"type":"Point"}
}