{
  "type": "Feature",
  "properties": {
    "gn:admin1_code":"26.0",
    "gn:asciiname":"Ahl el Aid",
    "gn:cc2":"DZ",
    "gn:country_code":"DZ",
    "gn:dem":74,
    "gn:feature_class":"P",
    "gn:feature_code":"PPL",
    "gn:name":"Ahl el A\u00efd",
    "gn:population":0,
    "gn:timezone":"Africa/Algiers",
    "iso:country":"DZ",
    "name:und_x_variant":[
        "Douar Ahl el A\u00efd",
        "Ahl el A\u00efd"
    ],
    "wof:name":"Ahl el Aid",
    "wof:placetype":"locality"
},
  "geometry": {"coordinates":[-0.26861,35.58389000000001],"type":"Point"}
}