{
  "type": "Feature",
  "properties": {
    "gn:admin1_code":"29.0",
    "gn:asciiname":"Mechta Darhar",
    "gn:country_code":"DZ",
    "gn:dem":931,
    "gn:feature_class":"P",
    "gn:feature_code":"PPL",
    "gn:name":"Mechta Darhar",
    "gn:population":0,
    "gn:timezone":"Africa/Algiers",
    "iso:country":"DZ",
    "name:und_x_variant":[
        "Mechtat Darhar",
        "Mechta Darhar"
    ],
    "wof:name":"Mechta Darhar",
    "wof:placetype":"locality"
},
  "geometry": {"coordinates":[7.56306,35.55389],"type":"Point"}
}