{
  "type": "Feature",
  "properties": {
    "gn:admin1_code":"15.0",
    "gn:asciiname":"Dar Boumediene",
    "gn:country_code":"DZ",
    "gn:dem":413,
    "gn:feature_class":"P",
    "gn:feature_code":"PPL",
    "gn:name":"Dar Boumediene",
    "gn:population":0,
    "gn:timezone":"Africa/Algiers",
    "iso:country":"DZ",
    "wof:name":"Dar Boumediene",
    "wof:placetype":"locality"
},
  "geometry": {"coordinates":[-1.93333,35.03333],"type":"Point"}
}