{
  "type": "Feature",
  "properties": {
    "gn:admin1_code":"48.0",
    "gn:asciiname":"Mechtat Beni Hameidane",
    "gn:country_code":"DZ",
    "gn:dem":440,
    "gn:feature_class":"P",
    "gn:feature_code":"PPL",
    "gn:name":"Mechtat Beni Hameidane",
    "gn:population":0,
    "gn:timezone":"Africa/Algiers",
    "iso:country":"DZ",
    "wof:name":"Mechtat Beni Hameidane",
    "wof:placetype":"locality"
},
  "geometry": {"coordinates":[6.54972,36.50556],"type":"Point"}
}