{
  "type": "Feature",
  "properties": {
    "gn:admin1_code":"41.0",
    "gn:asciiname":"'Ain Lellou",
    "gn:country_code":"DZ",
    "gn:dem":897,
    "gn:feature_class":"P",
    "gn:feature_code":"PPL",
    "gn:name":"\u2019A\u00efn Lellou",
    "gn:population":0,
    "gn:timezone":"Africa/Algiers",
    "iso:country":"DZ",
    "name:und_x_variant":[
        "A\u00efn Lelou",
        "\u2019A\u00efn Lellou"
    ],
    "wof:name":"'Ain Lellou",
    "wof:placetype":"locality"
},
  "geometry": {"coordinates":[1.56094,35.93527],"type":"Point"}
}