{
  "type": "Feature",
  "properties": {
    "gn:admin1_code":"39.0",
    "gn:asciiname":"El M'Khazene",
    "gn:country_code":"DZ",
    "gn:dem":864,
    "gn:feature_class":"P",
    "gn:feature_code":"PPL",
    "gn:name":"El M\u2019Khazene",
    "gn:population":0,
    "gn:timezone":"Africa/Algiers",
    "iso:country":"DZ",
    "name:und_x_variant":[
        "El M\u2019Krazene",
        "El M\u2019Khazene"
    ],
    "wof:name":"El M'Khazene",
    "wof:placetype":"locality"
},
  "geometry": {"coordinates":[4.7352,35.94062],"type":"Point"}
}