{
  "type": "Feature",
  "properties": {
    "gn:admin1_code":"7.0",
    "gn:asciiname":"Douar H'gagna",
    "gn:country_code":"DZ",
    "gn:dem":132,
    "gn:feature_class":"P",
    "gn:feature_code":"PPL",
    "gn:name":"Douar H\u2019gagna",
    "gn:population":0,
    "gn:timezone":"Africa/Algiers",
    "iso:country":"DZ",
    "wof:name":"Douar H'gagna",
    "wof:placetype":"locality"
},
  "geometry": {"coordinates":[0.44694,36.18028],"type":"Point"}
}