{
  "type": "Feature",
  "properties": {
    "gn:admin1_code":"31.0",
    "gn:asciiname":"Zribet Ka'ba Rhzel",
    "gn:country_code":"DZ",
    "gn:dem":137,
    "gn:feature_class":"P",
    "gn:feature_code":"PPL",
    "gn:name":"Zr\u00eebet Ka\u2019ba Rhz\u00eal",
    "gn:population":0,
    "gn:timezone":"Africa/Algiers",
    "iso:country":"DZ",
    "name:und_x_variant":[
        "Bou Begrat",
        "Zr\u00eebet Ka\u2019ba Rhz\u00eal"
    ],
    "wof:name":"Zribet Ka'ba Rhzel",
    "wof:placetype":"locality"
},
  "geometry": {"coordinates":[6.80333,36.74772],"type":"Point"}
}