{
  "type": "Feature",
  "properties": {
    "gn:admin1_code":"27.0",
    "gn:asciiname":"Hammam Dalaa",
    "gn:country_code":"DZ",
    "gn:dem":765,
    "gn:feature_class":"P",
    "gn:feature_code":"PPL",
    "gn:name":"Hammam Dalaa",
    "gn:population":0,
    "gn:timezone":"Africa/Algiers",
    "iso:country":"DZ",
    "name:und_x_variant":[
        "Hammam",
        "Hammam Dalaa"
    ],
    "wof:name":"Hammam Dalaa",
    "wof:placetype":"locality"
},
  "geometry": {"coordinates":[4.37471,35.92613],"type":"Point"}
}