{
  "type": "Feature",
  "properties": {
    "gn:admin1_code":"42.0",
    "gn:asciiname":"Tousmouline",
    "gn:country_code":"DZ",
    "gn:dem":1178,
    "gn:feature_class":"P",
    "gn:feature_code":"PPL",
    "gn:name":"Tousmouline",
    "gn:population":0,
    "gn:timezone":"Africa/Algiers",
    "iso:country":"DZ",
    "wof:name":"Tousmouline",
    "wof:placetype":"locality"
},
  "geometry": {"coordinates":[0.3086,33.65185],"type":"Point"}
}