{
  "type": "Feature",
  "properties": {
    "gn:admin1_code":"34.0",
    "gn:asciiname":"Tittaouine el Akhas",
    "gn:country_code":"DZ",
    "gn:dem":191,
    "gn:feature_class":"P",
    "gn:feature_code":"PPL",
    "gn:name":"Tittaouine el Akhas",
    "gn:population":0,
    "gn:timezone":"Africa/Algiers",
    "iso:country":"DZ",
    "wof:name":"Tittaouine el Akhas",
    "wof:placetype":"locality"
},
  "geometry": {"coordinates":[-0.10499,27.05721],"type":"Point"}
}