{
  "type": "Feature",
  "properties": {
    "gn:admin1_code":"51.0",
    "gn:asciiname":"Aouaouda",
    "gn:country_code":"DZ",
    "gn:dem":740,
    "gn:feature_class":"P",
    "gn:feature_code":"PPL",
    "gn:name":"Aouaouda",
    "gn:population":0,
    "gn:timezone":"Africa/Algiers",
    "iso:country":"DZ",
    "wof:name":"Aouaouda",
    "wof:placetype":"locality"
},
  "geometry": {"coordinates":[0.95061,35.52779],"type":"Point"}
}