{
  "type": "Feature",
  "properties": {
    "gn:admin1_code":"12.0",
    "gn:asciiname":"El Hachichia",
    "gn:country_code":"DZ",
    "gn:dem":973,
    "gn:feature_class":"P",
    "gn:feature_code":"PPL",
    "gn:name":"El Hachichia",
    "gn:population":0,
    "gn:timezone":"Africa/Algiers",
    "iso:country":"DZ",
    "wof:name":"El Hachichia",
    "wof:placetype":"locality"
},
  "geometry": {"coordinates":[5.32458,36.14544],"type":"Point"}
}