{
  "type": "Feature",
  "properties": {
    "gn:admin1_code":"14.0",
    "gn:asciiname":"Ait Aouana",
    "gn:country_code":"DZ",
    "gn:dem":706,
    "gn:feature_class":"P",
    "gn:feature_code":"PPL",
    "gn:name":"A\u00eft Aouana",
    "gn:population":0,
    "gn:timezone":"Africa/Algiers",
    "iso:country":"DZ",
    "wof:name":"Ait Aouana",
    "wof:placetype":"locality"
},
  "geometry": {"coordinates":[4.52932,36.73434],"type":"Point"}
}