{
  "type": "Feature",
  "properties": {
    "gn:admin1_code":"35.0",
    "gn:asciiname":"Douar Tadjemout",
    "gn:country_code":"DZ",
    "gn:dem":445,
    "gn:feature_class":"P",
    "gn:feature_code":"PPL",
    "gn:name":"Douar Tadjemout",
    "gn:population":0,
    "gn:timezone":"Africa/Algiers",
    "iso:country":"DZ",
    "wof:name":"Douar Tadjemout",
    "wof:placetype":"locality"
},
  "geometry": {"coordinates":[1.99105,36.07502],"type":"Point"}
}