{
  "type": "Feature",
  "properties": {
    "gn:admin1_code":"13.0",
    "gn:asciiname":"Douar Sbiba",
    "gn:country_code":"DZ",
    "gn:dem":1192,
    "gn:feature_class":"P",
    "gn:feature_code":"PPL",
    "gn:name":"Douar Sbiba",
    "gn:population":0,
    "gn:timezone":"Africa/Algiers",
    "iso:country":"DZ",
    "name:und_x_variant":[
        "Sbiba"
    ],
    "wof:name":"Douar Sbiba",
    "wof:placetype":"locality"
},
  "geometry": {"coordinates":[1.09784,35.01981],"type":"Point"}
}