{
  "type": "Feature",
  "properties": {
    "gn:admin1_code":"51.0",
    "gn:asciiname":"Douar Ouled Kaddour",
    "gn:country_code":"DZ",
    "gn:dem":54,
    "gn:feature_class":"P",
    "gn:feature_code":"PPL",
    "gn:name":"Douar Ouled Kaddour",
    "gn:population":0,
    "gn:timezone":"Africa/Algiers",
    "iso:country":"DZ",
    "name:und_x_variant":[
        "Oulad Caddour"
    ],
    "wof:name":"Douar Ouled Kaddour",
    "wof:placetype":"locality"
},
  "geometry": {"coordinates":[0.85936,35.98787],"type":"Point"}
}