{
  "type": "Feature",
  "properties": {
    "gn:admin1_code":"33.0",
    "gn:asciiname":"Hennchir Bel Frouts",
    "gn:country_code":"DZ",
    "gn:dem":984,
    "gn:feature_class":"P",
    "gn:feature_code":"PPL",
    "gn:name":"Hennchir Bel Frouts",
    "gn:population":0,
    "gn:timezone":"Africa/Algiers",
    "iso:country":"DZ",
    "wof:name":"Hennchir Bel Frouts",
    "wof:placetype":"locality"
},
  "geometry": {"coordinates":[7.83106,35.02945],"type":"Point"}
}