{
  "type": "Feature",
  "properties": {
    "gn:admin1_code":"7.0",
    "gn:asciiname":"Douar Chibia",
    "gn:country_code":"DZ",
    "gn:dem":383,
    "gn:feature_class":"P",
    "gn:feature_code":"PPL",
    "gn:name":"Douar Ch\u00efbia",
    "gn:population":0,
    "gn:timezone":"Africa/Algiers",
    "iso:country":"DZ",
    "name:und_x_variant":[
        "Douar Ch\u00efbia",
        "Douar Cha\u00efb\u00efa"
    ],
    "wof:name":"Douar Chibia",
    "wof:placetype":"locality"
},
  "geometry": {"coordinates":[0.40948,35.84689],"type":"Point"}
}