{
  "type": "Feature",
  "properties": {
    "gn:admin1_code":"10.0",
    "gn:asciiname":"Douar el Batarna",
    "gn:country_code":"DZ",
    "gn:dem":875,
    "gn:feature_class":"P",
    "gn:feature_code":"PPL",
    "gn:name":"Douar el Batarna",
    "gn:population":0,
    "gn:timezone":"Africa/Algiers",
    "iso:country":"DZ",
    "wof:name":"Douar el Batarna",
    "wof:placetype":"locality"
},
  "geometry": {"coordinates":[0.4261,35.00384],"type":"Point"}
}