{
  "type": "Feature",
  "properties": {
    "gn:admin1_code":"41.0",
    "gn:asciiname":"Ouled Ahmed",
    "gn:country_code":"DZ",
    "gn:dem":269,
    "gn:feature_class":"P",
    "gn:feature_code":"PPL",
    "gn:name":"Ouled Ahmed",
    "gn:population":0,
    "gn:timezone":"Africa/Algiers",
    "iso:country":"DZ",
    "wof:name":"Ouled Ahmed",
    "wof:placetype":"locality"
},
  "geometry": {"coordinates":[1.17069,36.41392000000001],"type":"Point"}
}