{
  "type": "Feature",
  "properties": {
    "gn:admin1_code":"30.0",
    "gn:asciiname":"Douar Chabane",
    "gn:country_code":"DZ",
    "gn:dem":600,
    "gn:feature_class":"P",
    "gn:feature_code":"PPL",
    "gn:name":"Douar Chabane",
    "gn:population":0,
    "gn:timezone":"Africa/Algiers",
    "iso:country":"DZ",
    "name:und_x_variant":[
        "Chabane",
        "Douar Chabane"
    ],
    "wof:name":"Douar Chabane",
    "wof:placetype":"locality"
},
  "geometry": {"coordinates":[-0.32779,35.2734],"type":"Point"}
}