{
  "type": "Feature",
  "properties": {
    "gn:admin1_code":"6.0",
    "gn:asciiname":"Ouled Ben Mouloud",
    "gn:country_code":"DZ",
    "gn:dem":1027,
    "gn:feature_class":"P",
    "gn:feature_code":"PPL",
    "gn:name":"Ouled Ben Mouloud",
    "gn:population":0,
    "gn:timezone":"Africa/Algiers",
    "iso:country":"DZ",
    "wof:name":"Ouled Ben Mouloud",
    "wof:placetype":"locality"
},
  "geometry": {"coordinates":[2.93186,36.2146],"type":"Point"}
}