{
  "type": "Feature",
  "properties": {
    "gn:admin1_code":"6.0",
    "gn:asciiname":"Tidjai",
    "gn:country_code":"DZ",
    "gn:dem":695,
    "gn:feature_class":"P",
    "gn:feature_code":"PPL",
    "gn:name":"Tidja\u00ef",
    "gn:population":0,
    "gn:timezone":"Africa/Algiers",
    "iso:country":"DZ",
    "wof:name":"Tidjai",
    "wof:placetype":"locality"
},
  "geometry": {"coordinates":[3.22928,36.39437],"type":"Point"}
}