{
  "type": "Feature",
  "properties": {
    "gn:admin1_code":"35.0",
    "gn:asciiname":"El Klaoucha",
    "gn:country_code":"DZ",
    "gn:dem":654,
    "gn:feature_class":"P",
    "gn:feature_code":"PPL",
    "gn:name":"El Klaoucha",
    "gn:population":0,
    "gn:timezone":"Africa/Algiers",
    "iso:country":"DZ",
    "wof:name":"El Klaoucha",
    "wof:placetype":"locality"
},
  "geometry": {"coordinates":[1.63423,36.36751],"type":"Point"}
}