{
  "type": "Feature",
  "properties": {
    "gn:country":"DZ",
    "gn:fcode":"PPL",
    "gn:pop":26662,
    "iso:country":"DZ",
    "name:ara_x_preferred":[
        "\u0628\u0648\u0642\u0627\u062f\u064a\u0631"
    ],
    "name:dut_x_preferred":[
        "Boukadir"
    ],
    "name:eng_x_preferred":[
        "Boukadir"
    ],
    "name:fre_x_preferred":[
        "Boukadir"
    ],
    "name:ita_x_preferred":[
        "Boukadir"
    ],
    "name:kab_x_preferred":[
        "Buqadir"
    ],
    "name:may_x_preferred":[
        "Boukadir"
    ],
    "name:per_x_preferred":[
        "\u0628\u0648\u0642\u0627\u062f\u06cc\u0631"
    ],
    "name:por_x_preferred":[
        "Boukadir"
    ],
    "name:rum_x_preferred":[
        "Boukadir"
    ],
    "name:rus_x_preferred":[
        "\u0411\u0443-\u041a\u0430\u0434\u0438\u0440"
    ],
    "name:swe_x_preferred":[
        "Boukadir"
    ],
    "name:unk_x_variant":[
        "Oued Ben Kader"
    ],
    "name:urd_x_preferred":[
        "\u0628\u0648\u0642\u0627\u062f\u06cc\u0631"
    ],
    "name:vie_x_preferred":[
        "Boukadir"
    ],
    "qs:name":"Boukadir",
    "qs:photos_9r":0,
    "qs:photos_sr":0,
    "qs:pop_sr":"7",
    "wd:wordcount":80,
    "wof:name":"Boukadir",
    "wof:placetype":"locality",
    "wof:population":26662
},
  "geometry": {"coordinates":[1.12602,36.06629],"type":"Point"}
}