{
  "type": "Feature",
  "properties": {
    "gn:admin1_code":"38.0",
    "gn:asciiname":"Zerhamra",
    "gn:country_code":"DZ",
    "gn:dem":506,
    "gn:feature_class":"P",
    "gn:feature_code":"PPL",
    "gn:name":"Zerhamra",
    "gn:population":0,
    "gn:timezone":"Africa/Algiers",
    "iso:country":"DZ",
    "name:ara_x_preferred":[
        "\u0627\u0644\u0632\u063a\u0627\u0645\u0631\u0629"
    ],
    "name:fra_x_preferred":[
        "Zeghamra"
    ],
    "name:pol_x_preferred":[
        "Zaghamra"
    ],
    "name:por_x_preferred":[
        "Zerhamra"
    ],
    "name:und_x_variant":[
        "Zeghamra",
        "Zegnamra",
        "Zerhamra"
    ],
    "wof:name":"Zerhamra",
    "wof:placetype":"locality"
},
  "geometry": {"coordinates":[-2.48532,29.98822],"type":"Point"}
}