{
  "type": "Feature",
  "properties": {
    "gn:admin1_code":"6.0",
    "gn:asciiname":"Ouled Amarane Gharbia",
    "gn:country_code":"DZ",
    "gn:dem":1131,
    "gn:feature_class":"P",
    "gn:feature_code":"PPL",
    "gn:name":"Ouled Amarane Gharbia",
    "gn:population":0,
    "gn:timezone":"Africa/Algiers",
    "iso:country":"DZ",
    "wof:name":"Ouled Amarane Gharbia",
    "wof:placetype":"locality"
},
  "geometry": {"coordinates":[2.76775,36.19255],"type":"Point"}
}