{
  "type": "Feature",
  "properties": {
    "gn:admin1_code":"41.0",
    "gn:asciiname":"Boukaat es Souamet",
    "gn:country_code":"DZ",
    "gn:dem":418,
    "gn:feature_class":"P",
    "gn:feature_code":"PPLL",
    "gn:name":"Boukaat es Souamet",
    "gn:population":0,
    "gn:timezone":"Africa/Algiers",
    "iso:country":"DZ",
    "wof:name":"Boukaat es Souamet",
    "wof:placetype":"locality"
},
  "geometry": {"coordinates":[1.33914,36.07478],"type":"Point"}
}