{
  "type": "Feature",
  "properties": {
    "gn:admin1_code":"14.0",
    "gn:asciiname":"Sidi Ali Moussa",
    "gn:country_code":"DZ",
    "gn:dem":484,
    "gn:feature_class":"P",
    "gn:feature_code":"PPL",
    "gn:name":"Sidi Ali Moussa",
    "gn:population":0,
    "gn:timezone":"Africa/Algiers",
    "iso:country":"DZ",
    "wof:name":"Sidi Ali Moussa",
    "wof:placetype":"locality"
},
  "geometry": {"coordinates":[3.99951,36.59169],"type":"Point"}
}