{
  "type": "Feature",
  "properties": {
    "gn:admin1_code":"40.0",
    "gn:asciiname":"Zemmouri el Bahri",
    "gn:cc2":"DZ",
    "gn:country_code":"DZ",
    "gn:dem":11,
    "gn:feature_class":"P",
    "gn:feature_code":"PPL",
    "gn:name":"Zemmouri el Bahri",
    "gn:population":0,
    "gn:timezone":"Africa/Algiers",
    "iso:country":"DZ",
    "name:ara_x_preferred":[
        "\u0632\u0645\u0648\u0631\u064a"
    ],
    "name:azb_x_preferred":[
        "\u0632\u0645\u0648\u0631\u06cc"
    ],
    "name:ber_x_preferred":[
        "\u2d5c\u2d49\u2d63\u2d49 \u2d4f \u2d30\u2d5c\u2d40 \u2d30\u0306\u2d49\u2d5b\u2d30"
    ],
    "name:fas_x_preferred":[
        "\u0632\u0645\u0648\u0631\u06cc"
    ],
    "name:fra_x_historical":[
        "Port-aux-Poules"
    ],
    "name:fra_x_preferred":[
        "Port-aux-Poules"
    ],
    "name:fra_x_variant":[
        "Zemmouri"
    ],
    "name:ita_x_preferred":[
        "Zemmouri"
    ],
    "name:kab_x_preferred":[
        "Zemmuri"
    ],
    "name:msa_x_preferred":[
        "Zemmouri"
    ],
    "name:por_x_preferred":[
        "Zemmouri"
    ],
    "name:ron_x_preferred":[
        "Zemmouri"
    ],
    "name:rus_x_preferred":[
        "\u0417\u0435\u043c\u043c\u0443\u0440\u0438"
    ],
    "name:spa_x_preferred":[
        "Zemmouri"
    ],
    "name:und_x_variant":[
        "Courbet Marine",
        "Zemmouri Bahar",
        "Zemmouri el Bahri"
    ],
    "name:vie_x_preferred":[
        "Zemmouri"
    ],
    "wof:name":"Zemmouri el Bahri",
    "wof:placetype":"locality"
},
  "geometry": {"coordinates":[3.565,36.80278],"type":"Point"}
}