{
  "type": "Feature",
  "properties": {
    "gn:country":"DZ",
    "gn:fcode":"PPL",
    "gn:pop":15030,
    "iso:country":"DZ",
    "name:ara_x_preferred":[
        "\u0622\u063a\u0631\u0627\u0645"
    ],
    "name:eng_x_preferred":[
        "Ighram"
    ],
    "name:fas_x_preferred":[
        "\u0627\u063a\u0631\u0627\u0645"
    ],
    "name:fra_x_preferred":[
        "Ighram"
    ],
    "name:ita_x_preferred":[
        "Ighram"
    ],
    "name:kab_x_preferred":[
        "I\u0263rem"
    ],
    "name:msa_x_preferred":[
        "Ighram"
    ],
    "name:nld_x_preferred":[
        "Ighram"
    ],
    "name:por_x_preferred":[
        "Ighram"
    ],
    "name:ron_x_preferred":[
        "Ighram"
    ],
    "name:swe_x_preferred":[
        "Ighram"
    ],
    "name:unk_x_variant":[
        "Irhram"
    ],
    "name:vie_x_preferred":[
        "Ighrem"
    ],
    "qs:name":"Ighram",
    "qs:photos_9r":0,
    "qs:photos_sr":0,
    "qs:pop_sr":"6",
    "wd:wordcount":271,
    "wof:name":"Ighram",
    "wof:placetype":"locality",
    "wof:population":15030
},
  "geometry": {"coordinates":[4.50532,36.46295],"type":"Point"}
}