{
  "type": "Feature",
  "properties": {
    "gn:admin1_code":"14.0",
    "gn:asciiname":"Ait Kheir",
    "gn:country_code":"DZ",
    "gn:dem":602,
    "gn:feature_class":"P",
    "gn:feature_code":"PPL",
    "gn:name":"A\u00eft Khe\u00efr",
    "gn:population":0,
    "gn:timezone":"Africa/Algiers",
    "iso:country":"DZ",
    "wof:name":"Ait Kheir",
    "wof:placetype":"locality"
},
  "geometry": {"coordinates":[4.30961,36.63202],"type":"Point"}
}