{
  "type": "Feature",
  "properties": {
    "gn:admin1_code":"34.0",
    "gn:asciiname":"Oulad Aissa",
    "gn:country_code":"DZ",
    "gn:dem":352,
    "gn:feature_class":"P",
    "gn:feature_code":"PPL",
    "gn:name":"Oulad A\u00efssa",
    "gn:population":0,
    "gn:timezone":"Africa/Algiers",
    "iso:country":"DZ",
    "name:ara_x_preferred":[
        "\u0623\u0648\u0644\u0627\u062f \u0639\u064a\u0633\u0649"
    ],
    "name:azb_x_preferred":[
        "\u0627\u0648\u0644\u0627\u062f \u0639\u06cc\u0633\u06cc"
    ],
    "name:deu_x_preferred":[
        "Ouled Aissa"
    ],
    "name:fas_x_preferred":[
        "\u0627\u0648\u0644\u0627\u062f \u0639\u06cc\u0633\u06cc"
    ],
    "name:fra_x_preferred":[
        "Ouled A\u00efssa"
    ],
    "name:ita_x_preferred":[
        "Ouled A\u00efssa"
    ],
    "name:msa_x_preferred":[
        "Ouled Aissa"
    ],
    "name:por_x_preferred":[
        "Ouled Aissa"
    ],
    "name:ron_x_preferred":[
        "Ouled A\u00efssa"
    ],
    "name:rus_x_preferred":[
        "\u0423\u043b\u0435\u0434-\u0410\u0439\u0441\u0430"
    ],
    "name:spa_x_preferred":[
        "Ouled A\u00efssa"
    ],
    "name:und_x_variant":[
        "Oulad A\u00efssa"
    ],
    "name:urd_x_preferred":[
        "\u0627\u0648\u0644\u0627\u062f \u0639\u06cc\u0633\u06cc"
    ],
    "name:vie_x_preferred":[
        "Ouled Aissa"
    ],
    "wof:name":"Oulad Aissa",
    "wof:placetype":"locality"
},
  "geometry": {"coordinates":[-0.08756,29.41836],"type":"Point"}
}