{
  "type": "Feature",
  "properties": {
    "gn:admin1_code":"34.0",
    "gn:asciiname":"Oulad Aissa",
    "gn:country_code":"DZ",
    "gn:dem":352,
    "gn:feature_class":"P",
    "gn:feature_code":"PPL",
    "gn:name":"Oulad A\u00efssa",
    "gn:population":0,
    "gn:timezone":"Africa/Algiers",
    "iso:country":"DZ",
    "name:und_x_variant":[
        "Ouled A\u00efssa",
        "Oulad A\u00efssa"
    ],
    "wof:name":"Oulad Aissa",
    "wof:placetype":"locality"
},
  "geometry": {"coordinates":[-0.08756,29.41836],"type":"Point"}
}