{
  "type": "Feature",
  "properties": {
    "gn:admin1_code":"35.0",
    "gn:asciiname":"Ouled Moussa",
    "gn:country_code":"DZ",
    "gn:dem":706,
    "gn:feature_class":"P",
    "gn:feature_code":"PPL",
    "gn:name":"Ouled Moussa",
    "gn:population":0,
    "gn:timezone":"Africa/Algiers",
    "iso:country":"DZ",
    "wof:name":"Ouled Moussa",
    "wof:placetype":"locality"
},
  "geometry": {"coordinates":[2.54729,36.24724000000001],"type":"Point"}
}