{
  "type": "Feature",
  "properties": {
    "gn:country":"DZ",
    "gn:fcode":"PPL",
    "gn:pop":40745,
    "iso:country":"DZ",
    "qs:name":"Souma",
    "qs:photos_9r":0,
    "qs:photos_sr":0,
    "qs:pop_sr":"7",
    "wd:wordcount":43,
    "wof:name":"Souma",
    "wof:placetype":"locality",
    "wof:population":40745
},
  "geometry": {"coordinates":[2.90528,36.51833],"type":"Point"}
}