{
  "type": "Feature",
  "properties": {
    "gn:admin1_code":"30.0",
    "gn:asciiname":"Chetouane",
    "gn:country_code":"DZ",
    "gn:dem":707,
    "gn:feature_class":"P",
    "gn:feature_code":"PPL",
    "gn:name":"Chetouane",
    "gn:population":0,
    "gn:timezone":"Africa/Algiers",
    "iso:country":"DZ",
    "name:ara_x_preferred":[
        "\u0634\u062a\u0648\u0627\u0646"
    ],
    "name:azb_x_preferred":[
        "\u0634\u062a\u0648\u0627\u0646"
    ],
    "name:ceb_x_preferred":[
        "Chetouane"
    ],
    "name:fas_x_preferred":[
        "\u0634\u062a\u0648\u0627\u0646"
    ],
    "name:fra_x_preferred":[
        "Chetouane"
    ],
    "name:ita_x_preferred":[
        "Chetouane"
    ],
    "name:kab_x_preferred":[
        "Ce\u1e6dwan"
    ],
    "name:msa_x_preferred":[
        "Chetouane"
    ],
    "name:por_x_preferred":[
        "Chetouane"
    ],
    "name:ron_x_preferred":[
        "Chetouane"
    ],
    "name:spa_x_preferred":[
        "Chetouane"
    ],
    "name:swe_x_preferred":[
        "Chetouane"
    ],
    "name:und_x_variant":[
        "Chitouane"
    ],
    "name:vie_x_preferred":[
        "Chetouane"
    ],
    "wof:name":"Chetouane",
    "wof:placetype":"locality"
},
  "geometry": {"coordinates":[-0.83675,34.95053],"type":"Point"}
}