{
  "type": "Feature",
  "properties": {
    "gn:admin1_code":"30.0",
    "gn:asciiname":"Chetouane",
    "gn:country_code":"DZ",
    "gn:dem":707,
    "gn:feature_class":"P",
    "gn:feature_code":"PPL",
    "gn:name":"Chetouane",
    "gn:population":0,
    "gn:timezone":"Africa/Algiers",
    "iso:country":"DZ",
    "name:und_x_variant":[
        "Chitouane",
        "Chetouane"
    ],
    "wof:name":"Chetouane",
    "wof:placetype":"locality"
},
  "geometry": {"coordinates":[-0.83675,34.95053],"type":"Point"}
}