{
  "type": "Feature",
  "properties": {
    "gn:admin1_code":"31.0",
    "gn:asciiname":"Bou el Djerad",
    "gn:country_code":"DZ",
    "gn:dem":463,
    "gn:feature_class":"P",
    "gn:feature_code":"PPL",
    "gn:name":"Bou el Djerad",
    "gn:population":0,
    "gn:timezone":"Africa/Algiers",
    "iso:country":"DZ",
    "wof:name":"Bou el Djerad",
    "wof:placetype":"locality"
},
  "geometry": {"coordinates":[6.27709,37.02075],"type":"Point"}
}