{
  "type": "Feature",
  "properties": {
    "gn:admin1_code":"33.0",
    "gn:asciiname":"El Meridj",
    "gn:country_code":"DZ",
    "gn:dem":629,
    "gn:feature_class":"P",
    "gn:feature_code":"PPL",
    "gn:name":"El Meridj",
    "gn:population":0,
    "gn:timezone":"Africa/Algiers",
    "iso:country":"DZ",
    "name:ara_x_preferred":[
        "\u0627\u0644\u0645\u0631\u064a\u062c"
    ],
    "name:azb_x_preferred":[
        "\u0645\u0631\u06cc\u062c"
    ],
    "name:fas_x_preferred":[
        "\u0645\u0631\u06cc\u062c"
    ],
    "name:fra_x_preferred":[
        "El Meridj"
    ],
    "name:ita_x_preferred":[
        "El Meridj"
    ],
    "name:msa_x_preferred":[
        "El Meridj"
    ],
    "name:por_x_preferred":[
        "El Meridj"
    ],
    "name:ron_x_preferred":[
        "El Meridj"
    ],
    "name:spa_x_preferred":[
        "El Meridj"
    ],
    "name:und_x_variant":[
        "Ancien Poste d\u2019el Meridj",
        "El Meridj"
    ],
    "name:vie_x_preferred":[
        "El Meridj"
    ],
    "name:zho_x_preferred":[
        "\u9081\u91cc\u5b63"
    ],
    "wof:name":"El Meridj",
    "wof:placetype":"locality"
},
  "geometry": {"coordinates":[8.22889,35.79335],"type":"Point"}
}