{
  "type": "Feature",
  "properties": {
    "gn:admin1_code":"33.0",
    "gn:asciiname":"El Meridj",
    "gn:country_code":"DZ",
    "gn:dem":629,
    "gn:feature_class":"P",
    "gn:feature_code":"PPL",
    "gn:name":"El Meridj",
    "gn:population":0,
    "gn:timezone":"Africa/Algiers",
    "iso:country":"DZ",
    "name:und_x_variant":[
        "Ancien Poste d\u2019el Meridj",
        "El Meridj"
    ],
    "wof:name":"El Meridj",
    "wof:placetype":"locality"
},
  "geometry": {"coordinates":[8.22889,35.79335],"type":"Point"}
}