{
  "type": "Feature",
  "properties": {
    "gn:admin1_code":"36.0",
    "gn:asciiname":"Djafra",
    "gn:country_code":"DZ",
    "gn:dem":105,
    "gn:feature_class":"P",
    "gn:feature_code":"PPL",
    "gn:name":"Djafra",
    "gn:population":0,
    "gn:timezone":"Africa/Algiers",
    "iso:country":"DZ",
    "wof:name":"Djafra",
    "wof:placetype":"locality"
},
  "geometry": {"coordinates":[-0.5982,35.48191],"type":"Point"}
}