{
  "type": "Feature",
  "properties": {
    "gn:admin1_code":"6.0",
    "gn:asciiname":"Ain Dhab",
    "gn:country_code":"DZ",
    "gn:dem":915,
    "gn:feature_class":"P",
    "gn:feature_code":"PPL",
    "gn:name":"A\u00efn Dhab",
    "gn:population":0,
    "gn:timezone":"Africa/Algiers",
    "iso:country":"DZ",
    "name:und_x_variant":[
        "Esmar",
        "Damiette",
        "A\u00efn Dhab"
    ],
    "wof:name":"Ain Dhab",
    "wof:placetype":"locality"
},
  "geometry": {"coordinates":[2.78464,36.26342],"type":"Point"}
}