{
  "type": "Feature",
  "properties": {
    "gn:admin1_code":"13.0",
    "gn:asciiname":"Douar Snais",
    "gn:country_code":"DZ",
    "gn:dem":807,
    "gn:feature_class":"P",
    "gn:feature_code":"PPL",
    "gn:name":"Douar Sna\u00efs",
    "gn:population":0,
    "gn:timezone":"Africa/Algiers",
    "iso:country":"DZ",
    "wof:name":"Douar Snais",
    "wof:placetype":"locality"
},
  "geometry": {"coordinates":[1.12316,35.24993],"type":"Point"}
}