{
  "type": "Feature",
  "properties": {
    "gn:admin1_code":"7.0",
    "gn:asciiname":"Cite ech Chegga",
    "gn:country_code":"DZ",
    "gn:dem":29,
    "gn:feature_class":"P",
    "gn:feature_code":"PPL",
    "gn:name":"Cit\u00e9 ech Chegga",
    "gn:population":0,
    "gn:timezone":"Africa/Algiers",
    "iso:country":"DZ",
    "wof:name":"Cite ech Chegga",
    "wof:placetype":"locality"
},
  "geometry": {"coordinates":[0.06226,35.78751],"type":"Point"}
}