{
  "type": "Feature",
  "properties": {
    "iso:country":"DZ",
    "name:ara_x_preferred":[
        "\u0639\u064a\u0646 \u0627\u0644\u062d\u062c\u0631"
    ],
    "name:azb_x_preferred":[
        "\u0639\u06cc\u0646 \u062d\u062c\u0631"
    ],
    "name:eng_x_preferred":[
        "A\u00efn El Hadjar"
    ],
    "name:fas_x_preferred":[
        "\u0639\u06cc\u0646 \u0627\u0644\u062d\u062c\u0631"
    ],
    "name:fas_x_variant":[
        "\u0639\u06cc\u0646 \u062d\u062c\u0631"
    ],
    "name:fra_x_preferred":[
        "A\u00efn El Hadjar"
    ],
    "name:ita_x_preferred":[
        "A\u00efn El Hadjar"
    ],
    "name:kab_x_preferred":[
        "\u0190in Le\u1e25jar"
    ],
    "name:msa_x_preferred":[
        "Ain El Hadjar"
    ],
    "name:msa_x_variant":[
        "A\u00efn El Hadjar"
    ],
    "name:nan_x_preferred":[
        "A\u00efn El Hadjar"
    ],
    "name:nld_x_preferred":[
        "A\u00efn El Hadjar"
    ],
    "name:por_x_preferred":[
        "Ain El Hadjar"
    ],
    "name:por_x_variant":[
        "A\u00efn El Hadjar"
    ],
    "name:ron_x_preferred":[
        "A\u00efn El Hadjar"
    ],
    "name:spa_x_preferred":[
        "A\u00efn El Hadjar"
    ],
    "name:und_x_variant":[
        "A\u00efne el Hadjar"
    ],
    "name:urd_x_preferred":[
        "\u0639\u06cc\u0646 \u0627\u0644\u062d\u062c\u0631"
    ],
    "name:vie_x_preferred":[
        "Ain El Hadjar"
    ],
    "qs:gn_country":"DZ",
    "qs:gn_fcode":"PPL",
    "qs:gn_pop":12996,
    "qs:name":"'Ain el Hadjar",
    "qs:name_adm0":"\u0627\u0644\u062c\u0632\u0627\u0626\u0631",
    "qs:name_adm1":"Saida",
    "qs:photos":0,
    "qs:photos_1k":0,
    "qs:photos_9k":0,
    "qs:photos_9r":0,
    "qs:photos_all":0,
    "qs:photos_sr":0,
    "qs:placetype":"Town",
    "qs:pop_sr":"6",
    "qs:woe_adm0":23424740,
    "wd:wordcount":41,
    "wof:name":"'Ain el Hadjar",
    "wof:placetype":"locality",
    "wof:population":12996
},
  "geometry": {"coordinates":[0.14528,34.75846],"type":"Point"}
}