{
  "type": "Feature",
  "properties": {
    "gn:admin1_code":"27.0",
    "gn:asciiname":"Meliane",
    "gn:country_code":"DZ",
    "gn:dem":518,
    "gn:feature_class":"P",
    "gn:feature_code":"PPL",
    "gn:name":"Meliane",
    "gn:population":0,
    "gn:timezone":"Africa/Algiers",
    "iso:country":"DZ",
    "name:und_x_variant":[
        "Douar Meliane",
        "Meliane"
    ],
    "wof:name":"Meliane",
    "wof:placetype":"locality"
},
  "geometry": {"coordinates":[4.72778,35.69667000000001],"type":"Point"}
}