{
  "type": "Feature",
  "properties": {
    "gn:admin1_code":"41.0",
    "gn:asciiname":"Douar el Braguich",
    "gn:country_code":"DZ",
    "gn:dem":340,
    "gn:feature_class":"P",
    "gn:feature_code":"PPL",
    "gn:name":"Douar el Braguich",
    "gn:population":0,
    "gn:timezone":"Africa/Algiers",
    "iso:country":"DZ",
    "wof:name":"Douar el Braguich",
    "wof:placetype":"locality"
},
  "geometry": {"coordinates":[1.37405,36.4212],"type":"Point"}
}