{
  "type": "Feature",
  "properties": {
    "gn:admin1_code":"12.0",
    "gn:asciiname":"Mechta Timdiouines",
    "gn:country_code":"DZ",
    "gn:dem":953,
    "gn:feature_class":"P",
    "gn:feature_code":"PPL",
    "gn:name":"Mechta Timdiouines",
    "gn:population":0,
    "gn:timezone":"Africa/Algiers",
    "iso:country":"DZ",
    "wof:name":"Mechta Timdiouines",
    "wof:placetype":"locality"
},
  "geometry": {"coordinates":[5.7245,35.86453],"type":"Point"}
}