{
  "type": "Feature",
  "properties": {
    "gn:admin1_code":"51.0",
    "gn:asciiname":"Douar el Homr",
    "gn:country_code":"DZ",
    "gn:dem":80,
    "gn:feature_class":"P",
    "gn:feature_code":"PPL",
    "gn:name":"Douar el Homr",
    "gn:population":0,
    "gn:timezone":"Africa/Algiers",
    "iso:country":"DZ",
    "name:und_x_variant":[
        "Mechtat el Homor"
    ],
    "wof:name":"Douar el Homr",
    "wof:placetype":"locality"
},
  "geometry": {"coordinates":[0.66624,35.8952],"type":"Point"}
}