{
  "type": "Feature",
  "properties": {
    "gn:admin1_code":"14.0",
    "gn:asciiname":"Ait Braham",
    "gn:country_code":"DZ",
    "gn:dem":337,
    "gn:feature_class":"P",
    "gn:feature_code":"PPL",
    "gn:name":"A\u00eft Braham",
    "gn:population":0,
    "gn:timezone":"Africa/Algiers",
    "iso:country":"DZ",
    "wof:name":"Ait Braham",
    "wof:placetype":"locality"
},
  "geometry": {"coordinates":[4.14542,36.74967],"type":"Point"}
}