{
  "type": "Feature",
  "properties": {
    "gn:admin1_code":"12.0",
    "gn:asciiname":"Mechta Baararou",
    "gn:country_code":"DZ",
    "gn:dem":900,
    "gn:feature_class":"P",
    "gn:feature_code":"PPL",
    "gn:name":"Mechta Baararou",
    "gn:population":0,
    "gn:timezone":"Africa/Algiers",
    "iso:country":"DZ",
    "wof:name":"Mechta Baararou",
    "wof:placetype":"locality"
},
  "geometry": {"coordinates":[5.74068,35.9483],"type":"Point"}
}