{
  "type": "Feature",
  "properties": {
    "gn:admin1_code":"7.0",
    "gn:asciiname":"Sidi Bouzid",
    "gn:country_code":"DZ",
    "gn:dem":329,
    "gn:feature_class":"P",
    "gn:feature_code":"PPL",
    "gn:name":"Sidi Bouzid",
    "gn:population":0,
    "gn:timezone":"Africa/Algiers",
    "iso:country":"DZ",
    "name:und_x_variant":[
        "Douar Sidi Bouzid",
        "Sidi Bouzid"
    ],
    "wof:name":"Sidi Bouzid",
    "wof:placetype":"locality"
},
  "geometry": {"coordinates":[0.44877,35.94297],"type":"Point"}
}