{
  "type": "Feature",
  "properties": {
    "iso:country":"DZ",
    "name:ara_x_preferred":[
        "\u0639\u0632\u0627\u0632\u0642\u0629"
    ],
    "name:bre_x_preferred":[
        "Azazga"
    ],
    "name:ceb_x_preferred":[
        "Azazga"
    ],
    "name:eng_x_preferred":[
        "Azazga"
    ],
    "name:fas_x_preferred":[
        "\u0639\u0632\u0627\u0632\u0642\u0647"
    ],
    "name:fra_x_preferred":[
        "Azazga"
    ],
    "name:ita_x_preferred":[
        "Azazga"
    ],
    "name:kab_x_preferred":[
        "I\u025be\u1e93\u1e93ugen"
    ],
    "name:msa_x_preferred":[
        "Azazga"
    ],
    "name:nld_x_preferred":[
        "Azazga"
    ],
    "name:por_x_preferred":[
        "Azazga"
    ],
    "name:ron_x_preferred":[
        "Azazga"
    ],
    "name:swe_x_preferred":[
        "Azazga"
    ],
    "name:unk_x_variant":[
        "Agagza"
    ],
    "name:vie_x_preferred":[
        "Azazga"
    ],
    "name:zho_min_nan_x_preferred":[
        "Azazga"
    ],
    "qs:gn_country":"DZ",
    "qs:gn_fcode":"PPL",
    "qs:gn_pop":40623,
    "qs:name":"Azazga",
    "qs:name_adm0":"\u0627\u0644\u062c\u0632\u0627\u0626\u0631",
    "qs:name_adm1":"\u0648\u0644\u0627\u064a\u0629 \u062a\u064a\u0632\u064a \u0648\u0632\u0648",
    "qs:photos":0,
    "qs:photos_1k":0,
    "qs:photos_9k":1,
    "qs:photos_9r":1,
    "qs:photos_all":1,
    "qs:photos_sr":0,
    "qs:placetype":"Town",
    "qs:pop_sr":"7",
    "qs:woe_adm0":23424740,
    "wd:wordcount":410,
    "wof:name":"Azazga",
    "wof:placetype":"locality",
    "wof:population":40623
},
  "geometry": {"coordinates":[4.37222,36.74472],"type":"Point"}
}