{
  "type": "Feature",
  "properties": {
    "gn:admin1_code":"41.0",
    "gn:asciiname":"Douar Tegagra",
    "gn:country_code":"DZ",
    "gn:dem":183,
    "gn:feature_class":"P",
    "gn:feature_code":"PPL",
    "gn:name":"Douar Tegagra",
    "gn:population":0,
    "gn:timezone":"Africa/Algiers",
    "iso:country":"DZ",
    "wof:name":"Douar Tegagra",
    "wof:placetype":"locality"
},
  "geometry": {"coordinates":[1.31994,36.22145],"type":"Point"}
}