{
  "type": "Feature",
  "properties": {
    "gn:admin1_code":"19.0",
    "gn:asciiname":"Djemmorah",
    "gn:country_code":"DZ",
    "gn:dem":554,
    "gn:feature_class":"P",
    "gn:feature_code":"PPL",
    "gn:name":"Djemmorah",
    "gn:population":0,
    "gn:timezone":"Africa/Algiers",
    "iso:country":"DZ",
    "name:ara_x_preferred":[
        "\u062c\u0645\u0648\u0631\u0629"
    ],
    "name:azb_x_preferred":[
        "\u062c\u0645\u0648\u0631\u0647"
    ],
    "name:fas_x_preferred":[
        "\u062c\u0645\u0648\u0631\u0647"
    ],
    "name:fra_x_preferred":[
        "Djemorah"
    ],
    "name:ita_x_preferred":[
        "Djemorah"
    ],
    "name:kab_x_preferred":[
        "At Jemmurt"
    ],
    "name:msa_x_preferred":[
        "Djemorah"
    ],
    "name:por_x_preferred":[
        "Djemorah"
    ],
    "name:ron_x_preferred":[
        "Djemorah"
    ],
    "name:spa_x_preferred":[
        "Djemorah"
    ],
    "name:und_x_variant":[
        "El Bir Djemora",
        "Djemmorah"
    ],
    "name:vie_x_preferred":[
        "Djemorah"
    ],
    "wof:name":"Djemmorah",
    "wof:placetype":"locality"
},
  "geometry": {"coordinates":[5.84265,35.07025],"type":"Point"}
}