{
  "type": "Feature",
  "properties": {
    "gn:admin1_code":"51.0",
    "gn:asciiname":"Douar Laadjaimia",
    "gn:country_code":"DZ",
    "gn:dem":242,
    "gn:feature_class":"P",
    "gn:feature_code":"PPLL",
    "gn:name":"Douar La\u00e2dja\u00efmia",
    "gn:population":0,
    "gn:timezone":"Africa/Algiers",
    "iso:country":"DZ",
    "wof:name":"Douar Laadjaimia",
    "wof:placetype":"locality"
},
  "geometry": {"coordinates":[0.6463,35.64380999999999],"type":"Point"}
}