{
  "type": "Feature",
  "properties": {
    "gn:admin1_code":"29.0",
    "gn:asciiname":"Mechta Kef el Hassi",
    "gn:country_code":"DZ",
    "gn:dem":904,
    "gn:feature_class":"P",
    "gn:feature_code":"PPL",
    "gn:name":"Mechta Kef el Hassi",
    "gn:population":0,
    "gn:timezone":"Africa/Algiers",
    "iso:country":"DZ",
    "wof:name":"Mechta Kef el Hassi",
    "wof:placetype":"locality"
},
  "geometry": {"coordinates":[6.49361,35.99167],"type":"Point"}
}