{
  "type": "Feature",
  "properties": {
    "gn:admin1_code":"41.0",
    "gn:asciiname":"Boukaat Bachir",
    "gn:country_code":"DZ",
    "gn:dem":79,
    "gn:feature_class":"P",
    "gn:feature_code":"PPL",
    "gn:name":"Boukaat Bachir",
    "gn:population":0,
    "gn:timezone":"Africa/Algiers",
    "iso:country":"DZ",
    "name:und_x_variant":[
        "El Bachiria"
    ],
    "wof:name":"Boukaat Bachir",
    "wof:placetype":"locality"
},
  "geometry": {"coordinates":[1.15639,36.08072],"type":"Point"}
}