{
  "type": "Feature",
  "properties": {
    "gn:admin1_code":"37.0",
    "gn:asciiname":"Henchir Mokhtar Abdullah el Medjid",
    "gn:country_code":"DZ",
    "gn:dem":69,
    "gn:feature_class":"P",
    "gn:feature_code":"PPL",
    "gn:name":"Henchir Mokhtar Abdullah el Medjid",
    "gn:population":0,
    "gn:timezone":"Africa/Algiers",
    "iso:country":"DZ",
    "wof:name":"Henchir Mokhtar Abdullah el Medjid",
    "wof:placetype":"locality"
},
  "geometry": {"coordinates":[7.70833,36.63889],"type":"Point"}
}