{
  "type": "Feature",
  "properties": {
    "gn:admin1_code":"10.0",
    "gn:asciiname":"Hammam Rabbi",
    "gn:cc2":"DZ",
    "gn:country_code":"DZ",
    "gn:dem":625,
    "gn:feature_class":"P",
    "gn:feature_code":"PPL",
    "gn:name":"Hammam Rabbi",
    "gn:population":0,
    "gn:timezone":"Africa/Algiers",
    "iso:country":"DZ",
    "name:und_x_variant":[
        "Hamman Rabbi",
        "Hammam Rabbi"
    ],
    "wof:name":"Hammam Rabbi",
    "wof:placetype":"locality"
},
  "geometry": {"coordinates":[0.16667,34.96667],"type":"Point"}
}