{
  "type": "Feature",
  "properties": {
    "iso:country":"DZ",
    "name:ara_x_preferred":[
        "La Marine"
    ],
    "name:ces_x_preferred":[
        "Mus\u00e9e national de la Marine"
    ],
    "name:deu_x_preferred":[
        "Mus\u00e9e national de la Marine"
    ],
    "name:fin_x_preferred":[
        "Mus\u00e9e national de la Marine"
    ],
    "name:fra_x_preferred":[
        "Mus\u00e9e national de la Marine"
    ],
    "name:ind_x_preferred":[
        "Mus\u00e9e de la Marine"
    ],
    "name:ita_x_preferred":[
        "Museo nazionale della marina"
    ],
    "name:jav_x_preferred":[
        "Museum Nasional De La Marine"
    ],
    "name:oci_x_preferred":[
        "Mus\u00e8u de la Marina de Par\u00eds"
    ],
    "name:slv_x_preferred":[
        "Mus\u00e9e national de la Marine"
    ],
    "name:unk_x_variant":[
        "La Marine"
    ],
    "name:vie_x_preferred":[
        "Mus\u00e9e national de la Marine"
    ],
    "qs:gn_adm0_cc":"DZ",
    "qs:gn_fcode":"PPLX",
    "qs:gn_local":2487134,
    "qs:gn_namadm1":"07",
    "qs:gn_name":"La Marine",
    "qs:local_max":136,
    "qs:local_sum":136,
    "qs:localhoods":1,
    "qs:name":"La Marine",
    "qs:name_adm0":"\u0627\u0644\u062c\u0632\u0627\u0626\u0631",
    "qs:name_adm1":"\u0648\u0644\u0627\u064a\u0629 \u0645\u0633\u062a\u063a\u0627\u0646\u0645",
    "qs:name_local":"\u0648\u0644\u0627\u064a\u0629 \u0645\u0633\u062a\u063a\u0627\u0646\u0645",
    "qs:photo_max":24,
    "qs:photo_sum":136,
    "qs:placetype":"Suburb",
    "qs:quad_count":22,
    "qs:woe_adm0":23424740,
    "qs:woe_adm1":2344583,
    "qs:woe_adm2":0,
    "qs:woe_lau":0,
    "qs:woe_local":1256487,
    "qs:woe_ver":"7.10.0",
    "wof:lang":[
        "ara"
    ],
    "wof:name":"La Marine",
    "wof:placetype":"neighbourhood"
},
  "geometry": {"coordinates":[0.08648,35.934983],"type":"Point"}
}