{
  "type": "Feature",
  "properties": {
    "gn:admin1_code":"51.0",
    "gn:asciiname":"Tirasse Sbaa",
    "gn:country_code":"DZ",
    "gn:dem":492,
    "gn:feature_class":"P",
    "gn:feature_code":"PPL",
    "gn:name":"Tirasse Sba\u00e2",
    "gn:population":0,
    "gn:timezone":"Africa/Algiers",
    "iso:country":"DZ",
    "wof:name":"Tirasse Sbaa",
    "wof:placetype":"locality"
},
  "geometry": {"coordinates":[0.78468,35.52211],"type":"Point"}
}