{
  "type": "Feature",
  "properties": {
    "gn:admin1_code":"25.0",
    "gn:asciiname":"Ksar Kabeg",
    "gn:country_code":"DZ",
    "gn:dem":698,
    "gn:feature_class":"P",
    "gn:feature_code":"PPL",
    "gn:name":"Ksar Kabeg",
    "gn:population":0,
    "gn:timezone":"Africa/Algiers",
    "iso:country":"DZ",
    "wof:name":"Ksar Kabeg",
    "wof:placetype":"locality"
},
  "geometry": {"coordinates":[3.18387,33.83132],"type":"Point"}
}