{
  "type": "Feature",
  "properties": {
    "gn:admin1_code":"41.0",
    "gn:asciiname":"Khantchoufene",
    "gn:country_code":"DZ",
    "gn:dem":395,
    "gn:feature_class":"P",
    "gn:feature_code":"PPL",
    "gn:name":"Khantchouf\u00e9ne",
    "gn:population":0,
    "gn:timezone":"Africa/Algiers",
    "iso:country":"DZ",
    "name:und_x_variant":[
        "Khantchouf\u00e9ne",
        "Kannchouffene"
    ],
    "wof:name":"Khantchoufene",
    "wof:placetype":"locality"
},
  "geometry": {"coordinates":[1.60514,36.02195],"type":"Point"}
}