{
  "type": "Feature",
  "properties": {
    "gn:admin1_code":"35.0",
    "gn:asciiname":"Tizgha",
    "gn:country_code":"DZ",
    "gn:dem":464,
    "gn:feature_class":"P",
    "gn:feature_code":"PPL",
    "gn:name":"Tizgha",
    "gn:population":0,
    "gn:timezone":"Africa/Algiers",
    "iso:country":"DZ",
    "wof:name":"Tizgha",
    "wof:placetype":"locality"
},
  "geometry": {"coordinates":[1.96734,36.17206],"type":"Point"}
}