{
  "type": "Feature",
  "properties": {
    "gn:admin1_code":"13.0",
    "gn:asciiname":"Dar el Aoudja",
    "gn:country_code":"DZ",
    "gn:dem":696,
    "gn:feature_class":"P",
    "gn:feature_code":"PPL",
    "gn:name":"Dar el Aoudja",
    "gn:population":0,
    "gn:timezone":"Africa/Algiers",
    "iso:country":"DZ",
    "wof:name":"Dar el Aoudja",
    "wof:placetype":"locality"
},
  "geometry": {"coordinates":[0.56208,35.10385],"type":"Point"}
}