{
  "type": "Feature",
  "properties": {
    "gn:admin1_code":"4.0",
    "gn:asciiname":"Zighout Youcef",
    "gn:country_code":"DZ",
    "gn:dem":545,
    "gn:feature_class":"P",
    "gn:feature_code":"PPL",
    "gn:name":"Zighout Youcef",
    "gn:population":0,
    "gn:timezone":"Africa/Algiers",
    "iso:country":"DZ",
    "name:ara_x_preferred":[
        "\u0632\u064a\u063a\u0648\u062f \u064a\u0648\u0633\u0641"
    ],
    "name:azb_x_preferred":[
        "\u0632\u06cc\u063a\u0648\u062f \u06cc\u0648\u0633\u0641"
    ],
    "name:bre_x_preferred":[
        "Zighoud Youcef"
    ],
    "name:fas_x_preferred":[
        "\u0632\u06cc\u063a\u0648\u062f \u06cc\u0648\u0633\u0641"
    ],
    "name:fra_x_preferred":[
        "Zighoud Youcef"
    ],
    "name:ita_x_preferred":[
        "Zighoud Youcef"
    ],
    "name:msa_x_preferred":[
        "Zighoud Youcef"
    ],
    "name:por_x_preferred":[
        "Zighoud Youcef"
    ],
    "name:ron_x_preferred":[
        "Zighoud Youcef"
    ],
    "name:spa_x_preferred":[
        "Zighoud Youcef"
    ],
    "name:und_x_variant":[
        "Cond\u00e9-Smendou",
        "Zirout-Youcef",
        "Zighoud Youcef",
        "Zighet-Youssef",
        "Zighout Youcef"
    ],
    "name:vie_x_preferred":[
        "Zighoud Youcef"
    ],
    "name:zho_x_preferred":[
        "\u6fdf\u53e4\u7279\u512a\u7d20\u798f"
    ],
    "wof:name":"Zighout Youcef",
    "wof:placetype":"locality"
},
  "geometry": {"coordinates":[6.71237,36.53307],"type":"Point"}
}