{
  "type": "Feature",
  "properties": {
    "gn:admin1_code":"4.0",
    "gn:asciiname":"Zighout Youcef",
    "gn:country_code":"DZ",
    "gn:dem":545,
    "gn:feature_class":"P",
    "gn:feature_code":"PPL",
    "gn:name":"Zighout Youcef",
    "gn:population":0,
    "gn:timezone":"Africa/Algiers",
    "iso:country":"DZ",
    "name:und_x_variant":[
        "Cond\u00e9-Smendou",
        "Zirout-Youcef",
        "Zighoud Youcef",
        "Zighet-Youssef",
        "Zighout Youcef"
    ],
    "wof:name":"Zighout Youcef",
    "wof:placetype":"locality"
},
  "geometry": {"coordinates":[6.71237,36.53307],"type":"Point"}
}