{
  "type": "Feature",
  "properties": {
    "gn:admin1_code":"24.0",
    "gn:asciiname":"Chekfa",
    "gn:country_code":"DZ",
    "gn:dem":70,
    "gn:feature_class":"P",
    "gn:feature_code":"PPL",
    "gn:name":"Chekfa",
    "gn:population":0,
    "gn:timezone":"Africa/Algiers",
    "iso:country":"DZ",
    "name:ara_x_preferred":[
        "\u0627\u0644\u0634\u0642\u0641\u0629"
    ],
    "name:azb_x_preferred":[
        "\u0634\u0642\u0641\u0647"
    ],
    "name:fas_x_preferred":[
        "\u0634\u0642\u0641\u0647"
    ],
    "name:fra_x_preferred":[
        "Chekfa"
    ],
    "name:ita_x_preferred":[
        "Chekfa"
    ],
    "name:msa_x_preferred":[
        "Chekfa"
    ],
    "name:por_x_preferred":[
        "Chekfa"
    ],
    "name:ron_x_preferred":[
        "Chekfa"
    ],
    "name:spa_x_preferred":[
        "Chekfa"
    ],
    "name:vie_x_preferred":[
        "Chekfa"
    ],
    "name:zho_x_preferred":[
        "\u820d\u514b\u6cd5"
    ],
    "wof:name":"Chekfa",
    "wof:placetype":"locality"
},
  "geometry": {"coordinates":[5.95728,36.7723],"type":"Point"}
}