{
  "type": "Feature",
  "properties": {
    "gn:admin1_code":"24.0",
    "gn:asciiname":"Zraa el Hadjer",
    "gn:country_code":"DZ",
    "gn:dem":705,
    "gn:feature_class":"P",
    "gn:feature_code":"PPL",
    "gn:name":"Zraa el Hadjer",
    "gn:population":0,
    "gn:timezone":"Africa/Algiers",
    "iso:country":"DZ",
    "wof:name":"Zraa el Hadjer",
    "wof:placetype":"locality"
},
  "geometry": {"coordinates":[5.55616,36.60789000000001],"type":"Point"}
}