{
  "type": "Feature",
  "properties": {
    "gn:admin1_code":"7.0",
    "gn:asciiname":"El Mhailia",
    "gn:country_code":"DZ",
    "gn:dem":89,
    "gn:feature_class":"P",
    "gn:feature_code":"PPL",
    "gn:name":"El Mha\u00eflia",
    "gn:population":0,
    "gn:timezone":"Africa/Algiers",
    "iso:country":"DZ",
    "wof:name":"El Mhailia",
    "wof:placetype":"locality"
},
  "geometry": {"coordinates":[0.10294,35.81544],"type":"Point"}
}