{
  "type": "Feature",
  "properties": {
    "gn:admin1_code":"53.0",
    "gn:asciiname":"El Barka",
    "gn:country_code":"DZ",
    "gn:dem":265,
    "gn:feature_class":"P",
    "gn:feature_code":"PPL",
    "gn:name":"El Barka",
    "gn:population":0,
    "gn:timezone":"Africa/Algiers",
    "iso:country":"DZ",
    "name:por_x_preferred":[
        "El Barka"
    ],
    "wof:name":"El Barka",
    "wof:placetype":"locality"
},
  "geometry": {"coordinates":[2.43186,27.1736],"type":"Point"}
}