{
  "type": "Feature",
  "properties": {
    "gn:admin1_code":"3.0",
    "gn:asciiname":"Ben Hebal",
    "gn:country_code":"DZ",
    "gn:dem":689,
    "gn:feature_class":"P",
    "gn:feature_code":"PPL",
    "gn:name":"Ben Hebal",
    "gn:population":0,
    "gn:timezone":"Africa/Algiers",
    "iso:country":"DZ",
    "wof:name":"Ben Hebal",
    "wof:placetype":"locality"
},
  "geometry": {"coordinates":[5.57643,35.43703],"type":"Point"}
}