{
  "type": "Feature",
  "properties": {
    "gn:admin1_code":"39.0",
    "gn:asciiname":"Mechta Guemmour",
    "gn:country_code":"DZ",
    "gn:dem":989,
    "gn:feature_class":"P",
    "gn:feature_code":"PPL",
    "gn:name":"Mechta Guemmour",
    "gn:population":0,
    "gn:timezone":"Africa/Algiers",
    "iso:country":"DZ",
    "name:und_x_variant":[
        "Mechtat Guemmour",
        "Mechta Guemmour"
    ],
    "wof:name":"Mechta Guemmour",
    "wof:placetype":"locality"
},
  "geometry": {"coordinates":[4.88427,36.03231],"type":"Point"}
}