{
  "type": "Feature",
  "properties": {
    "gn:admin1_code":"41.0",
    "gn:asciiname":"Imoumnayan",
    "gn:country_code":"DZ",
    "gn:dem":587,
    "gn:feature_class":"P",
    "gn:feature_code":"PPL",
    "gn:name":"Imoumnayan",
    "gn:population":0,
    "gn:timezone":"Africa/Algiers",
    "iso:country":"DZ",
    "wof:name":"Imoumnayan",
    "wof:placetype":"locality"
},
  "geometry": {"coordinates":[1.63685,36.37509],"type":"Point"}
}