{
  "type": "Feature",
  "properties": {
    "gn:admin1_code":"21.0",
    "gn:asciiname":"Mechta Talamine",
    "gn:country_code":"DZ",
    "gn:dem":548,
    "gn:feature_class":"P",
    "gn:feature_code":"PPL",
    "gn:name":"Mechta Talamine",
    "gn:population":0,
    "gn:timezone":"Africa/Algiers",
    "iso:country":"DZ",
    "name:und_x_variant":[
        "Mechtat Talamine",
        "Mechta Talamine"
    ],
    "wof:name":"Mechta Talamine",
    "wof:placetype":"locality"
},
  "geometry": {"coordinates":[3.96363,36.24762],"type":"Point"}
}