{
  "type": "Feature",
  "properties": {
    "gn:admin1_code":"51.0",
    "gn:asciiname":"Douar Mesmoud",
    "gn:country_code":"DZ",
    "gn:dem":197,
    "gn:feature_class":"P",
    "gn:feature_code":"PPL",
    "gn:name":"Douar Mesmoud",
    "gn:population":0,
    "gn:timezone":"Africa/Algiers",
    "iso:country":"DZ",
    "wof:name":"Douar Mesmoud",
    "wof:placetype":"locality"
},
  "geometry": {"coordinates":[0.65125,35.50552000000001],"type":"Point"}
}