{
  "type": "Feature",
  "properties": {
    "iso:country":"DZ",
    "name:und_x_variant":[
        "L\u2019 Esp\u00e9rance"
    ],
    "qs:gn_country":"DZ",
    "qs:gn_fcode":"PPLX",
    "qs:gn_pop":0,
    "qs:name":"Faubourg de l'Esp\u00e9rance",
    "qs:name_adm0":"\u0627\u0644\u062c\u0632\u0627\u0626\u0631",
    "qs:name_adm1":"\u0648\u0644\u0627\u064a\u0629 \u0633\u0643\u064a\u0643\u062f\u0629",
    "qs:photos":89,
    "qs:photos_1k":18,
    "qs:photos_9k":1,
    "qs:photos_9r":3,
    "qs:photos_all":89,
    "qs:photos_sr":3,
    "qs:placetype":"Suburb",
    "qs:pop_sr":"0",
    "qs:woe_adm0":23424740,
    "wof:name":"Faubourg de l'Esp\u00e9rance",
    "wof:placetype":"neighbourhood"
},
  "geometry": {"coordinates":[6.8988,36.87396],"type":"Point"}
}