{
  "type": "Feature",
  "properties": {
    "gn:admin1_code":"31.0",
    "gn:asciiname":"Guenguita",
    "gn:cc2":"DZ",
    "gn:country_code":"DZ",
    "gn:dem":117,
    "gn:feature_class":"P",
    "gn:feature_code":"PPL",
    "gn:name":"Guenguita",
    "gn:population":0,
    "gn:timezone":"Africa/Algiers",
    "iso:country":"DZ",
    "name:und_x_variant":[
        "Guenquira",
        "Guenguita"
    ],
    "wof:name":"Guenguita",
    "wof:placetype":"locality"
},
  "geometry": {"coordinates":[6.64944,36.71361],"type":"Point"}
}