{
  "type": "Feature",
  "properties": {
    "gn:admin1_code":"34.0",
    "gn:asciiname":"Bou Ali",
    "gn:country_code":"DZ",
    "gn:dem":202,
    "gn:feature_class":"P",
    "gn:feature_code":"PPL",
    "gn:name":"Bou Ali",
    "gn:population":0,
    "gn:timezone":"Africa/Algiers",
    "iso:country":"DZ",
    "wof:name":"Bou Ali",
    "wof:placetype":"locality"
},
  "geometry": {"coordinates":[-0.13885,27.1538],"type":"Point"}
}