{
  "type": "Feature",
  "properties": {
    "gn:admin1_code":"3.0",
    "gn:asciiname":"Takroumt Aouana",
    "gn:country_code":"DZ",
    "gn:dem":520,
    "gn:feature_class":"P",
    "gn:feature_code":"PPL",
    "gn:name":"Takroumt Aouana",
    "gn:population":0,
    "gn:timezone":"Africa/Algiers",
    "iso:country":"DZ",
    "wof:name":"Takroumt Aouana",
    "wof:placetype":"locality"
},
  "geometry": {"coordinates":[6.03956,34.97708],"type":"Point"}
}