{
  "type": "Feature",
  "properties": {
    "gn:admin1_code":"26.0",
    "gn:asciiname":"El Gaidia",
    "gn:country_code":"DZ",
    "gn:dem":515,
    "gn:feature_class":"P",
    "gn:feature_code":"PPL",
    "gn:name":"El Ga\u00efdia",
    "gn:population":0,
    "gn:timezone":"Africa/Algiers",
    "iso:country":"DZ",
    "wof:name":"El Gaidia",
    "wof:placetype":"locality"
},
  "geometry": {"coordinates":[0.24839,35.40479000000001],"type":"Point"}
}