{
  "type": "Feature",
  "properties": {
    "gn:admin1_code":"34.0",
    "gn:asciiname":"Anzeglouf",
    "gn:country_code":"DZ",
    "gn:dem":183,
    "gn:feature_class":"P",
    "gn:feature_code":"PPL",
    "gn:name":"Anzeglouf",
    "gn:population":0,
    "gn:timezone":"Africa/Algiers",
    "iso:country":"DZ",
    "wof:name":"Anzeglouf",
    "wof:placetype":"locality"
},
  "geometry": {"coordinates":[0.02951,26.82219000000001],"type":"Point"}
}