{
  "type": "Feature",
  "properties": {
    "gn:admin1_code":"51.0",
    "gn:asciiname":"El Araissia",
    "gn:country_code":"DZ",
    "gn:dem":653,
    "gn:feature_class":"P",
    "gn:feature_code":"PPL",
    "gn:name":"El Ara\u00efssia",
    "gn:population":0,
    "gn:timezone":"Africa/Algiers",
    "iso:country":"DZ",
    "name:und_x_variant":[
        "Douar el Ara\u00efssia",
        "El Ara\u00efssia"
    ],
    "wof:name":"El Araissia",
    "wof:placetype":"locality"
},
  "geometry": {"coordinates":[0.95289,35.60834000000001],"type":"Point"}
}