{
  "type": "Feature",
  "properties": {
    "gn:admin1_code":"51.0",
    "gn:asciiname":"Ouled Amara",
    "gn:country_code":"DZ",
    "gn:dem":286,
    "gn:feature_class":"P",
    "gn:feature_code":"PPL",
    "gn:name":"Ouled Amara",
    "gn:population":0,
    "gn:timezone":"Africa/Algiers",
    "iso:country":"DZ",
    "wof:name":"Ouled Amara",
    "wof:placetype":"locality"
},
  "geometry": {"coordinates":[0.82355,35.43345],"type":"Point"}
}