{
  "type": "Feature",
  "properties": {
    "iso:country":"DZ",
    "name:ara_x_preferred":[
        "\u062e\u0631\u0627\u0637\u0629"
    ],
    "name:ara_x_variant":[
        "\u062e\u0631\u0627\u0637\u0629\u060c\u0628\u062c\u0627\u064a\u0629"
    ],
    "name:azb_x_preferred":[
        "\u062e\u0631\u0627\u0637\u0647"
    ],
    "name:eng_x_preferred":[
        "Kherrata"
    ],
    "name:fas_x_preferred":[
        "\u062e\u0631\u0627\u0637\u0647"
    ],
    "name:fra_x_preferred":[
        "Kherrata"
    ],
    "name:ita_x_preferred":[
        "Kherrata"
    ],
    "name:kab_x_preferred":[
        "Xerra\u1e6d\u1e6da"
    ],
    "name:msa_x_preferred":[
        "Kherrata"
    ],
    "name:nan_x_preferred":[
        "Kherrata"
    ],
    "name:nld_x_preferred":[
        "Kherrata"
    ],
    "name:por_x_preferred":[
        "Kherrata"
    ],
    "name:ron_x_preferred":[
        "Kherrata"
    ],
    "name:spa_x_preferred":[
        "Kherrata"
    ],
    "name:unk_x_variant":[
        "Kerrato"
    ],
    "name:vie_x_preferred":[
        "Kherrata"
    ],
    "name:zho_min_nan_x_preferred":[
        "Kherrata"
    ],
    "name:zho_x_preferred":[
        "\u6d77\u62c9\u5854"
    ],
    "qs:gn_country":"DZ",
    "qs:gn_fcode":"PPL",
    "qs:gn_pop":0,
    "qs:name":"Kherrata",
    "qs:name_adm0":"\u0627\u0644\u062c\u0632\u0627\u0626\u0631",
    "qs:name_adm1":"Bejaia",
    "qs:photos":6,
    "qs:photos_1k":1,
    "qs:photos_9k":1,
    "qs:photos_9r":1,
    "qs:photos_all":6,
    "qs:photos_sr":1,
    "qs:placetype":"Town",
    "qs:pop_sr":"6",
    "qs:woe_adm0":23424740,
    "wd:wordcount":24,
    "wof:name":"Kherrata",
    "wof:placetype":"locality"
},
  "geometry": {"coordinates":[5.27802,36.49349],"type":"Point"}
}