{
  "type": "Feature",
  "properties": {
    "gn:admin1_code":"51.0",
    "gn:asciiname":"Mechta Ouled Saad",
    "gn:country_code":"DZ",
    "gn:dem":467,
    "gn:feature_class":"P",
    "gn:feature_code":"PPL",
    "gn:name":"Mechta Ouled Saad",
    "gn:population":0,
    "gn:timezone":"Africa/Algiers",
    "iso:country":"DZ",
    "wof:name":"Mechta Ouled Saad",
    "wof:placetype":"locality"
},
  "geometry": {"coordinates":[1.29274,35.8862],"type":"Point"}
}