{
  "type": "Feature",
  "properties": {
    "gn:admin1_code":"51.0",
    "gn:asciiname":"Ouled Sidi el Hadj",
    "gn:country_code":"DZ",
    "gn:dem":238,
    "gn:feature_class":"P",
    "gn:feature_code":"PPL",
    "gn:name":"Ouled Sidi el Hadj",
    "gn:population":0,
    "gn:timezone":"Africa/Algiers",
    "iso:country":"DZ",
    "wof:name":"Ouled Sidi el Hadj",
    "wof:placetype":"locality"
},
  "geometry": {"coordinates":[0.93287,35.78515],"type":"Point"}
}