{
  "type": "Feature",
  "properties": {
    "gn:admin1_code":"12.0",
    "gn:asciiname":"Ouled Ferdi",
    "gn:country_code":"DZ",
    "gn:dem":905,
    "gn:feature_class":"P",
    "gn:feature_code":"PPL",
    "gn:name":"Ouled Ferdi",
    "gn:population":0,
    "gn:timezone":"Africa/Algiers",
    "iso:country":"DZ",
    "wof:name":"Ouled Ferdi",
    "wof:placetype":"locality"
},
  "geometry": {"coordinates":[5.95444,35.87833],"type":"Point"}
}