{
  "type": "Feature",
  "properties": {
    "gn:admin1_code":"47.0",
    "gn:asciiname":"Tafrennt",
    "gn:country_code":"DZ",
    "gn:dem":1356,
    "gn:feature_class":"P",
    "gn:feature_code":"PPL",
    "gn:name":"Tafrennt",
    "gn:population":0,
    "gn:timezone":"Africa/Algiers",
    "iso:country":"DZ",
    "wof:name":"Tafrennt",
    "wof:placetype":"locality"
},
  "geometry": {"coordinates":[6.7262,35.3782],"type":"Point"}
}