{
  "type": "Feature",
  "properties": {
    "gn:admin1_code":"24.0",
    "gn:asciiname":"El Msila",
    "gn:country_code":"DZ",
    "gn:dem":663,
    "gn:feature_class":"P",
    "gn:feature_code":"PPL",
    "gn:name":"El Msila",
    "gn:population":0,
    "gn:timezone":"Africa/Algiers",
    "iso:country":"DZ",
    "wof:name":"El Msila",
    "wof:placetype":"locality"
},
  "geometry": {"coordinates":[5.67185,36.65944],"type":"Point"}
}