{
  "type": "Feature",
  "properties": {
    "gn:admin1_code":"7.0",
    "gn:asciiname":"Douar Titinguel",
    "gn:country_code":"DZ",
    "gn:dem":130,
    "gn:feature_class":"P",
    "gn:feature_code":"PPL",
    "gn:name":"Douar Titinguel",
    "gn:population":0,
    "gn:timezone":"Africa/Algiers",
    "iso:country":"DZ",
    "wof:name":"Douar Titinguel",
    "wof:placetype":"locality"
},
  "geometry": {"coordinates":[0.49333,36.21056],"type":"Point"}
}