{
  "type": "Feature",
  "properties": {
    "gn:admin1_code":"26.0",
    "gn:asciiname":"Douar Zaouia",
    "gn:country_code":"DZ",
    "gn:dem":479,
    "gn:feature_class":"P",
    "gn:feature_code":"PPLL",
    "gn:name":"Douar Zaouia",
    "gn:population":0,
    "gn:timezone":"Africa/Algiers",
    "iso:country":"DZ",
    "wof:name":"Douar Zaouia",
    "wof:placetype":"locality"
},
  "geometry": {"coordinates":[0.24499,35.34067],"type":"Point"}
}