{
  "type": "Feature",
  "properties": {
    "gn:admin1_code":"39.0",
    "gn:asciiname":"Beni Hafod",
    "gn:country_code":"DZ",
    "gn:dem":481,
    "gn:feature_class":"P",
    "gn:feature_code":"PPL",
    "gn:name":"Beni Hafod",
    "gn:population":0,
    "gn:timezone":"Africa/Algiers",
    "iso:country":"DZ",
    "name:und_x_variant":[
        "Beni Hafedh",
        "Beni Hafod"
    ],
    "wof:name":"Beni Hafod",
    "wof:placetype":"locality"
},
  "geometry": {"coordinates":[4.81054,36.39729000000001],"type":"Point"}
}