{
  "type": "Feature",
  "properties": {
    "gn:admin1_code":"35.0",
    "gn:asciiname":"Mechta Bessami Kechi",
    "gn:country_code":"DZ",
    "gn:dem":380,
    "gn:feature_class":"P",
    "gn:feature_code":"PPL",
    "gn:name":"Mechta Bessami Kechi",
    "gn:population":0,
    "gn:timezone":"Africa/Algiers",
    "iso:country":"DZ",
    "wof:name":"Mechta Bessami Kechi",
    "wof:placetype":"locality"
},
  "geometry": {"coordinates":[2.27908,36.11165],"type":"Point"}
}