{
  "type": "Feature",
  "properties": {
    "gn:admin1_code":"15.0",
    "gn:asciiname":"Oulad es Souaber",
    "gn:country_code":"DZ",
    "gn:dem":318,
    "gn:feature_class":"P",
    "gn:feature_code":"PPL",
    "gn:name":"Oulad es Souaber",
    "gn:population":0,
    "gn:timezone":"Africa/Algiers",
    "iso:country":"DZ",
    "wof:name":"Oulad es Souaber",
    "wof:placetype":"locality"
},
  "geometry": {"coordinates":[-1.58519,35.12423],"type":"Point"}
}