{
  "type": "Feature",
  "properties": {
    "gn:admin1_code":"14.0",
    "gn:asciiname":"Takribt",
    "gn:country_code":"DZ",
    "gn:dem":469,
    "gn:feature_class":"P",
    "gn:feature_code":"PPL",
    "gn:name":"Takribt",
    "gn:population":0,
    "gn:timezone":"Africa/Algiers",
    "iso:country":"DZ",
    "wof:name":"Takribt",
    "wof:placetype":"locality"
},
  "geometry": {"coordinates":[3.95179,36.63294000000001],"type":"Point"}
}