{
  "type": "Feature",
  "properties": {
    "gn:admin1_code":"35.0",
    "gn:asciiname":"Et Toug",
    "gn:country_code":"DZ",
    "gn:dem":338,
    "gn:feature_class":"P",
    "gn:feature_code":"PPL",
    "gn:name":"Et Toug",
    "gn:population":0,
    "gn:timezone":"Africa/Algiers",
    "iso:country":"DZ",
    "wof:name":"Et Toug",
    "wof:placetype":"locality"
},
  "geometry": {"coordinates":[1.99571,36.33996],"type":"Point"}
}