{
  "type": "Feature",
  "properties": {
    "gn:admin1_code":"3.0",
    "gn:asciiname":"Kef Fercha",
    "gn:country_code":"DZ",
    "gn:dem":1050,
    "gn:feature_class":"P",
    "gn:feature_code":"PPL",
    "gn:name":"Kef Fercha",
    "gn:population":0,
    "gn:timezone":"Africa/Algiers",
    "iso:country":"DZ",
    "wof:name":"Kef Fercha",
    "wof:placetype":"locality"
},
  "geometry": {"coordinates":[5.71868,35.41287],"type":"Point"}
}