{
  "type": "Feature",
  "properties": {
    "gn:admin1_code":"30.0",
    "gn:asciiname":"La Maison Blanche",
    "gn:country_code":"DZ",
    "gn:dem":552,
    "gn:feature_class":"P",
    "gn:feature_code":"PPL",
    "gn:name":"La Maison Blanche",
    "gn:population":0,
    "gn:timezone":"Africa/Algiers",
    "iso:country":"DZ",
    "wof:name":"La Maison Blanche",
    "wof:placetype":"locality"
},
  "geometry": {"coordinates":[-0.73057,35.08207],"type":"Point"}
}