{
  "type": "Feature",
  "properties": {
    "gn:admin1_code":"35.0",
    "gn:asciiname":"Touahria",
    "gn:country_code":"DZ",
    "gn:dem":469,
    "gn:feature_class":"P",
    "gn:feature_code":"PPL",
    "gn:name":"Touahria",
    "gn:population":0,
    "gn:timezone":"Africa/Algiers",
    "iso:country":"DZ",
    "name:ara_x_preferred":[
        "\u0627\u0644\u0637\u0648\u0627\u0647\u0631\u064a\u0629"
    ],
    "name:azb_x_preferred":[
        "\u0637\u0648\u0627\u0647\u0631\u06cc\u0647"
    ],
    "name:fas_x_preferred":[
        "\u0637\u0648\u0627\u0647\u0631\u06cc\u0647"
    ],
    "name:fra_x_preferred":[
        "Touahria"
    ],
    "name:ita_x_preferred":[
        "Touahria"
    ],
    "name:msa_x_preferred":[
        "Touahria"
    ],
    "name:por_x_preferred":[
        "Touahria"
    ],
    "name:ron_x_preferred":[
        "Touahria"
    ],
    "name:spa_x_preferred":[
        "Touahria"
    ],
    "name:vie_x_preferred":[
        "Touahria"
    ],
    "wof:name":"Touahria",
    "wof:placetype":"locality"
},
  "geometry": {"coordinates":[2.00246,36.05175],"type":"Point"}
}