{
  "type": "Feature",
  "properties": {
    "gn:admin1_code":"35.0",
    "gn:asciiname":"Touahria",
    "gn:country_code":"DZ",
    "gn:dem":469,
    "gn:feature_class":"P",
    "gn:feature_code":"PPL",
    "gn:name":"Touahria",
    "gn:population":0,
    "gn:timezone":"Africa/Algiers",
    "iso:country":"DZ",
    "wof:name":"Touahria",
    "wof:placetype":"locality"
},
  "geometry": {"coordinates":[2.00246,36.05175],"type":"Point"}
}