{
  "type": "Feature",
  "properties": {
    "gn:admin1_code":"55.0",
    "gn:asciiname":"Tizi Meblaf",
    "gn:country_code":"DZ",
    "gn:dem":289,
    "gn:feature_class":"P",
    "gn:feature_code":"PPL",
    "gn:name":"Tizi Meblaf",
    "gn:population":0,
    "gn:timezone":"Africa/Algiers",
    "iso:country":"DZ",
    "wof:name":"Tizi Meblaf",
    "wof:placetype":"locality"
},
  "geometry": {"coordinates":[2.04917,36.50479],"type":"Point"}
}