{
  "type": "Feature",
  "properties": {
    "gn:admin1_code":"4.0",
    "gn:asciiname":"Mechtat Sidi el Arbi",
    "gn:country_code":"DZ",
    "gn:dem":620,
    "gn:feature_class":"P",
    "gn:feature_code":"PPL",
    "gn:name":"Mechtat Sidi el Arbi",
    "gn:population":0,
    "gn:timezone":"Africa/Algiers",
    "iso:country":"DZ",
    "name:und_x_variant":[
        "Mechta Sidi el Arbi",
        "Mechtat Sidi el Arbi"
    ],
    "wof:name":"Mechtat Sidi el Arbi",
    "wof:placetype":"locality"
},
  "geometry": {"coordinates":[6.68026,36.52392],"type":"Point"}
}