{
  "type": "Feature",
  "properties": {
    "gn:admin1_code":"41.0",
    "gn:asciiname":"Ouled Ben Arbia",
    "gn:country_code":"DZ",
    "gn:dem":251,
    "gn:feature_class":"P",
    "gn:feature_code":"PPL",
    "gn:name":"Ouled Ben Arbia",
    "gn:population":0,
    "gn:timezone":"Africa/Algiers",
    "iso:country":"DZ",
    "wof:name":"Ouled Ben Arbia",
    "wof:placetype":"locality"
},
  "geometry": {"coordinates":[1.56401,36.16731],"type":"Point"}
}