{
  "type": "Feature",
  "properties": {
    "gn:admin1_code":"51.0",
    "gn:asciiname":"Douar el Hessasna",
    "gn:country_code":"DZ",
    "gn:dem":41,
    "gn:feature_class":"P",
    "gn:feature_code":"PPL",
    "gn:name":"Douar el Hessasna",
    "gn:population":0,
    "gn:timezone":"Africa/Algiers",
    "iso:country":"DZ",
    "name:und_x_variant":[
        "Douar el Hasasna"
    ],
    "wof:name":"Douar el Hessasna",
    "wof:placetype":"locality"
},
  "geometry": {"coordinates":[0.74375,35.94657],"type":"Point"}
}