{
  "type": "Feature",
  "properties": {
    "gn:admin1_code":"13.0",
    "gn:asciiname":"Douar ez Zouala",
    "gn:country_code":"DZ",
    "gn:dem":746,
    "gn:feature_class":"P",
    "gn:feature_code":"PPL",
    "gn:name":"Douar ez Zouala",
    "gn:population":0,
    "gn:timezone":"Africa/Algiers",
    "iso:country":"DZ",
    "wof:name":"Douar ez Zouala",
    "wof:placetype":"locality"
},
  "geometry": {"coordinates":[0.77803,35.10757],"type":"Point"}
}