{
  "type": "Feature",
  "properties": {
    "gn:admin1_code":"12.0",
    "gn:asciiname":"Taourirt Tamelalt",
    "gn:country_code":"DZ",
    "gn:dem":993,
    "gn:feature_class":"P",
    "gn:feature_code":"PPL",
    "gn:name":"Taourirt Tamelalt",
    "gn:population":0,
    "gn:timezone":"Africa/Algiers",
    "iso:country":"DZ",
    "wof:name":"Taourirt Tamelalt",
    "wof:placetype":"locality"
},
  "geometry": {"coordinates":[4.86386,36.33263],"type":"Point"}
}