{
  "type": "Feature",
  "properties": {
    "gn:admin1_code":"13.0",
    "gn:asciiname":"Ghabet Aouda",
    "gn:country_code":"DZ",
    "gn:dem":714,
    "gn:feature_class":"P",
    "gn:feature_code":"PPL",
    "gn:name":"Ghabet Aouda",
    "gn:population":0,
    "gn:timezone":"Africa/Algiers",
    "iso:country":"DZ",
    "name:und_x_variant":[
        "Metameur Rhabet Aouda",
        "Ghabet Aouda",
        "Rhabet Aouda"
    ],
    "wof:name":"Ghabet Aouda",
    "wof:placetype":"locality"
},
  "geometry": {"coordinates":[0.82273,35.18509],"type":"Point"}
}