{
  "type": "Feature",
  "properties": {
    "gn:admin1_code":"51.0",
    "gn:asciiname":"Melaab",
    "gn:country_code":"DZ",
    "gn:dem":951,
    "gn:feature_class":"P",
    "gn:feature_code":"PPL",
    "gn:name":"Melaab",
    "gn:population":0,
    "gn:timezone":"Africa/Algiers",
    "iso:country":"DZ",
    "name:und_x_variant":[
        "El Melaab",
        "Melaab"
    ],
    "wof:name":"Melaab",
    "wof:placetype":"locality"
},
  "geometry": {"coordinates":[1.33317,35.7148],"type":"Point"}
}