{
  "type": "Feature",
  "properties": {
    "gn:admin1_code":"51.0",
    "gn:asciiname":"Melaab",
    "gn:country_code":"DZ",
    "gn:dem":951,
    "gn:feature_class":"P",
    "gn:feature_code":"PPL",
    "gn:name":"Melaab",
    "gn:population":0,
    "gn:timezone":"Africa/Algiers",
    "iso:country":"DZ",
    "name:ara_x_preferred":[
        "\u0627\u0644\u0645\u0644\u0639\u0628"
    ],
    "name:azb_x_preferred":[
        "\u0645\u0644\u0639\u0628"
    ],
    "name:fas_x_preferred":[
        "\u0645\u0644\u0639\u0628"
    ],
    "name:fra_x_preferred":[
        "Melaab"
    ],
    "name:ita_x_preferred":[
        "Melaab"
    ],
    "name:msa_x_preferred":[
        "Melaab"
    ],
    "name:por_x_preferred":[
        "Melaab"
    ],
    "name:ron_x_preferred":[
        "Melaab"
    ],
    "name:spa_x_preferred":[
        "Melaab"
    ],
    "name:und_x_variant":[
        "El Melaab"
    ],
    "name:vie_x_preferred":[
        "Melaab"
    ],
    "wof:name":"Melaab",
    "wof:placetype":"locality"
},
  "geometry": {"coordinates":[1.33317,35.7148],"type":"Point"}
}