{
  "type": "Feature",
  "properties": {
    "gn:admin1_code":"22.0",
    "gn:asciiname":"Bordj",
    "gn:country_code":"DZ",
    "gn:dem":980,
    "gn:feature_class":"P",
    "gn:feature_code":"PPL",
    "gn:name":"Bordj",
    "gn:population":0,
    "gn:timezone":"Africa/Algiers",
    "iso:country":"DZ",
    "wof:name":"Bordj",
    "wof:placetype":"locality"
},
  "geometry": {"coordinates":[2.61591,34.64017],"type":"Point"}
}