{
  "type": "Feature",
  "properties": {
    "gn:admin1_code":"26.0",
    "gn:asciiname":"Douar M'Zaidia",
    "gn:country_code":"DZ",
    "gn:dem":483,
    "gn:feature_class":"P",
    "gn:feature_code":"PPLL",
    "gn:name":"Douar M\u2019Zaidia",
    "gn:population":0,
    "gn:timezone":"Africa/Algiers",
    "iso:country":"DZ",
    "wof:name":"Douar M'Zaidia",
    "wof:placetype":"locality"
},
  "geometry": {"coordinates":[0.54684,35.4008],"type":"Point"}
}