{
  "type": "Feature",
  "properties": {
    "gn:admin1_code":"34.0",
    "gn:asciiname":"Tidmaine",
    "gn:country_code":"DZ",
    "gn:dem":213,
    "gn:feature_class":"P",
    "gn:feature_code":"PPL",
    "gn:name":"Tidma\u00efne",
    "gn:population":0,
    "gn:timezone":"Africa/Algiers",
    "iso:country":"DZ",
    "wof:name":"Tidmaine",
    "wof:placetype":"locality"
},
  "geometry": {"coordinates":[-0.12061,27.09383],"type":"Point"}
}