{
  "type": "Feature",
  "properties": {
    "gn:admin1_code":"40.0",
    "gn:asciiname":"Ben N'Choud",
    "gn:country_code":"DZ",
    "gn:dem":26,
    "gn:feature_class":"P",
    "gn:feature_code":"PPL",
    "gn:name":"Ben N\u2019Choud",
    "gn:population":0,
    "gn:timezone":"Africa/Algiers",
    "iso:country":"DZ",
    "name:ara_x_preferred":[
        "\u0628\u0646 \u0634\u0648\u062f"
    ],
    "name:azb_x_preferred":[
        "\u0628\u0646 \u0634\u0648\u062f"
    ],
    "name:fas_x_preferred":[
        "\u0628\u0646 \u0634\u0648\u062f"
    ],
    "name:fra_x_preferred":[
        "Ben Choud"
    ],
    "name:ita_x_preferred":[
        "Ben Choud"
    ],
    "name:kab_x_preferred":[
        "At Ccud"
    ],
    "name:msa_x_preferred":[
        "Ben Choud"
    ],
    "name:por_x_preferred":[
        "Ben Choud"
    ],
    "name:ron_x_preferred":[
        "Ben Choud"
    ],
    "name:rus_x_preferred":[
        "\u0411\u0435\u043d-\u0428\u0443\u0434"
    ],
    "name:spa_x_preferred":[
        "Ben Choud"
    ],
    "name:und_x_variant":[
        "Ben Nchodd",
        "Ben N\u2019Choud"
    ],
    "name:vie_x_preferred":[
        "Ben Choud"
    ],
    "name:zho_x_preferred":[
        "\u672c\u8212\u5fb7"
    ],
    "wof:name":"Ben N'Choud",
    "wof:placetype":"locality"
},
  "geometry": {"coordinates":[3.88035,36.86318],"type":"Point"}
}