{
  "type": "Feature",
  "properties": {
    "gn:admin1_code":"40.0",
    "gn:asciiname":"Ben N'Choud",
    "gn:country_code":"DZ",
    "gn:dem":26,
    "gn:feature_class":"P",
    "gn:feature_code":"PPL",
    "gn:name":"Ben N\u2019Choud",
    "gn:population":0,
    "gn:timezone":"Africa/Algiers",
    "iso:country":"DZ",
    "name:und_x_variant":[
        "Ben Nchodd",
        "Ben N\u2019Choud"
    ],
    "wof:name":"Ben N'Choud",
    "wof:placetype":"locality"
},
  "geometry": {"coordinates":[3.88035,36.86318],"type":"Point"}
}