{
  "type": "Feature",
  "properties": {
    "gn:admin1_code":"39.0",
    "gn:asciiname":"Chouf Ranib",
    "gn:country_code":"DZ",
    "gn:dem":995,
    "gn:feature_class":"P",
    "gn:feature_code":"PPL",
    "gn:name":"Chouf Ranib",
    "gn:population":0,
    "gn:timezone":"Africa/Algiers",
    "iso:country":"DZ",
    "wof:name":"Chouf Ranib",
    "wof:placetype":"locality"
},
  "geometry": {"coordinates":[4.70824,36.25723],"type":"Point"}
}