{
  "type": "Feature",
  "properties": {
    "gn:admin1_code":"23.0",
    "gn:asciiname":"'Ain Hassainia",
    "gn:country_code":"DZ",
    "gn:dem":416,
    "gn:feature_class":"P",
    "gn:feature_code":"PPL",
    "gn:name":"\u2019A\u00efn Hassainia",
    "gn:population":0,
    "gn:timezone":"Africa/Algiers",
    "iso:country":"DZ",
    "name:und_x_variant":[
        "Clauzel",
        "A\u00efne Enchir Rayan",
        "A\u00efn-Hessa\u00efnia",
        "\u2019A\u00efn Hassainia"
    ],
    "wof:name":"'Ain Hassainia",
    "wof:placetype":"locality"
},
  "geometry": {"coordinates":[7.28862,36.41536],"type":"Point"}
}