{
  "type": "Feature",
  "properties": {
    "gn:admin1_code":"35.0",
    "gn:asciiname":"Ain Defla",
    "gn:country_code":"DZ",
    "gn:dem":264,
    "gn:feature_class":"P",
    "gn:feature_code":"PPLA",
    "gn:name":"A\u00efn Defla",
    "gn:population":52276,
    "gn:timezone":"Africa/Algiers",
    "iso:country":"DZ",
    "name:ara_x_preferred":[
        "\u0639\u064a\u0646 \u0627\u0644\u062f\u0641\u0644\u0649\u200e"
    ],
    "name:ara_x_variant":[
        "\u0639\u064a\u0646 \u0627\u0644\u062f\u0641\u0644\u0649",
        "\u0639\u064a\u0646 \u0627\u0644\u062f\u0641\u0644\u0629"
    ],
    "name:ceb_x_preferred":[
        "A\u00efn Defla"
    ],
    "name:fra_x_preferred":[
        "A\u00efn Defla"
    ],
    "name:ita_x_preferred":[
        "\u02bfAyn Defla"
    ],
    "name:kor_x_preferred":[
        "\uc544\uc778\ub370\ud50c\ub77c"
    ],
    "name:msa_x_preferred":[
        "A\u00efn Defla"
    ],
    "name:nld_x_preferred":[
        "A\u00efn Defla"
    ],
    "name:nor_x_preferred":[
        "A\u00efn Defla"
    ],
    "name:pol_x_preferred":[
        "Ajn ad-Dafla"
    ],
    "name:por_x_preferred":[
        "A\u00efn Defla"
    ],
    "name:ron_x_preferred":[
        "A\u00efn Defla"
    ],
    "name:rus_x_preferred":[
        "\u0410\u0439\u043d-\u0414\u0435\u0444\u043b\u0430"
    ],
    "name:spa_x_preferred":[
        "A\u00efn Defla"
    ],
    "name:swe_x_preferred":[
        "A\u00efn Defla"
    ],
    "name:ukr_x_preferred":[
        "\u0410\u0439\u043d-\u0414\u0435\u0444\u043b\u044f"
    ],
    "name:und_x_variant":[
        "Duperr\u00e9",
        "A\u00efn Defla"
    ],
    "name:urd_x_preferred":[
        "\u0639\u06cc\u0646 \u0627\u0644\u062f\u0641\u0644\u06cc"
    ],
    "name:vie_x_preferred":[
        "A\u00efn Defla"
    ],
    "name:war_x_preferred":[
        "A\u00efn Defla"
    ],
    "name:zho_x_preferred":[
        "\u827e\u56e0\u8fea\u592b\u62c9"
    ],
    "wof:name":"Ain Defla",
    "wof:placetype":"locality",
    "wof:population":52276
},
  "geometry": {"coordinates":[1.9679,36.26405],"type":"Point"}
}