{
  "type": "Feature",
  "properties": {
    "gn:admin1_code":"35.0",
    "gn:asciiname":"Ain Defla",
    "gn:country_code":"DZ",
    "gn:dem":264,
    "gn:feature_class":"P",
    "gn:feature_code":"PPLA",
    "gn:name":"A\u00efn Defla",
    "gn:population":52276,
    "gn:timezone":"Africa/Algiers",
    "iso:country":"DZ",
    "name:ara_x_preferred":[
        "\u0639\u064a\u0646 \u0627\u0644\u062f\u0641\u0644\u0649\u200e"
    ],
    "name:ara_x_variant":[
        "\u0639\u064a\u0646 \u0627\u0644\u062f\u0641\u0644\u0649",
        "\u0639\u064a\u0646 \u0627\u0644\u062f\u0641\u0644\u0629"
    ],
    "name:und_x_variant":[
        "Duperr\u00e9",
        "A\u00efn Defla"
    ],
    "wof:name":"Ain Defla",
    "wof:placetype":"locality",
    "wof:population":52276
},
  "geometry": {"coordinates":[1.9679,36.26405],"type":"Point"}
}