{
  "type": "Feature",
  "properties": {
    "gn:admin1_code":"43.0",
    "gn:asciiname":"Sidi Khelil",
    "gn:country_code":"DZ",
    "gn:dem":18,
    "gn:feature_class":"P",
    "gn:feature_code":"PPL",
    "gn:name":"Sidi Khelil",
    "gn:population":0,
    "gn:timezone":"Africa/Algiers",
    "iso:country":"DZ",
    "name:und_x_variant":[
        "Sidi Khelit",
        "Sidi Krelil",
        "Sidi Khelil"
    ],
    "wof:name":"Sidi Khelil",
    "wof:placetype":"locality"
},
  "geometry": {"coordinates":[5.95577,33.83689],"type":"Point"}
}