{
  "type": "Feature",
  "properties": {
    "gn:admin1_code":"21.0",
    "gn:asciiname":"Mechta Lachouaf",
    "gn:country_code":"DZ",
    "gn:dem":707,
    "gn:feature_class":"P",
    "gn:feature_code":"PPL",
    "gn:name":"Mechta Lachouaf",
    "gn:population":0,
    "gn:timezone":"Africa/Algiers",
    "iso:country":"DZ",
    "wof:name":"Mechta Lachouaf",
    "wof:placetype":"locality"
},
  "geometry": {"coordinates":[3.76062,35.92272],"type":"Point"}
}