{
  "type": "Feature",
  "properties": {
    "gn:admin1_code":"13.0",
    "gn:asciiname":"Fedoul",
    "gn:country_code":"DZ",
    "gn:dem":820,
    "gn:feature_class":"P",
    "gn:feature_code":"PPL",
    "gn:name":"Fedoul",
    "gn:population":0,
    "gn:timezone":"Africa/Algiers",
    "iso:country":"DZ",
    "wof:name":"Fedoul",
    "wof:placetype":"locality"
},
  "geometry": {"coordinates":[2.11189,35.49094],"type":"Point"}
}