{
  "type": "Feature",
  "properties": {
    "gn:admin1_code":"26.0",
    "gn:asciiname":"Douar Blaihia",
    "gn:country_code":"DZ",
    "gn:dem":417,
    "gn:feature_class":"P",
    "gn:feature_code":"PPL",
    "gn:name":"Douar Bla\u00efhia",
    "gn:population":0,
    "gn:timezone":"Africa/Algiers",
    "iso:country":"DZ",
    "name:und_x_variant":[
        "Sidi Blaha",
        "Douar Bla\u00efhia"
    ],
    "wof:name":"Douar Blaihia",
    "wof:placetype":"locality"
},
  "geometry": {"coordinates":[-0.35497,35.48304],"type":"Point"}
}