{
  "type": "Feature",
  "properties": {
    "gn:admin1_code":"44.0",
    "gn:asciiname":"Hammam Sidi Zid",
    "gn:country_code":"DZ",
    "gn:dem":341,
    "gn:feature_class":"P",
    "gn:feature_code":"PPL",
    "gn:name":"Hammam Sidi Zid",
    "gn:population":0,
    "gn:timezone":"Africa/Algiers",
    "iso:country":"DZ",
    "name:und_x_variant":[
        "Hammam Sidi Zitz",
        "Hammam Sidi Zid"
    ],
    "wof:name":"Hammam Sidi Zid",
    "wof:placetype":"locality"
},
  "geometry": {"coordinates":[8.15,36.46667],"type":"Point"}
}