{
  "type": "Feature",
  "properties": {
    "gn:admin1_code":"3.0",
    "gn:asciiname":"Mechtat Tafrennt Kbira",
    "gn:country_code":"DZ",
    "gn:dem":1107,
    "gn:feature_class":"P",
    "gn:feature_code":"PPL",
    "gn:name":"Mechtat Tafrennt Kbira",
    "gn:population":0,
    "gn:timezone":"Africa/Algiers",
    "iso:country":"DZ",
    "name:und_x_variant":[
        "Mechta Tafrennt Kebira",
        "Mechtat Tafrennt Kbira"
    ],
    "wof:name":"Mechtat Tafrennt Kbira",
    "wof:placetype":"locality"
},
  "geometry": {"coordinates":[6.00318,35.4324],"type":"Point"}
}