{
  "type": "Feature",
  "properties": {
    "gn:admin1_code":"41.0",
    "gn:asciiname":"Tafrente",
    "gn:country_code":"DZ",
    "gn:dem":557,
    "gn:feature_class":"P",
    "gn:feature_code":"PPL",
    "gn:name":"Tafrente",
    "gn:population":0,
    "gn:timezone":"Africa/Algiers",
    "iso:country":"DZ",
    "wof:name":"Tafrente",
    "wof:placetype":"locality"
},
  "geometry": {"coordinates":[1.70389,36.41468],"type":"Point"}
}