{
  "type": "Feature",
  "properties": {
    "gn:admin1_code":"12.0",
    "gn:asciiname":"Kou Klas",
    "gn:country_code":"DZ",
    "gn:dem":806,
    "gn:feature_class":"P",
    "gn:feature_code":"PPL",
    "gn:name":"Kou Klas",
    "gn:population":0,
    "gn:timezone":"Africa/Algiers",
    "iso:country":"DZ",
    "name:und_x_variant":[
        "Kou Klass",
        "Kou Klas"
    ],
    "wof:name":"Kou Klas",
    "wof:placetype":"locality"
},
  "geometry": {"coordinates":[5.59433,36.48147],"type":"Point"}
}