{
  "type": "Feature",
  "properties": {
    "gn:admin1_code":"6.0",
    "gn:asciiname":"Oulad Amor",
    "gn:country_code":"DZ",
    "gn:dem":1055,
    "gn:feature_class":"P",
    "gn:feature_code":"PPL",
    "gn:name":"Oulad Amor",
    "gn:population":0,
    "gn:timezone":"Africa/Algiers",
    "iso:country":"DZ",
    "wof:name":"Oulad Amor",
    "wof:placetype":"locality"
},
  "geometry": {"coordinates":[3.12383,35.91894],"type":"Point"}
}