{
  "type": "Feature",
  "properties": {
    "gn:admin1_code":"15.0",
    "gn:asciiname":"Es Sbabna",
    "gn:country_code":"DZ",
    "gn:dem":184,
    "gn:feature_class":"P",
    "gn:feature_code":"PPL",
    "gn:name":"Es Sb\u00e2bna",
    "gn:population":0,
    "gn:timezone":"Africa/Algiers",
    "iso:country":"DZ",
    "name:und_x_variant":[
        "Da\u00efa Sebabna",
        "Es Sb\u00e2bna"
    ],
    "wof:name":"Es Sbabna",
    "wof:placetype":"locality"
},
  "geometry": {"coordinates":[-2.11667,35.03333],"type":"Point"}
}