{
  "type": "Feature",
  "properties": {
    "gn:admin1_code":"36.0",
    "gn:asciiname":"Douar el Ounazra",
    "gn:country_code":"DZ",
    "gn:dem":288,
    "gn:feature_class":"P",
    "gn:feature_code":"PPL",
    "gn:name":"Douar el Ounazra",
    "gn:population":0,
    "gn:timezone":"Africa/Algiers",
    "iso:country":"DZ",
    "name:und_x_variant":[
        "El Ounazera",
        "Douar el Ounazra"
    ],
    "wof:name":"Douar el Ounazra",
    "wof:placetype":"locality"
},
  "geometry": {"coordinates":[-0.73223,35.36865],"type":"Point"}
}