{
  "type": "Feature",
  "properties": {
    "gn:admin1_code":"20.0",
    "gn:asciiname":"Hamlili",
    "gn:country_code":"DZ",
    "gn:dem":404,
    "gn:feature_class":"P",
    "gn:feature_code":"PPL",
    "gn:name":"Hamlili",
    "gn:population":0,
    "gn:timezone":"Africa/Algiers",
    "iso:country":"DZ",
    "wof:name":"Hamlili",
    "wof:placetype":"locality"
},
  "geometry": {"coordinates":[2.84111,36.44508],"type":"Point"}
}