{
  "type": "Feature",
  "properties": {
    "gn:admin1_code":"41.0",
    "gn:asciiname":"Khellafa",
    "gn:country_code":"DZ",
    "gn:dem":350,
    "gn:feature_class":"P",
    "gn:feature_code":"PPL",
    "gn:name":"Khellafa",
    "gn:population":0,
    "gn:timezone":"Africa/Algiers",
    "iso:country":"DZ",
    "wof:name":"Khellafa",
    "wof:placetype":"locality"
},
  "geometry": {"coordinates":[1.15113,36.27826],"type":"Point"}
}