{
  "type": "Feature",
  "properties": {
    "gn:admin1_code":"18.0",
    "gn:asciiname":"Taourirt",
    "gn:country_code":"DZ",
    "gn:dem":637,
    "gn:feature_class":"P",
    "gn:feature_code":"PPL",
    "gn:name":"Taourirt",
    "gn:population":0,
    "gn:timezone":"Africa/Algiers",
    "iso:country":"DZ",
    "name:ceb_x_preferred":[
        "Taourirt"
    ],
    "name:fra_x_preferred":[
        "Taourirt"
    ],
    "name:nld_x_preferred":[
        "Taourirt"
    ],
    "name:pol_x_preferred":[
        "Taurirt"
    ],
    "name:swe_x_preferred":[
        "Taourirt"
    ],
    "wof:name":"Taourirt",
    "wof:placetype":"locality"
},
  "geometry": {"coordinates":[4.6828,36.44334],"type":"Point"}
}