{
  "type": "Feature",
  "properties": {
    "gn:admin1_code":"24.0",
    "gn:asciiname":"Tamentout",
    "gn:country_code":"DZ",
    "gn:dem":871,
    "gn:feature_class":"P",
    "gn:feature_code":"PPL",
    "gn:name":"Tamentout",
    "gn:population":0,
    "gn:timezone":"Africa/Algiers",
    "iso:country":"DZ",
    "wof:name":"Tamentout",
    "wof:placetype":"locality"
},
  "geometry": {"coordinates":[5.83521,36.55228],"type":"Point"}
}