{
  "type": "Feature",
  "properties": {
    "gn:admin1_code":"26.0",
    "gn:asciiname":"Dar el Mechri",
    "gn:country_code":"DZ",
    "gn:dem":289,
    "gn:feature_class":"P",
    "gn:feature_code":"PPLL",
    "gn:name":"Dar el Mechri",
    "gn:population":0,
    "gn:timezone":"Africa/Algiers",
    "iso:country":"DZ",
    "wof:name":"Dar el Mechri",
    "wof:placetype":"locality"
},
  "geometry": {"coordinates":[0.60943,35.45104],"type":"Point"}
}