{
  "type": "Feature",
  "properties": {
    "gn:admin1_code":"39.0",
    "gn:asciiname":"Meheris",
    "gn:country_code":"DZ",
    "gn:dem":1034,
    "gn:feature_class":"P",
    "gn:feature_code":"PPL",
    "gn:name":"Meheris",
    "gn:population":0,
    "gn:timezone":"Africa/Algiers",
    "iso:country":"DZ",
    "wof:name":"Meheris",
    "wof:placetype":"locality"
},
  "geometry": {"coordinates":[4.96175,36.0757],"type":"Point"}
}