{
  "type": "Feature",
  "properties": {
    "iso:country":"DZ",
    "name:ara_x_colloquial":[
        "Hussein Dey"
    ],
    "name:ara_x_preferred":[
        "Husse\u00efn Dey",
        "\u0646\u0635\u0631 \u062d\u0633\u064a\u0646 \u062f\u0627\u064a"
    ],
    "name:ara_x_variant":[
        "Husseini Dey",
        "Ruisseau"
    ],
    "name:cat_x_preferred":[
        "Nasr Athl\u00e9tique de Hussein Dey"
    ],
    "name:deu_x_preferred":[
        "NA Hussein Dey"
    ],
    "name:epo_x_preferred":[
        "NA Hussein Dey"
    ],
    "name:fas_x_preferred":[
        "\u0628\u0627\u0634\u06af\u0627\u0647 \u0641\u0648\u062a\u0628\u0627\u0644 \u0646\u0635\u0631 \u062d\u0633\u06cc\u0646 \u062f\u0627\u06cc"
    ],
    "name:fra_x_preferred":[
        "Nasr athl\u00e9tique d'Hussein Dey"
    ],
    "name:ind_x_preferred":[
        "NA Hussein Dey"
    ],
    "name:ita_x_preferred":[
        "Nasr Athl\u00e9tique de Hussein Dey"
    ],
    "name:nld_x_preferred":[
        "NA Hussein Dey"
    ],
    "name:pol_x_preferred":[
        "NA Hussein Dey"
    ],
    "name:spa_x_preferred":[
        "NA Hussein Dey"
    ],
    "name:unk_x_variant":[
        "Husse\u00efn Dey"
    ],
    "name:zho_x_preferred":[
        "NA\u4faf\u8d5b\u56e0\u5fb7\u5c14"
    ],
    "qs:gn_adm0_cc":"DZ",
    "qs:gn_local":2507480,
    "qs:gn_nam_loc":"\u0648\u0644\u0627\u064a\u0629 \u0627\u0644\u062c\u0632\u0627\u0626\u0631, DZ, \u0627\u0644\u062c\u0632\u0627\u0626\u0631",
    "qs:gn_namadm1":"01",
    "qs:local_max":361,
    "qs:local_sum":1976,
    "qs:localhoods":16,
    "qs:name":"Husse\u00efn Dey",
    "qs:name_adm0":"\u0627\u0644\u062c\u0632\u0627\u0626\u0631",
    "qs:name_adm1":"\u0648\u0644\u0627\u064a\u0629 \u0627\u0644\u062c\u0632\u0627\u0626\u0631",
    "qs:name_local":"\u0627\u0644\u062c\u0632\u0627\u0626\u0631",
    "qs:photo_max":67,
    "qs:photo_sum":168,
    "qs:placetype":"Suburb",
    "qs:quad_count":15,
    "qs:woe_adm0":23424740,
    "qs:woe_adm1":2344579,
    "qs:woe_adm2":0,
    "qs:woe_lau":0,
    "qs:woe_local":1253079,
    "qs:woe_ver":"7.10.0",
    "wd:wordcount":645,
    "wof:lang":[
        "ara"
    ],
    "wof:name":"Husse\u00efn Dey",
    "wof:placetype":"neighbourhood"
},
  "geometry": {"coordinates":[3.113463,36.738754],"type":"Point"}
}