{
  "type": "Feature",
  "properties": {
    "gn:admin1_code":"14.0",
    "gn:asciiname":"Aguemoun Izem",
    "gn:country_code":"DZ",
    "gn:dem":851,
    "gn:feature_class":"P",
    "gn:feature_code":"PPL",
    "gn:name":"Aguemoun Izem",
    "gn:population":0,
    "gn:timezone":"Africa/Algiers",
    "iso:country":"DZ",
    "wof:name":"Aguemoun Izem",
    "wof:placetype":"locality"
},
  "geometry": {"coordinates":[4.27097,36.59981],"type":"Point"}
}