{
  "type": "Feature",
  "properties": {
    "gn:admin1_code":"7.0",
    "gn:asciiname":"Douar Krachla",
    "gn:country_code":"DZ",
    "gn:dem":149,
    "gn:feature_class":"P",
    "gn:feature_code":"PPL",
    "gn:name":"Douar Krachla",
    "gn:population":0,
    "gn:timezone":"Africa/Algiers",
    "iso:country":"DZ",
    "name:und_x_variant":[
        "Douar Schraba",
        "Douar Krachla",
        "Douar Kherechla"
    ],
    "wof:name":"Douar Krachla",
    "wof:placetype":"locality"
},
  "geometry": {"coordinates":[0.21514,35.84093],"type":"Point"}
}