{
  "type": "Feature",
  "properties": {
    "gn:admin1_code":"43.0",
    "gn:asciiname":"Casablanca",
    "gn:country_code":"DZ",
    "gn:dem":43,
    "gn:feature_class":"P",
    "gn:feature_code":"PPL",
    "gn:name":"Casablanca",
    "gn:population":0,
    "gn:timezone":"Africa/Algiers",
    "iso:country":"DZ",
    "wof:name":"Casablanca",
    "wof:placetype":"locality"
},
  "geometry": {"coordinates":[7.58333,33.53333],"type":"Point"}
}