{
  "type": "Feature",
  "properties": {
    "gn:admin1_code":"56.0",
    "gn:asciiname":"Rouabah",
    "gn:country_code":"DZ",
    "gn:dem":764,
    "gn:feature_class":"P",
    "gn:feature_code":"PPL",
    "gn:name":"Rouabah",
    "gn:population":0,
    "gn:timezone":"Africa/Algiers",
    "iso:country":"DZ",
    "wof:name":"Rouabah",
    "wof:placetype":"locality"
},
  "geometry": {"coordinates":[2.2536,35.61233],"type":"Point"}
}