{
  "type": "Feature",
  "properties": {
    "gn:admin1_code":"26.0",
    "gn:asciiname":"M'khaichia",
    "gn:country_code":"DZ",
    "gn:dem":716,
    "gn:feature_class":"P",
    "gn:feature_code":"PPL",
    "gn:name":"M\u2019kha\u00efchia",
    "gn:population":0,
    "gn:timezone":"Africa/Algiers",
    "iso:country":"DZ",
    "name:und_x_variant":[
        "M\u2019kha\u00efchia",
        "Douar Ouled Adda Ben Ahmed"
    ],
    "wof:name":"M'khaichia",
    "wof:placetype":"locality"
},
  "geometry": {"coordinates":[0.38171,35.51191],"type":"Point"}
}