{
  "type": "Feature",
  "properties": {
    "gn:admin1_code":"9.0",
    "gn:asciiname":"Sahouria",
    "gn:country_code":"DZ",
    "gn:dem":226,
    "gn:feature_class":"P",
    "gn:feature_code":"PPL",
    "gn:name":"Sahouria",
    "gn:population":0,
    "gn:timezone":"Africa/Algiers",
    "iso:country":"DZ",
    "wof:name":"Sahouria",
    "wof:placetype":"locality"
},
  "geometry": {"coordinates":[-0.5023,35.47445],"type":"Point"}
}