{
  "type": "Feature",
  "properties": {
    "gn:admin1_code":"24.0",
    "gn:asciiname":"Seratou",
    "gn:country_code":"DZ",
    "gn:dem":644,
    "gn:feature_class":"P",
    "gn:feature_code":"PPL",
    "gn:name":"Seratou",
    "gn:population":0,
    "gn:timezone":"Africa/Algiers",
    "iso:country":"DZ",
    "wof:name":"Seratou",
    "wof:placetype":"locality"
},
  "geometry": {"coordinates":[5.68994,36.59633],"type":"Point"}
}