{
  "type": "Feature",
  "properties": {
    "gn:admin1_code":"51.0",
    "gn:asciiname":"Douar el Grairia",
    "gn:country_code":"DZ",
    "gn:dem":204,
    "gn:feature_class":"P",
    "gn:feature_code":"PPL",
    "gn:name":"Douar el Grairia",
    "gn:population":0,
    "gn:timezone":"Africa/Algiers",
    "iso:country":"DZ",
    "wof:name":"Douar el Grairia",
    "wof:placetype":"locality"
},
  "geometry": {"coordinates":[0.32252,35.73754],"type":"Point"}
}