{
  "type": "Feature",
  "properties": {
    "gn:admin1_code":"24.0",
    "gn:asciiname":"Afarnou",
    "gn:country_code":"DZ",
    "gn:dem":551,
    "gn:feature_class":"P",
    "gn:feature_code":"PPL",
    "gn:name":"Afarnou",
    "gn:population":0,
    "gn:timezone":"Africa/Algiers",
    "iso:country":"DZ",
    "wof:name":"Afarnou",
    "wof:placetype":"locality"
},
  "geometry": {"coordinates":[5.56667,36.63333],"type":"Point"}
}