{
  "type": "Feature",
  "properties": {
    "gn:admin1_code":"55.0",
    "gn:asciiname":"Tala Kroubiz",
    "gn:country_code":"DZ",
    "gn:dem":705,
    "gn:feature_class":"P",
    "gn:feature_code":"PPLL",
    "gn:name":"Tala Kroubiz",
    "gn:population":0,
    "gn:timezone":"Africa/Algiers",
    "iso:country":"DZ",
    "wof:name":"Tala Kroubiz",
    "wof:placetype":"locality"
},
  "geometry": {"coordinates":[2.30243,36.44274],"type":"Point"}
}