{
  "type": "Feature",
  "properties": {
    "gn:country":"DZ",
    "gn:fcode":"PPL",
    "gn:population":20557,
    "iso:country":"DZ",
    "name:ara_x_preferred":[
        "\u0628\u0648\u062c\u064a\u0645\u0629"
    ],
    "name:azb_x_preferred":[
        "\u0628\u0648\u062c\u06cc\u0645\u0647"
    ],
    "name:ceb_x_preferred":[
        "Boudjima"
    ],
    "name:eng_x_preferred":[
        "Boudjima"
    ],
    "name:fas_x_preferred":[
        "\u0628\u0648\u062c\u06cc\u0645\u0647"
    ],
    "name:fra_x_preferred":[
        "Boudjima"
    ],
    "name:ita_x_preferred":[
        "Boudjima"
    ],
    "name:kab_x_preferred":[
        "Bu\u01e7ima"
    ],
    "name:msa_x_preferred":[
        "Boudjima"
    ],
    "name:nan_x_preferred":[
        "Boudjima"
    ],
    "name:nld_x_preferred":[
        "Boudjima"
    ],
    "name:por_x_preferred":[
        "Boudjima"
    ],
    "name:ron_x_preferred":[
        "Boudjima"
    ],
    "name:spa_x_preferred":[
        "Boudjima"
    ],
    "name:swe_x_preferred":[
        "Boudjima"
    ],
    "name:vie_x_preferred":[
        "Boudjima"
    ],
    "name:zho_x_preferred":[
        "\u5e03\u5409\u99ac"
    ],
    "qs:name":"Boudjima",
    "qs:photos_9r":0,
    "qs:photos_sr":0,
    "qs:pop_sr":"7",
    "wd:wordcount":38,
    "wof:name":"Boudjima",
    "wof:placetype":"locality",
    "wof:population":20557
},
  "geometry": {"coordinates":[4.15187,36.80218],"type":"Point"}
}