{
  "type": "Feature",
  "properties": {
    "gn:admin1_code":"22.0",
    "gn:asciiname":"Dar Tisselouine",
    "gn:country_code":"DZ",
    "gn:dem":1130,
    "gn:feature_class":"P",
    "gn:feature_code":"PPL",
    "gn:name":"Dar Tisselouine",
    "gn:population":0,
    "gn:timezone":"Africa/Algiers",
    "iso:country":"DZ",
    "wof:name":"Dar Tisselouine",
    "wof:placetype":"locality"
},
  "geometry": {"coordinates":[3.46183,34.77823],"type":"Point"}
}