{
  "type": "Feature",
  "properties": {
    "gn:admin1_code":"14.0",
    "gn:asciiname":"Tazazrait",
    "gn:country_code":"DZ",
    "gn:dem":146,
    "gn:feature_class":"P",
    "gn:feature_code":"PPL",
    "gn:name":"Tazazra\u00eft",
    "gn:population":0,
    "gn:timezone":"Africa/Algiers",
    "iso:country":"DZ",
    "wof:name":"Tazazrait",
    "wof:placetype":"locality"
},
  "geometry": {"coordinates":[4.20055,36.6929],"type":"Point"}
}