{
  "type": "Feature",
  "properties": {
    "gn:admin1_code":"22.0",
    "gn:asciiname":"Had Sahary",
    "gn:country_code":"DZ",
    "gn:dem":843,
    "gn:feature_class":"P",
    "gn:feature_code":"PPL",
    "gn:name":"Had Sahary",
    "gn:population":0,
    "gn:timezone":"Africa/Algiers",
    "iso:country":"DZ",
    "name:und_x_variant":[
        "Bouira Sahary",
        "Zemach",
        "Bouira Sahari",
        "Had Sahary",
        "Zenzach"
    ],
    "wof:name":"Had Sahary",
    "wof:placetype":"locality"
},
  "geometry": {"coordinates":[3.36528,35.35055999999999],"type":"Point"}
}