{
  "type": "Feature",
  "properties": {
    "gn:admin1_code":"27.0",
    "gn:asciiname":"'Ain Nakhar",
    "gn:country_code":"DZ",
    "gn:dem":435,
    "gn:feature_class":"P",
    "gn:feature_code":"PPL",
    "gn:name":"\u2019A\u00efn Nakhar",
    "gn:population":0,
    "gn:timezone":"Africa/Algiers",
    "iso:country":"DZ",
    "wof:name":"'Ain Nakhar",
    "wof:placetype":"locality"
},
  "geometry": {"coordinates":[5.0214,35.50864],"type":"Point"}
}