{
  "type": "Feature",
  "properties": {
    "gn:admin1_code":"31.0",
    "gn:asciiname":"El Arrouch",
    "gn:country_code":"DZ",
    "gn:dem":132,
    "gn:feature_class":"P",
    "gn:feature_code":"PPL",
    "gn:name":"El Arrouch",
    "gn:population":0,
    "gn:timezone":"Africa/Algiers",
    "iso:country":"DZ",
    "wof:name":"El Arrouch",
    "wof:placetype":"locality"
},
  "geometry": {"coordinates":[6.83639,36.65306],"type":"Point"}
}