{
  "type": "Feature",
  "properties": {
    "gn:admin1_code":"7.0",
    "gn:asciiname":"Mekhatria",
    "gn:country_code":"DZ",
    "gn:dem":286,
    "gn:feature_class":"P",
    "gn:feature_code":"PPL",
    "gn:name":"Mekhatria",
    "gn:population":0,
    "gn:timezone":"Africa/Algiers",
    "iso:country":"DZ",
    "name:und_x_variant":[
        "Douar el Mekh\u00e2tria",
        "Douar Mekhatria",
        "Mekhatria"
    ],
    "wof:name":"Mekhatria",
    "wof:placetype":"locality"
},
  "geometry": {"coordinates":[0.32251,35.79464],"type":"Point"}
}