{
  "type": "Feature",
  "properties": {
    "gn:admin1_code":"7.0",
    "gn:asciiname":"Mekhatria",
    "gn:country_code":"DZ",
    "gn:dem":286,
    "gn:feature_class":"P",
    "gn:feature_code":"PPL",
    "gn:name":"Mekhatria",
    "gn:population":0,
    "gn:timezone":"Africa/Algiers",
    "iso:country":"DZ",
    "name:ara_x_preferred":[
        "\u0627\u0644\u0645\u062e\u0627\u0637\u0631\u064a\u0629"
    ],
    "name:azb_x_preferred":[
        "\u0645\u062e\u0627\u0637\u0631\u06cc\u0647"
    ],
    "name:fas_x_preferred":[
        "\u0645\u062e\u0627\u0637\u0631\u06cc\u0647"
    ],
    "name:fra_x_preferred":[
        "Mekhatria"
    ],
    "name:msa_x_preferred":[
        "Mekhatria"
    ],
    "name:por_x_preferred":[
        "Mekhatria"
    ],
    "name:ron_x_preferred":[
        "Mekhatria"
    ],
    "name:spa_x_preferred":[
        "Mekhatria"
    ],
    "name:und_x_variant":[
        "Douar el Mekh\u00e2tria",
        "Douar Mekhatria"
    ],
    "name:vie_x_preferred":[
        "Mekhatria"
    ],
    "wof:name":"Mekhatria",
    "wof:placetype":"locality"
},
  "geometry": {"coordinates":[0.32251,35.79464],"type":"Point"}
}