{
  "type": "Feature",
  "properties": {
    "gn:admin1_code":"15.0",
    "gn:asciiname":"Rehamna",
    "gn:country_code":"DZ",
    "gn:dem":284,
    "gn:feature_class":"P",
    "gn:feature_code":"PPL",
    "gn:name":"Rehamna",
    "gn:population":0,
    "gn:timezone":"Africa/Algiers",
    "iso:country":"DZ",
    "name:und_x_variant":[
        "Rhamna",
        "Rehamna"
    ],
    "wof:name":"Rehamna",
    "wof:placetype":"locality"
},
  "geometry": {"coordinates":[-1.92131,35.06144],"type":"Point"}
}