{
  "type": "Feature",
  "properties": {
    "gn:admin1_code":"51.0",
    "gn:asciiname":"Chaif el Hassane",
    "gn:country_code":"DZ",
    "gn:dem":109,
    "gn:feature_class":"P",
    "gn:feature_code":"PPL",
    "gn:name":"Cha\u00eff el Hassane",
    "gn:population":0,
    "gn:timezone":"Africa/Algiers",
    "iso:country":"DZ",
    "wof:name":"Chaif el Hassane",
    "wof:placetype":"locality"
},
  "geometry": {"coordinates":[0.57378,35.67404000000001],"type":"Point"}
}