{
  "type": "Feature",
  "properties": {
    "gn:admin1_code":"6.0",
    "gn:asciiname":"Oulad Ali",
    "gn:country_code":"DZ",
    "gn:dem":875,
    "gn:feature_class":"P",
    "gn:feature_code":"PPL",
    "gn:name":"Oulad Ali",
    "gn:population":0,
    "gn:timezone":"Africa/Algiers",
    "iso:country":"DZ",
    "wof:name":"Oulad Ali",
    "wof:placetype":"locality"
},
  "geometry": {"coordinates":[3.13506,36.08149],"type":"Point"}
}