{
  "type": "Feature",
  "properties": {
    "gn:admin1_code":"33.0",
    "gn:asciiname":"El Mermoutsia",
    "gn:country_code":"DZ",
    "gn:dem":838,
    "gn:feature_class":"P",
    "gn:feature_code":"PPL",
    "gn:name":"El Mermoutsia",
    "gn:population":0,
    "gn:timezone":"Africa/Algiers",
    "iso:country":"DZ",
    "wof:name":"El Mermoutsia",
    "wof:placetype":"locality"
},
  "geometry": {"coordinates":[8.03333,34.85],"type":"Point"}
}