{
  "type": "Feature",
  "properties": {
    "gn:admin1_code":"6.0",
    "gn:asciiname":"Ouled er Rouabia",
    "gn:country_code":"DZ",
    "gn:dem":620,
    "gn:feature_class":"P",
    "gn:feature_code":"PPL",
    "gn:name":"Ouled er Rouabia",
    "gn:population":0,
    "gn:timezone":"Africa/Algiers",
    "iso:country":"DZ",
    "wof:name":"Ouled er Rouabia",
    "wof:placetype":"locality"
},
  "geometry": {"coordinates":[3.18208,36.23423],"type":"Point"}
}