{
  "type": "Feature",
  "properties": {
    "gn:admin1_code":"47.0",
    "gn:asciiname":"Afra",
    "gn:country_code":"DZ",
    "gn:dem":1265,
    "gn:feature_class":"P",
    "gn:feature_code":"PPL",
    "gn:name":"Afra",
    "gn:population":0,
    "gn:timezone":"Africa/Algiers",
    "iso:country":"DZ",
    "wof:name":"Afra",
    "wof:placetype":"locality"
},
  "geometry": {"coordinates":[6.82364,34.94742],"type":"Point"}
}