{
  "type": "Feature",
  "properties": {
    "gn:admin1_code":"26.0",
    "gn:asciiname":"Ouled Hadj Ahmed",
    "gn:country_code":"DZ",
    "gn:dem":423,
    "gn:feature_class":"P",
    "gn:feature_code":"PPLL",
    "gn:name":"Ouled Hadj Ahmed",
    "gn:population":0,
    "gn:timezone":"Africa/Algiers",
    "iso:country":"DZ",
    "wof:name":"Ouled Hadj Ahmed",
    "wof:placetype":"locality"
},
  "geometry": {"coordinates":[0.20171,35.48872],"type":"Point"}
}