{
  "type": "Feature",
  "properties": {
    "gn:admin1_code":"7.0",
    "gn:asciiname":"Douar Louza",
    "gn:country_code":"DZ",
    "gn:dem":53,
    "gn:feature_class":"P",
    "gn:feature_code":"PPL",
    "gn:name":"Douar Louza",
    "gn:population":0,
    "gn:timezone":"Africa/Algiers",
    "iso:country":"DZ",
    "name:und_x_variant":[
        "Louazia",
        "Douar Louza"
    ],
    "wof:name":"Douar Louza",
    "wof:placetype":"locality"
},
  "geometry": {"coordinates":[-0.07319,35.76263],"type":"Point"}
}