{
  "type": "Feature",
  "properties": {
    "gn:admin1_code":"55.0",
    "gn:asciiname":"Douar Bounamane",
    "gn:country_code":"DZ",
    "gn:dem":435,
    "gn:feature_class":"P",
    "gn:feature_code":"PPL",
    "gn:name":"Douar Bounamane",
    "gn:population":0,
    "gn:timezone":"Africa/Algiers",
    "iso:country":"DZ",
    "wof:name":"Douar Bounamane",
    "wof:placetype":"locality"
},
  "geometry": {"coordinates":[1.92655,36.51253],"type":"Point"}
}