{
  "type": "Feature",
  "properties": {
    "gn:admin1_code":"47.0",
    "gn:asciiname":"Mechta Halloufa",
    "gn:country_code":"DZ",
    "gn:dem":1043,
    "gn:feature_class":"P",
    "gn:feature_code":"PPL",
    "gn:name":"Mechta Halloufa",
    "gn:population":0,
    "gn:timezone":"Africa/Algiers",
    "iso:country":"DZ",
    "wof:name":"Mechta Halloufa",
    "wof:placetype":"locality"
},
  "geometry": {"coordinates":[7.41444,35.5236],"type":"Point"}
}