{
  "type": "Feature",
  "properties": {
    "gn:admin1_code":"31.0",
    "gn:asciiname":"Mechtat er R'Mel",
    "gn:country_code":"DZ",
    "gn:dem":24,
    "gn:feature_class":"P",
    "gn:feature_code":"PPL",
    "gn:name":"Mechtat er R\u2019Mel",
    "gn:population":0,
    "gn:timezone":"Africa/Algiers",
    "iso:country":"DZ",
    "wof:name":"Mechtat er R'Mel",
    "wof:placetype":"locality"
},
  "geometry": {"coordinates":[7.32533,36.80218],"type":"Point"}
}