{
  "type": "Feature",
  "properties": {
    "gn:admin1_code":"27.0",
    "gn:asciiname":"Mechta Bouira",
    "gn:country_code":"DZ",
    "gn:dem":737,
    "gn:feature_class":"P",
    "gn:feature_code":"PPL",
    "gn:name":"Mechta Bouira",
    "gn:population":0,
    "gn:timezone":"Africa/Algiers",
    "iso:country":"DZ",
    "wof:name":"Mechta Bouira",
    "wof:placetype":"locality"
},
  "geometry": {"coordinates":[5.07289,35.70395],"type":"Point"}
}