{
  "type": "Feature",
  "properties": {
    "gn:admin1_code":"35.0",
    "gn:asciiname":"El Atatfa",
    "gn:country_code":"DZ",
    "gn:dem":292,
    "gn:feature_class":"P",
    "gn:feature_code":"PPL",
    "gn:name":"El Atatfa",
    "gn:population":0,
    "gn:timezone":"Africa/Algiers",
    "iso:country":"DZ",
    "name:und_x_variant":[
        "El \u2019Attatfa"
    ],
    "wof:name":"El Atatfa",
    "wof:placetype":"locality"
},
  "geometry": {"coordinates":[1.92575,36.24293],"type":"Point"}
}