{
  "type": "Feature",
  "properties": {
    "gn:admin1_code":"41.0",
    "gn:asciiname":"Douar Bou Hamadi",
    "gn:country_code":"DZ",
    "gn:dem":430,
    "gn:feature_class":"P",
    "gn:feature_code":"PPL",
    "gn:name":"Douar Bou Hamadi",
    "gn:population":0,
    "gn:timezone":"Africa/Algiers",
    "iso:country":"DZ",
    "wof:name":"Douar Bou Hamadi",
    "wof:placetype":"locality"
},
  "geometry": {"coordinates":[1.45985,36.26386],"type":"Point"}
}