{
  "type": "Feature",
  "properties": {
    "gn:admin1_code":"41.0",
    "gn:asciiname":"Tadart Ou Ferraisse",
    "gn:country_code":"DZ",
    "gn:dem":51,
    "gn:feature_class":"P",
    "gn:feature_code":"PPL",
    "gn:name":"Tadart Ou Ferra\u00efsse",
    "gn:population":0,
    "gn:timezone":"Africa/Algiers",
    "iso:country":"DZ",
    "wof:name":"Tadart Ou Ferraisse",
    "wof:placetype":"locality"
},
  "geometry": {"coordinates":[1.55274,36.52783],"type":"Point"}
}