{
  "type": "Feature",
  "properties": {
    "gn:admin1_code":"40.0",
    "gn:asciiname":"Douar Kermoul",
    "gn:country_code":"DZ",
    "gn:dem":85,
    "gn:feature_class":"P",
    "gn:feature_code":"PPL",
    "gn:name":"Douar Kermoul",
    "gn:population":0,
    "gn:timezone":"Africa/Algiers",
    "iso:country":"DZ",
    "wof:name":"Douar Kermoul",
    "wof:placetype":"locality"
},
  "geometry": {"coordinates":[3.66611,36.78778],"type":"Point"}
}