{
  "type": "Feature",
  "properties": {
    "gn:admin1_code":"41.0",
    "gn:asciiname":"Boukaat Ziadnia",
    "gn:country_code":"DZ",
    "gn:dem":141,
    "gn:feature_class":"P",
    "gn:feature_code":"PPL",
    "gn:name":"Boukaat Ziadnia",
    "gn:population":0,
    "gn:timezone":"Africa/Algiers",
    "iso:country":"DZ",
    "wof:name":"Boukaat Ziadnia",
    "wof:placetype":"locality"
},
  "geometry": {"coordinates":[1.2734,36.04024],"type":"Point"}
}