{
  "type": "Feature",
  "properties": {
    "gn:admin1_code":"39.0",
    "gn:asciiname":"'Ain Defla",
    "gn:country_code":"DZ",
    "gn:dem":983,
    "gn:feature_class":"P",
    "gn:feature_code":"PPL",
    "gn:name":"\u2019A\u00efn Defla",
    "gn:population":0,
    "gn:timezone":"Africa/Algiers",
    "iso:country":"DZ",
    "name:und_x_variant":[
        "A\u00efne Defla",
        "\u2019A\u00efn Defla"
    ],
    "wof:name":"'Ain Defla",
    "wof:placetype":"locality"
},
  "geometry": {"coordinates":[4.54932,36.06966],"type":"Point"}
}