{
  "type": "Feature",
  "properties": {
    "gn:admin1_code":"50.0",
    "gn:asciiname":"El Ksour",
    "gn:country_code":"DZ",
    "gn:dem":57,
    "gn:feature_class":"P",
    "gn:feature_code":"PPL",
    "gn:name":"El Ksour",
    "gn:population":0,
    "gn:timezone":"Africa/Algiers",
    "iso:country":"DZ",
    "wof:name":"El Ksour",
    "wof:placetype":"locality"
},
  "geometry": {"coordinates":[6.07167,33.22528],"type":"Point"}
}