{
  "type": "Feature",
  "properties": {
    "gn:admin1_code":"50.0",
    "gn:asciiname":"El Ksour",
    "gn:country_code":"DZ",
    "gn:dem":57,
    "gn:feature_class":"P",
    "gn:feature_code":"PPL",
    "gn:name":"El Ksour",
    "gn:population":0,
    "gn:timezone":"Africa/Algiers",
    "iso:country":"DZ",
    "name:ara_x_preferred":[
        "\u0627\u0644\u0642\u0635\u0648\u0631"
    ],
    "name:cat_x_preferred":[
        "Ksour"
    ],
    "name:ceb_x_preferred":[
        "El Ksour"
    ],
    "name:fra_x_preferred":[
        "El Ksour"
    ],
    "name:ukr_x_preferred":[
        "\u0415\u043b\u044c-\u041a\u0441\u0443\u0440"
    ],
    "wof:name":"El Ksour",
    "wof:placetype":"locality"
},
  "geometry": {"coordinates":[6.07167,33.22528],"type":"Point"}
}