{
  "type": "Feature",
  "properties": {
    "gn:admin1_code":"26.0",
    "gn:asciiname":"Ouled Bel Hacene",
    "gn:country_code":"DZ",
    "gn:dem":73,
    "gn:feature_class":"P",
    "gn:feature_code":"PPL",
    "gn:name":"Ouled Bel Hac\u00e8ne",
    "gn:population":0,
    "gn:timezone":"Africa/Algiers",
    "iso:country":"DZ",
    "wof:name":"Ouled Bel Hacene",
    "wof:placetype":"locality"
},
  "geometry": {"coordinates":[0.06096,35.55403],"type":"Point"}
}