{
  "type": "Feature",
  "properties": {
    "gn:admin1_code":"18.0",
    "gn:asciiname":"Azrou Bou Ammar",
    "gn:country_code":"DZ",
    "gn:dem":171,
    "gn:feature_class":"P",
    "gn:feature_code":"PPL",
    "gn:name":"Azrou Bou Ammar",
    "gn:population":0,
    "gn:timezone":"Africa/Algiers",
    "iso:country":"DZ",
    "wof:name":"Azrou Bou Ammar",
    "wof:placetype":"locality"
},
  "geometry": {"coordinates":[4.93664,36.65513],"type":"Point"}
}