{
  "type": "Feature",
  "properties": {
    "gn:admin1_code":"6.0",
    "gn:asciiname":"Ouled Saha",
    "gn:country_code":"DZ",
    "gn:dem":733,
    "gn:feature_class":"P",
    "gn:feature_code":"PPL",
    "gn:name":"Ouled Saha",
    "gn:population":0,
    "gn:timezone":"Africa/Algiers",
    "iso:country":"DZ",
    "wof:name":"Ouled Saha",
    "wof:placetype":"locality"
},
  "geometry": {"coordinates":[2.39848,35.56454],"type":"Point"}
}