{
  "type": "Feature",
  "properties": {
    "gn:admin1_code":"18.0",
    "gn:asciiname":"Oued Ghir",
    "gn:country_code":"DZ",
    "gn:dem":66,
    "gn:feature_class":"P",
    "gn:feature_code":"PPL",
    "gn:name":"Oued Ghir",
    "gn:population":0,
    "gn:timezone":"Africa/Algiers",
    "iso:country":"DZ",
    "name:ara_x_preferred":[
        "\u0648\u0627\u062f\u064a \u063a\u064a\u0631"
    ],
    "name:azb_x_preferred":[
        "\u0648\u0627\u062f\u06cc \u063a\u06cc\u0631"
    ],
    "name:fas_x_preferred":[
        "\u0648\u0627\u062f\u06cc \u063a\u06cc\u0631"
    ],
    "name:fra_x_preferred":[
        "Oued Ghir"
    ],
    "name:ita_x_preferred":[
        "Oued Ghir"
    ],
    "name:msa_x_preferred":[
        "Oued Ghir"
    ],
    "name:por_x_preferred":[
        "Oued Ghir"
    ],
    "name:ron_x_preferred":[
        "Oued Ghir"
    ],
    "name:spa_x_preferred":[
        "Oued Ghir"
    ],
    "name:und_x_variant":[
        "La R\u00e9union",
        "Oued Rhir"
    ],
    "name:vie_x_preferred":[
        "Oued Ghir"
    ],
    "name:zho_x_preferred":[
        "\u74e6\u8fea\u5409\u723e"
    ],
    "wof:name":"Oued Ghir",
    "wof:placetype":"locality"
},
  "geometry": {"coordinates":[4.97731,36.71044000000001],"type":"Point"}
}