{
  "type": "Feature",
  "properties": {
    "gn:admin1_code":"18.0",
    "gn:asciiname":"Oued Ghir",
    "gn:country_code":"DZ",
    "gn:dem":66,
    "gn:feature_class":"P",
    "gn:feature_code":"PPL",
    "gn:name":"Oued Ghir",
    "gn:population":0,
    "gn:timezone":"Africa/Algiers",
    "iso:country":"DZ",
    "name:und_x_variant":[
        "La R\u00e9union",
        "Oued Rhir",
        "Oued Ghir"
    ],
    "wof:name":"Oued Ghir",
    "wof:placetype":"locality"
},
  "geometry": {"coordinates":[4.97731,36.71044000000001],"type":"Point"}
}