{
  "type": "Feature",
  "properties": {
    "gn:admin1_code":"26.0",
    "gn:asciiname":"Douar Ouled Youb",
    "gn:country_code":"DZ",
    "gn:dem":394,
    "gn:feature_class":"P",
    "gn:feature_code":"PPL",
    "gn:name":"Douar Ouled Youb",
    "gn:population":0,
    "gn:timezone":"Africa/Algiers",
    "iso:country":"DZ",
    "name:und_x_variant":[
        "Douar Ouled Ali Deniou",
        "Douar Ouled Youb",
        "Ouled Ali Deniou"
    ],
    "wof:name":"Douar Ouled Youb",
    "wof:placetype":"locality"
},
  "geometry": {"coordinates":[0.50022,35.44885],"type":"Point"}
}