{
  "type": "Feature",
  "properties": {
    "gn:admin1_code":"21.0",
    "gn:asciiname":"Kassim",
    "gn:country_code":"DZ",
    "gn:dem":355,
    "gn:feature_class":"P",
    "gn:feature_code":"PPL",
    "gn:name":"Kassim",
    "gn:population":0,
    "gn:timezone":"Africa/Algiers",
    "iso:country":"DZ",
    "wof:name":"Kassim",
    "wof:placetype":"locality"
},
  "geometry": {"coordinates":[4.20386,36.33737],"type":"Point"}
}