{
  "type": "Feature",
  "properties": {
    "gn:admin1_code":"43.0",
    "gn:asciiname":"Sidi Liman",
    "gn:country_code":"DZ",
    "gn:dem":85,
    "gn:feature_class":"P",
    "gn:feature_code":"PPL",
    "gn:name":"Sidi Liman",
    "gn:population":0,
    "gn:timezone":"Africa/Algiers",
    "iso:country":"DZ",
    "wof:name":"Sidi Liman",
    "wof:placetype":"locality"
},
  "geometry": {"coordinates":[6.90617,33.29146],"type":"Point"}
}