{
  "type": "Feature",
  "properties": {
    "gn:admin1_code":"26.0",
    "gn:asciiname":"Ouled Faya",
    "gn:cc2":"DZ",
    "gn:country_code":"DZ",
    "gn:dem":496,
    "gn:feature_class":"P",
    "gn:feature_code":"PPL",
    "gn:name":"Ouled Faya",
    "gn:population":0,
    "gn:timezone":"Africa/Algiers",
    "iso:country":"DZ",
    "name:und_x_variant":[
        "Douar Ouled Yahya",
        "Ouled Faya"
    ],
    "wof:name":"Ouled Faya",
    "wof:placetype":"locality"
},
  "geometry": {"coordinates":[0.195,35.53639000000001],"type":"Point"}
}