{
  "type": "Feature",
  "properties": {
    "gn:admin1_code":"35.0",
    "gn:asciiname":"Tinsissine",
    "gn:country_code":"DZ",
    "gn:dem":429,
    "gn:feature_class":"P",
    "gn:feature_code":"PPL",
    "gn:name":"Tinsissine",
    "gn:population":0,
    "gn:timezone":"Africa/Algiers",
    "iso:country":"DZ",
    "name:und_x_variant":[
        "Mechta Tinessissine",
        "Tinessissine"
    ],
    "wof:name":"Tinsissine",
    "wof:placetype":"locality"
},
  "geometry": {"coordinates":[2.1071,36.09064],"type":"Point"}
}