{
  "type": "Feature",
  "properties": {
    "gn:admin1_code":"18.0",
    "gn:asciiname":"Ibarissene",
    "gn:country_code":"DZ",
    "gn:dem":806,
    "gn:feature_class":"P",
    "gn:feature_code":"PPL",
    "gn:name":"Ibarissene",
    "gn:population":0,
    "gn:timezone":"Africa/Algiers",
    "iso:country":"DZ",
    "wof:name":"Ibarissene",
    "wof:placetype":"locality"
},
  "geometry": {"coordinates":[4.83333,36.75],"type":"Point"}
}