{
  "type": "Feature",
  "properties": {
    "gn:admin1_code":"13.0",
    "gn:asciiname":"Ouled Ali",
    "gn:country_code":"DZ",
    "gn:dem":659,
    "gn:feature_class":"P",
    "gn:feature_code":"PPL",
    "gn:name":"Ouled Ali",
    "gn:population":0,
    "gn:timezone":"Africa/Algiers",
    "iso:country":"DZ",
    "wof:name":"Ouled Ali",
    "wof:placetype":"locality"
},
  "geometry": {"coordinates":[0.63282,35.09197],"type":"Point"}
}