{
  "type": "Feature",
  "properties": {
    "gn:admin1_code":"7.0",
    "gn:asciiname":"Douar Ouled el Mokhtar",
    "gn:country_code":"DZ",
    "gn:dem":206,
    "gn:feature_class":"P",
    "gn:feature_code":"PPL",
    "gn:name":"Douar Ouled el Mokhtar",
    "gn:population":0,
    "gn:timezone":"Africa/Algiers",
    "iso:country":"DZ",
    "name:und_x_variant":[
        "Douar Ouled Mokretar",
        "Douar Ouled el Mokhtar",
        "Douar Ouled Mokhetar"
    ],
    "wof:name":"Douar Ouled el Mokhtar",
    "wof:placetype":"locality"
},
  "geometry": {"coordinates":[0.2163,35.86421],"type":"Point"}
}