{
  "type": "Feature",
  "properties": {
    "gn:admin1_code":"55.0",
    "gn:asciiname":"Imsad",
    "gn:country_code":"DZ",
    "gn:dem":544,
    "gn:feature_class":"P",
    "gn:feature_code":"PPL",
    "gn:name":"Imsad",
    "gn:population":0,
    "gn:timezone":"Africa/Algiers",
    "iso:country":"DZ",
    "wof:name":"Imsad",
    "wof:placetype":"locality"
},
  "geometry": {"coordinates":[1.76198,36.37836],"type":"Point"}
}