{
  "type": "Feature",
  "properties": {
    "iso:country":"DZ",
    "name:ara_x_preferred":[
        "\u0627\u0644\u0645\u0631\u0633\u0649 \u0627\u0644\u0643\u0628\u064a\u0631"
    ],
    "name:ara_x_variant":[
        "\u0628\u0644\u062f\u064a\u0629 \u0627\u0644\u0645\u0631\u0633\u0649 \u0627\u0644\u0643\u0628\u064a\u0631"
    ],
    "name:ast_x_preferred":[
        "Mazalquivir"
    ],
    "name:azb_x_preferred":[
        "\u0645\u0631\u0633\u06cc \u06a9\u0628\u06cc\u0631"
    ],
    "name:aze_x_preferred":[
        "Mers \u018fl K\u0259bir"
    ],
    "name:cat_x_preferred":[
        "Mers el-Kebir"
    ],
    "name:ceb_x_preferred":[
        "Mers el Kebir"
    ],
    "name:deu_x_preferred":[
        "Mers-el-K\u00e9bir"
    ],
    "name:ell_x_preferred":[
        "\u039c\u03b5\u03c1\u03c2 \u0395\u03bb \u039a\u03b5\u03bc\u03c0\u03af\u03c1"
    ],
    "name:eng_x_preferred":[
        "Mers El K\u00e9bir"
    ],
    "name:epo_x_preferred":[
        "Marsalkibir"
    ],
    "name:est_x_preferred":[
        "Mers el-K\u00e9bir"
    ],
    "name:eus_x_preferred":[
        "Mers el-Kebir"
    ],
    "name:fas_x_preferred":[
        "\u0645\u0631\u0633\u0649 \u06a9\u0628\u06cc\u0631"
    ],
    "name:fra_x_historical":[
        "Saint Andr\u00e9 de Mers-el-K\u00e9bir"
    ],
    "name:fra_x_preferred":[
        "Mers el-K\u00e9bir"
    ],
    "name:fra_x_variant":[
        "Saint Andr\u00e9 de Mers-el-K\u00e9bir"
    ],
    "name:ita_x_preferred":[
        "Mers-el-K\u00e9bir"
    ],
    "name:jpn_x_preferred":[
        "\u30e1\u30eb\u30b9\u30fb\u30a8\u30eb\u30fb\u30b1\u30d3\u30fc\u30eb"
    ],
    "name:kor_x_preferred":[
        "\uba54\ub974\uc2a4\uc5d8\ucf00\ube44\ub974"
    ],
    "name:mkd_x_preferred":[
        "\u041c\u0435\u0440\u0441 \u0435\u043b-\u041a\u0435\u0431\u0438\u0440"
    ],
    "name:msa_x_preferred":[
        "Mers El K\u00e9bir"
    ],
    "name:nan_x_preferred":[
        "Mers el-K\u00e9bir"
    ],
    "name:nld_x_preferred":[
        "Mers-el-K\u00e9bir"
    ],
    "name:nob_x_preferred":[
        "Mers-el-K\u00e9bir"
    ],
    "name:pol_x_preferred":[
        "Al-Marsa al-Kabir"
    ],
    "name:por_x_preferred":[
        "Mers El K\u00e9bir"
    ],
    "name:ron_x_preferred":[
        "Mers-el-Kebir"
    ],
    "name:rus_x_preferred":[
        "\u041c\u0435\u0440\u0441-\u044d\u043b\u044c-\u041a\u0435\u0431\u0438\u0440"
    ],
    "name:spa_x_preferred":[
        "Mazalquivir"
    ],
    "name:swe_x_preferred":[
        "Mers-el-K\u00e9bir"
    ],
    "name:tur_x_preferred":[
        "Mers\u00fc'l-Kebir"
    ],
    "name:ukr_x_preferred":[
        "\u041c\u0435\u0440\u0441-\u0435\u043b\u044c-\u041a\u0435\u0431\u0456\u0440"
    ],
    "name:und_x_variant":[
        "Mers el Kabir"
    ],
    "name:vie_x_preferred":[
        "Mers El Kebir"
    ],
    "name:zho_x_preferred":[
        "\u51f1\u6bd4\u723e\u6e2f"
    ],
    "qs:gn_country":"DZ",
    "qs:gn_fcode":"PPL",
    "qs:gn_pop":20178,
    "qs:name":"Mers el Kebir",
    "qs:name_adm0":"\u0627\u0644\u062c\u0632\u0627\u0626\u0631",
    "qs:name_adm1":"\u0648\u0644\u0627\u064a\u0629 \u0648\u0647\u0631\u0627\u0646",
    "qs:photos":17,
    "qs:photos_1k":3,
    "qs:photos_9k":1,
    "qs:photos_9r":1,
    "qs:photos_all":17,
    "qs:photos_sr":1,
    "qs:placetype":"Town",
    "qs:pop_sr":"7",
    "qs:woe_adm0":23424740,
    "wd:wordcount":389,
    "wof:name":"Mers el Kebir",
    "wof:placetype":"locality",
    "wof:population":20178
},
  "geometry": {"coordinates":[-0.7081,35.7279],"type":"Point"}
}