{
  "type": "Feature",
  "properties": {
    "gn:admin1_code":"39.0",
    "gn:asciiname":"Mechta Oulad Gassem",
    "gn:country_code":"DZ",
    "gn:dem":623,
    "gn:feature_class":"P",
    "gn:feature_code":"PPL",
    "gn:name":"Mechta Oulad Gassem",
    "gn:population":0,
    "gn:timezone":"Africa/Algiers",
    "iso:country":"DZ",
    "wof:name":"Mechta Oulad Gassem",
    "wof:placetype":"locality"
},
  "geometry": {"coordinates":[4.33192,36.08518],"type":"Point"}
}