{
  "type": "Feature",
  "properties": {
    "gn:admin1_code":"3.0",
    "gn:asciiname":"Sidi Aissa",
    "gn:country_code":"DZ",
    "gn:dem":945,
    "gn:feature_class":"P",
    "gn:feature_code":"PPL",
    "gn:name":"Sidi A\u00efssa",
    "gn:population":0,
    "gn:timezone":"Africa/Algiers",
    "iso:country":"DZ",
    "wof:name":"Sidi Aissa",
    "wof:placetype":"locality"
},
  "geometry": {"coordinates":[5.62823,35.48324],"type":"Point"}
}