{
  "type": "Feature",
  "properties": {
    "gn:admin1_code":"18.0",
    "gn:asciiname":"Tamokra",
    "gn:country_code":"DZ",
    "gn:dem":775,
    "gn:feature_class":"P",
    "gn:feature_code":"PPL",
    "gn:name":"Tamokra",
    "gn:population":0,
    "gn:timezone":"Africa/Algiers",
    "iso:country":"DZ",
    "wof:name":"Tamokra",
    "wof:placetype":"locality"
},
  "geometry": {"coordinates":[4.66446,36.39322],"type":"Point"}
}