{
  "type": "Feature",
  "properties": {
    "gn:admin1_code":"18.0",
    "gn:asciiname":"Tamokra",
    "gn:country_code":"DZ",
    "gn:dem":775,
    "gn:feature_class":"P",
    "gn:feature_code":"PPL",
    "gn:name":"Tamokra",
    "gn:population":0,
    "gn:timezone":"Africa/Algiers",
    "iso:country":"DZ",
    "name:ara_x_preferred":[
        "\u062a\u0645\u0642\u0631\u0629"
    ],
    "name:azb_x_preferred":[
        "\u062a\u0645\u0642\u0631\u0647"
    ],
    "name:fas_x_preferred":[
        "\u062a\u0645\u0642\u0631\u0647"
    ],
    "name:fra_x_preferred":[
        "Tamokra"
    ],
    "name:ita_x_preferred":[
        "Tamokra"
    ],
    "name:kab_x_preferred":[
        "Tamuqra"
    ],
    "name:msa_x_preferred":[
        "Tamokra"
    ],
    "name:por_x_preferred":[
        "Tamokra"
    ],
    "name:ron_x_preferred":[
        "Tamokra"
    ],
    "name:spa_x_preferred":[
        "Tamokra"
    ],
    "name:vie_x_preferred":[
        "Tamokra"
    ],
    "name:zho_x_preferred":[
        "\u5854\u83ab\u514b\u62c9"
    ],
    "wof:name":"Tamokra",
    "wof:placetype":"locality"
},
  "geometry": {"coordinates":[4.66446,36.39322],"type":"Point"}
}