{
  "type": "Feature",
  "properties": {
    "gn:admin1_code":"14.0",
    "gn:asciiname":"Tabouda",
    "gn:country_code":"DZ",
    "gn:dem":601,
    "gn:feature_class":"P",
    "gn:feature_code":"PPL",
    "gn:name":"Tabouda",
    "gn:population":0,
    "gn:timezone":"Africa/Algiers",
    "iso:country":"DZ",
    "name:ara_x_preferred":[
        "\u062a\u0627\u0628\u0648\u062f\u0629"
    ],
    "name:cat_x_preferred":[
        "Tabouda"
    ],
    "name:ceb_x_preferred":[
        "Tabouda"
    ],
    "name:swe_x_preferred":[
        "Tabouda"
    ],
    "wof:name":"Tabouda",
    "wof:placetype":"locality"
},
  "geometry": {"coordinates":[4.43503,36.56797],"type":"Point"}
}