{
  "type": "Feature",
  "properties": {
    "gn:admin1_code":"36.0",
    "gn:asciiname":"Hassi el Ghella",
    "gn:country_code":"DZ",
    "gn:dem":122,
    "gn:feature_class":"P",
    "gn:feature_code":"PPL",
    "gn:name":"Hassi el Ghella",
    "gn:population":0,
    "gn:timezone":"Africa/Algiers",
    "iso:country":"DZ",
    "name:ara_x_preferred":[
        "\u062d\u0627\u0633\u064a \u0627\u0644\u063a\u0644\u0629"
    ],
    "name:azb_x_preferred":[
        "\u062d\u0627\u0633\u06cc \u063a\u0644\u0647"
    ],
    "name:fas_x_preferred":[
        "\u062d\u0627\u0633\u06cc \u063a\u0644\u0647"
    ],
    "name:fra_x_preferred":[
        "Hassi El Ghella"
    ],
    "name:ita_x_preferred":[
        "Hassi El Ghella"
    ],
    "name:kab_x_preferred":[
        "\u1e24asi L\u0263ella"
    ],
    "name:msa_x_preferred":[
        "Hassi El Ghella"
    ],
    "name:por_x_preferred":[
        "Hassi El Ghella"
    ],
    "name:ron_x_preferred":[
        "Hassi El Ghella"
    ],
    "name:spa_x_preferred":[
        "Hassi El Ghella"
    ],
    "name:und_x_variant":[
        "Er Rahel",
        "Massi-el-Ghella",
        "El Rahel",
        "Hassi el Rhella",
        "Hassi el Ghella"
    ],
    "name:vie_x_preferred":[
        "Hassi El Ghella"
    ],
    "name:zho_x_preferred":[
        "\u54c8\u897f\u84cb\u62c9"
    ],
    "wof:name":"Hassi el Ghella",
    "wof:placetype":"locality"
},
  "geometry": {"coordinates":[-1.05266,35.45534],"type":"Point"}
}