{
  "type": "Feature",
  "properties": {
    "gn:admin1_code":"36.0",
    "gn:asciiname":"Hassi el Ghella",
    "gn:country_code":"DZ",
    "gn:dem":122,
    "gn:feature_class":"P",
    "gn:feature_code":"PPL",
    "gn:name":"Hassi el Ghella",
    "gn:population":0,
    "gn:timezone":"Africa/Algiers",
    "iso:country":"DZ",
    "name:und_x_variant":[
        "Er Rahel",
        "Massi-el-Ghella",
        "El Rahel",
        "Hassi el Rhella",
        "Hassi el Ghella"
    ],
    "wof:name":"Hassi el Ghella",
    "wof:placetype":"locality"
},
  "geometry": {"coordinates":[-1.05266,35.45534],"type":"Point"}
}