{
  "type": "Feature",
  "properties": {
    "gn:admin1_code":"21.0",
    "gn:asciiname":"Ouled Tessala",
    "gn:country_code":"DZ",
    "gn:dem":125,
    "gn:feature_class":"P",
    "gn:feature_code":"PPL",
    "gn:name":"Ouled Tessala",
    "gn:population":0,
    "gn:timezone":"Africa/Algiers",
    "iso:country":"DZ",
    "wof:name":"Ouled Tessala",
    "wof:placetype":"locality"
},
  "geometry": {"coordinates":[3.58076,36.54638],"type":"Point"}
}