{
  "type": "Feature",
  "properties": {
    "gn:admin1_code":"15.0",
    "gn:asciiname":"'Ain Tellout",
    "gn:country_code":"DZ",
    "gn:dem":728,
    "gn:feature_class":"P",
    "gn:feature_code":"PPL",
    "gn:name":"\u2019A\u00efn Tellout",
    "gn:population":0,
    "gn:timezone":"Africa/Algiers",
    "iso:country":"DZ",
    "name:und_x_variant":[
        "Aine Tellout",
        "\u2019A\u00efn Tellout"
    ],
    "wof:name":"'Ain Tellout",
    "wof:placetype":"locality"
},
  "geometry": {"coordinates":[-0.9571,34.92565],"type":"Point"}
}