{
  "type": "Feature",
  "properties": {
    "gn:admin1_code":"20.0",
    "gn:asciiname":"Oulad el Hallouat",
    "gn:country_code":"DZ",
    "gn:dem":775,
    "gn:feature_class":"P",
    "gn:feature_code":"PPL",
    "gn:name":"Oulad el Hallouat",
    "gn:population":0,
    "gn:timezone":"Africa/Algiers",
    "iso:country":"DZ",
    "name:und_x_variant":[
        "Oulad el Allaouat",
        "Oulad el Hallouat",
        "Oulad \u2019Aliouet"
    ],
    "wof:name":"Oulad el Hallouat",
    "wof:placetype":"locality"
},
  "geometry": {"coordinates":[3.03462,36.40678],"type":"Point"}
}