{
  "type": "Feature",
  "properties": {
    "gn:admin1_code":"6.0",
    "gn:asciiname":"'Ain Guelieb et Tsour",
    "gn:country_code":"DZ",
    "gn:dem":838,
    "gn:feature_class":"P",
    "gn:feature_code":"PPL",
    "gn:name":"\u2019A\u00efn Guelieb et Tsour",
    "gn:population":0,
    "gn:timezone":"Africa/Algiers",
    "iso:country":"DZ",
    "wof:name":"'Ain Guelieb et Tsour",
    "wof:placetype":"locality"
},
  "geometry": {"coordinates":[3.21727,35.77802],"type":"Point"}
}