{
  "type": "Feature",
  "properties": {
    "iso:country":"DZ",
    "name:ara_x_preferred":[
        "\u0628\u0646\u064a \u0645\u0633\u062a\u0627\u0631"
    ],
    "name:arz_x_preferred":[
        "\u0628\u0646\u0649 \u0645\u0633\u062a\u0627\u0631"
    ],
    "name:azb_x_preferred":[
        "\u0628\u0646\u06cc \u0645\u0633\u062a\u0627\u0631"
    ],
    "name:ceb_x_preferred":[
        "Beni Mester"
    ],
    "name:deu_x_preferred":[
        "Beni Mester"
    ],
    "name:eng_x_preferred":[
        "Beni Mester"
    ],
    "name:fas_x_preferred":[
        "\u0628\u0646\u06cc \u0645\u0633\u062a\u0627\u0631"
    ],
    "name:fra_x_preferred":[
        "Beni Mester"
    ],
    "name:ita_x_preferred":[
        "Beni Mester"
    ],
    "name:kab_x_preferred":[
        "Bni Mestar"
    ],
    "name:msa_x_preferred":[
        "Beni Mester"
    ],
    "name:nan_x_preferred":[
        "Beni Mester"
    ],
    "name:nld_x_preferred":[
        "Beni Mester"
    ],
    "name:pol_x_preferred":[
        "Bani Mastar"
    ],
    "name:pol_x_variant":[
        "Gmina Bani Mastar"
    ],
    "name:por_x_preferred":[
        "Beni Mester"
    ],
    "name:ron_x_preferred":[
        "Beni Mester"
    ],
    "name:spa_x_preferred":[
        "Beni Mester"
    ],
    "name:swe_x_preferred":[
        "Beni Mester"
    ],
    "name:uzb_x_preferred":[
        "Beni Mester"
    ],
    "name:vie_x_preferred":[
        "Beni Mester"
    ],
    "name:zho_min_nan_x_preferred":[
        "Beni Mester"
    ],
    "name:zul_x_preferred":[
        "Beni Mester"
    ],
    "qs:gn_country":"DZ",
    "qs:gn_fcode":"PPL",
    "qs:gn_pop":19808,
    "qs:name":"Beni Mester",
    "qs:name_adm0":"\u0627\u0644\u062c\u0632\u0627\u0626\u0631",
    "qs:name_adm1":"\u0648\u0644\u0627\u064a\u0629 \u062a\u0644\u0645\u0633\u0627\u0646",
    "qs:photos":0,
    "qs:photos_1k":0,
    "qs:photos_9k":0,
    "qs:photos_9r":0,
    "qs:photos_all":0,
    "qs:photos_sr":0,
    "qs:placetype":"Town",
    "qs:pop_sr":"6",
    "qs:woe_adm0":23424740,
    "wd:wordcount":38,
    "wof:name":"Beni Mester",
    "wof:placetype":"locality",
    "wof:population":19808
},
  "geometry": {"coordinates":[-1.42319,34.87045],"type":"Point"}
}