{
  "type": "Feature",
  "properties": {
    "gn:admin1_code":"12.0",
    "gn:asciiname":"Bazer Sakra",
    "gn:country_code":"DZ",
    "gn:dem":934,
    "gn:feature_class":"P",
    "gn:feature_code":"PPL",
    "gn:name":"Bazer Sakra",
    "gn:population":0,
    "gn:timezone":"Africa/Algiers",
    "iso:country":"DZ",
    "wof:name":"Bazer Sakra",
    "wof:placetype":"locality"
},
  "geometry": {"coordinates":[5.70972,36.11778],"type":"Point"}
}