{
  "type": "Feature",
  "properties": {
    "gn:admin1_code":"24.0",
    "gn:asciiname":"El Milia",
    "gn:country_code":"DZ",
    "gn:dem":58,
    "gn:feature_class":"P",
    "gn:feature_code":"PPL",
    "gn:name":"El Milia",
    "gn:population":0,
    "gn:timezone":"Africa/Algiers",
    "iso:country":"DZ",
    "wof:name":"El Milia",
    "wof:placetype":"locality"
},
  "geometry": {"coordinates":[6.2725,36.75472],"type":"Point"}
}