{
  "type": "Feature",
  "properties": {
    "gn:admin1_code":"24.0",
    "gn:asciiname":"El Milia",
    "gn:country_code":"DZ",
    "gn:dem":58,
    "gn:feature_class":"P",
    "gn:feature_code":"PPL",
    "gn:name":"El Milia",
    "gn:population":0,
    "gn:timezone":"Africa/Algiers",
    "iso:country":"DZ",
    "name:ara_x_preferred":[
        "\u0627\u0644\u0645\u064a\u0644\u064a\u0629"
    ],
    "name:azb_x_preferred":[
        "\u0645\u06cc\u0644\u06cc\u0647"
    ],
    "name:fas_x_preferred":[
        "\u0645\u06cc\u0644\u06cc\u0647"
    ],
    "name:fra_x_preferred":[
        "El Milia"
    ],
    "name:ita_x_preferred":[
        "El Milia"
    ],
    "name:kab_x_preferred":[
        "Lmileyya"
    ],
    "name:msa_x_preferred":[
        "El Milia"
    ],
    "name:por_x_preferred":[
        "El Milia"
    ],
    "name:ron_x_preferred":[
        "El Milia"
    ],
    "name:spa_x_preferred":[
        "El Milia"
    ],
    "name:vie_x_preferred":[
        "El Milia"
    ],
    "name:zho_x_preferred":[
        "\u7c73\u5229\u8036"
    ],
    "wof:name":"El Milia",
    "wof:placetype":"locality"
},
  "geometry": {"coordinates":[6.2725,36.75472],"type":"Point"}
}