{
  "type": "Feature",
  "properties": {
    "gn:admin1_code":"24.0",
    "gn:asciiname":"Arezzou",
    "gn:country_code":"DZ",
    "gn:dem":232,
    "gn:feature_class":"P",
    "gn:feature_code":"PPL",
    "gn:name":"Arezzou",
    "gn:population":0,
    "gn:timezone":"Africa/Algiers",
    "iso:country":"DZ",
    "wof:name":"Arezzou",
    "wof:placetype":"locality"
},
  "geometry": {"coordinates":[5.55753,36.66117],"type":"Point"}
}