{
  "type": "Feature",
  "properties": {
    "gn:country":"DZ",
    "gn:fcode":"PPL",
    "gn:pop":80,
    "iso:country":"DZ",
    "qs:name":"Ababsa",
    "qs:photos_9r":0,
    "qs:photos_sr":0,
    "qs:pop_sr":"1",
    "wd:wordcount":97,
    "wof:name":"Ababsa",
    "wof:placetype":"locality",
    "wof:population":80
},
  "geometry": {"coordinates":[0.72334,35.70697],"type":"Point"}
}