{
  "type": "Feature",
  "properties": {
    "gn:country":"DZ",
    "gn:fcode":"PPL",
    "gn:population":80,
    "iso:country":"DZ",
    "name:azb_x_preferred":[
        "\u0622\u0628\u0627\u0628\u0633\u0627"
    ],
    "name:fas_x_preferred":[
        "\u0622\u0628\u0627\u0628\u0633\u0627"
    ],
    "name:por_x_preferred":[
        "Ababsa"
    ],
    "qs:name":"Ababsa",
    "qs:photos_9r":0,
    "qs:photos_sr":0,
    "qs:pop_sr":"1",
    "wd:wordcount":97,
    "wof:name":"Ababsa",
    "wof:placetype":"locality",
    "wof:population":80
},
  "geometry": {"coordinates":[0.72334,35.70697],"type":"Point"}
}