{
  "type": "Feature",
  "properties": {
    "gn:admin1_code":"14.0",
    "gn:asciiname":"Egreb",
    "gn:country_code":"DZ",
    "gn:dem":739,
    "gn:feature_class":"P",
    "gn:feature_code":"PPL",
    "gn:name":"Egreb",
    "gn:population":0,
    "gn:timezone":"Africa/Algiers",
    "iso:country":"DZ",
    "wof:name":"Egreb",
    "wof:placetype":"locality"
},
  "geometry": {"coordinates":[4.4344,36.56515],"type":"Point"}
}