{
  "type": "Feature",
  "properties": {
    "gn:admin1_code":"7.0",
    "gn:asciiname":"Jardins de Figuiers",
    "gn:country_code":"DZ",
    "gn:dem":234,
    "gn:feature_class":"P",
    "gn:feature_code":"PPLL",
    "gn:name":"Jardins de Figuiers",
    "gn:population":0,
    "gn:timezone":"Africa/Algiers",
    "iso:country":"DZ",
    "wof:name":"Jardins de Figuiers",
    "wof:placetype":"locality"
},
  "geometry": {"coordinates":[0.1275,35.86222],"type":"Point"}
}