{
  "type": "Feature",
  "properties": {
    "gn:admin1_code":"41.0",
    "gn:asciiname":"Boukaat Ouled Kouider",
    "gn:country_code":"DZ",
    "gn:dem":477,
    "gn:feature_class":"P",
    "gn:feature_code":"PPL",
    "gn:name":"Boukaat Ouled Kouider",
    "gn:population":0,
    "gn:timezone":"Africa/Algiers",
    "iso:country":"DZ",
    "wof:name":"Boukaat Ouled Kouider",
    "wof:placetype":"locality"
},
  "geometry": {"coordinates":[1.35088,36.06848],"type":"Point"}
}