{
  "type": "Feature",
  "properties": {
    "gn:admin1_code":"21.0",
    "gn:asciiname":"Beaupretre",
    "gn:country_code":"DZ",
    "gn:dem":390,
    "gn:feature_class":"P",
    "gn:feature_code":"PPL",
    "gn:name":"Beaupr\u00eatre",
    "gn:population":0,
    "gn:timezone":"Africa/Algiers",
    "iso:country":"DZ",
    "name:und_x_variant":[
        "Bou Faima",
        "Beaupr\u00eate",
        "Beaupr\u00eatre"
    ],
    "wof:name":"Beaupretre",
    "wof:placetype":"locality"
},
  "geometry": {"coordinates":[3.80708,36.55164],"type":"Point"}
}