{
  "type": "Feature",
  "properties": {
    "gn:admin1_code":"3.0",
    "gn:asciiname":"Mzata",
    "gn:country_code":"DZ",
    "gn:dem":1028,
    "gn:feature_class":"P",
    "gn:feature_code":"PPL",
    "gn:name":"Mzata",
    "gn:population":0,
    "gn:timezone":"Africa/Algiers",
    "iso:country":"DZ",
    "wof:name":"Mzata",
    "wof:placetype":"locality"
},
  "geometry": {"coordinates":[6.31754,35.21561],"type":"Point"}
}