{
  "type": "Feature",
  "properties": {
    "gn:admin1_code":"51.0",
    "gn:asciiname":"Douar Yazerou",
    "gn:country_code":"DZ",
    "gn:dem":356,
    "gn:feature_class":"P",
    "gn:feature_code":"PPLL",
    "gn:name":"Douar Yazerou",
    "gn:population":0,
    "gn:timezone":"Africa/Algiers",
    "iso:country":"DZ",
    "wof:name":"Douar Yazerou",
    "wof:placetype":"locality"
},
  "geometry": {"coordinates":[0.65831,35.59334000000001],"type":"Point"}
}