{
  "type": "Feature",
  "properties": {
    "gn:admin1_code":"3.0",
    "gn:asciiname":"Tibehirine",
    "gn:country_code":"DZ",
    "gn:dem":1422,
    "gn:feature_class":"P",
    "gn:feature_code":"PPL",
    "gn:name":"Tibehirine",
    "gn:population":0,
    "gn:timezone":"Africa/Algiers",
    "iso:country":"DZ",
    "wof:name":"Tibehirine",
    "wof:placetype":"locality"
},
  "geometry": {"coordinates":[6.41041,35.31562],"type":"Point"}
}