{
  "type": "Feature",
  "properties": {
    "gn:admin1_code":"14.0",
    "gn:asciiname":"Iguer-n-Tala",
    "gn:country_code":"DZ",
    "gn:dem":381,
    "gn:feature_class":"P",
    "gn:feature_code":"PPL",
    "gn:name":"Iguer-n-Tala",
    "gn:population":0,
    "gn:timezone":"Africa/Algiers",
    "iso:country":"DZ",
    "wof:name":"Iguer-n-Tala",
    "wof:placetype":"locality"
},
  "geometry": {"coordinates":[4.182,36.87357],"type":"Point"}
}