{
  "type": "Feature",
  "properties": {
    "gn:admin1_code":"15.0",
    "gn:asciiname":"Bab el Assa",
    "gn:country_code":"DZ",
    "gn:dem":352,
    "gn:feature_class":"P",
    "gn:feature_code":"PPL",
    "gn:name":"Bab el Assa",
    "gn:population":0,
    "gn:timezone":"Africa/Algiers",
    "iso:country":"DZ",
    "name:und_x_variant":[
        "Bab el Hassa",
        "Bab el Assa"
    ],
    "wof:name":"Bab el Assa",
    "wof:placetype":"locality"
},
  "geometry": {"coordinates":[-2.0307,34.96683],"type":"Point"}
}