{
  "type": "Feature",
  "properties": {
    "gn:admin1_code":"15.0",
    "gn:asciiname":"Bab el Assa",
    "gn:country_code":"DZ",
    "gn:dem":352,
    "gn:feature_class":"P",
    "gn:feature_code":"PPL",
    "gn:name":"Bab el Assa",
    "gn:population":0,
    "gn:timezone":"Africa/Algiers",
    "iso:country":"DZ",
    "name:ara_x_preferred":[
        "\u0628\u0627\u0628 \u0627\u0644\u0639\u0633\u0629"
    ],
    "name:azb_x_preferred":[
        "\u0628\u0627\u0628 \u0639\u0633\u0647"
    ],
    "name:fas_x_preferred":[
        "\u0628\u0627\u0628 \u0639\u0633\u0647"
    ],
    "name:fra_x_preferred":[
        "Bab El Assa"
    ],
    "name:ita_x_preferred":[
        "Bab El Assa"
    ],
    "name:msa_x_preferred":[
        "Bab El Assa"
    ],
    "name:pol_x_preferred":[
        "Bab al-Asa"
    ],
    "name:por_x_preferred":[
        "Bab El Assa"
    ],
    "name:ron_x_preferred":[
        "Bab El Assa"
    ],
    "name:spa_x_preferred":[
        "Bab El Assa"
    ],
    "name:und_x_variant":[
        "Bab el Hassa",
        "Bab el Assa"
    ],
    "name:vie_x_preferred":[
        "Bab El Assa"
    ],
    "wof:name":"Bab el Assa",
    "wof:placetype":"locality"
},
  "geometry": {"coordinates":[-2.0307,34.96683],"type":"Point"}
}