{
  "type": "Feature",
  "properties": {
    "gn:admin1_code":"26.0",
    "gn:asciiname":"Douar el Bailek",
    "gn:country_code":"DZ",
    "gn:dem":431,
    "gn:feature_class":"P",
    "gn:feature_code":"PPL",
    "gn:name":"Douar el Bailek",
    "gn:population":0,
    "gn:timezone":"Africa/Algiers",
    "iso:country":"DZ",
    "wof:name":"Douar el Bailek",
    "wof:placetype":"locality"
},
  "geometry": {"coordinates":[0.51638,35.41237],"type":"Point"}
}