{
  "type": "Feature",
  "properties": {
    "iso:country":"DZ",
    "name:ara_x_preferred":[
        "\u0628\u0644\u062f\u064a\u0629 \u0628\u0631\u062c \u0627\u0644\u0628\u062d\u0631\u064a"
    ],
    "name:arz_x_preferred":[
        "\u0628\u0631\u062c \u0627\u0644\u0628\u062d\u0631\u0649"
    ],
    "name:azb_x_preferred":[
        "\u0628\u0631\u062c \u0628\u062d\u0631\u06cc"
    ],
    "name:ell_x_preferred":[
        "\u039c\u03c0\u03bf\u03c1\u03c4\u03b6 \u0395\u03bb \u039c\u03c0\u03b1\u03c7\u03c1\u03af"
    ],
    "name:eng_x_preferred":[
        "Bordj El Bahri"
    ],
    "name:fas_x_preferred":[
        "\u0634\u0647\u0631\u062f\u0627\u0631\u06cc \u0628\u0631\u062c \u0628\u062d\u0631\u06cc"
    ],
    "name:fra_x_preferred":[
        "Bordj El Bahri"
    ],
    "name:ita_x_preferred":[
        "Bordj El Bahri"
    ],
    "name:jpn_x_preferred":[
        "\u30a2\u30eb\u30b8\u30a7\u6c96\u5408"
    ],
    "name:kab_x_preferred":[
        "Burj Lbe\u1e25ri"
    ],
    "name:msa_x_preferred":[
        "Bordj El Bahri"
    ],
    "name:nan_x_preferred":[
        "Bordj El Bahri"
    ],
    "name:nld_x_preferred":[
        "Bordj El Bahri"
    ],
    "name:por_x_preferred":[
        "Bordj El Bahri"
    ],
    "name:ron_x_preferred":[
        "Bordj El Bahri"
    ],
    "name:spa_x_preferred":[
        "Bordj El Bahri"
    ],
    "name:tur_x_preferred":[
        "Burc\u00fc'l-Bahri"
    ],
    "name:und_x_variant":[
        "Matifou"
    ],
    "name:urd_x_preferred":[
        "\u0628\u0631\u062c \u0627\u0644\u0628\u062d\u0631\u06cc"
    ],
    "name:vie_x_preferred":[
        "Bordj El Bahri"
    ],
    "name:zho_min_nan_x_preferred":[
        "Bordj El Bahri"
    ],
    "name:zho_x_preferred":[
        "\u5df4\u8d6b\u91cc\u5821"
    ],
    "qs:gn_country":"DZ",
    "qs:gn_fcode":"PPL",
    "qs:gn_pop":0,
    "qs:name":"Bordj el Bahri",
    "qs:name_adm0":"\u0627\u0644\u062c\u0632\u0627\u0626\u0631",
    "qs:name_adm1":"Boumerdes",
    "qs:photos":136,
    "qs:photos_1k":28,
    "qs:photos_9k":1,
    "qs:photos_9r":3,
    "qs:photos_all":136,
    "qs:photos_sr":3,
    "qs:placetype":"Town",
    "qs:pop_sr":"0",
    "qs:woe_adm0":23424740,
    "wd:wordcount":46,
    "wof:name":"Bordj el Bahri",
    "wof:placetype":"locality"
},
  "geometry": {"coordinates":[3.24952,36.79068],"type":"Point"}
}