{
  "type": "Feature",
  "properties": {
    "gn:admin1_code":"7.0",
    "gn:asciiname":"Hassi Maameche",
    "gn:country_code":"DZ",
    "gn:dem":138,
    "gn:feature_class":"P",
    "gn:feature_code":"PPL",
    "gn:name":"Hassi Maameche",
    "gn:population":0,
    "gn:timezone":"Africa/Algiers",
    "iso:country":"DZ",
    "name:und_x_variant":[
        "Rivoli",
        "Hassi Lameche",
        "Hassi Maameche",
        "Hassi Mameche"
    ],
    "wof:name":"Hassi Maameche",
    "wof:placetype":"locality"
},
  "geometry": {"coordinates":[0.07329,35.86049000000001],"type":"Point"}
}