{
  "type": "Feature",
  "properties": {
    "gn:admin1_code":"7.0",
    "gn:asciiname":"Hassi Maameche",
    "gn:country_code":"DZ",
    "gn:dem":138,
    "gn:feature_class":"P",
    "gn:feature_code":"PPL",
    "gn:name":"Hassi Maameche",
    "gn:population":0,
    "gn:timezone":"Africa/Algiers",
    "iso:country":"DZ",
    "name:ara_x_preferred":[
        "\u062d\u0627\u0633\u064a \u0645\u0645\u0627\u0634"
    ],
    "name:azb_x_preferred":[
        "\u062d\u0627\u0633\u06cc \u0645\u0645\u0627\u0634"
    ],
    "name:fas_x_preferred":[
        "\u062d\u0627\u0633\u06cc \u0645\u0645\u0627\u0634"
    ],
    "name:fra_x_preferred":[
        "Hassi Mameche"
    ],
    "name:ita_x_preferred":[
        "Hassi Mameche"
    ],
    "name:kab_x_preferred":[
        "\u1e24asi Me\u025bmac"
    ],
    "name:msa_x_preferred":[
        "Hassi Mam\u00e8che"
    ],
    "name:por_x_preferred":[
        "Hassi Mam\u00e8che"
    ],
    "name:ron_x_preferred":[
        "Hassi Mameche"
    ],
    "name:spa_x_preferred":[
        "Hassi Mameche"
    ],
    "name:und_x_variant":[
        "Rivoli",
        "Hassi Lameche",
        "Hassi Maameche"
    ],
    "name:vie_x_preferred":[
        "Hassi Mameche"
    ],
    "wof:name":"Hassi Maameche",
    "wof:placetype":"locality"
},
  "geometry": {"coordinates":[0.07329,35.86049000000001],"type":"Point"}
}