{
  "type": "Feature",
  "properties": {
    "gn:admin1_code":"26.0",
    "gn:asciiname":"Sidi M'barek",
    "gn:country_code":"DZ",
    "gn:dem":981,
    "gn:feature_class":"P",
    "gn:feature_code":"PPL",
    "gn:name":"Sidi M\u2019barek",
    "gn:population":0,
    "gn:timezone":"Africa/Algiers",
    "iso:country":"DZ",
    "wof:name":"Sidi M'barek",
    "wof:placetype":"locality"
},
  "geometry": {"coordinates":[0.35811,35.17039],"type":"Point"}
}