{
  "type": "Feature",
  "properties": {
    "gn:admin1_code":"34.0",
    "gn:asciiname":"Taouennza",
    "gn:country_code":"DZ",
    "gn:dem":374,
    "gn:feature_class":"P",
    "gn:feature_code":"PPL",
    "gn:name":"Taouennza",
    "gn:population":0,
    "gn:timezone":"Africa/Algiers",
    "iso:country":"DZ",
    "name:und_x_variant":[
        "Touenza",
        "Taouenza",
        "Taouennza"
    ],
    "wof:name":"Taouennza",
    "wof:placetype":"locality"
},
  "geometry": {"coordinates":[0.04496,29.54082],"type":"Point"}
}