{
  "type": "Feature",
  "properties": {
    "gn:admin1_code":"13.0",
    "gn:asciiname":"Douar Kaddari",
    "gn:country_code":"DZ",
    "gn:dem":652,
    "gn:feature_class":"P",
    "gn:feature_code":"PPL",
    "gn:name":"Douar Kaddari",
    "gn:population":0,
    "gn:timezone":"Africa/Algiers",
    "iso:country":"DZ",
    "wof:name":"Douar Kaddari",
    "wof:placetype":"locality"
},
  "geometry": {"coordinates":[0.96739,35.34649],"type":"Point"}
}