{
  "type": "Feature",
  "properties": {
    "gn:admin1_code":"35.0",
    "gn:asciiname":"Bou Fatis",
    "gn:country_code":"DZ",
    "gn:dem":937,
    "gn:feature_class":"P",
    "gn:feature_code":"PPL",
    "gn:name":"Bou Fatis",
    "gn:population":0,
    "gn:timezone":"Africa/Algiers",
    "iso:country":"DZ",
    "wof:name":"Bou Fatis",
    "wof:placetype":"locality"
},
  "geometry": {"coordinates":[2.50056,35.99106],"type":"Point"}
}