{
  "type": "Feature",
  "properties": {
    "gn:admin1_code":"6.0",
    "gn:asciiname":"Bou Regaa",
    "gn:country_code":"DZ",
    "gn:dem":644,
    "gn:feature_class":"P",
    "gn:feature_code":"PPL",
    "gn:name":"Bou Regaa",
    "gn:population":0,
    "gn:timezone":"Africa/Algiers",
    "iso:country":"DZ",
    "wof:name":"Bou Regaa",
    "wof:placetype":"locality"
},
  "geometry": {"coordinates":[2.7221,35.85561],"type":"Point"}
}