{
  "type": "Feature",
  "properties": {
    "gn:admin1_code":"41.0",
    "gn:asciiname":"Thouabet",
    "gn:country_code":"DZ",
    "gn:dem":258,
    "gn:feature_class":"P",
    "gn:feature_code":"PPL",
    "gn:name":"Thouabet",
    "gn:population":0,
    "gn:timezone":"Africa/Algiers",
    "iso:country":"DZ",
    "wof:name":"Thouabet",
    "wof:placetype":"locality"
},
  "geometry": {"coordinates":[1.59979,36.09532],"type":"Point"}
}