{
  "type": "Feature",
  "properties": {
    "gn:admin1_code":"27.0",
    "gn:asciiname":"Et Touablia",
    "gn:country_code":"DZ",
    "gn:dem":412,
    "gn:feature_class":"P",
    "gn:feature_code":"PPL",
    "gn:name":"Et Touablia",
    "gn:population":0,
    "gn:timezone":"Africa/Algiers",
    "iso:country":"DZ",
    "wof:name":"Et Touablia",
    "wof:placetype":"locality"
},
  "geometry": {"coordinates":[4.32938,35.52146],"type":"Point"}
}