{
  "type": "Feature",
  "properties": {
    "gn:admin1_code":"12.0",
    "gn:asciiname":"Merdj Moumene",
    "gn:country_code":"DZ",
    "gn:dem":927,
    "gn:feature_class":"P",
    "gn:feature_code":"PPL",
    "gn:name":"Merdj Moumene",
    "gn:population":0,
    "gn:timezone":"Africa/Algiers",
    "iso:country":"DZ",
    "wof:name":"Merdj Moumene",
    "wof:placetype":"locality"
},
  "geometry": {"coordinates":[5.19724,36.41599],"type":"Point"}
}