{
  "type": "Feature",
  "properties": {
    "gn:admin1_code":"33.0",
    "gn:asciiname":"Mechta Mohammed Ben Bouzid",
    "gn:country_code":"DZ",
    "gn:dem":1180,
    "gn:feature_class":"P",
    "gn:feature_code":"PPLL",
    "gn:name":"Mechta Mohammed Ben Bouzid",
    "gn:population":0,
    "gn:timezone":"Africa/Algiers",
    "iso:country":"DZ",
    "wof:name":"Mechta Mohammed Ben Bouzid",
    "wof:placetype":"locality"
},
  "geometry": {"coordinates":[7.63191,35.28354],"type":"Point"}
}