{
  "type": "Feature",
  "properties": {
    "gn:admin1_code":"13.0",
    "gn:asciiname":"El Mzili",
    "gn:country_code":"DZ",
    "gn:dem":1066,
    "gn:feature_class":"P",
    "gn:feature_code":"PPL",
    "gn:name":"El Mzili",
    "gn:population":0,
    "gn:timezone":"Africa/Algiers",
    "iso:country":"DZ",
    "name:und_x_variant":[
        "Douar el Mzili",
        "El Mzili"
    ],
    "wof:name":"El Mzili",
    "wof:placetype":"locality"
},
  "geometry": {"coordinates":[1.03781,35.23064],"type":"Point"}
}