{
  "type": "Feature",
  "properties": {
    "gn:admin1_code":"6.0",
    "gn:asciiname":"Maison Blanche",
    "gn:country_code":"DZ",
    "gn:dem":587,
    "gn:feature_class":"P",
    "gn:feature_code":"PPL",
    "gn:name":"Maison Blanche",
    "gn:population":0,
    "gn:timezone":"Africa/Algiers",
    "iso:country":"DZ",
    "wof:name":"Maison Blanche",
    "wof:placetype":"locality"
},
  "geometry": {"coordinates":[2.7867,35.95592],"type":"Point"}
}