{
  "type": "Feature",
  "properties": {
    "gn:admin1_code":"15.0",
    "gn:asciiname":"Diar Salah",
    "gn:country_code":"DZ",
    "gn:dem":246,
    "gn:feature_class":"P",
    "gn:feature_code":"PPL",
    "gn:name":"Diar S\u00e2lah",
    "gn:population":0,
    "gn:timezone":"Africa/Algiers",
    "iso:country":"DZ",
    "name:und_x_variant":[
        "Dar-Sala",
        "Diar S\u00e2lah"
    ],
    "wof:name":"Diar Salah",
    "wof:placetype":"locality"
},
  "geometry": {"coordinates":[-1.97285,35.03833],"type":"Point"}
}