{
  "type": "Feature",
  "properties": {
    "gn:admin1_code":"51.0",
    "gn:asciiname":"Douar Ben Bouziane",
    "gn:country_code":"DZ",
    "gn:dem":480,
    "gn:feature_class":"P",
    "gn:feature_code":"PPL",
    "gn:name":"Douar Ben Bouziane",
    "gn:population":0,
    "gn:timezone":"Africa/Algiers",
    "iso:country":"DZ",
    "wof:name":"Douar Ben Bouziane",
    "wof:placetype":"locality"
},
  "geometry": {"coordinates":[0.75586,35.5637],"type":"Point"}
}