{
  "type": "Feature",
  "properties": {
    "gn:admin1_code":"45.0",
    "gn:asciiname":"Bel Bachir",
    "gn:country_code":"DZ",
    "gn:dem":400,
    "gn:feature_class":"P",
    "gn:feature_code":"PPL",
    "gn:name":"Bel Bachir",
    "gn:population":0,
    "gn:timezone":"Africa/Algiers",
    "iso:country":"DZ",
    "wof:name":"Bel Bachir",
    "wof:placetype":"locality"
},
  "geometry": {"coordinates":[2.87994,30.60757000000001],"type":"Point"}
}