{
  "type": "Feature",
  "properties": {
    "gn:admin1_code":"26.0",
    "gn:asciiname":"Oulad Bou Kaddour",
    "gn:country_code":"DZ",
    "gn:dem":631,
    "gn:feature_class":"P",
    "gn:feature_code":"PPL",
    "gn:name":"Oulad Bou Kaddour",
    "gn:population":0,
    "gn:timezone":"Africa/Algiers",
    "iso:country":"DZ",
    "wof:name":"Oulad Bou Kaddour",
    "wof:placetype":"locality"
},
  "geometry": {"coordinates":[0.24413,35.24715],"type":"Point"}
}