{
  "type": "Feature",
  "properties": {
    "iso:country":"DZ",
    "name:ara_x_preferred":[
        "Les Trembles"
    ],
    "qs:gn_adm0_cc":"DZ",
    "qs:gn_local":2507480,
    "qs:gn_nam_loc":"\u0648\u0644\u0627\u064a\u0629 \u0627\u0644\u062c\u0632\u0627\u0626\u0631, DZ, \u0627\u0644\u062c\u0632\u0627\u0626\u0631",
    "qs:gn_namadm1":"01",
    "qs:local_max":361,
    "qs:local_sum":1976,
    "qs:localhoods":16,
    "qs:name":"Les Trembles",
    "qs:name_adm0":"\u0627\u0644\u062c\u0632\u0627\u0626\u0631",
    "qs:name_adm1":"\u0648\u0644\u0627\u064a\u0629 \u0627\u0644\u062c\u0632\u0627\u0626\u0631",
    "qs:name_local":"\u0627\u0644\u062c\u0632\u0627\u0626\u0631",
    "qs:photo_max":48,
    "qs:photo_sum":162,
    "qs:placetype":"Suburb",
    "qs:quad_count":14,
    "qs:woe_adm0":23424740,
    "qs:woe_adm1":2344579,
    "qs:woe_adm2":0,
    "qs:woe_lau":0,
    "qs:woe_local":1253079,
    "qs:woe_ver":"7.10.0",
    "wof:lang":[
        "ara"
    ],
    "wof:name":"Les Trembles",
    "wof:placetype":"neighbourhood"
},
  "geometry": {"coordinates":[3.045083,36.763444],"type":"Point"}
}