{
  "type": "Feature",
  "properties": {
    "gn:admin1_code":"47.0",
    "gn:asciiname":"Tadount",
    "gn:country_code":"DZ",
    "gn:dem":1072,
    "gn:feature_class":"P",
    "gn:feature_code":"PPL",
    "gn:name":"Tadount",
    "gn:population":0,
    "gn:timezone":"Africa/Algiers",
    "iso:country":"DZ",
    "wof:name":"Tadount",
    "wof:placetype":"locality"
},
  "geometry": {"coordinates":[6.8264,34.93102],"type":"Point"}
}