{
  "type": "Feature",
  "properties": {
    "gn:admin1_code":"48.0",
    "gn:asciiname":"Sidi Salah",
    "gn:country_code":"DZ",
    "gn:dem":821,
    "gn:feature_class":"P",
    "gn:feature_code":"PPL",
    "gn:name":"Sidi Salah",
    "gn:population":0,
    "gn:timezone":"Africa/Algiers",
    "iso:country":"DZ",
    "wof:name":"Sidi Salah",
    "wof:placetype":"locality"
},
  "geometry": {"coordinates":[6.1193,36.23239],"type":"Point"}
}