{
  "type": "Feature",
  "properties": {
    "gn:admin1_code":"43.0",
    "gn:asciiname":"Amiche",
    "gn:country_code":"DZ",
    "gn:dem":86,
    "gn:feature_class":"P",
    "gn:feature_code":"PPL",
    "gn:name":"Amiche",
    "gn:population":0,
    "gn:timezone":"Africa/Algiers",
    "iso:country":"DZ",
    "wof:name":"Amiche",
    "wof:placetype":"locality"
},
  "geometry": {"coordinates":[6.9026,33.3052],"type":"Point"}
}