{
  "type": "Feature",
  "properties": {
    "gn:admin1_code":"13.0",
    "gn:asciiname":"El Mssatfa",
    "gn:country_code":"DZ",
    "gn:dem":763,
    "gn:feature_class":"P",
    "gn:feature_code":"PPL",
    "gn:name":"El Mssatfa",
    "gn:population":0,
    "gn:timezone":"Africa/Algiers",
    "iso:country":"DZ",
    "name:und_x_variant":[
        "Metameur Oulad Mostefa",
        "Oulad Mostefa",
        "El Mssatfa"
    ],
    "wof:name":"El Mssatfa",
    "wof:placetype":"locality"
},
  "geometry": {"coordinates":[0.80127,35.17096],"type":"Point"}
}