{
  "type": "Feature",
  "properties": {
    "gn:admin1_code":"40.0",
    "gn:asciiname":"Kef el Aogab",
    "gn:country_code":"DZ",
    "gn:dem":38,
    "gn:feature_class":"P",
    "gn:feature_code":"PPL",
    "gn:name":"Kef el Aogab",
    "gn:population":0,
    "gn:timezone":"Africa/Algiers",
    "iso:country":"DZ",
    "name:und_x_variant":[
        "Kef el \u2019Og\u00e2b"
    ],
    "wof:name":"Kef el Aogab",
    "wof:placetype":"locality"
},
  "geometry": {"coordinates":[3.88121,36.76111],"type":"Point"}
}