{
  "type": "Feature",
  "properties": {
    "gn:admin1_code":"12.0",
    "gn:asciiname":"El Baouch",
    "gn:country_code":"DZ",
    "gn:dem":1037,
    "gn:feature_class":"P",
    "gn:feature_code":"PPL",
    "gn:name":"El Baouch",
    "gn:population":0,
    "gn:timezone":"Africa/Algiers",
    "iso:country":"DZ",
    "wof:name":"El Baouch",
    "wof:placetype":"locality"
},
  "geometry": {"coordinates":[5.16667,36.36667],"type":"Point"}
}