{
  "type": "Feature",
  "properties": {
    "gn:admin1_code":"9.0",
    "gn:asciiname":"Gdyel",
    "gn:country_code":"DZ",
    "gn:dem":143,
    "gn:feature_class":"P",
    "gn:feature_code":"PPL",
    "gn:name":"Gdyel",
    "gn:population":0,
    "gn:timezone":"Africa/Algiers",
    "iso:country":"DZ",
    "name:fra_x_preferred":[
        "Gdyel"
    ],
    "name:ita_x_preferred":[
        "Gdyel"
    ],
    "name:kab_x_preferred":[
        "Gdeyyel"
    ],
    "name:por_x_preferred":[
        "Gdyel"
    ],
    "name:ron_x_preferred":[
        "Gdyel"
    ],
    "name:spa_x_preferred":[
        "Gdyel"
    ],
    "name:und_x_variant":[
        "Gudhiel",
        "Saint-Cloud-d\u2019Alg\u00e9rie",
        "Saint-Cloud",
        "Gdeyel"
    ],
    "name:vie_x_preferred":[
        "Gdyel"
    ],
    "name:zho_x_preferred":[
        "\u683c\u8fea\u8036\u52d2"
    ],
    "wof:name":"Gdyel",
    "wof:placetype":"locality"
},
  "geometry": {"coordinates":[-0.42581,35.78111],"type":"Point"}
}