{
  "type": "Feature",
  "properties": {
    "gn:admin1_code":"6.0",
    "gn:asciiname":"'Ain Fekirine",
    "gn:country_code":"DZ",
    "gn:dem":769,
    "gn:feature_class":"P",
    "gn:feature_code":"PPL",
    "gn:name":"\u2019A\u00efn Fekirine",
    "gn:population":0,
    "gn:timezone":"Africa/Algiers",
    "iso:country":"DZ",
    "wof:name":"'Ain Fekirine",
    "wof:placetype":"locality"
},
  "geometry": {"coordinates":[3.35049,35.81475],"type":"Point"}
}