{
  "type": "Feature",
  "properties": {
    "gn:admin1_code":"6.0",
    "gn:asciiname":"Ouled Yahia",
    "gn:country_code":"DZ",
    "gn:dem":581,
    "gn:feature_class":"P",
    "gn:feature_code":"PPLL",
    "gn:name":"Ouled Yahia",
    "gn:population":0,
    "gn:timezone":"Africa/Algiers",
    "iso:country":"DZ",
    "wof:name":"Ouled Yahia",
    "wof:placetype":"locality"
},
  "geometry": {"coordinates":[3.35694,36.22139],"type":"Point"}
}