{
  "type": "Feature",
  "properties": {
    "gn:admin1_code":"35.0",
    "gn:asciiname":"Douar Bendrisse",
    "gn:country_code":"DZ",
    "gn:dem":434,
    "gn:feature_class":"P",
    "gn:feature_code":"PPL",
    "gn:name":"Douar Bendrisse",
    "gn:population":0,
    "gn:timezone":"Africa/Algiers",
    "iso:country":"DZ",
    "wof:name":"Douar Bendrisse",
    "wof:placetype":"locality"
},
  "geometry": {"coordinates":[1.68857,36.12278],"type":"Point"}
}