{
  "type": "Feature",
  "properties": {
    "gn:admin1_code":"3.0",
    "gn:asciiname":"Oued el Ma",
    "gn:country_code":"DZ",
    "gn:dem":1027,
    "gn:feature_class":"P",
    "gn:feature_code":"PPL",
    "gn:name":"Oued el Ma",
    "gn:population":0,
    "gn:timezone":"Africa/Algiers",
    "iso:country":"DZ",
    "name:ara_x_preferred":[
        "\u0648\u0627\u062f\u064a \u0627\u0644\u0645\u0627\u0621"
    ],
    "name:azb_x_preferred":[
        "\u0648\u0627\u062f\u06cc \u0622\u0644\u0645\u0627"
    ],
    "name:fas_x_preferred":[
        "\u0648\u0627\u062f\u06cc \u0622\u0644\u0645\u0627"
    ],
    "name:fra_x_preferred":[
        "Oued El Ma"
    ],
    "name:ita_x_preferred":[
        "Oued El Ma"
    ],
    "name:msa_x_preferred":[
        "Oued El Ma"
    ],
    "name:por_x_preferred":[
        "Oued El Ma"
    ],
    "name:ron_x_preferred":[
        "Oued El Ma"
    ],
    "name:spa_x_preferred":[
        "Oued El Ma"
    ],
    "name:und_x_variant":[
        "Bernelle",
        "Oued el Ma"
    ],
    "name:vie_x_preferred":[
        "Oued El Ma"
    ],
    "wof:name":"Oued el Ma",
    "wof:placetype":"locality"
},
  "geometry": {"coordinates":[5.99605,35.64525],"type":"Point"}
}