{
  "type": "Feature",
  "properties": {
    "gn:admin1_code":"48.0",
    "gn:asciiname":"Grarem",
    "gn:country_code":"DZ",
    "gn:dem":309,
    "gn:feature_class":"P",
    "gn:feature_code":"PPL",
    "gn:name":"Grarem",
    "gn:population":0,
    "gn:timezone":"Africa/Algiers",
    "iso:country":"DZ",
    "wof:name":"Grarem",
    "wof:placetype":"locality"
},
  "geometry": {"coordinates":[6.32722,36.51611],"type":"Point"}
}