{
  "type": "Feature",
  "properties": {
    "gn:admin1_code":"27.0",
    "gn:asciiname":"Maachat",
    "gn:country_code":"DZ",
    "gn:dem":698,
    "gn:feature_class":"P",
    "gn:feature_code":"PPL",
    "gn:name":"Maachat",
    "gn:population":0,
    "gn:timezone":"Africa/Algiers",
    "iso:country":"DZ",
    "wof:name":"Maachat",
    "wof:placetype":"locality"
},
  "geometry": {"coordinates":[5.35904,35.58278],"type":"Point"}
}