{
  "type": "Feature",
  "properties": {
    "gn:admin1_code":"27.0",
    "gn:asciiname":"Mechta Kassari",
    "gn:country_code":"DZ",
    "gn:dem":592,
    "gn:feature_class":"P",
    "gn:feature_code":"PPL",
    "gn:name":"Mechta Kassari",
    "gn:population":0,
    "gn:timezone":"Africa/Algiers",
    "iso:country":"DZ",
    "wof:name":"Mechta Kassari",
    "wof:placetype":"locality"
},
  "geometry": {"coordinates":[4.0396,35.82844],"type":"Point"}
}