{
  "type": "Feature",
  "properties": {
    "gn:admin1_code":"23.0",
    "gn:asciiname":"'Ain Amara",
    "gn:country_code":"DZ",
    "gn:dem":533,
    "gn:feature_class":"P",
    "gn:feature_code":"PPL",
    "gn:name":"\u2019A\u00efn Amara",
    "gn:population":0,
    "gn:timezone":"Africa/Algiers",
    "iso:country":"DZ",
    "name:und_x_variant":[
        "A\u00efne Amara",
        "\u2019A\u00efn Amara"
    ],
    "wof:name":"'Ain Amara",
    "wof:placetype":"locality"
},
  "geometry": {"coordinates":[7.26943,36.4053],"type":"Point"}
}