{
  "type": "Feature",
  "properties": {
    "gn:admin1_code":"19.0",
    "gn:asciiname":"Oulach",
    "gn:country_code":"DZ",
    "gn:dem":539,
    "gn:feature_class":"P",
    "gn:feature_code":"PPL",
    "gn:name":"Oulach",
    "gn:population":0,
    "gn:timezone":"Africa/Algiers",
    "iso:country":"DZ",
    "wof:name":"Oulach",
    "wof:placetype":"locality"
},
  "geometry": {"coordinates":[6.1681,34.91276],"type":"Point"}
}