{
  "type": "Feature",
  "properties": {
    "gn:admin1_code":"6.0",
    "gn:asciiname":"Sekhairia",
    "gn:country_code":"DZ",
    "gn:dem":594,
    "gn:feature_class":"P",
    "gn:feature_code":"PPL",
    "gn:name":"Sekha\u00efria",
    "gn:population":0,
    "gn:timezone":"Africa/Algiers",
    "iso:country":"DZ",
    "wof:name":"Sekhairia",
    "wof:placetype":"locality"
},
  "geometry": {"coordinates":[3.32524,36.22152],"type":"Point"}
}