{
  "type": "Feature",
  "properties": {
    "gn:admin1_code":"27.0",
    "gn:asciiname":"Bir Heni",
    "gn:country_code":"DZ",
    "gn:dem":423,
    "gn:feature_class":"P",
    "gn:feature_code":"PPL",
    "gn:name":"Bir Heni",
    "gn:population":0,
    "gn:timezone":"Africa/Algiers",
    "iso:country":"DZ",
    "wof:name":"Bir Heni",
    "wof:placetype":"locality"
},
  "geometry": {"coordinates":[4.40707,35.32264],"type":"Point"}
}