{
  "type": "Feature",
  "properties": {
    "gn:admin1_code":"14.0",
    "gn:asciiname":"Ouadhia",
    "gn:country_code":"DZ",
    "gn:dem":405,
    "gn:feature_class":"P",
    "gn:feature_code":"PPL",
    "gn:name":"Ouadhia",
    "gn:population":0,
    "gn:timezone":"Africa/Algiers",
    "iso:country":"DZ",
    "wof:name":"Ouadhia",
    "wof:placetype":"locality"
},
  "geometry": {"coordinates":[4.08972,36.55611],"type":"Point"}
}