{
  "type": "Feature",
  "properties": {
    "gn:admin1_code":"14.0",
    "gn:asciiname":"Ouadhia",
    "gn:country_code":"DZ",
    "gn:dem":405,
    "gn:feature_class":"P",
    "gn:feature_code":"PPL",
    "gn:name":"Ouadhia",
    "gn:population":0,
    "gn:timezone":"Africa/Algiers",
    "iso:country":"DZ",
    "name:ara_x_preferred":[
        "\u0648\u0627\u0636\u064a\u0629"
    ],
    "name:azb_x_preferred":[
        "\u0648\u0627\u0636\u06cc\u0647"
    ],
    "name:fas_x_preferred":[
        "\u0648\u0627\u0636\u06cc\u0647"
    ],
    "name:fra_x_preferred":[
        "Ouadhia"
    ],
    "name:ita_x_preferred":[
        "Ouadhia"
    ],
    "name:kab_x_preferred":[
        "Iwa\u1e0diyen"
    ],
    "name:msa_x_preferred":[
        "Ouadhia"
    ],
    "name:por_x_preferred":[
        "Ouadhia"
    ],
    "name:ron_x_preferred":[
        "Ouadhia"
    ],
    "name:spa_x_preferred":[
        "Ouadhia"
    ],
    "name:vie_x_preferred":[
        "Ouadhia"
    ],
    "name:zho_x_preferred":[
        "\u74e6\u9f4a\u8036"
    ],
    "wof:name":"Ouadhia",
    "wof:placetype":"locality"
},
  "geometry": {"coordinates":[4.08972,36.55611],"type":"Point"}
}