{
  "type": "Feature",
  "properties": {
    "gn:admin1_code":"20.0",
    "gn:asciiname":"Ouled Salem",
    "gn:country_code":"DZ",
    "gn:dem":370,
    "gn:feature_class":"P",
    "gn:feature_code":"PPL",
    "gn:name":"Ouled Salem",
    "gn:population":0,
    "gn:timezone":"Africa/Algiers",
    "iso:country":"DZ",
    "wof:name":"Ouled Salem",
    "wof:placetype":"locality"
},
  "geometry": {"coordinates":[3.32483,36.61309],"type":"Point"}
}