{
  "type": "Feature",
  "properties": {
    "gn:admin1_code":"1.0",
    "gn:asciiname":"Ouled Maamar",
    "gn:country_code":"DZ",
    "gn:dem":29,
    "gn:feature_class":"P",
    "gn:feature_code":"PPL",
    "gn:name":"Ouled Maamar",
    "gn:population":0,
    "gn:timezone":"Africa/Algiers",
    "iso:country":"DZ",
    "name:und_x_variant":[
        "Oulad Ma\u2019ammar"
    ],
    "wof:name":"Ouled Maamar",
    "wof:placetype":"locality"
},
  "geometry": {"coordinates":[3.29795,36.77068],"type":"Point"}
}