{
  "type": "Feature",
  "properties": {
    "gn:admin1_code":"51.0",
    "gn:asciiname":"Douar Oulad Nouasseur",
    "gn:country_code":"DZ",
    "gn:dem":295,
    "gn:feature_class":"P",
    "gn:feature_code":"PPL",
    "gn:name":"Douar Oulad Nouasseur",
    "gn:population":0,
    "gn:timezone":"Africa/Algiers",
    "iso:country":"DZ",
    "wof:name":"Douar Oulad Nouasseur",
    "wof:placetype":"locality"
},
  "geometry": {"coordinates":[0.70167,35.62305999999999],"type":"Point"}
}