{
  "type": "Feature",
  "properties": {
    "gn:admin1_code":"6.0",
    "gn:asciiname":"Douar Cheraria",
    "gn:country_code":"DZ",
    "gn:dem":1022,
    "gn:feature_class":"P",
    "gn:feature_code":"PPL",
    "gn:name":"Douar Cheraria",
    "gn:population":0,
    "gn:timezone":"Africa/Algiers",
    "iso:country":"DZ",
    "name:und_x_variant":[
        "Cheraria"
    ],
    "wof:name":"Douar Cheraria",
    "wof:placetype":"locality"
},
  "geometry": {"coordinates":[2.96059,36.05331],"type":"Point"}
}