{
  "type": "Feature",
  "properties": {
    "gn:admin1_code":"3.0",
    "gn:asciiname":"Mechta Mezzari",
    "gn:country_code":"DZ",
    "gn:dem":904,
    "gn:feature_class":"P",
    "gn:feature_code":"PPL",
    "gn:name":"Mechta Mezzari",
    "gn:population":0,
    "gn:timezone":"Africa/Algiers",
    "iso:country":"DZ",
    "wof:name":"Mechta Mezzari",
    "wof:placetype":"locality"
},
  "geometry": {"coordinates":[6.30685,35.66976],"type":"Point"}
}