{
  "type": "Feature",
  "properties": {
    "gn:admin1_code":"7.0",
    "gn:asciiname":"Douar Oulad Kaddour",
    "gn:country_code":"DZ",
    "gn:dem":198,
    "gn:feature_class":"P",
    "gn:feature_code":"PPL",
    "gn:name":"Douar Oulad Kaddour",
    "gn:population":0,
    "gn:timezone":"Africa/Algiers",
    "iso:country":"DZ",
    "wof:name":"Douar Oulad Kaddour",
    "wof:placetype":"locality"
},
  "geometry": {"coordinates":[0.29556,35.82167000000001],"type":"Point"}
}