{
  "type": "Feature",
  "properties": {
    "gn:admin1_code":"21.0",
    "gn:asciiname":"Sidi Mohammed Ben ed Dif",
    "gn:country_code":"DZ",
    "gn:dem":944,
    "gn:feature_class":"P",
    "gn:feature_code":"PPL",
    "gn:name":"Sidi Mohammed Ben ed Dif",
    "gn:population":0,
    "gn:timezone":"Africa/Algiers",
    "iso:country":"DZ",
    "wof:name":"Sidi Mohammed Ben ed Dif",
    "wof:placetype":"locality"
},
  "geometry": {"coordinates":[4.02842,36.11432],"type":"Point"}
}