{
  "type": "Feature",
  "properties": {
    "gn:admin1_code":"34.0",
    "gn:asciiname":"El Mansour",
    "gn:country_code":"DZ",
    "gn:dem":251,
    "gn:feature_class":"P",
    "gn:feature_code":"PPL",
    "gn:name":"El Mansour",
    "gn:population":0,
    "gn:timezone":"Africa/Algiers",
    "iso:country":"DZ",
    "wof:name":"El Mansour",
    "wof:placetype":"locality"
},
  "geometry": {"coordinates":[0.03297,28.76234],"type":"Point"}
}