{
  "type": "Feature",
  "properties": {
    "gn:admin1_code":"51.0",
    "gn:asciiname":"Douar Eddabala",
    "gn:country_code":"DZ",
    "gn:dem":472,
    "gn:feature_class":"P",
    "gn:feature_code":"PPL",
    "gn:name":"Douar Eddabala",
    "gn:population":0,
    "gn:timezone":"Africa/Algiers",
    "iso:country":"DZ",
    "wof:name":"Douar Eddabala",
    "wof:placetype":"locality"
},
  "geometry": {"coordinates":[0.69256,35.53648],"type":"Point"}
}