{
  "type": "Feature",
  "properties": {
    "gn:admin1_code":"26.0",
    "gn:asciiname":"Sidi Mimoun",
    "gn:country_code":"DZ",
    "gn:dem":678,
    "gn:feature_class":"P",
    "gn:feature_code":"PPL",
    "gn:name":"Sidi Mimoun",
    "gn:population":0,
    "gn:timezone":"Africa/Algiers",
    "iso:country":"DZ",
    "wof:name":"Sidi Mimoun",
    "wof:placetype":"locality"
},
  "geometry": {"coordinates":[0.38415,35.04749],"type":"Point"}
}