{
  "type": "Feature",
  "properties": {
    "gn:admin1_code":"14.0",
    "gn:asciiname":"Klaa",
    "gn:country_code":"DZ",
    "gn:dem":751,
    "gn:feature_class":"P",
    "gn:feature_code":"PPL",
    "gn:name":"Klaa",
    "gn:population":0,
    "gn:timezone":"Africa/Algiers",
    "iso:country":"DZ",
    "name:und_x_variant":[
        "El Klaa",
        "Klaa"
    ],
    "wof:name":"Klaa",
    "wof:placetype":"locality"
},
  "geometry": {"coordinates":[4.31342,36.64557],"type":"Point"}
}