{
  "type": "Feature",
  "properties": {
    "gn:admin1_code":"26.0",
    "gn:asciiname":"Mocta Douz",
    "gn:country_code":"DZ",
    "gn:dem":16,
    "gn:feature_class":"P",
    "gn:feature_code":"PPL",
    "gn:name":"Mocta Douz",
    "gn:population":0,
    "gn:timezone":"Africa/Algiers",
    "iso:country":"DZ",
    "name:ara_x_preferred":[
        "\u0645\u0642\u0637\u0639 \u062f\u0648\u0632"
    ],
    "name:azb_x_preferred":[
        "\u0645\u0642\u0637\u0639 \u062f\u0648\u0632"
    ],
    "name:fas_x_preferred":[
        "\u0645\u0642\u0637\u0639 \u062f\u0648\u0632"
    ],
    "name:fra_x_preferred":[
        "Mocta Douz"
    ],
    "name:ita_x_preferred":[
        "Mocta Douz"
    ],
    "name:msa_x_preferred":[
        "Mocta Douz"
    ],
    "name:por_x_preferred":[
        "Mocta Douz"
    ],
    "name:ron_x_preferred":[
        "Mocta Douz"
    ],
    "name:spa_x_preferred":[
        "Mocta Douz"
    ],
    "name:und_x_variant":[
        "Mokta Douz"
    ],
    "name:vie_x_preferred":[
        "Mocta Douz"
    ],
    "wof:name":"Mocta Douz",
    "wof:placetype":"locality"
},
  "geometry": {"coordinates":[-0.04694,35.60432],"type":"Point"}
}