{
  "type": "Feature",
  "properties": {
    "gn:admin1_code":"14.0",
    "gn:asciiname":"Timarhas",
    "gn:country_code":"DZ",
    "gn:dem":743,
    "gn:feature_class":"P",
    "gn:feature_code":"PPL",
    "gn:name":"Timarhas",
    "gn:population":0,
    "gn:timezone":"Africa/Algiers",
    "iso:country":"DZ",
    "wof:name":"Timarhas",
    "wof:placetype":"locality"
},
  "geometry": {"coordinates":[4.19301,36.49243],"type":"Point"}
}