{
  "type": "Feature",
  "properties": {
    "gn:admin1_code":"31.0",
    "gn:asciiname":"Cheraia",
    "gn:country_code":"DZ",
    "gn:dem":332,
    "gn:feature_class":"P",
    "gn:feature_code":"PPL",
    "gn:name":"Chera\u00efa",
    "gn:population":0,
    "gn:timezone":"Africa/Algiers",
    "iso:country":"DZ",
    "name:ara_x_preferred":[
        "\u0627\u0644\u0634\u0631\u0627\u064a\u0639"
    ],
    "name:azb_x_preferred":[
        "\u0634\u0631\u0627\u06cc\u0639"
    ],
    "name:fas_x_preferred":[
        "\u0634\u0631\u0627\u06cc\u0639"
    ],
    "name:fra_x_preferred":[
        "Chera\u00efa"
    ],
    "name:ita_x_preferred":[
        "Cheraia"
    ],
    "name:kab_x_preferred":[
        "Ccera\u025bi\u025b"
    ],
    "name:msa_x_preferred":[
        "Cheraia"
    ],
    "name:por_x_preferred":[
        "Cheraia"
    ],
    "name:ron_x_preferred":[
        "Cheraia"
    ],
    "name:spa_x_preferred":[
        "Cheraia"
    ],
    "name:und_x_variant":[
        "Cher\u00e2ya"
    ],
    "name:vie_x_preferred":[
        "Cheraia"
    ],
    "name:zho_x_preferred":[
        "\u820d\u62c9\u8036"
    ],
    "wof:name":"Cheraia",
    "wof:placetype":"locality"
},
  "geometry": {"coordinates":[6.51359,37.00174000000001],"type":"Point"}
}