{
  "type": "Feature",
  "properties": {
    "gn:admin1_code":"31.0",
    "gn:asciiname":"Es Sebt",
    "gn:country_code":"DZ",
    "gn:dem":158,
    "gn:feature_class":"P",
    "gn:feature_code":"PPL",
    "gn:name":"Es Sebt",
    "gn:population":0,
    "gn:timezone":"Africa/Algiers",
    "iso:country":"DZ",
    "name:ara_x_preferred":[
        "\u0627\u0644\u0633\u0628\u062a"
    ],
    "name:azb_x_preferred":[
        "\u0633\u0628\u062a"
    ],
    "name:fas_x_preferred":[
        "\u0633\u0628\u062a"
    ],
    "name:fra_x_preferred":[
        "Es Sebt"
    ],
    "name:ita_x_preferred":[
        "Es Sebt"
    ],
    "name:msa_x_preferred":[
        "Essebt"
    ],
    "name:por_x_preferred":[
        "Essebt"
    ],
    "name:ron_x_preferred":[
        "Es Sebt"
    ],
    "name:spa_x_preferred":[
        "Es Sebt"
    ],
    "name:und_x_variant":[
        "Souk es Sebt",
        "La Robertsau"
    ],
    "name:vie_x_preferred":[
        "Es Sebt"
    ],
    "wof:name":"Es Sebt",
    "wof:placetype":"locality"
},
  "geometry": {"coordinates":[7.07759,36.6638],"type":"Point"}
}