{
  "type": "Feature",
  "properties": {
    "gn:admin1_code":"20.0",
    "gn:asciiname":"Lechaa",
    "gn:country_code":"DZ",
    "gn:dem":449,
    "gn:feature_class":"P",
    "gn:feature_code":"PPL",
    "gn:name":"Lechaa",
    "gn:population":0,
    "gn:timezone":"Africa/Algiers",
    "iso:country":"DZ",
    "name:und_x_variant":[
        "Douar Lech\u2019a"
    ],
    "wof:name":"Lechaa",
    "wof:placetype":"locality"
},
  "geometry": {"coordinates":[3.19909,36.51376],"type":"Point"}
}