{
  "type": "Feature",
  "properties": {
    "gn:admin1_code":"15.0",
    "gn:asciiname":"Oulad Breouch",
    "gn:country_code":"DZ",
    "gn:dem":1056,
    "gn:feature_class":"P",
    "gn:feature_code":"PPL",
    "gn:name":"Oulad Breouch",
    "gn:population":0,
    "gn:timezone":"Africa/Algiers",
    "iso:country":"DZ",
    "name:und_x_variant":[
        "Douar Oulad Breouch",
        "Oulad Breouch"
    ],
    "wof:name":"Oulad Breouch",
    "wof:placetype":"locality"
},
  "geometry": {"coordinates":[-1.21769,34.78400999999999],"type":"Point"}
}