{
  "type": "Feature",
  "properties": {
    "gn:admin1_code":"21.0",
    "gn:asciiname":"Ouled Rached",
    "gn:country_code":"DZ",
    "gn:dem":932,
    "gn:feature_class":"P",
    "gn:feature_code":"PPL",
    "gn:name":"Ouled Rached",
    "gn:population":0,
    "gn:timezone":"Africa/Algiers",
    "iso:country":"DZ",
    "name:ara_x_preferred":[
        "\u0623\u0648\u0644\u0627\u062f \u0631\u0627\u0634\u062f"
    ],
    "name:azb_x_preferred":[
        "\u0627\u0648\u0644\u0627\u062f \u0631\u0627\u0634\u062f"
    ],
    "name:fas_x_preferred":[
        "\u0627\u0648\u0644\u0627\u062f \u0631\u0627\u0634\u062f"
    ],
    "name:fra_x_preferred":[
        "Ouled Rached"
    ],
    "name:ita_x_preferred":[
        "Ouled Rached"
    ],
    "name:kab_x_preferred":[
        "At Raced"
    ],
    "name:msa_x_preferred":[
        "Ouled Rached"
    ],
    "name:por_x_preferred":[
        "Ouled Rached"
    ],
    "name:ron_x_preferred":[
        "Ouled Rached"
    ],
    "name:spa_x_preferred":[
        "Ouled Rached"
    ],
    "name:urd_x_preferred":[
        "\u0627\u0648\u0644\u0627\u062f \u0631\u0627\u0634\u062f"
    ],
    "name:vie_x_preferred":[
        "Ouled Rached"
    ],
    "wof:name":"Ouled Rached",
    "wof:placetype":"locality"
},
  "geometry": {"coordinates":[4.10992,36.21122],"type":"Point"}
}