{
  "type": "Feature",
  "properties": {
    "gn:admin1_code":"51.0",
    "gn:asciiname":"Hassasna",
    "gn:country_code":"DZ",
    "gn:dem":467,
    "gn:feature_class":"P",
    "gn:feature_code":"PPL",
    "gn:name":"Hassasna",
    "gn:population":0,
    "gn:timezone":"Africa/Algiers",
    "iso:country":"DZ",
    "name:und_x_variant":[
        "Village des Hassasna",
        "Hassasna"
    ],
    "wof:name":"Hassasna",
    "wof:placetype":"locality"
},
  "geometry": {"coordinates":[0.88079,36.13038],"type":"Point"}
}