{
  "type": "Feature",
  "properties": {
    "gn:admin1_code":"51.0",
    "gn:asciiname":"Hassasna",
    "gn:country_code":"DZ",
    "gn:dem":467,
    "gn:feature_class":"P",
    "gn:feature_code":"PPL",
    "gn:name":"Hassasna",
    "gn:population":0,
    "gn:timezone":"Africa/Algiers",
    "iso:country":"DZ",
    "name:ara_x_preferred":[
        "\u0627\u0644\u062d\u0633\u0627\u0633\u0646\u0629"
    ],
    "name:azb_x_preferred":[
        "\u062d\u0633\u0627\u0633\u0646\u0647"
    ],
    "name:fas_x_preferred":[
        "\u062d\u0633\u0627\u0633\u0646\u0647"
    ],
    "name:fra_x_preferred":[
        "Hassasna"
    ],
    "name:ita_x_preferred":[
        "Hassasna"
    ],
    "name:kab_x_preferred":[
        "\u1e24sasna"
    ],
    "name:msa_x_preferred":[
        "Hassasna"
    ],
    "name:por_x_preferred":[
        "Hassasna"
    ],
    "name:ron_x_preferred":[
        "Hassasna"
    ],
    "name:spa_x_preferred":[
        "Hassasna"
    ],
    "name:und_x_variant":[
        "Village des Hassasna"
    ],
    "name:vie_x_preferred":[
        "Hassasna"
    ],
    "name:zho_x_preferred":[
        "\u54c8\u85a9\u65af\u7d0d"
    ],
    "wof:name":"Hassasna",
    "wof:placetype":"locality"
},
  "geometry": {"coordinates":[0.88079,36.13038],"type":"Point"}
}