{
  "type": "Feature",
  "properties": {
    "gn:admin1_code":"23.0",
    "gn:asciiname":"Ouled Bou 'Aziz",
    "gn:country_code":"DZ",
    "gn:dem":428,
    "gn:feature_class":"P",
    "gn:feature_code":"PPL",
    "gn:name":"Ouled Bou \u2019Aziz",
    "gn:population":0,
    "gn:timezone":"Africa/Algiers",
    "iso:country":"DZ",
    "wof:name":"Ouled Bou 'Aziz",
    "wof:placetype":"locality"
},
  "geometry": {"coordinates":[7.46667,36.61667],"type":"Point"}
}