{
  "type": "Feature",
  "properties": {
    "gn:admin1_code":"15.0",
    "gn:asciiname":"Douar Oulad Bachir",
    "gn:country_code":"DZ",
    "gn:dem":122,
    "gn:feature_class":"P",
    "gn:feature_code":"PPL",
    "gn:name":"Douar Oulad Bachir",
    "gn:population":0,
    "gn:timezone":"Africa/Algiers",
    "iso:country":"DZ",
    "name:und_x_variant":[
        "Oulad Bachir",
        "Douar Oulad Bachir"
    ],
    "wof:name":"Douar Oulad Bachir",
    "wof:placetype":"locality"
},
  "geometry": {"coordinates":[-1.97929,35.01353],"type":"Point"}
}