{
  "type": "Feature",
  "properties": {
    "gn:admin1_code":"13.0",
    "gn:asciiname":"Rechaiga",
    "gn:country_code":"DZ",
    "gn:dem":847,
    "gn:feature_class":"P",
    "gn:feature_code":"PPL",
    "gn:name":"Recha\u00efga",
    "gn:population":0,
    "gn:timezone":"Africa/Algiers",
    "iso:country":"DZ",
    "name:und_x_variant":[
        "De Foucauld",
        "Recheiga",
        "Recha\u00efga"
    ],
    "wof:name":"Rechaiga",
    "wof:placetype":"locality"
},
  "geometry": {"coordinates":[1.97386,35.40681],"type":"Point"}
}