{
  "type": "Feature",
  "properties": {
    "gn:admin1_code":"13.0",
    "gn:asciiname":"Rechaiga",
    "gn:country_code":"DZ",
    "gn:dem":847,
    "gn:feature_class":"P",
    "gn:feature_code":"PPL",
    "gn:name":"Recha\u00efga",
    "gn:population":0,
    "gn:timezone":"Africa/Algiers",
    "iso:country":"DZ",
    "name:ara_x_preferred":[
        "\u0627\u0644\u0631\u0634\u0627\u064a\u0642\u0629"
    ],
    "name:azb_x_preferred":[
        "\u0631\u0634\u0627\u06cc\u0642\u0647"
    ],
    "name:fas_x_preferred":[
        "\u0631\u0634\u0627\u06cc\u0642\u0647"
    ],
    "name:fra_x_preferred":[
        "Rechaiga"
    ],
    "name:ita_x_preferred":[
        "Rechaiga"
    ],
    "name:msa_x_preferred":[
        "Rechaiga"
    ],
    "name:por_x_preferred":[
        "Rechaiga"
    ],
    "name:ron_x_preferred":[
        "Rechaiga"
    ],
    "name:spa_x_preferred":[
        "Rechaiga"
    ],
    "name:und_x_variant":[
        "De Foucauld",
        "Recheiga",
        "Recha\u00efga"
    ],
    "name:vie_x_preferred":[
        "Rechaiga"
    ],
    "wof:name":"Rechaiga",
    "wof:placetype":"locality"
},
  "geometry": {"coordinates":[1.97386,35.40681],"type":"Point"}
}