{
  "type": "Feature",
  "properties": {
    "gn:admin1_code":"41.0",
    "gn:asciiname":"Bouriache",
    "gn:country_code":"DZ",
    "gn:dem":559,
    "gn:feature_class":"P",
    "gn:feature_code":"PPL",
    "gn:name":"Bouriache",
    "gn:population":0,
    "gn:timezone":"Africa/Algiers",
    "iso:country":"DZ",
    "name:und_x_variant":[
        "Bou Riach",
        "Bouriache"
    ],
    "wof:name":"Bouriache",
    "wof:placetype":"locality"
},
  "geometry": {"coordinates":[1.54611,36.41971],"type":"Point"}
}