{
  "type": "Feature",
  "properties": {
    "gn:admin1_code":"41.0",
    "gn:asciiname":"Idjdhikth",
    "gn:country_code":"DZ",
    "gn:dem":426,
    "gn:feature_class":"P",
    "gn:feature_code":"PPL",
    "gn:name":"Idjdhikth",
    "gn:population":0,
    "gn:timezone":"Africa/Algiers",
    "iso:country":"DZ",
    "wof:name":"Idjdhikth",
    "wof:placetype":"locality"
},
  "geometry": {"coordinates":[1.64557,36.49339000000001],"type":"Point"}
}