{
  "type": "Feature",
  "properties": {
    "gn:admin1_code":"51.0",
    "gn:asciiname":"Sidi Lazreg",
    "gn:country_code":"DZ",
    "gn:dem":582,
    "gn:feature_class":"P",
    "gn:feature_code":"PPL",
    "gn:name":"Sidi Lazreg",
    "gn:population":0,
    "gn:timezone":"Africa/Algiers",
    "iso:country":"DZ",
    "wof:name":"Sidi Lazreg",
    "wof:placetype":"locality"
},
  "geometry": {"coordinates":[0.77796,35.64625],"type":"Point"}
}