{
  "type": "Feature",
  "properties": {
    "gn:admin1_code":"51.0",
    "gn:asciiname":"Sidi Lazreg",
    "gn:country_code":"DZ",
    "gn:dem":582,
    "gn:feature_class":"P",
    "gn:feature_code":"PPL",
    "gn:name":"Sidi Lazreg",
    "gn:population":0,
    "gn:timezone":"Africa/Algiers",
    "iso:country":"DZ",
    "name:ara_x_preferred":[
        "\u0633\u064a\u062f\u064a \u0644\u0632\u0631\u0642"
    ],
    "name:azb_x_preferred":[
        "\u0633\u06cc\u062f\u06cc \u0644\u0632\u0631\u0642"
    ],
    "name:fas_x_preferred":[
        "\u0633\u06cc\u062f\u06cc \u0644\u0632\u0631\u0642"
    ],
    "name:fra_x_preferred":[
        "Sidi Lazreg"
    ],
    "name:ita_x_preferred":[
        "Sidi Lazreg"
    ],
    "name:msa_x_preferred":[
        "Sidi Lazreg"
    ],
    "name:por_x_preferred":[
        "Sidi Lazreg"
    ],
    "name:ron_x_preferred":[
        "Sidi Lazreg"
    ],
    "name:spa_x_preferred":[
        "Sidi Lazreg"
    ],
    "name:vie_x_preferred":[
        "Sidi Lazreg"
    ],
    "name:zho_x_preferred":[
        "\u897f\u8fea\u62c9\u8332\u62c9\u683c"
    ],
    "wof:name":"Sidi Lazreg",
    "wof:placetype":"locality"
},
  "geometry": {"coordinates":[0.77796,35.64625],"type":"Point"}
}