{
  "type": "Feature",
  "properties": {
    "gn:admin1_code":"23.0",
    "gn:asciiname":"Mechtat el Hennchir",
    "gn:country_code":"DZ",
    "gn:dem":845,
    "gn:feature_class":"P",
    "gn:feature_code":"PPL",
    "gn:name":"Mechtat el Hennchir",
    "gn:population":0,
    "gn:timezone":"Africa/Algiers",
    "iso:country":"DZ",
    "name:und_x_variant":[
        "Mechta el Hennchir",
        "Mechtat el Hennchir"
    ],
    "wof:name":"Mechtat el Hennchir",
    "wof:placetype":"locality"
},
  "geometry": {"coordinates":[7.3777,36.22919],"type":"Point"}
}