{
  "type": "Feature",
  "properties": {
    "gn:admin1_code":"51.0",
    "gn:asciiname":"Hateb el Ouarta",
    "gn:country_code":"DZ",
    "gn:dem":297,
    "gn:feature_class":"P",
    "gn:feature_code":"PPL",
    "gn:name":"Hateb el Ouarta",
    "gn:population":0,
    "gn:timezone":"Africa/Algiers",
    "iso:country":"DZ",
    "wof:name":"Hateb el Ouarta",
    "wof:placetype":"locality"
},
  "geometry": {"coordinates":[0.76694,35.72111],"type":"Point"}
}