{
  "type": "Feature",
  "properties": {
    "gn:admin1_code":"51.0",
    "gn:asciiname":"Mechtat el Araissia",
    "gn:country_code":"DZ",
    "gn:dem":63,
    "gn:feature_class":"P",
    "gn:feature_code":"PPL",
    "gn:name":"Mechtat el Ara\u00efssia",
    "gn:population":0,
    "gn:timezone":"Africa/Algiers",
    "iso:country":"DZ",
    "wof:name":"Mechtat el Araissia",
    "wof:placetype":"locality"
},
  "geometry": {"coordinates":[0.6721,35.813],"type":"Point"}
}