{
  "type": "Feature",
  "properties": {
    "gn:admin1_code":"24.0",
    "gn:asciiname":"Mechta Ouled Bou Khina",
    "gn:country_code":"DZ",
    "gn:dem":68,
    "gn:feature_class":"P",
    "gn:feature_code":"PPL",
    "gn:name":"Mechta Ouled Bo\u00fb Kh\u00eena",
    "gn:population":0,
    "gn:timezone":"Africa/Algiers",
    "iso:country":"DZ",
    "name:und_x_variant":[
        "Dechret Ouled Bou Khina",
        "Mechta Ouled Bo\u00fb Kh\u00eena"
    ],
    "wof:name":"Mechta Ouled Bou Khina",
    "wof:placetype":"locality"
},
  "geometry": {"coordinates":[6.21787,36.78265],"type":"Point"}
}