{
  "type": "Feature",
  "properties": {
    "gn:admin1_code":"51.0",
    "gn:asciiname":"Zebabidj el Khenaga",
    "gn:cc2":"DZ",
    "gn:country_code":"DZ",
    "gn:dem":573,
    "gn:feature_class":"P",
    "gn:feature_code":"PPL",
    "gn:name":"Zebabidj el Khenaga",
    "gn:population":0,
    "gn:timezone":"Africa/Algiers",
    "iso:country":"DZ",
    "name:und_x_variant":[
        "Zebabidj el Krenaga",
        "Zebabidj el Khenaga"
    ],
    "wof:name":"Zebabidj el Khenaga",
    "wof:placetype":"locality"
},
  "geometry": {"coordinates":[0.89333,35.68528],"type":"Point"}
}