{
  "type": "Feature",
  "properties": {
    "gn:admin1_code":"41.0",
    "gn:asciiname":"Touabia",
    "gn:country_code":"DZ",
    "gn:dem":112,
    "gn:feature_class":"P",
    "gn:feature_code":"PPL",
    "gn:name":"Touabia",
    "gn:population":0,
    "gn:timezone":"Africa/Algiers",
    "iso:country":"DZ",
    "wof:name":"Touabia",
    "wof:placetype":"locality"
},
  "geometry": {"coordinates":[1.3617,36.20027],"type":"Point"}
}