{
  "type": "Feature",
  "properties": {
    "gn:admin1_code":"30.0",
    "gn:asciiname":"Mezaourou",
    "gn:country_code":"DZ",
    "gn:dem":831,
    "gn:feature_class":"P",
    "gn:feature_code":"PPL",
    "gn:name":"Mezaourou",
    "gn:population":0,
    "gn:timezone":"Africa/Algiers",
    "iso:country":"DZ",
    "name:ara_x_preferred":[
        "\u0645\u0632\u0627\u0648\u0631\u0648"
    ],
    "name:azb_x_preferred":[
        "\u0645\u0632\u0627\u0648\u0631\u0648"
    ],
    "name:fas_x_preferred":[
        "\u0645\u0632\u0627\u0648\u0631\u0648"
    ],
    "name:fra_x_preferred":[
        "Mezaourou"
    ],
    "name:ita_x_preferred":[
        "Mezaourou"
    ],
    "name:kab_x_preferred":[
        "Mezawru"
    ],
    "name:msa_x_preferred":[
        "Mezaourou"
    ],
    "name:pol_x_preferred":[
        "Mazauru"
    ],
    "name:por_x_preferred":[
        "Mezaourou"
    ],
    "name:ron_x_preferred":[
        "Mezaourou"
    ],
    "name:spa_x_preferred":[
        "Mezaourou"
    ],
    "name:und_x_variant":[
        "Rochambeau",
        "Mezaourou"
    ],
    "name:vie_x_preferred":[
        "Mezaourou"
    ],
    "wof:name":"Mezaourou",
    "wof:placetype":"locality"
},
  "geometry": {"coordinates":[-0.62376,34.81822],"type":"Point"}
}