{
  "type": "Feature",
  "properties": {
    "gn:admin1_code":"30.0",
    "gn:asciiname":"Mezaourou",
    "gn:country_code":"DZ",
    "gn:dem":831,
    "gn:feature_class":"P",
    "gn:feature_code":"PPL",
    "gn:name":"Mezaourou",
    "gn:population":0,
    "gn:timezone":"Africa/Algiers",
    "iso:country":"DZ",
    "name:und_x_variant":[
        "Rochambeau",
        "Mezaourou"
    ],
    "wof:name":"Mezaourou",
    "wof:placetype":"locality"
},
  "geometry": {"coordinates":[-0.62376,34.81822],"type":"Point"}
}