{
  "type": "Feature",
  "properties": {
    "gn:admin1_code":"9.0",
    "gn:asciiname":"Oued Tlelat",
    "gn:country_code":"DZ",
    "gn:dem":133,
    "gn:feature_class":"P",
    "gn:feature_code":"PPL",
    "gn:name":"Oued Tl\u00e9lat",
    "gn:population":0,
    "gn:timezone":"Africa/Algiers",
    "iso:country":"DZ",
    "name:und_x_variant":[
        "Sainte-Barbe-du-Tl\u00e9lat",
        "Telat",
        "Sainte-Barbe-de-Tl\u00e9lat",
        "Oued-Trelat",
        "Sainte-Barbe-Du-Tr\u00e9lat",
        "Saint-Barbe-du-Tl\u00e9lat",
        "Oued Tl\u00e9lat"
    ],
    "wof:name":"Oued Tlelat",
    "wof:placetype":"locality"
},
  "geometry": {"coordinates":[-0.45141,35.5512],"type":"Point"}
}