{
  "type": "Feature",
  "properties": {
    "gn:admin1_code":"9.0",
    "gn:asciiname":"Oued Tlelat",
    "gn:country_code":"DZ",
    "gn:dem":133,
    "gn:feature_class":"P",
    "gn:feature_code":"PPL",
    "gn:name":"Oued Tl\u00e9lat",
    "gn:population":0,
    "gn:timezone":"Africa/Algiers",
    "iso:country":"DZ",
    "name:ara_x_preferred":[
        "\u0648\u0627\u062f\u064a \u062a\u0644\u064a\u0644\u0627\u062a"
    ],
    "name:azb_x_preferred":[
        "\u0648\u0627\u062f\u06cc \u062a\u0644\u06cc\u0644\u0627\u062a"
    ],
    "name:fas_x_preferred":[
        "\u0648\u0627\u062f\u06cc \u062a\u0644\u06cc\u0644\u0627\u062a"
    ],
    "name:fra_x_preferred":[
        "Oued Tlelat"
    ],
    "name:ita_x_preferred":[
        "Oued Tlelat"
    ],
    "name:kab_x_preferred":[
        "Wad Tlilat"
    ],
    "name:msa_x_preferred":[
        "Oued Tl\u00e9lat"
    ],
    "name:por_x_preferred":[
        "Oued Tl\u00e9lat"
    ],
    "name:ron_x_preferred":[
        "Oued Tlelat"
    ],
    "name:spa_x_preferred":[
        "Oued Tlelat"
    ],
    "name:und_x_variant":[
        "Sainte-Barbe-du-Tl\u00e9lat",
        "Telat",
        "Sainte-Barbe-de-Tl\u00e9lat",
        "Oued-Trelat",
        "Sainte-Barbe-Du-Tr\u00e9lat",
        "Saint-Barbe-du-Tl\u00e9lat"
    ],
    "name:vie_x_preferred":[
        "Oued Tlelat"
    ],
    "name:zho_x_preferred":[
        "\u74e6\u8fea\u7279\u840a\u62c9\u7279"
    ],
    "wof:name":"Oued Tlelat",
    "wof:placetype":"locality"
},
  "geometry": {"coordinates":[-0.45141,35.5512],"type":"Point"}
}