{
  "type": "Feature",
  "properties": {
    "gn:admin1_code":"12.0",
    "gn:asciiname":"Tarfat",
    "gn:country_code":"DZ",
    "gn:dem":865,
    "gn:feature_class":"P",
    "gn:feature_code":"PPL",
    "gn:name":"Tarfat",
    "gn:population":0,
    "gn:timezone":"Africa/Algiers",
    "iso:country":"DZ",
    "wof:name":"Tarfat",
    "wof:placetype":"locality"
},
  "geometry": {"coordinates":[4.87113,36.46827],"type":"Point"}
}