{
  "type": "Feature",
  "properties": {
    "gn:admin1_code":"35.0",
    "gn:asciiname":"Ferkat el Ghoualem",
    "gn:country_code":"DZ",
    "gn:dem":296,
    "gn:feature_class":"P",
    "gn:feature_code":"PPL",
    "gn:name":"Ferkat el Ghoualem",
    "gn:population":0,
    "gn:timezone":"Africa/Algiers",
    "iso:country":"DZ",
    "name:und_x_variant":[
        "Ghoualem"
    ],
    "wof:name":"Ferkat el Ghoualem",
    "wof:placetype":"locality"
},
  "geometry": {"coordinates":[2.05146,36.20891],"type":"Point"}
}