{
  "type": "Feature",
  "properties": {
    "gn:admin1_code":"10.0",
    "gn:asciiname":"El Louza",
    "gn:country_code":"DZ",
    "gn:dem":881,
    "gn:feature_class":"P",
    "gn:feature_code":"PPLL",
    "gn:name":"El Louza",
    "gn:population":0,
    "gn:timezone":"Africa/Algiers",
    "iso:country":"DZ",
    "wof:name":"El Louza",
    "wof:placetype":"locality"
},
  "geometry": {"coordinates":[0.10684,34.81593],"type":"Point"}
}