{
  "type": "Feature",
  "properties": {
    "gn:admin1_code":"40.0",
    "gn:asciiname":"Tihbobine",
    "gn:country_code":"DZ",
    "gn:dem":301,
    "gn:feature_class":"P",
    "gn:feature_code":"PPL",
    "gn:name":"Tihbobine",
    "gn:population":0,
    "gn:timezone":"Africa/Algiers",
    "iso:country":"DZ",
    "wof:name":"Tihbobine",
    "wof:placetype":"locality"
},
  "geometry": {"coordinates":[3.72371,36.66165],"type":"Point"}
}