{
  "type": "Feature",
  "properties": {
    "gn:admin1_code":"7.0",
    "gn:asciiname":"Zaouiat el Hadj Belahouel",
    "gn:country_code":"DZ",
    "gn:dem":144,
    "gn:feature_class":"P",
    "gn:feature_code":"PPL",
    "gn:name":"Zaouiat el Hadj Belahouel",
    "gn:population":0,
    "gn:timezone":"Africa/Algiers",
    "iso:country":"DZ",
    "wof:name":"Zaouiat el Hadj Belahouel",
    "wof:placetype":"locality"
},
  "geometry": {"coordinates":[0.39191,35.96769000000001],"type":"Point"}
}