{
  "type": "Feature",
  "properties": {
    "gn:admin1_code":"41.0",
    "gn:asciiname":"El M'Rah",
    "gn:country_code":"DZ",
    "gn:dem":450,
    "gn:feature_class":"P",
    "gn:feature_code":"PPL",
    "gn:name":"El M\u2019Rah",
    "gn:population":0,
    "gn:timezone":"Africa/Algiers",
    "iso:country":"DZ",
    "name:und_x_variant":[
        "El M\u2019Rah",
        "El Mia"
    ],
    "wof:name":"El M'Rah",
    "wof:placetype":"locality"
},
  "geometry": {"coordinates":[1.58179,36.05519],"type":"Point"}
}