{
  "type": "Feature",
  "properties": {
    "gn:admin1_code":"53.0",
    "gn:asciiname":"Base Sonarem",
    "gn:country_code":"DZ",
    "gn:dem":1048,
    "gn:feature_class":"P",
    "gn:feature_code":"PPL",
    "gn:name":"Base Sonarem",
    "gn:population":0,
    "gn:timezone":"Africa/Algiers",
    "iso:country":"DZ",
    "wof:name":"Base Sonarem",
    "wof:placetype":"locality"
},
  "geometry": {"coordinates":[5.1193,23.93775],"type":"Point"}
}