{
  "type": "Feature",
  "properties": {
    "gn:admin1_code":"41.0",
    "gn:asciiname":"Sendjas",
    "gn:country_code":"DZ",
    "gn:dem":258,
    "gn:feature_class":"P",
    "gn:feature_code":"PPL",
    "gn:name":"Sendjas",
    "gn:population":0,
    "gn:timezone":"Africa/Algiers",
    "iso:country":"DZ",
    "name:ara_x_preferred":[
        "\u0633\u0646\u062c\u0627\u0633"
    ],
    "name:azb_x_preferred":[
        "\u0633\u0646\u062c\u0627\u0633"
    ],
    "name:fas_x_preferred":[
        "\u0633\u0646\u062c\u0627\u0633"
    ],
    "name:fra_x_preferred":[
        "Sendjas"
    ],
    "name:ita_x_preferred":[
        "Sendjas"
    ],
    "name:msa_x_preferred":[
        "Sendjas"
    ],
    "name:por_x_preferred":[
        "Sendjas"
    ],
    "name:ron_x_preferred":[
        "Sendjas"
    ],
    "name:spa_x_preferred":[
        "Sendjas"
    ],
    "name:und_x_variant":[
        "Bougainville"
    ],
    "name:urd_x_preferred":[
        "\u0633\u0646\u062c\u0627\u0633"
    ],
    "name:vie_x_preferred":[
        "Sendjas"
    ],
    "wof:name":"Sendjas",
    "wof:placetype":"locality"
},
  "geometry": {"coordinates":[1.39393,36.06965],"type":"Point"}
}