{
  "type": "Feature",
  "properties": {
    "gn:admin1_code":"39.0",
    "gn:asciiname":"'Ain Melsa",
    "gn:country_code":"DZ",
    "gn:dem":936,
    "gn:feature_class":"P",
    "gn:feature_code":"PPL",
    "gn:name":"\u2019A\u00efn Melsa",
    "gn:population":0,
    "gn:timezone":"Africa/Algiers",
    "iso:country":"DZ",
    "name:und_x_variant":[
        "A\u00efne Melsa",
        "\u2019A\u00efn Melsa"
    ],
    "wof:name":"'Ain Melsa",
    "wof:placetype":"locality"
},
  "geometry": {"coordinates":[5.28032,36.12481],"type":"Point"}
}