{
  "type": "Feature",
  "properties": {
    "gn:admin1_code":"35.0",
    "gn:asciiname":"Douar Ouled Boudjemaa",
    "gn:country_code":"DZ",
    "gn:dem":478,
    "gn:feature_class":"P",
    "gn:feature_code":"PPLL",
    "gn:name":"Douar Ouled Boudjem\u00e2a",
    "gn:population":0,
    "gn:timezone":"Africa/Algiers",
    "iso:country":"DZ",
    "name:und_x_variant":[
        "Douar Ouled Boudjem\u00e2a",
        "Oulad Bou Djemaa"
    ],
    "wof:name":"Douar Ouled Boudjemaa",
    "wof:placetype":"locality"
},
  "geometry": {"coordinates":[1.81083,36.06894000000001],"type":"Point"}
}