{
  "type": "Feature",
  "properties": {
    "gn:admin1_code":"18.0",
    "gn:asciiname":"Bou Moussa",
    "gn:country_code":"DZ",
    "gn:dem":1053,
    "gn:feature_class":"P",
    "gn:feature_code":"PPL",
    "gn:name":"Bou Moussa",
    "gn:population":0,
    "gn:timezone":"Africa/Algiers",
    "iso:country":"DZ",
    "name:und_x_variant":[
        "Dechret Bou Moussa",
        "Bou Moussa"
    ],
    "wof:name":"Bou Moussa",
    "wof:placetype":"locality"
},
  "geometry": {"coordinates":[5.48787,36.47002],"type":"Point"}
}