{
  "type": "Feature",
  "properties": {
    "gn:country":"DZ",
    "gn:fcode":"PPL",
    "gn:population":36995,
    "iso:country":"DZ",
    "name:ara_x_preferred":[
        "\u0646\u062f\u0631\u0648\u0645\u0629"
    ],
    "name:arq_x_preferred":[
        "\u0646\u062f\u0631\u0648\u0645\u0629"
    ],
    "name:arz_x_preferred":[
        "\u0646\u062f\u0631\u0648\u0645\u0647"
    ],
    "name:azb_x_preferred":[
        "\u0646\u062f\u0631\u0648\u0645\u0647"
    ],
    "name:cat_x_preferred":[
        "N\u00e9droma"
    ],
    "name:ceb_x_preferred":[
        "Nedroma"
    ],
    "name:deu_x_preferred":[
        "Nedroma"
    ],
    "name:eng_x_preferred":[
        "Nedroma"
    ],
    "name:fas_x_preferred":[
        "\u0646\u062f\u0631\u0648\u0645\u0647"
    ],
    "name:fra_x_preferred":[
        "Nedroma"
    ],
    "name:ita_x_preferred":[
        "Nedroma"
    ],
    "name:kab_x_preferred":[
        "Nadruma"
    ],
    "name:kab_x_variant":[
        "Nedruma"
    ],
    "name:msa_x_preferred":[
        "Nedroma"
    ],
    "name:nan_x_preferred":[
        "Nedroma"
    ],
    "name:nld_x_preferred":[
        "Nedroma"
    ],
    "name:pol_x_preferred":[
        "Nidruma"
    ],
    "name:por_x_preferred":[
        "Nedroma"
    ],
    "name:ron_x_preferred":[
        "Nedroma"
    ],
    "name:spa_x_preferred":[
        "Nedroma"
    ],
    "name:swe_x_preferred":[
        "Nedroma"
    ],
    "name:urd_x_preferred":[
        "\u0646\u062f\u0631\u0648\u0645\u06c1"
    ],
    "name:uzb_x_preferred":[
        "Nedroma"
    ],
    "name:vie_x_preferred":[
        "Nedroma"
    ],
    "name:zho_x_preferred":[
        "\u5167\u5fb7\u7f85\u99ac"
    ],
    "name:zul_x_preferred":[
        "Nedroma"
    ],
    "qs_pg:aaroncc":"DZ",
    "qs_pg:gn_country":"DZ",
    "qs_pg:gn_fcode":"PPL",
    "qs_pg:gn_pop":36995,
    "qs_pg:name":"Nedroma",
    "qs_pg:photos_9r":0,
    "qs_pg:photos_sr":0,
    "qs_pg:pop_sr":7,
    "qs_pg:qs_pg_placetype":"locality",
    "wof:name":"Nedroma",
    "wof:placetype":"locality",
    "wof:population":36995
},
  "geometry": {"coordinates":[-1.74799,35.01361],"type":"Point"}
}