{
  "type": "Feature",
  "properties": {
    "gn:gn_country":"DZ",
    "gn:gn_fcode":"PPL",
    "gn:gn_pop":36995,
    "gn:population":36995,
    "iso:country":"DZ",
    "name:ara_x_preferred":[
        "\u0646\u062f\u0631\u0648\u0645\u0629"
    ],
    "name:cat_x_preferred":[
        "N\u00e9droma"
    ],
    "name:dut_x_preferred":[
        "Nedroma"
    ],
    "name:eng_x_preferred":[
        "Nedroma"
    ],
    "name:fre_x_preferred":[
        "Nedroma"
    ],
    "name:ita_x_preferred":[
        "Nedroma"
    ],
    "name:kab_x_preferred":[
        "Nadruma"
    ],
    "name:may_x_preferred":[
        "Nedroma"
    ],
    "name:per_x_preferred":[
        "\u0646\u062f\u0631\u0648\u0645\u0647"
    ],
    "name:pol_x_preferred":[
        "Nidruma"
    ],
    "name:por_x_preferred":[
        "Nedroma"
    ],
    "name:rum_x_preferred":[
        "Nedroma"
    ],
    "name:spa_x_preferred":[
        "Nedroma"
    ],
    "name:swe_x_preferred":[
        "Nedroma"
    ],
    "name:vie_x_preferred":[
        "Nedroma"
    ],
    "qs_pg:aaroncc":"DZ",
    "qs_pg:gn_country":"DZ",
    "qs_pg:gn_fcode":"PPL",
    "qs_pg:gn_pop":36995,
    "qs_pg:name":"Nedroma",
    "qs_pg:photos_9r":0,
    "qs_pg:photos_sr":0,
    "qs_pg:pop_sr":7,
    "qs_pg:qs_pg_placetype":"locality",
    "wof:name":"Nedroma",
    "wof:placetype":"locality",
    "wof:population":36995
},
  "geometry": {"coordinates":[-1.74799,35.01361],"type":"Point"}
}