{
  "type": "Feature",
  "properties": {
    "gn:admin1_code":"39.0",
    "gn:asciiname":"Bir Kasdali",
    "gn:country_code":"DZ",
    "gn:dem":978,
    "gn:feature_class":"P",
    "gn:feature_code":"PPL",
    "gn:name":"Bir Kasdali",
    "gn:population":0,
    "gn:timezone":"Africa/Algiers",
    "iso:country":"DZ",
    "name:ara_x_preferred":[
        "\u0628\u0626\u0631 \u0642\u0635\u062f \u0639\u0644\u064a"
    ],
    "name:azb_x_preferred":[
        "\u0628\u0626\u0631 \u0642\u0635\u062f \u0639\u0644\u06cc"
    ],
    "name:fas_x_preferred":[
        "\u0628\u0626\u0631 \u0642\u0635\u062f \u0639\u0644\u06cc"
    ],
    "name:fra_x_preferred":[
        "Bir Kasdali"
    ],
    "name:ita_x_preferred":[
        "Bir Kasd Ali"
    ],
    "name:msa_x_preferred":[
        "Bir Kasdali"
    ],
    "name:por_x_preferred":[
        "Bir Kasdali"
    ],
    "name:ron_x_preferred":[
        "Bir Kasdali"
    ],
    "name:spa_x_preferred":[
        "Bir Kasdali"
    ],
    "name:vie_x_preferred":[
        "Bir Kasdali"
    ],
    "wof:name":"Bir Kasdali",
    "wof:placetype":"locality"
},
  "geometry": {"coordinates":[5.02762,36.14447],"type":"Point"}
}