{
  "type": "Feature",
  "properties": {
    "gn:admin1_code":"27.0",
    "gn:asciiname":"Bir el Khoubbana",
    "gn:country_code":"DZ",
    "gn:dem":400,
    "gn:feature_class":"P",
    "gn:feature_code":"PPL",
    "gn:name":"Bir el Khoubbana",
    "gn:population":0,
    "gn:timezone":"Africa/Algiers",
    "iso:country":"DZ",
    "wof:name":"Bir el Khoubbana",
    "wof:placetype":"locality"
},
  "geometry": {"coordinates":[4.55888,35.34656],"type":"Point"}
}