{
  "type": "Feature",
  "properties": {
    "gn:admin1_code":"18.0",
    "gn:asciiname":"Amalou",
    "gn:country_code":"DZ",
    "gn:dem":491,
    "gn:feature_class":"P",
    "gn:feature_code":"PPL",
    "gn:name":"Amalou",
    "gn:population":0,
    "gn:timezone":"Africa/Algiers",
    "iso:country":"DZ",
    "name:ara_x_preferred":[
        "\u0623\u0645\u0627\u0644\u0648"
    ],
    "name:azb_x_preferred":[
        "\u0627\u0645\u0627\u0644\u0648"
    ],
    "name:fas_x_preferred":[
        "\u0627\u0645\u0627\u0644\u0648"
    ],
    "name:fra_x_preferred":[
        "Amalou"
    ],
    "name:ita_x_preferred":[
        "Amalou"
    ],
    "name:kab_x_preferred":[
        "Amalu"
    ],
    "name:msa_x_preferred":[
        "Amalou"
    ],
    "name:por_x_preferred":[
        "Amalou"
    ],
    "name:ron_x_preferred":[
        "Amalou"
    ],
    "name:spa_x_preferred":[
        "Amalou"
    ],
    "name:und_x_variant":[
        "Mahfouda"
    ],
    "name:vie_x_preferred":[
        "Amalou"
    ],
    "name:zho_x_preferred":[
        "\u963f\u99ac\u76e7"
    ],
    "wof:name":"Amalou",
    "wof:placetype":"locality"
},
  "geometry": {"coordinates":[4.65,36.48333],"type":"Point"}
}