{
  "type": "Feature",
  "properties": {
    "gn:admin1_code":"14.0",
    "gn:asciiname":"Mechreck",
    "gn:country_code":"DZ",
    "gn:dem":737,
    "gn:feature_class":"P",
    "gn:feature_code":"PPL",
    "gn:name":"Mechreck",
    "gn:population":0,
    "gn:timezone":"Africa/Algiers",
    "iso:country":"DZ",
    "wof:name":"Mechreck",
    "wof:placetype":"locality"
},
  "geometry": {"coordinates":[4.15158,36.52001],"type":"Point"}
}