{
  "type": "Feature",
  "properties": {
    "gn:admin1_code":"51.0",
    "gn:asciiname":"Argoub Aissa",
    "gn:country_code":"DZ",
    "gn:dem":403,
    "gn:feature_class":"P",
    "gn:feature_code":"PPL",
    "gn:name":"Argoub A\u00efssa",
    "gn:population":0,
    "gn:timezone":"Africa/Algiers",
    "iso:country":"DZ",
    "wof:name":"Argoub Aissa",
    "wof:placetype":"locality"
},
  "geometry": {"coordinates":[0.71736,35.54104],"type":"Point"}
}