{
  "type": "Feature",
  "properties": {
    "gn:admin1_code":"24.0",
    "gn:asciiname":"Taher",
    "gn:country_code":"DZ",
    "gn:dem":65,
    "gn:feature_class":"P",
    "gn:feature_code":"PPL",
    "gn:name":"Taher",
    "gn:population":0,
    "gn:timezone":"Africa/Algiers",
    "iso:country":"DZ",
    "name:ara_x_preferred":[
        "\u0627\u0644\u0637\u0627\u0647\u064a\u0631"
    ],
    "name:azb_x_preferred":[
        "\u0637\u0627\u0647\u06cc\u0631"
    ],
    "name:fas_x_preferred":[
        "\u0637\u0627\u0647\u06cc\u0631"
    ],
    "name:fra_x_preferred":[
        "Taher"
    ],
    "name:ita_x_preferred":[
        "Taher"
    ],
    "name:kab_x_preferred":[
        "\u1e6cahir"
    ],
    "name:msa_x_preferred":[
        "Taher"
    ],
    "name:pol_x_preferred":[
        "At-Tahir"
    ],
    "name:por_x_preferred":[
        "Taher"
    ],
    "name:ron_x_preferred":[
        "Taher"
    ],
    "name:spa_x_preferred":[
        "Taher"
    ],
    "name:ukr_x_preferred":[
        "\u0422\u0430\u0445\u0435\u0440"
    ],
    "name:vie_x_preferred":[
        "Taher"
    ],
    "name:zho_x_preferred":[
        "\u5854\u6d77\u723e"
    ],
    "wof:name":"Taher",
    "wof:placetype":"locality"
},
  "geometry": {"coordinates":[5.89788,36.76304],"type":"Point"}
}