{
  "type": "Feature",
  "properties": {
    "gn:admin1_code":"24.0",
    "gn:asciiname":"Taher",
    "gn:country_code":"DZ",
    "gn:dem":65,
    "gn:feature_class":"P",
    "gn:feature_code":"PPL",
    "gn:name":"Taher",
    "gn:population":0,
    "gn:timezone":"Africa/Algiers",
    "iso:country":"DZ",
    "wof:name":"Taher",
    "wof:placetype":"locality"
},
  "geometry": {"coordinates":[5.89788,36.76304],"type":"Point"}
}