{
  "type": "Feature",
  "properties": {
    "gn:admin1_code":"24.0",
    "gn:asciiname":"Bou 'Asli",
    "gn:country_code":"DZ",
    "gn:dem":686,
    "gn:feature_class":"P",
    "gn:feature_code":"PPL",
    "gn:name":"Bou \u2019Asli",
    "gn:population":0,
    "gn:timezone":"Africa/Algiers",
    "iso:country":"DZ",
    "name:und_x_variant":[
        "Mechtat Ben Azli",
        "Bou \u2019Asli"
    ],
    "wof:name":"Bou 'Asli",
    "wof:placetype":"locality"
},
  "geometry": {"coordinates":[5.67252,36.70546],"type":"Point"}
}