{
  "type": "Feature",
  "properties": {
    "gn:admin1_code":"3.0",
    "gn:asciiname":"Mechtat Sidi Marklouf",
    "gn:country_code":"DZ",
    "gn:dem":1262,
    "gn:feature_class":"P",
    "gn:feature_code":"PPL",
    "gn:name":"Mechtat Sidi Marklouf",
    "gn:population":0,
    "gn:timezone":"Africa/Algiers",
    "iso:country":"DZ",
    "name:und_x_variant":[
        "Mechta Sidi Makhlouf",
        "Mechtat Sidi Marklouf"
    ],
    "wof:name":"Mechtat Sidi Marklouf",
    "wof:placetype":"locality"
},
  "geometry": {"coordinates":[5.88481,35.4728],"type":"Point"}
}