{
  "type": "Feature",
  "properties": {
    "gn:admin1_code":"14.0",
    "gn:asciiname":"Kanntidja",
    "gn:country_code":"DZ",
    "gn:dem":145,
    "gn:feature_class":"P",
    "gn:feature_code":"PPL",
    "gn:name":"Kanntidja",
    "gn:population":0,
    "gn:timezone":"Africa/Algiers",
    "iso:country":"DZ",
    "wof:name":"Kanntidja",
    "wof:placetype":"locality"
},
  "geometry": {"coordinates":[3.91504,36.61643],"type":"Point"}
}