{
  "type": "Feature",
  "properties": {
    "gn:admin1_code":"34.0",
    "gn:asciiname":"I-n-Rhar",
    "gn:country_code":"DZ",
    "gn:dem":258,
    "gn:feature_class":"P",
    "gn:feature_code":"PPL",
    "gn:name":"I-n-Rhar",
    "gn:population":0,
    "gn:timezone":"Africa/Algiers",
    "iso:country":"DZ",
    "wof:name":"I-n-Rhar",
    "wof:placetype":"locality"
},
  "geometry": {"coordinates":[1.9092,27.103],"type":"Point"}
}