{
  "type": "Feature",
  "properties": {
    "gn:admin1_code":"18.0",
    "gn:asciiname":"Abeid",
    "gn:country_code":"DZ",
    "gn:dem":631,
    "gn:feature_class":"P",
    "gn:feature_code":"PPL",
    "gn:name":"Abe\u00efd",
    "gn:population":0,
    "gn:timezone":"Africa/Algiers",
    "iso:country":"DZ",
    "name:rus_x_preferred":[
        "\u0410\u0431\u0435\u0439\u0434"
    ],
    "wof:name":"Abeid",
    "wof:placetype":"locality"
},
  "geometry": {"coordinates":[4.98795,36.59002],"type":"Point"}
}