{
  "type": "Feature",
  "properties": {
    "gn:admin1_code":"3.0",
    "gn:asciiname":"Maafa",
    "gn:country_code":"DZ",
    "gn:dem":974,
    "gn:feature_class":"P",
    "gn:feature_code":"PPL",
    "gn:name":"Maafa",
    "gn:population":0,
    "gn:timezone":"Africa/Algiers",
    "iso:country":"DZ",
    "name:ara_x_preferred":[
        "\u0645\u0639\u0627\u0641\u0629"
    ],
    "name:azb_x_preferred":[
        "\u0645\u0639\u0627\u0641\u0647"
    ],
    "name:fas_x_preferred":[
        "\u0645\u0639\u0627\u0641\u0647"
    ],
    "name:fra_x_preferred":[
        "Maafa"
    ],
    "name:ita_x_preferred":[
        "Maafa"
    ],
    "name:msa_x_preferred":[
        "Ma\u00e2fa"
    ],
    "name:por_x_preferred":[
        "Ma\u00e2fa"
    ],
    "name:ron_x_preferred":[
        "Maafa"
    ],
    "name:spa_x_preferred":[
        "Maafa"
    ],
    "name:urd_x_preferred":[
        "\u0645\u0627\u0641\u0627"
    ],
    "name:vie_x_preferred":[
        "Ma\u00e2fa"
    ],
    "wof:name":"Maafa",
    "wof:placetype":"locality"
},
  "geometry": {"coordinates":[5.89764,35.26345999999999],"type":"Point"}
}