{
  "type": "Feature",
  "properties": {
    "gn:admin1_code":"12.0",
    "gn:asciiname":"Mechtat el Djahli",
    "gn:country_code":"DZ",
    "gn:dem":905,
    "gn:feature_class":"P",
    "gn:feature_code":"PPL",
    "gn:name":"Mechtat el Djahli",
    "gn:population":0,
    "gn:timezone":"Africa/Algiers",
    "iso:country":"DZ",
    "name:und_x_variant":[
        "Mechtet el Djahli",
        "Mechtat el Djahli"
    ],
    "wof:name":"Mechtat el Djahli",
    "wof:placetype":"locality"
},
  "geometry": {"coordinates":[6.00799,36.03043],"type":"Point"}
}