{
  "type": "Feature",
  "properties": {
    "gn:admin1_code":"34.0",
    "gn:asciiname":"Bour Ouled Moussa",
    "gn:country_code":"DZ",
    "gn:dem":317,
    "gn:feature_class":"P",
    "gn:feature_code":"PPL",
    "gn:name":"Bour Ouled Moussa",
    "gn:population":0,
    "gn:timezone":"Africa/Algiers",
    "iso:country":"DZ",
    "wof:name":"Bour Ouled Moussa",
    "wof:placetype":"locality"
},
  "geometry": {"coordinates":[0.00711,29.30866],"type":"Point"}
}