{
  "type": "Feature",
  "properties": {
    "gn:admin1_code":"6.0",
    "gn:asciiname":"Saneg",
    "gn:country_code":"DZ",
    "gn:dem":767,
    "gn:feature_class":"P",
    "gn:feature_code":"PPL",
    "gn:name":"Saneg",
    "gn:population":0,
    "gn:timezone":"Africa/Algiers",
    "iso:country":"DZ",
    "name:ara_x_preferred":[
        "\u0633\u0627\u0646\u0642"
    ],
    "name:azb_x_preferred":[
        "\u0633\u0627\u0646\u0642"
    ],
    "name:fas_x_preferred":[
        "\u0633\u0627\u0646\u0642"
    ],
    "name:fra_x_preferred":[
        "Saneg"
    ],
    "name:ita_x_preferred":[
        "Saneg"
    ],
    "name:msa_x_preferred":[
        "Saneg"
    ],
    "name:por_x_preferred":[
        "Saneg"
    ],
    "name:ron_x_preferred":[
        "Saneg"
    ],
    "name:spa_x_preferred":[
        "Saneg"
    ],
    "name:vie_x_preferred":[
        "Saneg"
    ],
    "name:zho_x_preferred":[
        "\u85a9\u5948\u683c"
    ],
    "wof:name":"Saneg",
    "wof:placetype":"locality"
},
  "geometry": {"coordinates":[2.88825,35.84848],"type":"Point"}
}