{
  "type": "Feature",
  "properties": {
    "gn:admin1_code":"6.0",
    "gn:asciiname":"Saneg",
    "gn:country_code":"DZ",
    "gn:dem":767,
    "gn:feature_class":"P",
    "gn:feature_code":"PPL",
    "gn:name":"Saneg",
    "gn:population":0,
    "gn:timezone":"Africa/Algiers",
    "iso:country":"DZ",
    "wof:name":"Saneg",
    "wof:placetype":"locality"
},
  "geometry": {"coordinates":[2.88825,35.84848],"type":"Point"}
}