{
  "type": "Feature",
  "properties": {
    "gn:admin1_code":"14.0",
    "gn:asciiname":"Irhil Bouzerou",
    "gn:country_code":"DZ",
    "gn:dem":577,
    "gn:feature_class":"P",
    "gn:feature_code":"PPL",
    "gn:name":"Irhil Bouzerou",
    "gn:population":0,
    "gn:timezone":"Africa/Algiers",
    "iso:country":"DZ",
    "wof:name":"Irhil Bouzerou",
    "wof:placetype":"locality"
},
  "geometry": {"coordinates":[4.08009,36.66205],"type":"Point"}
}