{
  "type": "Feature",
  "properties": {
    "gn:admin1_code":"31.0",
    "gn:asciiname":"Bou Aziz",
    "gn:country_code":"DZ",
    "gn:dem":287,
    "gn:feature_class":"P",
    "gn:feature_code":"PPL",
    "gn:name":"Bou Aziz",
    "gn:population":0,
    "gn:timezone":"Africa/Algiers",
    "iso:country":"DZ",
    "wof:name":"Bou Aziz",
    "wof:placetype":"locality"
},
  "geometry": {"coordinates":[7.10254,36.88744000000001],"type":"Point"}
}