{
  "type": "Feature",
  "properties": {
    "gn:admin1_code":"42.0",
    "gn:asciiname":"Sidi Slimane",
    "gn:country_code":"DZ",
    "gn:dem":1315,
    "gn:feature_class":"P",
    "gn:feature_code":"PPL",
    "gn:name":"Sidi Slimane",
    "gn:population":0,
    "gn:timezone":"Africa/Algiers",
    "iso:country":"DZ",
    "wof:name":"Sidi Slimane",
    "wof:placetype":"locality"
},
  "geometry": {"coordinates":[1.72976,33.83333],"type":"Point"}
}