{
  "type": "Feature",
  "properties": {
    "gn:admin1_code":"52.0",
    "gn:asciiname":"Mechta Rouiguet",
    "gn:country_code":"DZ",
    "gn:dem":696,
    "gn:feature_class":"P",
    "gn:feature_code":"PPL",
    "gn:name":"Mechta Rouiguet",
    "gn:population":0,
    "gn:timezone":"Africa/Algiers",
    "iso:country":"DZ",
    "wof:name":"Mechta Rouiguet",
    "wof:placetype":"locality"
},
  "geometry": {"coordinates":[8.29715,36.37215],"type":"Point"}
}