{
  "type": "Feature",
  "properties": {
    "gn:country":"DZ",
    "gn:fcode":"PPL",
    "gn:population":26407,
    "iso:country":"DZ",
    "name:ara_x_preferred":[
        "\u0627\u0644\u0639\u0627\u0645\u0631\u064a\u0629"
    ],
    "name:azb_x_preferred":[
        "\u0639\u0627\u0645\u0631\u06cc\u0647"
    ],
    "name:ceb_x_preferred":[
        "El Amria"
    ],
    "name:eng_x_preferred":[
        "El Amria"
    ],
    "name:fas_x_preferred":[
        "\u0639\u0627\u0645\u0631\u06cc\u0647"
    ],
    "name:fra_x_preferred":[
        "El Amria"
    ],
    "name:ita_x_preferred":[
        "El Amria"
    ],
    "name:kab_x_preferred":[
        "L\u025bemreyya"
    ],
    "name:msa_x_preferred":[
        "El Amria"
    ],
    "name:nan_x_preferred":[
        "El Amria"
    ],
    "name:nld_x_preferred":[
        "El Amria"
    ],
    "name:por_x_preferred":[
        "El Amria"
    ],
    "name:ron_x_preferred":[
        "El Amria"
    ],
    "name:spa_x_preferred":[
        "El Amria"
    ],
    "name:swe_x_preferred":[
        "El Amria"
    ],
    "name:und_x_variant":[
        "Lourmel"
    ],
    "name:vie_x_preferred":[
        "El Amria"
    ],
    "name:zho_x_preferred":[
        "\u963f\u59c6\u91cc\u8036"
    ],
    "qs:name":"El Amria",
    "qs:photos_9r":0,
    "qs:photos_sr":0,
    "qs:pop_sr":"7",
    "wd:wordcount":20,
    "wof:name":"El Amria",
    "wof:placetype":"locality",
    "wof:population":26407
},
  "geometry": {"coordinates":[-1.01577,35.52439],"type":"Point"}
}