{
  "type": "Feature",
  "properties": {
    "gn:admin1_code":"13.0",
    "gn:asciiname":"Ouled el Hadj Kaddour",
    "gn:country_code":"DZ",
    "gn:dem":718,
    "gn:feature_class":"P",
    "gn:feature_code":"PPL",
    "gn:name":"Ouled el Hadj Kaddour",
    "gn:population":0,
    "gn:timezone":"Africa/Algiers",
    "iso:country":"DZ",
    "name:und_x_variant":[
        "Douar Ouled Hadj Kaddour",
        "Ouled el Hadj Kaddour"
    ],
    "wof:name":"Ouled el Hadj Kaddour",
    "wof:placetype":"locality"
},
  "geometry": {"coordinates":[1.09176,35.55828],"type":"Point"}
}