{
  "type": "Feature",
  "properties": {
    "gn:admin1_code":"40.0",
    "gn:asciiname":"Corso Tahtani",
    "gn:cc2":"DZ",
    "gn:country_code":"DZ",
    "gn:dem":31,
    "gn:feature_class":"P",
    "gn:feature_code":"PPL",
    "gn:name":"Corso Tahtani",
    "gn:population":0,
    "gn:timezone":"Africa/Algiers",
    "iso:country":"DZ",
    "name:und_x_variant":[
        "Corso el Tahatini",
        "Corso Tahtani"
    ],
    "wof:name":"Corso Tahtani",
    "wof:placetype":"locality"
},
  "geometry": {"coordinates":[3.44278,36.75472],"type":"Point"}
}