{
  "type": "Feature",
  "properties": {
    "gn:admin1_code":"41.0",
    "gn:asciiname":"Chenatra",
    "gn:country_code":"DZ",
    "gn:dem":686,
    "gn:feature_class":"P",
    "gn:feature_code":"PPL",
    "gn:name":"Chenatra",
    "gn:population":0,
    "gn:timezone":"Africa/Algiers",
    "iso:country":"DZ",
    "wof:name":"Chenatra",
    "wof:placetype":"locality"
},
  "geometry": {"coordinates":[1.47644,36.00417],"type":"Point"}
}