{
  "type": "Feature",
  "properties": {
    "gn:admin1_code":"36.0",
    "gn:asciiname":"Oulad Bou en Nouar",
    "gn:country_code":"DZ",
    "gn:dem":286,
    "gn:feature_class":"P",
    "gn:feature_code":"PPL",
    "gn:name":"Oulad Bou en Nouar",
    "gn:population":0,
    "gn:timezone":"Africa/Algiers",
    "iso:country":"DZ",
    "name:und_x_variant":[
        "Oulad Bou el Nouar",
        "Oulad Bou en Nouar"
    ],
    "wof:name":"Oulad Bou en Nouar",
    "wof:placetype":"locality"
},
  "geometry": {"coordinates":[-1.51945,35.21173],"type":"Point"}
}