{
  "type": "Feature",
  "properties": {
    "gn:admin1_code":"7.0",
    "gn:asciiname":"Douar Zouaria",
    "gn:country_code":"DZ",
    "gn:dem":118,
    "gn:feature_class":"P",
    "gn:feature_code":"PPL",
    "gn:name":"Douar Zou\u00e2ria",
    "gn:population":0,
    "gn:timezone":"Africa/Algiers",
    "iso:country":"DZ",
    "wof:name":"Douar Zouaria",
    "wof:placetype":"locality"
},
  "geometry": {"coordinates":[0.27755,35.77326],"type":"Point"}
}