{
  "type": "Feature",
  "properties": {
    "gn:admin1_code":"35.0",
    "gn:asciiname":"Matmata",
    "gn:country_code":"DZ",
    "gn:dem":436,
    "gn:feature_class":"P",
    "gn:feature_code":"PPL",
    "gn:name":"Matmata",
    "gn:population":0,
    "gn:timezone":"Africa/Algiers",
    "iso:country":"DZ",
    "name:ceb_x_preferred":[
        "Matmata"
    ],
    "name:eus_x_preferred":[
        "Matmata"
    ],
    "name:fra_x_preferred":[
        "Matmata"
    ],
    "name:swe_x_preferred":[
        "Matmata"
    ],
    "wof:name":"Matmata",
    "wof:placetype":"locality"
},
  "geometry": {"coordinates":[2.29958,36.06725],"type":"Point"}
}