{
  "type": "Feature",
  "properties": {
    "gn:admin1_code":"41.0",
    "gn:asciiname":"Haouch es Serdj",
    "gn:country_code":"DZ",
    "gn:dem":321,
    "gn:feature_class":"P",
    "gn:feature_code":"PPL",
    "gn:name":"Haouch es Serdj",
    "gn:population":0,
    "gn:timezone":"Africa/Algiers",
    "iso:country":"DZ",
    "wof:name":"Haouch es Serdj",
    "wof:placetype":"locality"
},
  "geometry": {"coordinates":[1.26361,36.46854],"type":"Point"}
}