{
  "type": "Feature",
  "properties": {
    "gn:admin1_code":"29.0",
    "gn:asciiname":"Mechta Ras Oulmene",
    "gn:cc2":"DZ",
    "gn:country_code":"DZ",
    "gn:dem":984,
    "gn:feature_class":"P",
    "gn:feature_code":"PPL",
    "gn:name":"Mechta R\u00e2s Oulmene",
    "gn:population":0,
    "gn:timezone":"Africa/Algiers",
    "iso:country":"DZ",
    "name:und_x_variant":[
        "Mechta Rass Oulmen",
        "Mechta R\u00e2s Oulmene"
    ],
    "wof:name":"Mechta Ras Oulmene",
    "wof:placetype":"locality"
},
  "geometry": {"coordinates":[7.41667,35.75],"type":"Point"}
}