{
  "type": "Feature",
  "properties": {
    "gn:admin1_code":"51.0",
    "gn:asciiname":"Hamadena Bouroukba",
    "gn:country_code":"DZ",
    "gn:dem":78,
    "gn:feature_class":"P",
    "gn:feature_code":"PPL",
    "gn:name":"Hamadena Bouroukba",
    "gn:population":0,
    "gn:timezone":"Africa/Algiers",
    "iso:country":"DZ",
    "wof:name":"Hamadena Bouroukba",
    "wof:placetype":"locality"
},
  "geometry": {"coordinates":[0.73938,35.89660999999999],"type":"Point"}
}