{
  "type": "Feature",
  "properties": {
    "gn:admin1_code":"51.0",
    "gn:asciiname":"Oulad Ali",
    "gn:country_code":"DZ",
    "gn:dem":362,
    "gn:feature_class":"P",
    "gn:feature_code":"PPL",
    "gn:name":"Oulad Ali",
    "gn:population":0,
    "gn:timezone":"Africa/Algiers",
    "iso:country":"DZ",
    "wof:name":"Oulad Ali",
    "wof:placetype":"locality"
},
  "geometry": {"coordinates":[0.93063,36.09929],"type":"Point"}
}