{
  "type": "Feature",
  "properties": {
    "gn:admin1_code":"55.0",
    "gn:asciiname":"Haouch ben Daouin",
    "gn:country_code":"DZ",
    "gn:dem":65,
    "gn:feature_class":"P",
    "gn:feature_code":"PPL",
    "gn:name":"Haouch ben Daouin",
    "gn:population":0,
    "gn:timezone":"Africa/Algiers",
    "iso:country":"DZ",
    "wof:name":"Haouch ben Daouin",
    "wof:placetype":"locality"
},
  "geometry": {"coordinates":[2.4925,36.54583],"type":"Point"}
}