{
  "type": "Feature",
  "properties": {
    "gn:admin1_code":"41.0",
    "gn:asciiname":"Chekalil",
    "gn:country_code":"DZ",
    "gn:dem":167,
    "gn:feature_class":"P",
    "gn:feature_code":"PPL",
    "gn:name":"Chekalil",
    "gn:population":0,
    "gn:timezone":"Africa/Algiers",
    "iso:country":"DZ",
    "wof:name":"Chekalil",
    "wof:placetype":"locality"
},
  "geometry": {"coordinates":[1.36993,36.21142],"type":"Point"}
}