{
  "type": "Feature",
  "properties": {
    "gn:admin1_code":"29.0",
    "gn:asciiname":"Mechtat Bir el Arbi",
    "gn:country_code":"DZ",
    "gn:dem":918,
    "gn:feature_class":"P",
    "gn:feature_code":"PPL",
    "gn:name":"Mechtat Bir el Arbi",
    "gn:population":0,
    "gn:timezone":"Africa/Algiers",
    "iso:country":"DZ",
    "wof:name":"Mechtat Bir el Arbi",
    "wof:placetype":"locality"
},
  "geometry": {"coordinates":[6.86712,36.16588],"type":"Point"}
}