{
  "type": "Feature",
  "properties": {
    "gn:admin1_code":"13.0",
    "gn:asciiname":"Beni Ouendjel",
    "gn:country_code":"DZ",
    "gn:dem":883,
    "gn:feature_class":"P",
    "gn:feature_code":"PPL",
    "gn:name":"Beni Ouendjel",
    "gn:population":0,
    "gn:timezone":"Africa/Algiers",
    "iso:country":"DZ",
    "wof:name":"Beni Ouendjel",
    "wof:placetype":"locality"
},
  "geometry": {"coordinates":[0.90382,35.03413],"type":"Point"}
}