{
  "type": "Feature",
  "properties": {
    "gn:admin1_code":"15.0",
    "gn:asciiname":"Douar Ouled Kaddour Asrhar",
    "gn:country_code":"DZ",
    "gn:dem":422,
    "gn:feature_class":"P",
    "gn:feature_code":"PPLL",
    "gn:name":"Douar Ouled Kaddo\u00fbr Asrh\u00e2r",
    "gn:population":0,
    "gn:timezone":"Africa/Algiers",
    "iso:country":"DZ",
    "name:und_x_variant":[
        "Oulad Kaddour",
        "Douar Oulad Kaddour",
        "Douar Ouled Kaddo\u00fbr Asrh\u00e2r"
    ],
    "wof:name":"Douar Ouled Kaddour Asrhar",
    "wof:placetype":"locality"
},
  "geometry": {"coordinates":[-1.75179,34.81366],"type":"Point"}
}