{
  "type": "Feature",
  "properties": {
    "gn:admin1_code":"26.0",
    "gn:asciiname":"Dar Sidi Mahmoud",
    "gn:country_code":"DZ",
    "gn:dem":559,
    "gn:feature_class":"P",
    "gn:feature_code":"PPL",
    "gn:name":"Dar Sidi Mahmoud",
    "gn:population":0,
    "gn:timezone":"Africa/Algiers",
    "iso:country":"DZ",
    "wof:name":"Dar Sidi Mahmoud",
    "wof:placetype":"locality"
},
  "geometry": {"coordinates":[0.38569,35.48094000000001],"type":"Point"}
}