{
  "type": "Feature",
  "properties": {
    "gn:admin1_code":"34.0",
    "gn:asciiname":"El Maiz",
    "gn:country_code":"DZ",
    "gn:dem":261,
    "gn:feature_class":"P",
    "gn:feature_code":"PPL",
    "gn:name":"El Ma\u00efz",
    "gn:population":0,
    "gn:timezone":"Africa/Algiers",
    "iso:country":"DZ",
    "wof:name":"El Maiz",
    "wof:placetype":"locality"
},
  "geometry": {"coordinates":[-0.22013,28.347],"type":"Point"}
}