{
  "type": "Feature",
  "properties": {
    "gn:admin1_code":"13.0",
    "gn:asciiname":"Souk el Had",
    "gn:country_code":"DZ",
    "gn:dem":804,
    "gn:feature_class":"P",
    "gn:feature_code":"PPL",
    "gn:name":"Souk el Had",
    "gn:population":0,
    "gn:timezone":"Africa/Algiers",
    "iso:country":"DZ",
    "name:und_x_variant":[
        "El Had",
        "Souk el Had"
    ],
    "wof:name":"Souk el Had",
    "wof:placetype":"locality"
},
  "geometry": {"coordinates":[2.17869,35.49383],"type":"Point"}
}