{
  "type": "Feature",
  "properties": {
    "gn:admin1_code":"41.0",
    "gn:asciiname":"Douar Yarmoul",
    "gn:country_code":"DZ",
    "gn:dem":204,
    "gn:feature_class":"P",
    "gn:feature_code":"PPL",
    "gn:name":"Douar Yarmoul",
    "gn:population":0,
    "gn:timezone":"Africa/Algiers",
    "iso:country":"DZ",
    "name:und_x_variant":[
        "Douar Yermoul"
    ],
    "wof:name":"Douar Yarmoul",
    "wof:placetype":"locality"
},
  "geometry": {"coordinates":[1.42327,36.25238],"type":"Point"}
}