{
  "type": "Feature",
  "properties": {
    "gn:admin1_code":"35.0",
    "gn:asciiname":"Moualdia",
    "gn:country_code":"DZ",
    "gn:dem":628,
    "gn:feature_class":"P",
    "gn:feature_code":"PPL",
    "gn:name":"Moualdia",
    "gn:population":0,
    "gn:timezone":"Africa/Algiers",
    "iso:country":"DZ",
    "wof:name":"Moualdia",
    "wof:placetype":"locality"
},
  "geometry": {"coordinates":[2.38333,36.06667],"type":"Point"}
}