{
  "type": "Feature",
  "properties": {
    "gn:admin1_code":"33.0",
    "gn:asciiname":"Mechta Oulad Mohammed",
    "gn:country_code":"DZ",
    "gn:dem":1318,
    "gn:feature_class":"P",
    "gn:feature_code":"PPL",
    "gn:name":"Mechta Oulad Mohammed",
    "gn:population":0,
    "gn:timezone":"Africa/Algiers",
    "iso:country":"DZ",
    "wof:name":"Mechta Oulad Mohammed",
    "wof:placetype":"locality"
},
  "geometry": {"coordinates":[7.98444,35.29589],"type":"Point"}
}