{
  "type": "Feature",
  "properties": {
    "gn:admin1_code":"3.0",
    "gn:asciiname":"Markouna",
    "gn:country_code":"DZ",
    "gn:dem":1237,
    "gn:feature_class":"P",
    "gn:feature_code":"PPL",
    "gn:name":"Markoun\u00e2",
    "gn:population":0,
    "gn:timezone":"Africa/Algiers",
    "iso:country":"DZ",
    "name:und_x_variant":[
        "Marcouna",
        "Markoun\u00e2"
    ],
    "wof:name":"Markouna",
    "wof:placetype":"locality"
},
  "geometry": {"coordinates":[6.29138,35.48455],"type":"Point"}
}