{
  "type": "Feature",
  "properties": {
    "gn:admin1_code":"35.0",
    "gn:asciiname":"Labadnia",
    "gn:country_code":"DZ",
    "gn:dem":415,
    "gn:feature_class":"P",
    "gn:feature_code":"PPL",
    "gn:name":"Labadnia",
    "gn:population":0,
    "gn:timezone":"Africa/Algiers",
    "iso:country":"DZ",
    "wof:name":"Labadnia",
    "wof:placetype":"locality"
},
  "geometry": {"coordinates":[1.69239,36.33229],"type":"Point"}
}