{
  "type": "Feature",
  "properties": {
    "gn:admin1_code":"19.0",
    "gn:asciiname":"El Bania",
    "gn:country_code":"DZ",
    "gn:dem":291,
    "gn:feature_class":"P",
    "gn:feature_code":"PPL",
    "gn:name":"El Bania",
    "gn:population":0,
    "gn:timezone":"Africa/Algiers",
    "iso:country":"DZ",
    "wof:name":"El Bania",
    "wof:placetype":"locality"
},
  "geometry": {"coordinates":[4.97831,33.93547],"type":"Point"}
}