{
  "type": "Feature",
  "properties": {
    "gn:admin1_code":"3.0",
    "gn:asciiname":"Ouled Achoura",
    "gn:country_code":"DZ",
    "gn:dem":840,
    "gn:feature_class":"P",
    "gn:feature_code":"PPL",
    "gn:name":"Ouled Achoura",
    "gn:population":0,
    "gn:timezone":"Africa/Algiers",
    "iso:country":"DZ",
    "wof:name":"Ouled Achoura",
    "wof:placetype":"locality"
},
  "geometry": {"coordinates":[6.38736,35.79052],"type":"Point"}
}