{
  "type": "Feature",
  "properties": {
    "gn:admin1_code":"18.0",
    "gn:asciiname":"Takourrabet",
    "gn:country_code":"DZ",
    "gn:dem":457,
    "gn:feature_class":"P",
    "gn:feature_code":"PPL",
    "gn:name":"Takourrabet",
    "gn:population":0,
    "gn:timezone":"Africa/Algiers",
    "iso:country":"DZ",
    "wof:name":"Takourrabet",
    "wof:placetype":"locality"
},
  "geometry": {"coordinates":[4.48675,36.35738],"type":"Point"}
}