{
  "type": "Feature",
  "properties": {
    "gn:admin1_code":"12.0",
    "gn:asciiname":"Tikesriine",
    "gn:country_code":"DZ",
    "gn:dem":688,
    "gn:feature_class":"P",
    "gn:feature_code":"PPL",
    "gn:name":"Tikesriine",
    "gn:population":0,
    "gn:timezone":"Africa/Algiers",
    "iso:country":"DZ",
    "wof:name":"Tikesriine",
    "wof:placetype":"locality"
},
  "geometry": {"coordinates":[5.14504,36.47248],"type":"Point"}
}