{
  "type": "Feature",
  "properties": {
    "iso:country":"DZ",
    "name:ara_x_preferred":[
        "\u062a\u0645\u0627\u0644\u0648\u0633"
    ],
    "name:azb_x_preferred":[
        "\u062a\u0645\u0627\u0644\u0648\u0633"
    ],
    "name:ceb_x_preferred":[
        "Tamalous"
    ],
    "name:eng_x_preferred":[
        "Tamalous"
    ],
    "name:fas_x_preferred":[
        "\u062a\u0645\u0627\u0644\u0648\u0633"
    ],
    "name:fra_x_preferred":[
        "Tamalous"
    ],
    "name:ita_x_preferred":[
        "Tamalous"
    ],
    "name:kab_x_preferred":[
        "Tamalus"
    ],
    "name:msa_x_preferred":[
        "Tamalous"
    ],
    "name:nan_x_preferred":[
        "Tamalous"
    ],
    "name:nld_x_preferred":[
        "Tamalous"
    ],
    "name:por_x_preferred":[
        "Tamalous"
    ],
    "name:ron_x_preferred":[
        "Tamalous"
    ],
    "name:spa_x_preferred":[
        "Tamalous"
    ],
    "name:swe_x_preferred":[
        "Tamalous"
    ],
    "name:vie_x_preferred":[
        "Tamalous"
    ],
    "name:zho_min_nan_x_preferred":[
        "Tamalous"
    ],
    "name:zho_x_preferred":[
        "\u5854\u99ac\u76e7\u65af"
    ],
    "qs:gn_country":"DZ",
    "qs:gn_fcode":"PPL",
    "qs:gn_pop":32579,
    "qs:name":"Tamalous",
    "qs:name_adm0":"\u0627\u0644\u062c\u0632\u0627\u0626\u0631",
    "qs:name_adm1":"\u0648\u0644\u0627\u064a\u0629 \u0633\u0643\u064a\u0643\u062f\u0629",
    "qs:photos":0,
    "qs:photos_1k":0,
    "qs:photos_9k":1,
    "qs:photos_9r":1,
    "qs:photos_all":2,
    "qs:photos_sr":0,
    "qs:placetype":"Town",
    "qs:pop_sr":"7",
    "qs:woe_adm0":23424740,
    "wd:wordcount":38,
    "wof:name":"Tamalous",
    "wof:placetype":"locality",
    "wof:population":32579
},
  "geometry": {"coordinates":[6.64018,36.83763],"type":"Point"}
}