{
  "type": "Feature",
  "properties": {
    "gn:admin1_code":"12.0",
    "gn:asciiname":"Oum Ladjoul",
    "gn:country_code":"DZ",
    "gn:dem":907,
    "gn:feature_class":"P",
    "gn:feature_code":"PPL",
    "gn:name":"Oum Ladjoul",
    "gn:population":0,
    "gn:timezone":"Africa/Algiers",
    "iso:country":"DZ",
    "name:und_x_variant":[
        "Pierre Curie",
        "Oum Ladjoul"
    ],
    "wof:name":"Oum Ladjoul",
    "wof:placetype":"locality"
},
  "geometry": {"coordinates":[5.89531,35.93293],"type":"Point"}
}