{
  "type": "Feature",
  "properties": {
    "gn:admin1_code":"39.0",
    "gn:asciiname":"El Guettar",
    "gn:country_code":"DZ",
    "gn:dem":1268,
    "gn:feature_class":"P",
    "gn:feature_code":"PPL",
    "gn:name":"El Guettar",
    "gn:population":0,
    "gn:timezone":"Africa/Algiers",
    "iso:country":"DZ",
    "name:ceb_x_preferred":[
        "El Guettar"
    ],
    "name:deu_x_preferred":[
        "El Guettar"
    ],
    "name:fra_x_preferred":[
        "El Guettar"
    ],
    "name:swe_x_preferred":[
        "El Guettar"
    ],
    "wof:name":"El Guettar",
    "wof:placetype":"locality"
},
  "geometry": {"coordinates":[4.94576,35.9487],"type":"Point"}
}