{
  "type": "Feature",
  "properties": {
    "gn:admin1_code":"41.0",
    "gn:asciiname":"Douar Maaichid",
    "gn:country_code":"DZ",
    "gn:dem":550,
    "gn:feature_class":"P",
    "gn:feature_code":"PPL",
    "gn:name":"Douar Maaichid",
    "gn:population":0,
    "gn:timezone":"Africa/Algiers",
    "iso:country":"DZ",
    "wof:name":"Douar Maaichid",
    "wof:placetype":"locality"
},
  "geometry": {"coordinates":[1.02154,36.361],"type":"Point"}
}