{
  "type": "Feature",
  "properties": {
    "gn:admin1_code":"47.0",
    "gn:asciiname":"Chebla",
    "gn:country_code":"DZ",
    "gn:dem":502,
    "gn:feature_class":"P",
    "gn:feature_code":"PPL",
    "gn:name":"Chebla",
    "gn:population":0,
    "gn:timezone":"Africa/Algiers",
    "iso:country":"DZ",
    "wof:name":"Chebla",
    "wof:placetype":"locality"
},
  "geometry": {"coordinates":[6.73758,34.97682],"type":"Point"}
}