{
  "type": "Feature",
  "properties": {
    "gn:admin1_code":"6.0",
    "gn:asciiname":"Oulad Aissa",
    "gn:country_code":"DZ",
    "gn:dem":836,
    "gn:feature_class":"P",
    "gn:feature_code":"PPL",
    "gn:name":"Oulad A\u00efssa",
    "gn:population":0,
    "gn:timezone":"Africa/Algiers",
    "iso:country":"DZ",
    "name:ara_x_preferred":[
        "\u0623\u0648\u0644\u0627\u062f \u0639\u064a\u0633\u0649"
    ],
    "name:cat_x_preferred":[
        "Ouled Aissa"
    ],
    "name:ita_x_preferred":[
        "Oulad Aissa"
    ],
    "wof:name":"Oulad Aissa",
    "wof:placetype":"locality"
},
  "geometry": {"coordinates":[3.54136,35.98264],"type":"Point"}
}