{
  "type": "Feature",
  "properties": {
    "gn:admin1_code":"6.0",
    "gn:asciiname":"Merabtine",
    "gn:country_code":"DZ",
    "gn:dem":646,
    "gn:feature_class":"P",
    "gn:feature_code":"PPL",
    "gn:name":"Merabtine",
    "gn:population":0,
    "gn:timezone":"Africa/Algiers",
    "iso:country":"DZ",
    "wof:name":"Merabtine",
    "wof:placetype":"locality"
},
  "geometry": {"coordinates":[3.28904,36.24509000000001],"type":"Point"}
}