{
  "type": "Feature",
  "properties": {
    "gn:admin1_code":"31.0",
    "gn:asciiname":"Bissy",
    "gn:country_code":"DZ",
    "gn:dem":331,
    "gn:feature_class":"P",
    "gn:feature_code":"PPL",
    "gn:name":"Bissy",
    "gn:population":0,
    "gn:timezone":"Africa/Algiers",
    "iso:country":"DZ",
    "wof:name":"Bissy",
    "wof:placetype":"locality"
},
  "geometry": {"coordinates":[7.01667,36.76667],"type":"Point"}
}