{
  "type": "Feature",
  "properties": {
    "gn:admin1_code":"33.0",
    "gn:asciiname":"Aouinet el Mora",
    "gn:country_code":"DZ",
    "gn:dem":785,
    "gn:feature_class":"P",
    "gn:feature_code":"PPL",
    "gn:name":"Aouinet el Mora",
    "gn:population":0,
    "gn:timezone":"Africa/Algiers",
    "iso:country":"DZ",
    "name:und_x_variant":[
        "Anouinet Mora",
        "Aouinet el Mora"
    ],
    "wof:name":"Aouinet el Mora",
    "wof:placetype":"locality"
},
  "geometry": {"coordinates":[7.88463,35.67957],"type":"Point"}
}