{
  "type": "Feature",
  "properties": {
    "gn:admin1_code":"51.0",
    "gn:asciiname":"Baiguia",
    "gn:country_code":"DZ",
    "gn:dem":485,
    "gn:feature_class":"P",
    "gn:feature_code":"PPL",
    "gn:name":"Ba\u00efguia",
    "gn:population":0,
    "gn:timezone":"Africa/Algiers",
    "iso:country":"DZ",
    "wof:name":"Baiguia",
    "wof:placetype":"locality"
},
  "geometry": {"coordinates":[0.93062,35.91903],"type":"Point"}
}