{
  "type": "Feature",
  "properties": {
    "gn:admin1_code":"30.0",
    "gn:asciiname":"Douar Ouled Ouis",
    "gn:country_code":"DZ",
    "gn:dem":606,
    "gn:feature_class":"P",
    "gn:feature_code":"PPL",
    "gn:name":"Douar Ouled Ouis",
    "gn:population":0,
    "gn:timezone":"Africa/Algiers",
    "iso:country":"DZ",
    "name:und_x_variant":[
        "Ouled Ou\u00efs",
        "Douar Ouled Ouis"
    ],
    "wof:name":"Douar Ouled Ouis",
    "wof:placetype":"locality"
},
  "geometry": {"coordinates":[-0.35091,35.27378],"type":"Point"}
}