{
  "type": "Feature",
  "properties": {
    "iso:country":"DZ",
    "name:ara_x_preferred":[
        "\u0628\u0631\u0628\u0627\u0634\u0629"
    ],
    "name:eng_x_preferred":[
        "Barbacha"
    ],
    "name:fas_x_preferred":[
        "\u0628\u0631\u0628\u0627\u0634\u0647"
    ],
    "name:fra_x_preferred":[
        "Barbacha"
    ],
    "name:ita_x_preferred":[
        "Barbacha"
    ],
    "name:kab_x_preferred":[
        "Iberbacen"
    ],
    "name:msa_x_preferred":[
        "Barbacha"
    ],
    "name:nld_x_preferred":[
        "Barbacha"
    ],
    "name:por_x_preferred":[
        "Barbacha"
    ],
    "name:ron_x_preferred":[
        "Barbacha"
    ],
    "name:swe_x_preferred":[
        "Barbacha"
    ],
    "name:unk_x_variant":[
        "Souk et Tl\u00e9ta"
    ],
    "name:vie_x_preferred":[
        "Berbacha"
    ],
    "qs:gn_country":"DZ",
    "qs:gn_fcode":"PPL",
    "qs:gn_pop":31983,
    "qs:name":"Souk et Tleta",
    "qs:name_adm0":"\u0627\u0644\u062c\u0632\u0627\u0626\u0631",
    "qs:name_adm1":"Bejaia",
    "qs:photos":0,
    "qs:photos_1k":0,
    "qs:photos_9k":0,
    "qs:photos_9r":0,
    "qs:photos_all":0,
    "qs:photos_sr":0,
    "qs:placetype":"Town",
    "qs:pop_sr":"7",
    "qs:woe_adm0":23424740,
    "wof:name":"Souk et Tleta",
    "wof:placetype":"locality",
    "wof:population":31983
},
  "geometry": {"coordinates":[4.96667,36.56667],"type":"Point"}
}