{
  "type": "Feature",
  "properties": {
    "gn:admin1_code":"26.0",
    "gn:asciiname":"Kariat Nourdine",
    "gn:country_code":"DZ",
    "gn:dem":748,
    "gn:feature_class":"P",
    "gn:feature_code":"PPL",
    "gn:name":"Kariat Nourdine",
    "gn:population":0,
    "gn:timezone":"Africa/Algiers",
    "iso:country":"DZ",
    "wof:name":"Kariat Nourdine",
    "wof:placetype":"locality"
},
  "geometry": {"coordinates":[0.21539,35.43951],"type":"Point"}
}