{
  "type": "Feature",
  "properties": {
    "gn:admin1_code":"14.0",
    "gn:asciiname":"Fliki",
    "gn:country_code":"DZ",
    "gn:dem":248,
    "gn:feature_class":"P",
    "gn:feature_code":"PPL",
    "gn:name":"Fliki",
    "gn:population":0,
    "gn:timezone":"Africa/Algiers",
    "iso:country":"DZ",
    "wof:name":"Fliki",
    "wof:placetype":"locality"
},
  "geometry": {"coordinates":[4.36722,36.70229000000001],"type":"Point"}
}