{
  "type": "Feature",
  "properties": {
    "gn:admin1_code":"51.0",
    "gn:asciiname":"Mrabtine",
    "gn:country_code":"DZ",
    "gn:dem":323,
    "gn:feature_class":"P",
    "gn:feature_code":"PPL",
    "gn:name":"Mrabtine",
    "gn:population":0,
    "gn:timezone":"Africa/Algiers",
    "iso:country":"DZ",
    "wof:name":"Mrabtine",
    "wof:placetype":"locality"
},
  "geometry": {"coordinates":[0.78259,35.80682],"type":"Point"}
}