{
  "type": "Feature",
  "properties": {
    "gn:admin1_code":"7.0",
    "gn:asciiname":"Douar Z'maaiche",
    "gn:country_code":"DZ",
    "gn:dem":106,
    "gn:feature_class":"P",
    "gn:feature_code":"PPL",
    "gn:name":"Douar Z\u2019maa\u00efche",
    "gn:population":0,
    "gn:timezone":"Africa/Algiers",
    "iso:country":"DZ",
    "wof:name":"Douar Z'maaiche",
    "wof:placetype":"locality"
},
  "geometry": {"coordinates":[0.4225,36.18],"type":"Point"}
}