{
  "type": "Feature",
  "properties": {
    "gn:admin1_code":"27.0",
    "gn:asciiname":"Bir el Keraa",
    "gn:country_code":"DZ",
    "gn:dem":399,
    "gn:feature_class":"P",
    "gn:feature_code":"PPL",
    "gn:name":"Bir el Keraa",
    "gn:population":0,
    "gn:timezone":"Africa/Algiers",
    "iso:country":"DZ",
    "wof:name":"Bir el Keraa",
    "wof:placetype":"locality"
},
  "geometry": {"coordinates":[4.64691,35.35262],"type":"Point"}
}