{
  "type": "Feature",
  "properties": {
    "gn:admin1_code":"15.0",
    "gn:asciiname":"Taffessera",
    "gn:country_code":"DZ",
    "gn:dem":788,
    "gn:feature_class":"P",
    "gn:feature_code":"PPL",
    "gn:name":"Taffessera",
    "gn:population":0,
    "gn:timezone":"Africa/Algiers",
    "iso:country":"DZ",
    "name:und_x_variant":[
        "Tafessera",
        "Taffessera"
    ],
    "wof:name":"Taffessera",
    "wof:placetype":"locality"
},
  "geometry": {"coordinates":[-1.44604,34.67978],"type":"Point"}
}