{
  "type": "Feature",
  "properties": {
    "gn:admin1_code":"26.0",
    "gn:asciiname":"Ferraguig",
    "gn:country_code":"DZ",
    "gn:dem":600,
    "gn:feature_class":"P",
    "gn:feature_code":"PPL",
    "gn:name":"Ferraguig",
    "gn:population":0,
    "gn:timezone":"Africa/Algiers",
    "iso:country":"DZ",
    "wof:name":"Ferraguig",
    "wof:placetype":"locality"
},
  "geometry": {"coordinates":[0.15556,35.53306],"type":"Point"}
}