{
  "type": "Feature",
  "properties": {
    "gn:admin1_code":"20.0",
    "gn:asciiname":"Abd el Krim",
    "gn:country_code":"DZ",
    "gn:dem":459,
    "gn:feature_class":"P",
    "gn:feature_code":"PPL",
    "gn:name":"Abd el Kr\u00eem",
    "gn:population":0,
    "gn:timezone":"Africa/Algiers",
    "iso:country":"DZ",
    "name:und_x_variant":[
        "Abd el Kerim",
        "Abd el Kr\u00eem"
    ],
    "wof:name":"Abd el Krim",
    "wof:placetype":"locality"
},
  "geometry": {"coordinates":[3.0356,36.37369],"type":"Point"}
}