{
  "type": "Feature",
  "properties": {
    "gn:admin1_code":"13.0",
    "gn:asciiname":"Douar Ouled Lakhdar",
    "gn:country_code":"DZ",
    "gn:dem":813,
    "gn:feature_class":"P",
    "gn:feature_code":"PPL",
    "gn:name":"Douar Ouled Lakhdar",
    "gn:population":0,
    "gn:timezone":"Africa/Algiers",
    "iso:country":"DZ",
    "wof:name":"Douar Ouled Lakhdar",
    "wof:placetype":"locality"
},
  "geometry": {"coordinates":[0.84193,35.11349000000001],"type":"Point"}
}