{
  "type": "Feature",
  "properties": {
    "gn:admin1_code":"35.0",
    "gn:asciiname":"Ouled Tifidh",
    "gn:country_code":"DZ",
    "gn:dem":477,
    "gn:feature_class":"P",
    "gn:feature_code":"PPL",
    "gn:name":"Ouled Tifidh",
    "gn:population":0,
    "gn:timezone":"Africa/Algiers",
    "iso:country":"DZ",
    "wof:name":"Ouled Tifidh",
    "wof:placetype":"locality"
},
  "geometry": {"coordinates":[1.62825,36.3295],"type":"Point"}
}