{
  "type": "Feature",
  "properties": {
    "gn:admin1_code":"41.0",
    "gn:asciiname":"Douar Blablia",
    "gn:country_code":"DZ",
    "gn:dem":216,
    "gn:feature_class":"P",
    "gn:feature_code":"PPL",
    "gn:name":"Douar Blablia",
    "gn:population":0,
    "gn:timezone":"Africa/Algiers",
    "iso:country":"DZ",
    "wof:name":"Douar Blablia",
    "wof:placetype":"locality"
},
  "geometry": {"coordinates":[1.49417,36.15957],"type":"Point"}
}