{
  "type": "Feature",
  "properties": {
    "gn:admin1_code":"26.0",
    "gn:asciiname":"Douar Lahouaora",
    "gn:country_code":"DZ",
    "gn:dem":704,
    "gn:feature_class":"P",
    "gn:feature_code":"PPL",
    "gn:name":"Douar Lahouaora",
    "gn:population":0,
    "gn:timezone":"Africa/Algiers",
    "iso:country":"DZ",
    "wof:name":"Douar Lahouaora",
    "wof:placetype":"locality"
},
  "geometry": {"coordinates":[0.37011,35.13806],"type":"Point"}
}