{
  "type": "Feature",
  "properties": {
    "gn:admin1_code":"41.0",
    "gn:asciiname":"Douar Harbil",
    "gn:country_code":"DZ",
    "gn:dem":67,
    "gn:feature_class":"P",
    "gn:feature_code":"PPL",
    "gn:name":"Douar Harbil",
    "gn:population":0,
    "gn:timezone":"Africa/Algiers",
    "iso:country":"DZ",
    "wof:name":"Douar Harbil",
    "wof:placetype":"locality"
},
  "geometry": {"coordinates":[1.75296,36.53952],"type":"Point"}
}