{
  "type": "Feature",
  "properties": {
    "gn:admin1_code":"51.0",
    "gn:asciiname":"Chaita Oumeur",
    "gn:country_code":"DZ",
    "gn:dem":175,
    "gn:feature_class":"P",
    "gn:feature_code":"PPL",
    "gn:name":"Cha\u00efta Oumeur",
    "gn:population":0,
    "gn:timezone":"Africa/Algiers",
    "iso:country":"DZ",
    "wof:name":"Chaita Oumeur",
    "wof:placetype":"locality"
},
  "geometry": {"coordinates":[0.47308,35.654],"type":"Point"}
}