{
  "type": "Feature",
  "properties": {
    "gn:admin1_code":"35.0",
    "gn:asciiname":"Ferhaiha",
    "gn:country_code":"DZ",
    "gn:dem":281,
    "gn:feature_class":"P",
    "gn:feature_code":"PPL",
    "gn:name":"Ferha\u00efha",
    "gn:population":0,
    "gn:timezone":"Africa/Algiers",
    "iso:country":"DZ",
    "name:und_x_variant":[
        "Fegha\u00efha",
        "Ferha\u00efha"
    ],
    "wof:name":"Ferhaiha",
    "wof:placetype":"locality"
},
  "geometry": {"coordinates":[2.02088,36.25731],"type":"Point"}
}