{
  "type": "Feature",
  "properties": {
    "gn:admin1_code":"41.0",
    "gn:asciiname":"Ech Cheraga",
    "gn:country_code":"DZ",
    "gn:dem":252,
    "gn:feature_class":"P",
    "gn:feature_code":"PPL",
    "gn:name":"Ech Cheraga",
    "gn:population":0,
    "gn:timezone":"Africa/Algiers",
    "iso:country":"DZ",
    "name:und_x_variant":[
        "Mechtat ech Cheraga",
        "Ech Cheraga"
    ],
    "wof:name":"Ech Cheraga",
    "wof:placetype":"locality"
},
  "geometry": {"coordinates":[1.52499,36.25232000000001],"type":"Point"}
}