{
  "type": "Feature",
  "properties": {
    "gn:admin1_code":"48.0",
    "gn:asciiname":"Rhebala",
    "gn:country_code":"DZ",
    "gn:dem":517,
    "gn:feature_class":"P",
    "gn:feature_code":"PPL",
    "gn:name":"Rhebala",
    "gn:population":0,
    "gn:timezone":"Africa/Algiers",
    "iso:country":"DZ",
    "wof:name":"Rhebala",
    "wof:placetype":"locality"
},
  "geometry": {"coordinates":[6.13441,36.52511],"type":"Point"}
}