{
  "type": "Feature",
  "properties": {
    "gn:admin1_code":"33.0",
    "gn:asciiname":"Youkous",
    "gn:country_code":"DZ",
    "gn:dem":1018,
    "gn:feature_class":"P",
    "gn:feature_code":"PPL",
    "gn:name":"Youkous",
    "gn:population":0,
    "gn:timezone":"Africa/Algiers",
    "iso:country":"DZ",
    "wof:name":"Youkous",
    "wof:placetype":"locality"
},
  "geometry": {"coordinates":[7.96789,35.41465],"type":"Point"}
}