{
  "type": "Feature",
  "properties": {
    "gn:admin1_code":"51.0",
    "gn:asciiname":"Cite Aatya",
    "gn:country_code":"DZ",
    "gn:dem":59,
    "gn:feature_class":"P",
    "gn:feature_code":"PPL",
    "gn:name":"Cit\u00e9 Aatya",
    "gn:population":0,
    "gn:timezone":"Africa/Algiers",
    "iso:country":"DZ",
    "wof:name":"Cite Aatya",
    "wof:placetype":"locality"
},
  "geometry": {"coordinates":[0.5641,35.75646],"type":"Point"}
}