{
  "type": "Feature",
  "properties": {
    "gn:admin1_code":"26.0",
    "gn:asciiname":"Dar Ould el Hadj Taieb",
    "gn:country_code":"DZ",
    "gn:dem":528,
    "gn:feature_class":"P",
    "gn:feature_code":"PPL",
    "gn:name":"Dar Ould el Hadj Ta\u00efeb",
    "gn:population":0,
    "gn:timezone":"Africa/Algiers",
    "iso:country":"DZ",
    "wof:name":"Dar Ould el Hadj Taieb",
    "wof:placetype":"locality"
},
  "geometry": {"coordinates":[0.28333,35.59667],"type":"Point"}
}