{
  "type": "Feature",
  "properties": {
    "gn:admin1_code":"6.0",
    "gn:asciiname":"El Kheneg",
    "gn:country_code":"DZ",
    "gn:dem":816,
    "gn:feature_class":"P",
    "gn:feature_code":"PPL",
    "gn:name":"El Kheneg",
    "gn:population":0,
    "gn:timezone":"Africa/Algiers",
    "iso:country":"DZ",
    "name:und_x_variant":[
        "Kheneg"
    ],
    "wof:name":"El Kheneg",
    "wof:placetype":"locality"
},
  "geometry": {"coordinates":[3.3138,36.12361],"type":"Point"}
}