{
  "type": "Feature",
  "properties": {
    "gn:admin1_code":"48.0",
    "gn:asciiname":"Baba Ali",
    "gn:country_code":"DZ",
    "gn:dem":889,
    "gn:feature_class":"P",
    "gn:feature_code":"PPL",
    "gn:name":"Baba Ali",
    "gn:population":0,
    "gn:timezone":"Africa/Algiers",
    "iso:country":"DZ",
    "name:ara_x_preferred":[
        "\u0628\u0627\u0628\u0627 \u0639\u0644\u064a"
    ],
    "name:azb_x_preferred":[
        "\u0628\u0627\u0628\u0627 \u0639\u0644\u06cc"
    ],
    "name:fas_x_preferred":[
        "\u0628\u0627\u0628\u0627 \u0639\u0644\u06cc"
    ],
    "name:por_x_preferred":[
        "Baba Ali"
    ],
    "name:spa_x_preferred":[
        "Baba Ali"
    ],
    "name:sqi_x_preferred":[
        "Baba Ali"
    ],
    "name:und_x_variant":[
        "Douar Baba Ali"
    ],
    "wof:name":"Baba Ali",
    "wof:placetype":"locality"
},
  "geometry": {"coordinates":[6.34622,36.36498],"type":"Point"}
}