{
  "type": "Feature",
  "properties": {
    "gn:admin1_code":"6.0",
    "gn:asciiname":"El Guelali",
    "gn:cc2":"DZ",
    "gn:country_code":"DZ",
    "gn:dem":661,
    "gn:feature_class":"P",
    "gn:feature_code":"PPL",
    "gn:name":"El Guelali",
    "gn:population":0,
    "gn:timezone":"Africa/Algiers",
    "iso:country":"DZ",
    "wof:name":"El Guelali",
    "wof:placetype":"locality"
},
  "geometry": {"coordinates":[3.65,35.88333],"type":"Point"}
}