{
  "type": "Feature",
  "properties": {
    "gn:admin1_code":"15.0",
    "gn:asciiname":"Oulad Hamamou",
    "gn:country_code":"DZ",
    "gn:dem":262,
    "gn:feature_class":"P",
    "gn:feature_code":"PPL",
    "gn:name":"Oulad Hamamou",
    "gn:population":0,
    "gn:timezone":"Africa/Algiers",
    "iso:country":"DZ",
    "name:und_x_variant":[
        "Douar Oulad Amamou",
        "Oulad Hamamou"
    ],
    "wof:name":"Oulad Hamamou",
    "wof:placetype":"locality"
},
  "geometry": {"coordinates":[-1.49536,34.97368],"type":"Point"}
}