{
  "type": "Feature",
  "properties": {
    "gn:gn_country":"DZ",
    "gn:gn_fcode":"PPL",
    "gn:gn_pop":41091,
    "gn:population":41091,
    "iso:country":"DZ",
    "name:ara_x_preferred":[
        "\u062a\u0628\u0633\u0628\u0633\u062a"
    ],
    "name:eng_x_preferred":[
        "Tebesbest"
    ],
    "name:fas_x_preferred":[
        "\u062a\u0628\u0633\u0628\u0633\u062a"
    ],
    "name:fra_x_preferred":[
        "Tebesbest"
    ],
    "name:ita_x_preferred":[
        "Tebesbest"
    ],
    "name:msa_x_preferred":[
        "Tebesbest"
    ],
    "name:nan_x_preferred":[
        "Tebesbest"
    ],
    "name:nld_x_preferred":[
        "Tebesbest"
    ],
    "name:por_x_preferred":[
        "Tebesbest"
    ],
    "name:ron_x_preferred":[
        "Tebesbest"
    ],
    "name:spa_x_preferred":[
        "Tebesbest"
    ],
    "name:swe_x_preferred":[
        "Tebesbest"
    ],
    "name:vie_x_preferred":[
        "Tebesbest"
    ],
    "qs_pg:aaroncc":"DZ",
    "qs_pg:gn_country":"DZ",
    "qs_pg:gn_fcode":"PPL",
    "qs_pg:gn_pop":41091,
    "qs_pg:name":"Tebesbest",
    "qs_pg:photos_9r":0,
    "qs_pg:photos_sr":0,
    "qs_pg:pop_sr":7,
    "qs_pg:qs_pg_placetype":"locality",
    "wof:name":"Tebesbest",
    "wof:placetype":"locality",
    "wof:population":41091
},
  "geometry": {"coordinates":[6.08333,33.11667],"type":"Point"}
}