{
  "type": "Feature",
  "properties": {
    "gn:admin1_code":"21.0",
    "gn:asciiname":"Khabbouzia",
    "gn:country_code":"DZ",
    "gn:dem":696,
    "gn:feature_class":"P",
    "gn:feature_code":"PPL",
    "gn:name":"Khabbouzia",
    "gn:population":0,
    "gn:timezone":"Africa/Algiers",
    "iso:country":"DZ",
    "name:und_x_variant":[
        "Hoche",
        "Krabousia",
        "Khabbouzia",
        "El Khabouzia"
    ],
    "wof:name":"Khabbouzia",
    "wof:placetype":"locality"
},
  "geometry": {"coordinates":[3.60047,36.31585],"type":"Point"}
}