{
  "type": "Feature",
  "properties": {
    "gn:admin1_code":"34.0",
    "gn:asciiname":"Oufrane",
    "gn:country_code":"DZ",
    "gn:dem":291,
    "gn:feature_class":"P",
    "gn:feature_code":"PPL",
    "gn:name":"Oufrane",
    "gn:population":0,
    "gn:timezone":"Africa/Algiers",
    "iso:country":"DZ",
    "wof:name":"Oufrane",
    "wof:placetype":"locality"
},
  "geometry": {"coordinates":[0.18428,28.54009000000001],"type":"Point"}
}