{
  "type": "Feature",
  "properties": {
    "gn:admin1_code":"40.0",
    "gn:asciiname":"Ouled Ben Mechk",
    "gn:country_code":"DZ",
    "gn:dem":351,
    "gn:feature_class":"P",
    "gn:feature_code":"PPL",
    "gn:name":"Ouled Ben Mechk",
    "gn:population":0,
    "gn:timezone":"Africa/Algiers",
    "iso:country":"DZ",
    "wof:name":"Ouled Ben Mechk",
    "wof:placetype":"locality"
},
  "geometry": {"coordinates":[3.61552,36.62239],"type":"Point"}
}