{
  "type": "Feature",
  "properties": {
    "gn:admin1_code":"7.0",
    "gn:asciiname":"Hadjadj Plage",
    "gn:country_code":"DZ",
    "gn:dem":11,
    "gn:feature_class":"P",
    "gn:feature_code":"PPL",
    "gn:name":"Hadjadj Plage",
    "gn:population":0,
    "gn:timezone":"Africa/Algiers",
    "iso:country":"DZ",
    "name:und_x_variant":[
        "Plage de Hadjadj",
        "Bosquet-Plage",
        "Hadjadj Plage"
    ],
    "wof:name":"Hadjadj Plage",
    "wof:placetype":"locality"
},
  "geometry": {"coordinates":[0.30338,36.1466],"type":"Point"}
}