{
  "type": "Feature",
  "properties": {
    "gn:admin1_code":"3.0",
    "gn:asciiname":"Mechtat Tiguernizine",
    "gn:country_code":"DZ",
    "gn:dem":1244,
    "gn:feature_class":"P",
    "gn:feature_code":"PPL",
    "gn:name":"Mechtat Tiguernizine",
    "gn:population":0,
    "gn:timezone":"Africa/Algiers",
    "iso:country":"DZ",
    "name:und_x_variant":[
        "Mechtet Tigarniz\u00eene",
        "Mechtat Tiguernizine"
    ],
    "wof:name":"Mechtat Tiguernizine",
    "wof:placetype":"locality"
},
  "geometry": {"coordinates":[6.05525,35.62070999999999],"type":"Point"}
}