{
  "type": "Feature",
  "properties": {
    "gn:admin1_code":"3.0",
    "gn:asciiname":"Ouled Mbarek",
    "gn:country_code":"DZ",
    "gn:dem":419,
    "gn:feature_class":"P",
    "gn:feature_code":"PPL",
    "gn:name":"Ouled Mbarek",
    "gn:population":0,
    "gn:timezone":"Africa/Algiers",
    "iso:country":"DZ",
    "wof:name":"Ouled Mbarek",
    "wof:placetype":"locality"
},
  "geometry": {"coordinates":[4.94381,35.51298],"type":"Point"}
}