{
  "type": "Feature",
  "properties": {
    "gn:admin1_code":"31.0",
    "gn:asciiname":"Haouch Hammadi Krouma",
    "gn:country_code":"DZ",
    "gn:dem":12,
    "gn:feature_class":"P",
    "gn:feature_code":"PPL",
    "gn:name":"Haouch Hamm\u00e2di Kro\u00fbma",
    "gn:population":0,
    "gn:timezone":"Africa/Algiers",
    "iso:country":"DZ",
    "name:und_x_variant":[
        "Ferme Barot",
        "Haouch Hamm\u00e2di Kro\u00fbma"
    ],
    "wof:name":"Haouch Hammadi Krouma",
    "wof:placetype":"locality"
},
  "geometry": {"coordinates":[6.96406,36.85971],"type":"Point"}
}