{
  "type": "Feature",
  "properties": {
    "iso:country":"DZ",
    "name:unk_x_variant":[
        "Larbi Ben M\u2019Hidi"
    ],
    "qs:gn_country":"DZ",
    "qs:gn_fcode":"PPLX",
    "qs:gn_pop":0,
    "qs:name":"Ayet el 'Arbi Ben Lemhidi",
    "qs:name_adm0":"\u0627\u0644\u062c\u0632\u0627\u0626\u0631",
    "qs:name_adm1":"\u0648\u0644\u0627\u064a\u0629 \u0633\u064a\u062f\u064a \u0628\u0644\u0639\u0628\u0627\u0633",
    "qs:photos":36,
    "qs:photos_1k":7,
    "qs:photos_9k":1,
    "qs:photos_9r":2,
    "qs:photos_all":36,
    "qs:photos_sr":2,
    "qs:placetype":"Suburb",
    "qs:pop_sr":"0",
    "qs:woe_adm0":23424740,
    "wof:name":"Ayet el 'Arbi Ben Lemhidi",
    "wof:placetype":"neighbourhood"
},
  "geometry": {"coordinates":[-0.64667,35.20393],"type":"Point"}
}