{
  "type": "Feature",
  "properties": {
    "gn:admin1_code":"55.0",
    "gn:asciiname":"Timerdjanine",
    "gn:country_code":"DZ",
    "gn:dem":511,
    "gn:feature_class":"P",
    "gn:feature_code":"PPL",
    "gn:name":"Timerdjanine",
    "gn:population":0,
    "gn:timezone":"Africa/Algiers",
    "iso:country":"DZ",
    "wof:name":"Timerdjanine",
    "wof:placetype":"locality"
},
  "geometry": {"coordinates":[1.72805,36.44781],"type":"Point"}
}