{
  "type": "Feature",
  "properties": {
    "gn:admin1_code":"44.0",
    "gn:asciiname":"Mechtat Loudei",
    "gn:country_code":"DZ",
    "gn:dem":438,
    "gn:feature_class":"P",
    "gn:feature_code":"PPL",
    "gn:name":"Mechtat Loudei",
    "gn:population":0,
    "gn:timezone":"Africa/Algiers",
    "iso:country":"DZ",
    "wof:name":"Mechtat Loudei",
    "wof:placetype":"locality"
},
  "geometry": {"coordinates":[8.33389,36.61167],"type":"Point"}
}