{
  "type": "Feature",
  "properties": {
    "gn:admin1_code":"3.0",
    "gn:asciiname":"Trharhet",
    "gn:country_code":"DZ",
    "gn:dem":1574,
    "gn:feature_class":"P",
    "gn:feature_code":"PPL",
    "gn:name":"Trharhet",
    "gn:population":0,
    "gn:timezone":"Africa/Algiers",
    "iso:country":"DZ",
    "wof:name":"Trharhet",
    "wof:placetype":"locality"
},
  "geometry": {"coordinates":[6.35128,35.09316],"type":"Point"}
}