{
  "type": "Feature",
  "properties": {
    "gn:admin1_code":"12.0",
    "gn:asciiname":"Mechta 'Ain el Bey",
    "gn:country_code":"DZ",
    "gn:dem":994,
    "gn:feature_class":"P",
    "gn:feature_code":"PPL",
    "gn:name":"Mechta \u2019A\u00efn el Bey",
    "gn:population":0,
    "gn:timezone":"Africa/Algiers",
    "iso:country":"DZ",
    "name:und_x_variant":[
        "\u2019A\u00efn el Bey",
        "Mechtat A\u00efne el Bey",
        "Mechta \u2019A\u00efn el Bey"
    ],
    "wof:name":"Mechta 'Ain el Bey",
    "wof:placetype":"locality"
},
  "geometry": {"coordinates":[5.58413,36.09391],"type":"Point"}
}