{
  "type": "Feature",
  "properties": {
    "gn:admin1_code":"15.0",
    "gn:asciiname":"El Hacaiba",
    "gn:country_code":"DZ",
    "gn:dem":935,
    "gn:feature_class":"P",
    "gn:feature_code":"PPL",
    "gn:name":"El Haca\u00efba",
    "gn:population":0,
    "gn:timezone":"Africa/Algiers",
    "iso:country":"DZ",
    "name:ara_x_preferred":[
        "\u0627\u0644\u062d\u0635\u064a\u0628\u0629"
    ],
    "name:fra_x_preferred":[
        "El Ha\u00e7aiba"
    ],
    "name:ita_x_preferred":[
        "El Ha\u00e7aiba"
    ],
    "name:kab_x_preferred":[
        "L\u1e25asayba"
    ],
    "name:msa_x_preferred":[
        "El Hacaiba"
    ],
    "name:pol_x_preferred":[
        "Al-Hasajba"
    ],
    "name:por_x_preferred":[
        "El Hacaiba"
    ],
    "name:ron_x_preferred":[
        "El Ha\u00e7aiba"
    ],
    "name:spa_x_preferred":[
        "El Ha\u00e7aiba"
    ],
    "name:und_x_variant":[
        "Magenta",
        "El Assa\u00efba",
        "El Haca\u00efba"
    ],
    "name:vie_x_preferred":[
        "El Hacaiba"
    ],
    "wof:name":"El Hacaiba",
    "wof:placetype":"locality"
},
  "geometry": {"coordinates":[-0.76046,34.70083],"type":"Point"}
}