{
  "type": "Feature",
  "properties": {
    "gn:admin1_code":"15.0",
    "gn:asciiname":"El Hacaiba",
    "gn:country_code":"DZ",
    "gn:dem":935,
    "gn:feature_class":"P",
    "gn:feature_code":"PPL",
    "gn:name":"El Haca\u00efba",
    "gn:population":0,
    "gn:timezone":"Africa/Algiers",
    "iso:country":"DZ",
    "name:und_x_variant":[
        "Magenta",
        "El Assa\u00efba",
        "El Haca\u00efba"
    ],
    "wof:name":"El Hacaiba",
    "wof:placetype":"locality"
},
  "geometry": {"coordinates":[-0.76046,34.70083],"type":"Point"}
}