{
  "type": "Feature",
  "properties": {
    "gn:admin1_code":"6.0",
    "gn:asciiname":"Oulad Hammadi",
    "gn:country_code":"DZ",
    "gn:dem":855,
    "gn:feature_class":"P",
    "gn:feature_code":"PPL",
    "gn:name":"Oulad Hammadi",
    "gn:population":0,
    "gn:timezone":"Africa/Algiers",
    "iso:country":"DZ",
    "wof:name":"Oulad Hammadi",
    "wof:placetype":"locality"
},
  "geometry": {"coordinates":[2.90333,36.31972],"type":"Point"}
}