{
  "type": "Feature",
  "properties": {
    "gn:admin1_code":"34.0",
    "gn:asciiname":"Badriane",
    "gn:country_code":"DZ",
    "gn:dem":281,
    "gn:feature_class":"P",
    "gn:feature_code":"PPL",
    "gn:name":"Badriane",
    "gn:population":0,
    "gn:timezone":"Africa/Algiers",
    "iso:country":"DZ",
    "wof:name":"Badriane",
    "wof:placetype":"locality"
},
  "geometry": {"coordinates":[0.34044,29.33824000000001],"type":"Point"}
}