{
  "type": "Feature",
  "properties": {
    "gn:admin1_code":"19.0",
    "gn:asciiname":"Menaa",
    "gn:country_code":"DZ",
    "gn:dem":924,
    "gn:feature_class":"P",
    "gn:feature_code":"PPL",
    "gn:name":"Menaa",
    "gn:population":0,
    "gn:timezone":"Africa/Algiers",
    "iso:country":"DZ",
    "name:ara_x_preferred":[
        "\u0645\u0646\u0639\u0629"
    ],
    "name:azb_x_preferred":[
        "\u0645\u0646\u0639\u0647"
    ],
    "name:eng_x_preferred":[
        "Mena\u00e2"
    ],
    "name:fas_x_preferred":[
        "\u0645\u0646\u0639\u0647"
    ],
    "name:fra_x_preferred":[
        "Menaa"
    ],
    "name:ita_x_preferred":[
        "Mena\u00e2"
    ],
    "name:msa_x_preferred":[
        "Menaa"
    ],
    "name:por_x_preferred":[
        "Mena\u00e2"
    ],
    "name:ron_x_preferred":[
        "Menaa"
    ],
    "name:vie_x_preferred":[
        "Mena\u00e2"
    ],
    "wof:name":"Menaa",
    "wof:placetype":"locality"
},
  "geometry": {"coordinates":[6.00422,35.17769000000001],"type":"Point"}
}