{
  "type": "Feature",
  "properties": {
    "gn:admin1_code":"6.0",
    "gn:asciiname":"El Guenadzia",
    "gn:country_code":"DZ",
    "gn:dem":965,
    "gn:feature_class":"P",
    "gn:feature_code":"PPL",
    "gn:name":"El Guenadzia",
    "gn:population":0,
    "gn:timezone":"Africa/Algiers",
    "iso:country":"DZ",
    "wof:name":"El Guenadzia",
    "wof:placetype":"locality"
},
  "geometry": {"coordinates":[3.42065,36.04987],"type":"Point"}
}