{
  "type": "Feature",
  "properties": {
    "gn:admin1_code":"19.0",
    "gn:asciiname":"El Alia",
    "gn:country_code":"DZ",
    "gn:dem":133,
    "gn:feature_class":"P",
    "gn:feature_code":"PPL",
    "gn:name":"El Alia",
    "gn:population":0,
    "gn:timezone":"Africa/Algiers",
    "iso:country":"DZ",
    "name:ara_x_preferred":[
        "\u0627\u0644\u0639\u0627\u0644\u064a\u0629"
    ],
    "name:cat_x_preferred":[
        "El Alia"
    ],
    "name:ceb_x_preferred":[
        "Al \u2018\u0100liyah"
    ],
    "name:ell_x_preferred":[
        "\u0395\u03bb \u0391\u03bb\u03af\u03b1"
    ],
    "name:fra_x_preferred":[
        "El Alia"
    ],
    "name:ukr_x_preferred":[
        "\u0415\u043b\u044c-\u0410\u043b\u044c\u044f"
    ],
    "wof:name":"El Alia",
    "wof:placetype":"locality"
},
  "geometry": {"coordinates":[5.73962,34.868],"type":"Point"}
}