{
  "type": "Feature",
  "properties": {
    "gn:admin1_code":"19.0",
    "gn:asciiname":"El Alia",
    "gn:country_code":"DZ",
    "gn:dem":133,
    "gn:feature_class":"P",
    "gn:feature_code":"PPL",
    "gn:name":"El Alia",
    "gn:population":0,
    "gn:timezone":"Africa/Algiers",
    "iso:country":"DZ",
    "wof:name":"El Alia",
    "wof:placetype":"locality"
},
  "geometry": {"coordinates":[5.73962,34.868],"type":"Point"}
}