{
  "type": "Feature",
  "properties": {
    "gn:admin1_code":"26.0",
    "gn:asciiname":"Douar Ouled el Mahi",
    "gn:country_code":"DZ",
    "gn:dem":474,
    "gn:feature_class":"P",
    "gn:feature_code":"PPL",
    "gn:name":"Douar Ouled el Mahi",
    "gn:population":0,
    "gn:timezone":"Africa/Algiers",
    "iso:country":"DZ",
    "wof:name":"Douar Ouled el Mahi",
    "wof:placetype":"locality"
},
  "geometry": {"coordinates":[0.16376,35.2894],"type":"Point"}
}