{
  "type": "Feature",
  "properties": {
    "gn:admin1_code":"14.0",
    "gn:asciiname":"Azerou Kellat",
    "gn:country_code":"DZ",
    "gn:dem":763,
    "gn:feature_class":"P",
    "gn:feature_code":"PPL",
    "gn:name":"Azerou Kellat",
    "gn:population":0,
    "gn:timezone":"Africa/Algiers",
    "iso:country":"DZ",
    "wof:name":"Azerou Kellat",
    "wof:placetype":"locality"
},
  "geometry": {"coordinates":[4.28604,36.5873],"type":"Point"}
}