{
  "type": "Feature",
  "properties": {
    "gn:country":"DZ",
    "gn:fcode":"PPL",
    "gn:pop":22819,
    "iso:country":"DZ",
    "name:ara_x_preferred":[
        "\u0648\u0627\u062f\u064a \u0627\u0644\u0623\u0628\u0637\u0627\u0644"
    ],
    "name:azb_x_preferred":[
        "\u0648\u0627\u062f\u06cc \u0627\u0628\u0637\u0627\u0644"
    ],
    "name:ceb_x_preferred":[
        "Oued el Abtal"
    ],
    "name:eng_x_preferred":[
        "Oued El Abtal"
    ],
    "name:fas_x_preferred":[
        "\u0648\u0627\u062f\u06cc \u0627\u0628\u0637\u0627\u0644"
    ],
    "name:fra_x_preferred":[
        "Oued El Abtal"
    ],
    "name:ita_x_preferred":[
        "Oued El Abtal"
    ],
    "name:kab_x_preferred":[
        "Asif Lab\u1e6dal"
    ],
    "name:msa_x_preferred":[
        "Oued El Abtal"
    ],
    "name:nan_x_preferred":[
        "Oued El Abtal"
    ],
    "name:nld_x_preferred":[
        "Oued El Abtal"
    ],
    "name:por_x_preferred":[
        "Oued El Abtal"
    ],
    "name:ron_x_preferred":[
        "Oued El Abtal"
    ],
    "name:rus_x_preferred":[
        "\u0422\u043e\u0440\u043a\u0438-\u043b\u0435-\u0414\u044e\u043a"
    ],
    "name:spa_x_preferred":[
        "Oued El Abtal"
    ],
    "name:swe_x_preferred":[
        "Oued el Abtal"
    ],
    "name:unk_x_variant":[
        "Uz\u00e8s-le-Due"
    ],
    "name:vie_x_preferred":[
        "Oued El Abtal"
    ],
    "qs:name":"Oued el Abtal",
    "qs:photos_9r":0,
    "qs:photos_sr":0,
    "qs:pop_sr":"7",
    "wd:wordcount":44,
    "wof:name":"Oued el Abtal",
    "wof:placetype":"locality",
    "wof:population":22819
},
  "geometry": {"coordinates":[0.68778,35.45595],"type":"Point"}
}