{
  "type": "Feature",
  "properties": {
    "gn:admin1_code":"41.0",
    "gn:asciiname":"Zouatnia",
    "gn:country_code":"DZ",
    "gn:dem":280,
    "gn:feature_class":"P",
    "gn:feature_code":"PPL",
    "gn:name":"Zouatnia",
    "gn:population":0,
    "gn:timezone":"Africa/Algiers",
    "iso:country":"DZ",
    "wof:name":"Zouatnia",
    "wof:placetype":"locality"
},
  "geometry": {"coordinates":[1.42885,36.13739],"type":"Point"}
}