{
  "type": "Feature",
  "properties": {
    "gn:admin1_code":"3.0",
    "gn:asciiname":"Taachount",
    "gn:country_code":"DZ",
    "gn:dem":1097,
    "gn:feature_class":"P",
    "gn:feature_code":"PPL",
    "gn:name":"Taachount",
    "gn:population":0,
    "gn:timezone":"Africa/Algiers",
    "iso:country":"DZ",
    "wof:name":"Taachount",
    "wof:placetype":"locality"
},
  "geometry": {"coordinates":[6.27942,35.20271],"type":"Point"}
}