{
  "type": "Feature",
  "properties": {
    "gn:admin1_code":"13.0",
    "gn:asciiname":"Douar Touaoucha",
    "gn:country_code":"DZ",
    "gn:dem":595,
    "gn:feature_class":"P",
    "gn:feature_code":"PPL",
    "gn:name":"Douar Touaoucha",
    "gn:population":0,
    "gn:timezone":"Africa/Algiers",
    "iso:country":"DZ",
    "wof:name":"Douar Touaoucha",
    "wof:placetype":"locality"
},
  "geometry": {"coordinates":[0.97527,35.37418],"type":"Point"}
}