{
  "type": "Feature",
  "properties": {
    "gn:admin1_code":"44.0",
    "gn:asciiname":"El Tarf",
    "gn:country_code":"DZ",
    "gn:dem":24,
    "gn:feature_class":"P",
    "gn:feature_code":"PPLA",
    "gn:name":"El Tarf",
    "gn:population":20300,
    "gn:timezone":"Africa/Algiers",
    "iso:country":"DZ",
    "name:ara_x_preferred":[
        "\u0627\u0644\u0637\u0627\u0631\u0641"
    ],
    "name:azb_x_preferred":[
        "\u0637\u0627\u0631\u0641"
    ],
    "name:ceb_x_preferred":[
        "El Tarf"
    ],
    "name:deu_x_preferred":[
        "El Taref"
    ],
    "name:fas_x_preferred":[
        "\u0637\u0627\u0631\u0641"
    ],
    "name:fra_x_preferred":[
        "El Tarf"
    ],
    "name:hun_x_preferred":[
        "El Tarf"
    ],
    "name:ita_x_preferred":[
        "El Tarf"
    ],
    "name:kor_x_preferred":[
        "\uc5d8\ud0c0\ub974\ud504"
    ],
    "name:msa_x_preferred":[
        "El Taref"
    ],
    "name:nld_x_preferred":[
        "El Tarf"
    ],
    "name:pol_x_preferred":[
        "At-Tarif"
    ],
    "name:por_x_preferred":[
        "El Tarf"
    ],
    "name:ron_x_preferred":[
        "El Tarf"
    ],
    "name:rus_x_preferred":[
        "\u042d\u043b\u044c-\u0422\u0430\u0440\u0444"
    ],
    "name:swe_x_preferred":[
        "El Tarf"
    ],
    "name:ukr_x_preferred":[
        "\u0410\u0442-\u0422\u0430\u0440\u0444"
    ],
    "name:und_x_variant":[
        "Le Tarf"
    ],
    "name:urd_x_preferred":[
        "\u0627\u0644\u0637\u0627\u0631\u0641"
    ],
    "name:vie_x_preferred":[
        "El Tarf"
    ],
    "name:war_x_preferred":[
        "El Tarf"
    ],
    "name:zho_x_preferred":[
        "\u5854\u91cc\u592b"
    ],
    "wof:name":"El Tarf",
    "wof:placetype":"locality",
    "wof:population":20300
},
  "geometry": {"coordinates":[8.31377,36.7672],"type":"Point"}
}