{
  "type": "Feature",
  "properties": {
    "gn:admin1_code":"44.0",
    "gn:asciiname":"El Tarf",
    "gn:country_code":"DZ",
    "gn:dem":24,
    "gn:feature_class":"P",
    "gn:feature_code":"PPLA",
    "gn:name":"El Tarf",
    "gn:population":20300,
    "gn:timezone":"Africa/Algiers",
    "iso:country":"DZ",
    "name:ara_x_preferred":[
        "\u0627\u0644\u0637\u0627\u0631\u0641"
    ],
    "name:und_x_variant":[
        "Le Tarf",
        "El Tarf"
    ],
    "wof:name":"El Tarf",
    "wof:placetype":"locality",
    "wof:population":20300
},
  "geometry": {"coordinates":[8.31377,36.7672],"type":"Point"}
}