{
  "type": "Feature",
  "properties": {
    "gn:admin1_code":"6.0",
    "gn:asciiname":"Douar Zerarka",
    "gn:country_code":"DZ",
    "gn:dem":870,
    "gn:feature_class":"P",
    "gn:feature_code":"PPL",
    "gn:name":"Douar Zerarka",
    "gn:population":0,
    "gn:timezone":"Africa/Algiers",
    "iso:country":"DZ",
    "wof:name":"Douar Zerarka",
    "wof:placetype":"locality"
},
  "geometry": {"coordinates":[2.94818,36.15828],"type":"Point"}
}