{
  "type": "Feature",
  "properties": {
    "gn:admin1_code":"3.0",
    "gn:asciiname":"Mechta Feltane",
    "gn:country_code":"DZ",
    "gn:dem":818,
    "gn:feature_class":"P",
    "gn:feature_code":"PPL",
    "gn:name":"Mechta Feltane",
    "gn:population":0,
    "gn:timezone":"Africa/Algiers",
    "iso:country":"DZ",
    "wof:name":"Mechta Feltane",
    "wof:placetype":"locality"
},
  "geometry": {"coordinates":[6.14458,35.79511],"type":"Point"}
}