{
  "type": "Feature",
  "properties": {
    "iso:country":"DZ",
    "name:ara_x_preferred":[
        "\u0627\u0644\u0628\u0633\u0628\u0627\u0633"
    ],
    "name:ceb_x_preferred":[
        "Besbes"
    ],
    "name:deu_x_preferred":[
        "Besbes"
    ],
    "name:eng_x_preferred":[
        "Besbes"
    ],
    "name:fra_x_preferred":[
        "Besbes"
    ],
    "name:ita_x_preferred":[
        "Besbes"
    ],
    "name:msa_x_preferred":[
        "Besbes"
    ],
    "name:nan_x_preferred":[
        "Besbes"
    ],
    "name:nld_x_preferred":[
        "Besbes"
    ],
    "name:por_x_preferred":[
        "Besbes"
    ],
    "name:ron_x_preferred":[
        "Besbes"
    ],
    "name:swe_x_preferred":[
        "Besbes"
    ],
    "name:und_x_variant":[
        "Randon"
    ],
    "name:vie_x_preferred":[
        "Besbes"
    ],
    "name:zho_min_nan_x_preferred":[
        "Besbes"
    ],
    "name:zho_x_preferred":[
        "\u8c9d\u65af\u8c9d\u65af"
    ],
    "qs:gn_country":"DZ",
    "qs:gn_fcode":"PPL",
    "qs:gn_pop":66287,
    "qs:name":"Besbes",
    "qs:name_adm0":"\u0627\u0644\u062c\u0632\u0627\u0626\u0631",
    "qs:name_adm1":"\u0648\u0644\u0627\u064a\u0629 \u0627\u0644\u0637\u0627\u0631\u0641",
    "qs:photos":0,
    "qs:photos_1k":0,
    "qs:photos_9k":0,
    "qs:photos_9r":0,
    "qs:photos_all":0,
    "qs:photos_sr":0,
    "qs:placetype":"Town",
    "qs:pop_sr":"8",
    "qs:woe_adm0":23424740,
    "wd:wordcount":184,
    "wof:name":"Besbes",
    "wof:placetype":"locality",
    "wof:population":66287
},
  "geometry": {"coordinates":[7.84722,36.70222],"type":"Point"}
}