{
  "type": "Feature",
  "properties": {
    "gn:admin1_code":"41.0",
    "gn:asciiname":"Amzaika",
    "gn:country_code":"DZ",
    "gn:dem":181,
    "gn:feature_class":"P",
    "gn:feature_code":"PPL",
    "gn:name":"Amza\u00efka",
    "gn:population":0,
    "gn:timezone":"Africa/Algiers",
    "iso:country":"DZ",
    "wof:name":"Amzaika",
    "wof:placetype":"locality"
},
  "geometry": {"coordinates":[1.64907,36.20902],"type":"Point"}
}