{
  "type": "Feature",
  "properties": {
    "gn:admin1_code":"35.0",
    "gn:asciiname":"Dar el Hadj Abdellah",
    "gn:country_code":"DZ",
    "gn:dem":648,
    "gn:feature_class":"P",
    "gn:feature_code":"PPL",
    "gn:name":"Dar el Hadj Abdellah",
    "gn:population":0,
    "gn:timezone":"Africa/Algiers",
    "iso:country":"DZ",
    "name:und_x_variant":[
        "El Hadj Abdallah"
    ],
    "wof:name":"Dar el Hadj Abdellah",
    "wof:placetype":"locality"
},
  "geometry": {"coordinates":[2.5591,36.07529],"type":"Point"}
}