{
  "type": "Feature",
  "properties": {
    "gn:country":"DZ",
    "gn:fcode":"PPL",
    "gn:pop":11989,
    "iso:country":"DZ",
    "name:ara_x_preferred":[
        "\u0639\u064a\u0646 \u0628\u0648\u0633\u064a\u0641"
    ],
    "name:azb_x_preferred":[
        "\u0639\u06cc\u0646 \u0628\u0648\u0633\u06cc\u0641"
    ],
    "name:eng_x_preferred":[
        "A\u00efn Boucif"
    ],
    "name:fas_x_preferred":[
        "\u0639\u06cc\u0646 \u0628\u0648\u0633\u06cc\u0641"
    ],
    "name:fra_x_preferred":[
        "A\u00efn Boucif"
    ],
    "name:ita_x_preferred":[
        "A\u00efn Boucif"
    ],
    "name:msa_x_preferred":[
        "A\u00efn Boucif"
    ],
    "name:nan_x_preferred":[
        "A\u00efn Boucif"
    ],
    "name:nld_x_preferred":[
        "A\u00efn Boucif"
    ],
    "name:por_x_preferred":[
        "A\u00efn Boucif"
    ],
    "name:ron_x_preferred":[
        "A\u00efn Boucif"
    ],
    "name:spa_x_preferred":[
        "A\u00efn Boucif"
    ],
    "name:unk_x_variant":[
        "Bordj A\u00efn Boucif"
    ],
    "name:vie_x_preferred":[
        "Ain Boucif"
    ],
    "name:zho_x_preferred":[
        "\u827e\u56e0\u5e03\u897f\u592b"
    ],
    "qs:name":"\u2019A\u00efn Boucif",
    "qs:photos_9r":0,
    "qs:photos_sr":0,
    "qs:pop_sr":"6",
    "wd:wordcount":46,
    "wof:name":"\u2019A\u00efn Boucif",
    "wof:placetype":"locality",
    "wof:population":11989
},
  "geometry": {"coordinates":[3.1585,35.89123],"type":"Point"}
}