{
  "type": "Feature",
  "properties": {
    "gn:country":"DZ",
    "gn:fcode":"PPL",
    "gn:pop":11989,
    "iso:country":"DZ",
    "name:unk_x_variant":[
        "Bordj A\u00efn Boucif"
    ],
    "qs:name":"\u2019A\u00efn Boucif",
    "qs:photos_9r":0,
    "qs:photos_sr":0,
    "qs:pop_sr":"6",
    "wd:wordcount":46,
    "wof:name":"\u2019A\u00efn Boucif",
    "wof:placetype":"locality",
    "wof:population":11989
},
  "geometry": {"coordinates":[3.1585,35.89123],"type":"Point"}
}