{
  "type": "Feature",
  "properties": {
    "gn:admin1_code":"6.0",
    "gn:asciiname":"Sidi Saadane",
    "gn:country_code":"DZ",
    "gn:dem":962,
    "gn:feature_class":"P",
    "gn:feature_code":"PPL",
    "gn:name":"Sidi Saadane",
    "gn:population":0,
    "gn:timezone":"Africa/Algiers",
    "iso:country":"DZ",
    "wof:name":"Sidi Saadane",
    "wof:placetype":"locality"
},
  "geometry": {"coordinates":[2.99908,36.00340999999999],"type":"Point"}
}