{
  "type": "Feature",
  "properties": {
    "gn:admin1_code":"6.0",
    "gn:asciiname":"Oulad Zeguia",
    "gn:country_code":"DZ",
    "gn:dem":857,
    "gn:feature_class":"P",
    "gn:feature_code":"PPL",
    "gn:name":"Oulad Zeguia",
    "gn:population":0,
    "gn:timezone":"Africa/Algiers",
    "iso:country":"DZ",
    "wof:name":"Oulad Zeguia",
    "wof:placetype":"locality"
},
  "geometry": {"coordinates":[2.9825,36.04778],"type":"Point"}
}