{
  "type": "Feature",
  "properties": {
    "gn:admin1_code":"34.0",
    "gn:asciiname":"Sali",
    "gn:country_code":"DZ",
    "gn:dem":212,
    "gn:feature_class":"P",
    "gn:feature_code":"PPL",
    "gn:name":"Sali",
    "gn:population":0,
    "gn:timezone":"Africa/Algiers",
    "iso:country":"DZ",
    "name:ara_x_preferred":[
        "\u0633\u0627\u0644\u064a"
    ],
    "name:azb_x_preferred":[
        "\u0633\u0627\u0644\u06cc"
    ],
    "name:deu_x_preferred":[
        "Sali"
    ],
    "name:fas_x_preferred":[
        "\u0633\u0627\u0644\u06cc"
    ],
    "name:fra_x_preferred":[
        "Sali"
    ],
    "name:ita_x_preferred":[
        "Sali"
    ],
    "name:msa_x_preferred":[
        "Sali"
    ],
    "name:por_x_preferred":[
        "Sali"
    ],
    "name:ron_x_preferred":[
        "Sali"
    ],
    "name:rus_x_preferred":[
        "\u0421\u0430\u043b\u0438"
    ],
    "name:spa_x_preferred":[
        "Sali"
    ],
    "name:urd_x_preferred":[
        "\u0633\u0627\u0644\u06cc"
    ],
    "name:vie_x_preferred":[
        "Sali"
    ],
    "wof:name":"Sali",
    "wof:placetype":"locality"
},
  "geometry": {"coordinates":[-0.04042,26.96548],"type":"Point"}
}