{
  "type": "Feature",
  "properties": {
    "gn:admin1_code":"14.0",
    "gn:asciiname":"Isseradjene",
    "gn:country_code":"DZ",
    "gn:dem":365,
    "gn:feature_class":"P",
    "gn:feature_code":"PPL",
    "gn:name":"Isseradjene",
    "gn:population":0,
    "gn:timezone":"Africa/Algiers",
    "iso:country":"DZ",
    "wof:name":"Isseradjene",
    "wof:placetype":"locality"
},
  "geometry": {"coordinates":[4.1628,36.80231],"type":"Point"}
}