{
  "type": "Feature",
  "properties": {
    "gn:admin1_code":"51.0",
    "gn:asciiname":"Douar Choueikh",
    "gn:country_code":"DZ",
    "gn:dem":275,
    "gn:feature_class":"P",
    "gn:feature_code":"PPL",
    "gn:name":"Douar Choue\u00efkh",
    "gn:population":0,
    "gn:timezone":"Africa/Algiers",
    "iso:country":"DZ",
    "wof:name":"Douar Choueikh",
    "wof:placetype":"locality"
},
  "geometry": {"coordinates":[0.74164,35.78423],"type":"Point"}
}