{
  "type": "Feature",
  "properties": {
    "gn:admin1_code":"20.0",
    "gn:asciiname":"Beni Slimane",
    "gn:country_code":"DZ",
    "gn:dem":709,
    "gn:feature_class":"P",
    "gn:feature_code":"PPL",
    "gn:name":"Beni Slimane",
    "gn:population":0,
    "gn:timezone":"Africa/Algiers",
    "iso:country":"DZ",
    "name:ara_x_preferred":[
        "\u0628\u0646\u064a \u0633\u0644\u064a\u0645\u0627\u0646"
    ],
    "name:azb_x_preferred":[
        "\u0628\u0646\u06cc \u0633\u0644\u06cc\u0645\u0627\u0646"
    ],
    "name:fas_x_preferred":[
        "\u0628\u0646\u06cc \u0633\u0644\u06cc\u0645\u0627\u0646"
    ],
    "name:fra_x_preferred":[
        "Beni Slimane"
    ],
    "name:ita_x_preferred":[
        "Beni Slimane"
    ],
    "name:msa_x_preferred":[
        "Beni Slimane"
    ],
    "name:por_x_preferred":[
        "Beni Slimane"
    ],
    "name:ron_x_preferred":[
        "Beni Slimane"
    ],
    "name:spa_x_preferred":[
        "Beni Slimane"
    ],
    "name:vie_x_preferred":[
        "Beni Slimane"
    ],
    "name:zho_x_preferred":[
        "\u8c9d\u5c3c\u8607\u840a\u66fc"
    ],
    "wof:name":"Beni Slimane",
    "wof:placetype":"locality"
},
  "geometry": {"coordinates":[2.75472,36.34889],"type":"Point"}
}