{
  "type": "Feature",
  "properties": {
    "gn:admin1_code":"20.0",
    "gn:asciiname":"Beni Slimane",
    "gn:country_code":"DZ",
    "gn:dem":709,
    "gn:feature_class":"P",
    "gn:feature_code":"PPL",
    "gn:name":"Beni Slimane",
    "gn:population":0,
    "gn:timezone":"Africa/Algiers",
    "iso:country":"DZ",
    "wof:name":"Beni Slimane",
    "wof:placetype":"locality"
},
  "geometry": {"coordinates":[2.75472,36.34889],"type":"Point"}
}