{
  "type": "Feature",
  "properties": {
    "iso:country":"DZ",
    "name:deu_x_preferred":[
        "Mar\u00e9chal Foch"
    ],
    "name:fra_x_preferred":[
        "Mar\u00e9chal Foch"
    ],
    "name:pol_x_preferred":[
        "Mar\u00e9chal Foch"
    ],
    "name:unk_x_variant":[
        "L\u2019Arbetache"
    ],
    "qs:gn_country":"DZ",
    "qs:gn_fcode":"PPL",
    "qs:gn_pop":17481,
    "qs:name":"Marechal Foch",
    "qs:name_adm0":"\u0627\u0644\u062c\u0632\u0627\u0626\u0631",
    "qs:name_adm1":"Boumerdes",
    "qs:photos":0,
    "qs:photos_1k":0,
    "qs:photos_9k":1,
    "qs:photos_9r":1,
    "qs:photos_all":2,
    "qs:photos_sr":0,
    "qs:placetype":"Town",
    "qs:pop_sr":"6",
    "qs:woe_adm0":23424740,
    "wd:wordcount":488,
    "wof:name":"Marechal Foch",
    "wof:placetype":"locality",
    "wof:population":17481
},
  "geometry": {"coordinates":[3.37127,36.63773],"type":"Point"}
}