{
  "type": "Feature",
  "properties": {
    "gn:admin1_code":"48.0",
    "gn:asciiname":"Mechta 'Ain Kedaine",
    "gn:country_code":"DZ",
    "gn:dem":1070,
    "gn:feature_class":"P",
    "gn:feature_code":"PPL",
    "gn:name":"Mechta \u2019A\u00efn Keda\u00efne",
    "gn:population":0,
    "gn:timezone":"Africa/Algiers",
    "iso:country":"DZ",
    "wof:name":"Mechta 'Ain Kedaine",
    "wof:placetype":"locality"
},
  "geometry": {"coordinates":[5.97578,36.25014],"type":"Point"}
}