{
  "type": "Feature",
  "properties": {
    "gn:admin1_code":"13.0",
    "gn:asciiname":"'Ain Dzarit",
    "gn:country_code":"DZ",
    "gn:dem":930,
    "gn:feature_class":"P",
    "gn:feature_code":"PPL",
    "gn:name":"\u2019A\u00efn Dzarit",
    "gn:population":0,
    "gn:timezone":"Africa/Algiers",
    "iso:country":"DZ",
    "name:und_x_variant":[
        "A\u00efn Djarit",
        "A\u00efne Dzarit",
        "\u2019A\u00efn Dzarit"
    ],
    "wof:name":"'Ain Dzarit",
    "wof:placetype":"locality"
},
  "geometry": {"coordinates":[1.6674,35.35325],"type":"Point"}
}