{
  "type": "Feature",
  "properties": {
    "gn:admin1_code":"51.0",
    "gn:asciiname":"Mechtat Oued Ouis",
    "gn:country_code":"DZ",
    "gn:dem":46,
    "gn:feature_class":"P",
    "gn:feature_code":"PPL",
    "gn:name":"Mechtat Oued Ouis",
    "gn:population":0,
    "gn:timezone":"Africa/Algiers",
    "iso:country":"DZ",
    "wof:name":"Mechtat Oued Ouis",
    "wof:placetype":"locality"
},
  "geometry": {"coordinates":[0.77694,35.98722],"type":"Point"}
}