{
  "type": "Feature",
  "properties": {
    "gn:admin1_code":"41.0",
    "gn:asciiname":"Boukaat Ouled Tahar",
    "gn:country_code":"DZ",
    "gn:dem":78,
    "gn:feature_class":"P",
    "gn:feature_code":"PPLL",
    "gn:name":"Boukaat Ouled Tahar",
    "gn:population":0,
    "gn:timezone":"Africa/Algiers",
    "iso:country":"DZ",
    "name:und_x_variant":[
        "Ouled Ben-et Tahar",
        "Boukaat Ouled Tahar",
        "Boka\u2019et Ouled Tahar"
    ],
    "wof:name":"Boukaat Ouled Tahar",
    "wof:placetype":"locality"
},
  "geometry": {"coordinates":[1.15202,36.08622],"type":"Point"}
}