{
  "type": "Feature",
  "properties": {
    "gn:gn_country":"DZ",
    "gn:gn_fcode":"PPL",
    "gn:gn_pop":23001,
    "gn:population":23001,
    "iso:country":"DZ",
    "name:ara_x_preferred":[
        "\u0639\u0645\u064a \u0645\u0648\u0633\u0649"
    ],
    "name:dut_x_preferred":[
        "Ammi Moussa"
    ],
    "name:eng_x_preferred":[
        "Ammi Moussa"
    ],
    "name:fre_x_preferred":[
        "Ammi Moussa"
    ],
    "name:hin_x_preferred":[
        "\u090f\u092e\u0940 \u092e\u094c\u0938\u093e"
    ],
    "name:ita_x_preferred":[
        "Ammi Moussa"
    ],
    "name:may_x_preferred":[
        "Ammi Moussa"
    ],
    "name:per_x_preferred":[
        "\u0639\u0645\u06cc \u0645\u0648\u0633\u0649"
    ],
    "name:por_x_preferred":[
        "Ammi Moussa"
    ],
    "name:rum_x_preferred":[
        "Ammi Moussa"
    ],
    "name:swe_x_preferred":[
        "Ammi Moussa"
    ],
    "name:vie_x_preferred":[
        "Ammi Moussa"
    ],
    "qs_pg:aaroncc":"DZ",
    "qs_pg:gn_country":"DZ",
    "qs_pg:gn_fcode":"PPL",
    "qs_pg:gn_pop":23001,
    "qs_pg:name":"Ammi Moussa",
    "qs_pg:photos_9r":0,
    "qs_pg:photos_sr":0,
    "qs_pg:pop_sr":7,
    "qs_pg:qs_pg_placetype":"locality",
    "wof:name":"Ammi Moussa",
    "wof:placetype":"locality",
    "wof:population":23001
},
  "geometry": {"coordinates":[1.11143,35.86781],"type":"Point"}
}