{
  "type": "Feature",
  "properties": {
    "gn:country":"DZ",
    "gn:fcode":"PPL",
    "gn:population":23001,
    "iso:country":"DZ",
    "name:ara_x_preferred":[
        "\u0639\u0645\u064a \u0645\u0648\u0633\u0649"
    ],
    "name:arz_x_preferred":[
        "\u0639\u0645\u0649 \u0645\u0648\u0633\u0649"
    ],
    "name:azb_x_preferred":[
        "\u0639\u0645\u06cc \u0645\u0648\u0633\u06cc"
    ],
    "name:ceb_x_preferred":[
        "Ammi Moussa"
    ],
    "name:eng_x_preferred":[
        "Ammi Moussa"
    ],
    "name:fas_x_preferred":[
        "\u0639\u0645\u06cc \u0645\u0648\u0633\u0649"
    ],
    "name:fra_x_preferred":[
        "Ammi Moussa"
    ],
    "name:hin_x_preferred":[
        "\u090f\u092e\u0940 \u092e\u094c\u0938\u093e"
    ],
    "name:ita_x_preferred":[
        "Ammi Moussa"
    ],
    "name:kab_x_preferred":[
        "\u0190emmi Musa"
    ],
    "name:msa_x_preferred":[
        "Ammi Moussa"
    ],
    "name:nan_x_preferred":[
        "Ammi Moussa"
    ],
    "name:nld_x_preferred":[
        "Ammi Moussa"
    ],
    "name:por_x_preferred":[
        "Ammi Moussa"
    ],
    "name:ron_x_preferred":[
        "Ammi Moussa"
    ],
    "name:spa_x_preferred":[
        "Ammi Moussa"
    ],
    "name:swe_x_preferred":[
        "Ammi Moussa"
    ],
    "name:uzb_x_preferred":[
        "Ammi Moussa"
    ],
    "name:vie_x_preferred":[
        "Ammi Moussa"
    ],
    "name:zho_x_preferred":[
        "\u963f\u7c73\u7a46\u85a9"
    ],
    "qs_pg:aaroncc":"DZ",
    "qs_pg:gn_country":"DZ",
    "qs_pg:gn_fcode":"PPL",
    "qs_pg:gn_pop":23001,
    "qs_pg:name":"Ammi Moussa",
    "qs_pg:photos_9r":0,
    "qs_pg:photos_sr":0,
    "qs_pg:pop_sr":7,
    "qs_pg:qs_pg_placetype":"locality",
    "wof:name":"Ammi Moussa",
    "wof:placetype":"locality",
    "wof:population":23001
},
  "geometry": {"coordinates":[1.11143,35.86781],"type":"Point"}
}