{
  "type": "Feature",
  "properties": {
    "iso:country":"DZ",
    "name:ara_x_preferred":[
        "\u0648\u0644\u0627\u064a\u0629 \u062a\u064a\u0628\u0627\u0632\u0629"
    ],
    "name:eng_x_preferred":[
        "Tipaza Province"
    ],
    "qs:gn_pop":0,
    "qs:name":"\u0648\u0644\u0627\u064a\u0629 \u062a\u064a\u0628\u0627\u0632\u0629",
    "qs:name_adm0":"\u0627\u0644\u062c\u0632\u0627\u0626\u0631",
    "qs:name_adm1":"Tipaza",
    "qs:photos":521,
    "qs:photos_1k":106,
    "qs:photos_9k":2,
    "qs:photos_9r":5,
    "qs:photos_all":521,
    "qs:photos_sr":7,
    "qs:placetype":"Town",
    "qs:pop_sr":"0",
    "qs:woe_adm0":23424740,
    "wof:name":"Tipaza Province",
    "wof:placetype":"locality"
},
  "geometry": {"coordinates":[2.446583,36.587276],"type":"Point"}
}