{
  "type": "Feature",
  "properties": {
    "gn:admin1_code":"23.0",
    "gn:asciiname":"Mechtat Ahmed Bel Ajmi",
    "gn:country_code":"DZ",
    "gn:dem":584,
    "gn:feature_class":"P",
    "gn:feature_code":"PPL",
    "gn:name":"Mechtat Ahmed Bel Ajmi",
    "gn:population":0,
    "gn:timezone":"Africa/Algiers",
    "iso:country":"DZ",
    "wof:name":"Mechtat Ahmed Bel Ajmi",
    "wof:placetype":"locality"
},
  "geometry": {"coordinates":[7.50833,36.33472],"type":"Point"}
}