{
  "type": "Feature",
  "properties": {
    "gn:admin1_code":"13.0",
    "gn:asciiname":"Dar Ben Chahra",
    "gn:country_code":"DZ",
    "gn:dem":1230,
    "gn:feature_class":"P",
    "gn:feature_code":"PPL",
    "gn:name":"Dar Ben Chahra",
    "gn:population":0,
    "gn:timezone":"Africa/Algiers",
    "iso:country":"DZ",
    "wof:name":"Dar Ben Chahra",
    "wof:placetype":"locality"
},
  "geometry": {"coordinates":[1.45571,34.99097],"type":"Point"}
}