{
  "type": "Feature",
  "properties": {
    "gn:admin1_code":"41.0",
    "gn:asciiname":"T'haridj",
    "gn:country_code":"DZ",
    "gn:dem":119,
    "gn:feature_class":"P",
    "gn:feature_code":"PPL",
    "gn:name":"T\u2019haridj",
    "gn:population":0,
    "gn:timezone":"Africa/Algiers",
    "iso:country":"DZ",
    "wof:name":"T'haridj",
    "wof:placetype":"locality"
},
  "geometry": {"coordinates":[1.23981,36.08589],"type":"Point"}
}