{
  "type": "Feature",
  "properties": {
    "gn:admin1_code":"35.0",
    "gn:asciiname":"Mahaizia",
    "gn:country_code":"DZ",
    "gn:dem":421,
    "gn:feature_class":"P",
    "gn:feature_code":"PPL",
    "gn:name":"Maha\u00efzia",
    "gn:population":0,
    "gn:timezone":"Africa/Algiers",
    "iso:country":"DZ",
    "wof:name":"Mahaizia",
    "wof:placetype":"locality"
},
  "geometry": {"coordinates":[2.53778,36.35639000000001],"type":"Point"}
}