{
  "type": "Feature",
  "properties": {
    "gn:admin1_code":"41.0",
    "gn:asciiname":"Ouled el Agha",
    "gn:country_code":"DZ",
    "gn:dem":554,
    "gn:feature_class":"P",
    "gn:feature_code":"PPL",
    "gn:name":"Ouled el Agha",
    "gn:population":0,
    "gn:timezone":"Africa/Algiers",
    "iso:country":"DZ",
    "wof:name":"Ouled el Agha",
    "wof:placetype":"locality"
},
  "geometry": {"coordinates":[1.42069,36.00396],"type":"Point"}
}