{
  "type": "Feature",
  "properties": {
    "gn:admin1_code":"49.0",
    "gn:asciiname":"Moghrar",
    "gn:country_code":"DZ",
    "gn:dem":983,
    "gn:feature_class":"P",
    "gn:feature_code":"PPL",
    "gn:name":"Moghrar",
    "gn:population":0,
    "gn:timezone":"Africa/Algiers",
    "iso:country":"DZ",
    "name:ara_x_preferred":[
        "\u0645\u063a\u0631\u0627\u0631"
    ],
    "name:azb_x_preferred":[
        "\u0645\u063a\u0631\u0627\u0631"
    ],
    "name:fas_x_preferred":[
        "\u0645\u063a\u0631\u0627\u0631"
    ],
    "name:fra_x_preferred":[
        "Moghrar"
    ],
    "name:ita_x_preferred":[
        "Moghrar"
    ],
    "name:kab_x_preferred":[
        "Megrar"
    ],
    "name:msa_x_preferred":[
        "Moghrar"
    ],
    "name:por_x_preferred":[
        "Moghrar"
    ],
    "name:ron_x_preferred":[
        "Moghrar"
    ],
    "name:spa_x_preferred":[
        "Moghrar"
    ],
    "name:und_x_variant":[
        "Mograr Foukania",
        "Moghar-Foukani",
        "Morhar Foukani",
        "Mograr Foukani",
        "Morhar",
        "Moghrar"
    ],
    "name:vie_x_preferred":[
        "Moghrar"
    ],
    "wof:name":"Moghrar",
    "wof:placetype":"locality"
},
  "geometry": {"coordinates":[-0.58816,32.51229],"type":"Point"}
}