{
  "type": "Feature",
  "properties": {
    "gn:admin1_code":"49.0",
    "gn:asciiname":"Moghrar",
    "gn:country_code":"DZ",
    "gn:dem":983,
    "gn:feature_class":"P",
    "gn:feature_code":"PPL",
    "gn:name":"Moghrar",
    "gn:population":0,
    "gn:timezone":"Africa/Algiers",
    "iso:country":"DZ",
    "name:und_x_variant":[
        "Mograr Foukania",
        "Moghar-Foukani",
        "Morhar Foukani",
        "Mograr Foukani",
        "Morhar",
        "Moghrar"
    ],
    "wof:name":"Moghrar",
    "wof:placetype":"locality"
},
  "geometry": {"coordinates":[-0.58816,32.51229],"type":"Point"}
}