{
  "type": "Feature",
  "properties": {
    "iso:country":"DZ",
    "name:ara_x_preferred":[
        "\u0628\u0644\u062f\u064a\u0629 \u062f\u0648\u064a\u0631\u0629"
    ],
    "name:ara_x_variant":[
        "\u0627\u0644\u062f\u0648\u064a\u0631\u0629"
    ],
    "name:arz_x_preferred":[
        "\u0627\u0644\u062f\u0648\u064a\u0631\u0647"
    ],
    "name:azb_x_preferred":[
        "\u062f\u0648\u06cc\u0631\u0647"
    ],
    "name:ceb_x_preferred":[
        "Douera"
    ],
    "name:eng_x_preferred":[
        "Dou\u00e9ra"
    ],
    "name:fas_x_preferred":[
        "\u0634\u0647\u0631\u062f\u0627\u0631\u06cc \u062f\u0648\u06cc\u0631\u0647"
    ],
    "name:fra_x_preferred":[
        "Douera"
    ],
    "name:ita_x_preferred":[
        "Douera"
    ],
    "name:kab_x_preferred":[
        "Ddwira"
    ],
    "name:msa_x_preferred":[
        "Dou\u00e9ra"
    ],
    "name:nan_x_preferred":[
        "Douera"
    ],
    "name:nld_x_preferred":[
        "Dou\u00e9ra"
    ],
    "name:por_x_preferred":[
        "Dou\u00e9ra"
    ],
    "name:ron_x_preferred":[
        "Douera"
    ],
    "name:spa_x_preferred":[
        "Douera"
    ],
    "name:swe_x_preferred":[
        "Douera"
    ],
    "name:tur_x_preferred":[
        "Duveyre"
    ],
    "name:urd_x_preferred":[
        "\u062f\u0648\u06cc\u0631\u06c1"
    ],
    "name:vie_x_preferred":[
        "Douera"
    ],
    "qs:gn_country":"DZ",
    "qs:gn_fcode":"PPL",
    "qs:gn_pop":26926,
    "qs:name":"Douera",
    "qs:name_adm0":"\u0627\u0644\u062c\u0632\u0627\u0626\u0631",
    "qs:name_adm1":"Tipaza",
    "qs:photos":5,
    "qs:photos_1k":1,
    "qs:photos_9k":1,
    "qs:photos_9r":1,
    "qs:photos_all":5,
    "qs:photos_sr":1,
    "qs:placetype":"Town",
    "qs:pop_sr":"7",
    "qs:woe_adm0":23424740,
    "wd:wordcount":29,
    "wof:name":"Douera",
    "wof:placetype":"locality",
    "wof:population":26926
},
  "geometry": {"coordinates":[2.94444,36.67],"type":"Point"}
}