{
  "type": "Feature",
  "properties": {
    "gn:admin1_code":"41.0",
    "gn:asciiname":"Douar Oued Fatty",
    "gn:country_code":"DZ",
    "gn:dem":65,
    "gn:feature_class":"P",
    "gn:feature_code":"PPL",
    "gn:name":"Douar Oued Fatty",
    "gn:population":0,
    "gn:timezone":"Africa/Algiers",
    "iso:country":"DZ",
    "wof:name":"Douar Oued Fatty",
    "wof:placetype":"locality"
},
  "geometry": {"coordinates":[1.00721,36.05758],"type":"Point"}
}