{
  "type": "Feature",
  "properties": {
    "gn:admin1_code":"26.0",
    "gn:asciiname":"Mohammed Ben Djilah",
    "gn:country_code":"DZ",
    "gn:dem":690,
    "gn:feature_class":"P",
    "gn:feature_code":"PPL",
    "gn:name":"Mohammed Ben Djilah",
    "gn:population":0,
    "gn:timezone":"Africa/Algiers",
    "iso:country":"DZ",
    "name:und_x_variant":[
        "Douar Mohammed Ben Djilah",
        "Mohammed Ben Djilah"
    ],
    "wof:name":"Mohammed Ben Djilah",
    "wof:placetype":"locality"
},
  "geometry": {"coordinates":[0.26894,35.55119000000001],"type":"Point"}
}