{
  "type": "Feature",
  "properties": {
    "gn:admin1_code":"26.0",
    "gn:asciiname":"Douar el Mouelek",
    "gn:country_code":"DZ",
    "gn:dem":757,
    "gn:feature_class":"P",
    "gn:feature_code":"PPL",
    "gn:name":"Douar el Mouelek",
    "gn:population":0,
    "gn:timezone":"Africa/Algiers",
    "iso:country":"DZ",
    "name:und_x_variant":[
        "Dar Kaddour ben Amrane"
    ],
    "wof:name":"Douar el Mouelek",
    "wof:placetype":"locality"
},
  "geometry": {"coordinates":[0.3514,35.53935],"type":"Point"}
}