{
  "type": "Feature",
  "properties": {
    "gn:admin1_code":"36.0",
    "gn:asciiname":"Douar des Zenakra",
    "gn:country_code":"DZ",
    "gn:dem":102,
    "gn:feature_class":"P",
    "gn:feature_code":"PPL",
    "gn:name":"Douar des Zenakra",
    "gn:population":0,
    "gn:timezone":"Africa/Algiers",
    "iso:country":"DZ",
    "wof:name":"Douar des Zenakra",
    "wof:placetype":"locality"
},
  "geometry": {"coordinates":[-0.83333,35.43333],"type":"Point"}
}