{
  "type": "Feature",
  "properties": {
    "gn:admin1_code":"6.0",
    "gn:asciiname":"Douar Alalma",
    "gn:country_code":"DZ",
    "gn:dem":765,
    "gn:feature_class":"P",
    "gn:feature_code":"PPL",
    "gn:name":"Douar Alalma",
    "gn:population":0,
    "gn:timezone":"Africa/Algiers",
    "iso:country":"DZ",
    "name:und_x_variant":[
        "Alama"
    ],
    "wof:name":"Douar Alalma",
    "wof:placetype":"locality"
},
  "geometry": {"coordinates":[2.97948,36.03041],"type":"Point"}
}