{
  "type": "Feature",
  "properties": {
    "gn:admin1_code":"51.0",
    "gn:asciiname":"Cheragua",
    "gn:country_code":"DZ",
    "gn:dem":620,
    "gn:feature_class":"P",
    "gn:feature_code":"PPL",
    "gn:name":"Cheragua",
    "gn:population":0,
    "gn:timezone":"Africa/Algiers",
    "iso:country":"DZ",
    "wof:name":"Cheragua",
    "wof:placetype":"locality"
},
  "geometry": {"coordinates":[0.91732,35.54486],"type":"Point"}
}