{
  "type": "Feature",
  "properties": {
    "gn:admin1_code":"13.0",
    "gn:asciiname":"'Ain en Nef",
    "gn:country_code":"DZ",
    "gn:dem":1208,
    "gn:feature_class":"P",
    "gn:feature_code":"PPL",
    "gn:name":"\u2019A\u00efn en Nef",
    "gn:population":0,
    "gn:timezone":"Africa/Algiers",
    "iso:country":"DZ",
    "wof:name":"'Ain en Nef",
    "wof:placetype":"locality"
},
  "geometry": {"coordinates":[1.58875,34.95836],"type":"Point"}
}