{
  "type": "Feature",
  "properties": {
    "gn:admin1_code":"36.0",
    "gn:asciiname":"Douar el Msaid",
    "gn:country_code":"DZ",
    "gn:dem":202,
    "gn:feature_class":"P",
    "gn:feature_code":"PPL",
    "gn:name":"Douar el Msa\u00efd",
    "gn:population":0,
    "gn:timezone":"Africa/Algiers",
    "iso:country":"DZ",
    "wof:name":"Douar el Msaid",
    "wof:placetype":"locality"
},
  "geometry": {"coordinates":[-1.11667,35.55],"type":"Point"}
}