{
  "type": "Feature",
  "properties": {
    "gn:admin1_code":"35.0",
    "gn:asciiname":"Douar el Msaif",
    "gn:country_code":"DZ",
    "gn:dem":546,
    "gn:feature_class":"P",
    "gn:feature_code":"PPL",
    "gn:name":"Douar el Msa\u00eff",
    "gn:population":0,
    "gn:timezone":"Africa/Algiers",
    "iso:country":"DZ",
    "wof:name":"Douar el Msaif",
    "wof:placetype":"locality"
},
  "geometry": {"coordinates":[1.763,36.1029],"type":"Point"}
}