{
  "type": "Feature",
  "properties": {
    "gn:admin1_code":"1.0",
    "gn:asciiname":"Tixeraine",
    "gn:country_code":"DZ",
    "gn:dem":145,
    "gn:feature_class":"P",
    "gn:feature_code":"PPL",
    "gn:name":"Tixera\u00efne",
    "gn:population":0,
    "gn:timezone":"Africa/Algiers",
    "iso:country":"DZ",
    "wof:name":"Tixeraine",
    "wof:placetype":"locality"
},
  "geometry": {"coordinates":[3.02729,36.72365],"type":"Point"}
}