{
  "type": "Feature",
  "properties": {
    "gn:admin1_code":"55.0",
    "gn:asciiname":"El Kalla",
    "gn:country_code":"DZ",
    "gn:dem":479,
    "gn:feature_class":"P",
    "gn:feature_code":"PPL",
    "gn:name":"El Kalla",
    "gn:population":0,
    "gn:timezone":"Africa/Algiers",
    "iso:country":"DZ",
    "wof:name":"El Kalla",
    "wof:placetype":"locality"
},
  "geometry": {"coordinates":[1.89891,36.5314],"type":"Point"}
}