{
  "type": "Feature",
  "properties": {
    "gn:admin1_code":"35.0",
    "gn:asciiname":"Souk el Attaf",
    "gn:country_code":"DZ",
    "gn:dem":636,
    "gn:feature_class":"P",
    "gn:feature_code":"PPL",
    "gn:name":"Souk el Attaf",
    "gn:population":0,
    "gn:timezone":"Africa/Algiers",
    "iso:country":"DZ",
    "wof:name":"Souk el Attaf",
    "wof:placetype":"locality"
},
  "geometry": {"coordinates":[2.23434,36.00457],"type":"Point"}
}