{
  "type": "Feature",
  "properties": {
    "gn:admin1_code":"40.0",
    "gn:asciiname":"Ben Amara",
    "gn:country_code":"DZ",
    "gn:dem":296,
    "gn:feature_class":"P",
    "gn:feature_code":"PPL",
    "gn:name":"Ben Amara",
    "gn:population":0,
    "gn:timezone":"Africa/Algiers",
    "iso:country":"DZ",
    "wof:name":"Ben Amara",
    "wof:placetype":"locality"
},
  "geometry": {"coordinates":[3.93109,36.86985],"type":"Point"}
}