{
  "type": "Feature",
  "properties": {
    "gn:admin1_code":"51.0",
    "gn:asciiname":"Koualil",
    "gn:country_code":"DZ",
    "gn:dem":674,
    "gn:feature_class":"P",
    "gn:feature_code":"PPL",
    "gn:name":"Koualil",
    "gn:population":0,
    "gn:timezone":"Africa/Algiers",
    "iso:country":"DZ",
    "wof:name":"Koualil",
    "wof:placetype":"locality"
},
  "geometry": {"coordinates":[0.9599,35.532],"type":"Point"}
}