{
  "type": "Feature",
  "properties": {
    "gn:admin1_code":"7.0",
    "gn:asciiname":"Douar el Aouaicia",
    "gn:country_code":"DZ",
    "gn:dem":171,
    "gn:feature_class":"P",
    "gn:feature_code":"PPL",
    "gn:name":"Douar el Aoua\u00efcia",
    "gn:population":0,
    "gn:timezone":"Africa/Algiers",
    "iso:country":"DZ",
    "wof:name":"Douar el Aouaicia",
    "wof:placetype":"locality"
},
  "geometry": {"coordinates":[0.28667,35.78498],"type":"Point"}
}