{
  "type": "Feature",
  "properties": {
    "gn:admin1_code":"39.0",
    "gn:asciiname":"Aourir Ouelmi",
    "gn:country_code":"DZ",
    "gn:dem":803,
    "gn:feature_class":"P",
    "gn:feature_code":"PPL",
    "gn:name":"Aourir Ouelmi",
    "gn:population":0,
    "gn:timezone":"Africa/Algiers",
    "iso:country":"DZ",
    "name:und_x_variant":[
        "Aourir Ou Eulmi",
        "Aourir Ouelmi"
    ],
    "wof:name":"Aourir Ouelmi",
    "wof:placetype":"locality"
},
  "geometry": {"coordinates":[4.80852,36.35898],"type":"Point"}
}