{
  "type": "Feature",
  "properties": {
    "gn:admin1_code":"55.0",
    "gn:asciiname":"Ben Salah",
    "gn:country_code":"DZ",
    "gn:dem":29,
    "gn:feature_class":"P",
    "gn:feature_code":"PPL",
    "gn:name":"Ben Salah",
    "gn:population":0,
    "gn:timezone":"Africa/Algiers",
    "iso:country":"DZ",
    "wof:name":"Ben Salah",
    "wof:placetype":"locality"
},
  "geometry": {"coordinates":[2.80614,36.57363],"type":"Point"}
}