{
  "type": "Feature",
  "properties": {
    "gn:country":"DZ",
    "gn:fcode":"PPL",
    "gn:pop":36834,
    "iso:country":"DZ",
    "name:ara_x_preferred":[
        "\u0627\u0644\u062f\u0628\u064a\u0644\u0629"
    ],
    "name:cze_x_preferred":[
        "Debila"
    ],
    "name:dut_x_preferred":[
        "Debila"
    ],
    "name:eng_x_preferred":[
        "Debila"
    ],
    "name:fre_x_preferred":[
        "Debila"
    ],
    "name:ita_x_preferred":[
        "Distretto di Debila"
    ],
    "name:may_x_preferred":[
        "Debila"
    ],
    "name:per_x_preferred":[
        "\u062f\u0628\u06cc\u0644\u0647"
    ],
    "name:por_x_preferred":[
        "Debila"
    ],
    "name:rum_x_preferred":[
        "Debila"
    ],
    "name:swe_x_preferred":[
        "Debila"
    ],
    "name:vie_x_preferred":[
        "Debila"
    ],
    "qs:name":"Debila",
    "qs:photos_9r":0,
    "qs:photos_sr":0,
    "qs:pop_sr":"7",
    "wd:wordcount":326,
    "wof:name":"Debila",
    "wof:placetype":"locality",
    "wof:population":36834
},
  "geometry": {"coordinates":[6.95,33.51667],"type":"Point"}
}