{
  "type": "Feature",
  "properties": {
    "gn:admin1_code":"40.0",
    "gn:asciiname":"Ouled Ben Bekrta",
    "gn:country_code":"DZ",
    "gn:dem":168,
    "gn:feature_class":"P",
    "gn:feature_code":"PPL",
    "gn:name":"Ouled Ben Bekrta",
    "gn:population":0,
    "gn:timezone":"Africa/Algiers",
    "iso:country":"DZ",
    "name:und_x_variant":[
        "Ouled Ben Bekhta"
    ],
    "wof:name":"Ouled Ben Bekrta",
    "wof:placetype":"locality"
},
  "geometry": {"coordinates":[3.45865,36.69321],"type":"Point"}
}