{
  "type": "Feature",
  "properties": {
    "gn:admin1_code":"51.0",
    "gn:asciiname":"Ouled Bou Ali",
    "gn:country_code":"DZ",
    "gn:dem":123,
    "gn:feature_class":"P",
    "gn:feature_code":"PPLL",
    "gn:name":"Ouled Bou Ali",
    "gn:population":0,
    "gn:timezone":"Africa/Algiers",
    "iso:country":"DZ",
    "wof:name":"Ouled Bou Ali",
    "wof:placetype":"locality"
},
  "geometry": {"coordinates":[0.51111,35.64889],"type":"Point"}
}