{
  "type": "Feature",
  "properties": {
    "gn:admin1_code":"14.0",
    "gn:asciiname":"Souk el Arba",
    "gn:country_code":"DZ",
    "gn:dem":362,
    "gn:feature_class":"P",
    "gn:feature_code":"PPL",
    "gn:name":"Souk el Arba",
    "gn:population":0,
    "gn:timezone":"Africa/Algiers",
    "iso:country":"DZ",
    "wof:name":"Souk el Arba",
    "wof:placetype":"locality"
},
  "geometry": {"coordinates":[4.2059,36.52177],"type":"Point"}
}