{
  "type": "Feature",
  "properties": {
    "gn:admin1_code":"6.0",
    "gn:asciiname":"Oulad Mamora",
    "gn:country_code":"DZ",
    "gn:dem":772,
    "gn:feature_class":"P",
    "gn:feature_code":"PPL",
    "gn:name":"Oulad Mamora",
    "gn:population":0,
    "gn:timezone":"Africa/Algiers",
    "iso:country":"DZ",
    "wof:name":"Oulad Mamora",
    "wof:placetype":"locality"
},
  "geometry": {"coordinates":[3.57716,35.98687],"type":"Point"}
}