{
  "type": "Feature",
  "properties": {
    "gn:admin1_code":"18.0",
    "gn:asciiname":"El Mennchar",
    "gn:country_code":"DZ",
    "gn:dem":803,
    "gn:feature_class":"P",
    "gn:feature_code":"PPL",
    "gn:name":"El Mennchar",
    "gn:population":0,
    "gn:timezone":"Africa/Algiers",
    "iso:country":"DZ",
    "name:und_x_variant":[
        "El Menchar",
        "El Mennchar"
    ],
    "wof:name":"El Mennchar",
    "wof:placetype":"locality"
},
  "geometry": {"coordinates":[5.33899,36.48186],"type":"Point"}
}