{
  "type": "Feature",
  "properties": {
    "gn:admin1_code":"27.0",
    "gn:asciiname":"Ben S'rourr",
    "gn:country_code":"DZ",
    "gn:dem":711,
    "gn:feature_class":"P",
    "gn:feature_code":"PPL",
    "gn:name":"Ben S\u2019rourr",
    "gn:population":0,
    "gn:timezone":"Africa/Algiers",
    "iso:country":"DZ",
    "wof:name":"Ben S'rourr",
    "wof:placetype":"locality"
},
  "geometry": {"coordinates":[4.56229,35.04053],"type":"Point"}
}