{
  "type": "Feature",
  "properties": {
    "gn:admin1_code":"13.0",
    "gn:asciiname":"'Ain Sidi Ali",
    "gn:country_code":"DZ",
    "gn:dem":1216,
    "gn:feature_class":"P",
    "gn:feature_code":"PPL",
    "gn:name":"\u2019A\u00efn Sidi Ali",
    "gn:population":0,
    "gn:timezone":"Africa/Algiers",
    "iso:country":"DZ",
    "wof:name":"'Ain Sidi Ali",
    "wof:placetype":"locality"
},
  "geometry": {"coordinates":[1.54179,34.15691],"type":"Point"}
}