{
  "type": "Feature",
  "properties": {
    "gn:admin1_code":"20.0",
    "gn:asciiname":"El Gourzi",
    "gn:country_code":"DZ",
    "gn:dem":867,
    "gn:feature_class":"P",
    "gn:feature_code":"PPL",
    "gn:name":"El Gourzi",
    "gn:population":0,
    "gn:timezone":"Africa/Algiers",
    "iso:country":"DZ",
    "wof:name":"El Gourzi",
    "wof:placetype":"locality"
},
  "geometry": {"coordinates":[3.18093,36.43513],"type":"Point"}
}