{
  "type": "Feature",
  "properties": {
    "gn:admin1_code":"12.0",
    "gn:asciiname":"Mechta Mokhtar",
    "gn:country_code":"DZ",
    "gn:dem":860,
    "gn:feature_class":"P",
    "gn:feature_code":"PPL",
    "gn:name":"Mechta Mokhtar",
    "gn:population":0,
    "gn:timezone":"Africa/Algiers",
    "iso:country":"DZ",
    "wof:name":"Mechta Mokhtar",
    "wof:placetype":"locality"
},
  "geometry": {"coordinates":[5.38353,35.64799],"type":"Point"}
}