{
  "type": "Feature",
  "properties": {
    "gn:admin1_code":"24.0",
    "gn:asciiname":"Habassa",
    "gn:country_code":"DZ",
    "gn:dem":412,
    "gn:feature_class":"P",
    "gn:feature_code":"PPL",
    "gn:name":"Habassa",
    "gn:population":0,
    "gn:timezone":"Africa/Algiers",
    "iso:country":"DZ",
    "name:und_x_variant":[
        "Dechra Haoutra",
        "Haoutra",
        "Habassa"
    ],
    "wof:name":"Habassa",
    "wof:placetype":"locality"
},
  "geometry": {"coordinates":[5.74524,36.7089],"type":"Point"}
}