{
  "type": "Feature",
  "properties": {
    "gn:admin1_code":"41.0",
    "gn:asciiname":"Douar Ouled Belkacem",
    "gn:country_code":"DZ",
    "gn:dem":325,
    "gn:feature_class":"P",
    "gn:feature_code":"PPL",
    "gn:name":"Douar Ouled Belkacem",
    "gn:population":0,
    "gn:timezone":"Africa/Algiers",
    "iso:country":"DZ",
    "wof:name":"Douar Ouled Belkacem",
    "wof:placetype":"locality"
},
  "geometry": {"coordinates":[1.03549,36.21839],"type":"Point"}
}