{
  "type": "Feature",
  "properties": {
    "gn:admin1_code":"40.0",
    "gn:asciiname":"Guerebissa",
    "gn:country_code":"DZ",
    "gn:dem":276,
    "gn:feature_class":"P",
    "gn:feature_code":"PPL",
    "gn:name":"Guerebissa",
    "gn:population":0,
    "gn:timezone":"Africa/Algiers",
    "iso:country":"DZ",
    "wof:name":"Guerebissa",
    "wof:placetype":"locality"
},
  "geometry": {"coordinates":[3.8398,36.8269],"type":"Point"}
}