{
  "type": "Feature",
  "properties": {
    "gn:admin1_code":"51.0",
    "gn:asciiname":"El Hmadena",
    "gn:country_code":"DZ",
    "gn:dem":74,
    "gn:feature_class":"P",
    "gn:feature_code":"PPL",
    "gn:name":"El Hmadena",
    "gn:population":0,
    "gn:timezone":"Africa/Algiers",
    "iso:country":"DZ",
    "name:und_x_variant":[
        "Krourara",
        "Hamadena",
        "El Hmadena",
        "El H\u2019madna"
    ],
    "wof:name":"El Hmadena",
    "wof:placetype":"locality"
},
  "geometry": {"coordinates":[0.77456,35.90627],"type":"Point"}
}