{
  "type": "Feature",
  "properties": {
    "gn:admin1_code":"51.0",
    "gn:asciiname":"Mechtat Chaaba el Hamra",
    "gn:country_code":"DZ",
    "gn:dem":105,
    "gn:feature_class":"P",
    "gn:feature_code":"PPL",
    "gn:name":"Mechtat Chaaba el Hamra",
    "gn:population":0,
    "gn:timezone":"Africa/Algiers",
    "iso:country":"DZ",
    "wof:name":"Mechtat Chaaba el Hamra",
    "wof:placetype":"locality"
},
  "geometry": {"coordinates":[0.85241,35.93079],"type":"Point"}
}