{
  "type": "Feature",
  "properties": {
    "gn:admin1_code":"20.0",
    "gn:asciiname":"Dalmatie",
    "gn:country_code":"DZ",
    "gn:dem":205,
    "gn:feature_class":"P",
    "gn:feature_code":"PPL",
    "gn:name":"Dalmatie",
    "gn:population":0,
    "gn:timezone":"Africa/Algiers",
    "iso:country":"DZ",
    "wof:name":"Dalmatie",
    "wof:placetype":"locality"
},
  "geometry": {"coordinates":[2.86076,36.49754],"type":"Point"}
}