{
  "type": "Feature",
  "properties": {
    "gn:admin1_code":"51.0",
    "gn:asciiname":"Douar Ouled el Djilalli",
    "gn:country_code":"DZ",
    "gn:dem":47,
    "gn:feature_class":"P",
    "gn:feature_code":"PPL",
    "gn:name":"Douar Ouled el Djilalli",
    "gn:population":0,
    "gn:timezone":"Africa/Algiers",
    "iso:country":"DZ",
    "name:und_x_variant":[
        "Oulad Djilali"
    ],
    "wof:name":"Douar Ouled el Djilalli",
    "wof:placetype":"locality"
},
  "geometry": {"coordinates":[0.77796,35.97788],"type":"Point"}
}