{
  "type": "Feature",
  "properties": {
    "gn:admin1_code":"36.0",
    "gn:asciiname":"Terga",
    "gn:country_code":"DZ",
    "gn:dem":30,
    "gn:feature_class":"P",
    "gn:feature_code":"PPL",
    "gn:name":"Terga",
    "gn:population":0,
    "gn:timezone":"Africa/Algiers",
    "iso:country":"DZ",
    "name:und_x_variant":[
        "Targa",
        "Turgot",
        "Terga"
    ],
    "wof:name":"Terga",
    "wof:placetype":"locality"
},
  "geometry": {"coordinates":[-1.17921,35.41835],"type":"Point"}
}