{
  "type": "Feature",
  "properties": {
    "gn:admin1_code":"36.0",
    "gn:asciiname":"Terga",
    "gn:country_code":"DZ",
    "gn:dem":30,
    "gn:feature_class":"P",
    "gn:feature_code":"PPL",
    "gn:name":"Terga",
    "gn:population":0,
    "gn:timezone":"Africa/Algiers",
    "iso:country":"DZ",
    "name:ara_x_preferred":[
        "\u062a\u0627\u0631\u0642\u0629"
    ],
    "name:azb_x_preferred":[
        "\u062a\u0627\u0631\u0642\u0647"
    ],
    "name:fas_x_preferred":[
        "\u062a\u0627\u0631\u0642\u0647"
    ],
    "name:fra_x_preferred":[
        "Terga"
    ],
    "name:kab_x_preferred":[
        "Targa"
    ],
    "name:msa_x_preferred":[
        "Terga"
    ],
    "name:por_x_preferred":[
        "Terga"
    ],
    "name:ron_x_preferred":[
        "Terga"
    ],
    "name:spa_x_preferred":[
        "Terga"
    ],
    "name:und_x_variant":[
        "Turgot"
    ],
    "name:vie_x_preferred":[
        "Terga"
    ],
    "name:zho_x_preferred":[
        "\u6cf0\u723e\u52a0"
    ],
    "wof:name":"Terga",
    "wof:placetype":"locality"
},
  "geometry": {"coordinates":[-1.17921,35.41835],"type":"Point"}
}