{
  "type": "Feature",
  "properties": {
    "gn:admin1_code":"14.0",
    "gn:asciiname":"Taguemount Azzouz",
    "gn:country_code":"DZ",
    "gn:dem":626,
    "gn:feature_class":"P",
    "gn:feature_code":"PPL",
    "gn:name":"Taguemount Azzouz",
    "gn:population":0,
    "gn:timezone":"Africa/Algiers",
    "iso:country":"DZ",
    "wof:name":"Taguemount Azzouz",
    "wof:placetype":"locality"
},
  "geometry": {"coordinates":[4.10818,36.60331],"type":"Point"}
}