{
  "type": "Feature",
  "properties": {
    "gn:admin1_code":"34.0",
    "gn:asciiname":"Anguellou",
    "gn:country_code":"DZ",
    "gn:dem":363,
    "gn:feature_class":"P",
    "gn:feature_code":"PPL",
    "gn:name":"Anguellou",
    "gn:population":0,
    "gn:timezone":"Africa/Algiers",
    "iso:country":"DZ",
    "wof:name":"Anguellou",
    "wof:placetype":"locality"
},
  "geometry": {"coordinates":[0.34134,29.66951],"type":"Point"}
}