{
  "type": "Feature",
  "properties": {
    "gn:admin1_code":"39.0",
    "gn:asciiname":"Mechta Maifrene",
    "gn:country_code":"DZ",
    "gn:dem":866,
    "gn:feature_class":"P",
    "gn:feature_code":"PPL",
    "gn:name":"Mechta Ma\u00effrene",
    "gn:population":0,
    "gn:timezone":"Africa/Algiers",
    "iso:country":"DZ",
    "wof:name":"Mechta Maifrene",
    "wof:placetype":"locality"
},
  "geometry": {"coordinates":[4.63917,35.96361],"type":"Point"}
}