{
  "type": "Feature",
  "properties": {
    "gn:admin1_code":"41.0",
    "gn:asciiname":"Douar el Aadjab",
    "gn:country_code":"DZ",
    "gn:dem":551,
    "gn:feature_class":"P",
    "gn:feature_code":"PPL",
    "gn:name":"Douar el Aadjab",
    "gn:population":0,
    "gn:timezone":"Africa/Algiers",
    "iso:country":"DZ",
    "wof:name":"Douar el Aadjab",
    "wof:placetype":"locality"
},
  "geometry": {"coordinates":[1.10834,36.30765],"type":"Point"}
}