{
  "type": "Feature",
  "properties": {
    "gn:admin1_code":"4.0",
    "gn:asciiname":"Lambleche",
    "gn:country_code":"DZ",
    "gn:dem":678,
    "gn:feature_class":"P",
    "gn:feature_code":"PPL",
    "gn:name":"Lambl\u00e8che",
    "gn:population":0,
    "gn:timezone":"Africa/Algiers",
    "iso:country":"DZ",
    "wof:name":"Lambleche",
    "wof:placetype":"locality"
},
  "geometry": {"coordinates":[6.7034,36.3479],"type":"Point"}
}