{
  "type": "Feature",
  "properties": {
    "gn:admin1_code":"41.0",
    "gn:asciiname":"Lari Ouzou",
    "gn:country_code":"DZ",
    "gn:dem":554,
    "gn:feature_class":"P",
    "gn:feature_code":"PPL",
    "gn:name":"Lari Ouzou",
    "gn:population":0,
    "gn:timezone":"Africa/Algiers",
    "iso:country":"DZ",
    "wof:name":"Lari Ouzou",
    "wof:placetype":"locality"
},
  "geometry": {"coordinates":[1.70361,36.47639],"type":"Point"}
}