{
  "type": "Feature",
  "properties": {
    "gn:admin1_code":"51.0",
    "gn:asciiname":"Ouled Ben Abd er Rehim",
    "gn:country_code":"DZ",
    "gn:dem":810,
    "gn:feature_class":"P",
    "gn:feature_code":"PPL",
    "gn:name":"Ouled Ben Abd er Rehim",
    "gn:population":0,
    "gn:timezone":"Africa/Algiers",
    "iso:country":"DZ",
    "name:und_x_variant":[
        "Douar Ouled Ben Abd el Rehim",
        "Ouled Ben Abd er Rehim"
    ],
    "wof:name":"Ouled Ben Abd er Rehim",
    "wof:placetype":"locality"
},
  "geometry": {"coordinates":[1.05513,35.61335],"type":"Point"}
}