{
  "type": "Feature",
  "properties": {
    "gn:admin1_code":"3.0",
    "gn:asciiname":"El Hammam",
    "gn:country_code":"DZ",
    "gn:dem":1268,
    "gn:feature_class":"P",
    "gn:feature_code":"PPL",
    "gn:name":"El Hammam",
    "gn:population":0,
    "gn:timezone":"Africa/Algiers",
    "iso:country":"DZ",
    "wof:name":"El Hammam",
    "wof:placetype":"locality"
},
  "geometry": {"coordinates":[6.45582,35.27366],"type":"Point"}
}