{
  "type": "Feature",
  "properties": {
    "gn:admin1_code":"41.0",
    "gn:asciiname":"Ouled Bou Henni",
    "gn:country_code":"DZ",
    "gn:dem":238,
    "gn:feature_class":"P",
    "gn:feature_code":"PPL",
    "gn:name":"Ouled Bou Henni",
    "gn:population":0,
    "gn:timezone":"Africa/Algiers",
    "iso:country":"DZ",
    "wof:name":"Ouled Bou Henni",
    "wof:placetype":"locality"
},
  "geometry": {"coordinates":[1.17908,36.01104],"type":"Point"}
}