{
  "type": "Feature",
  "properties": {
    "gn:admin1_code":"27.0",
    "gn:asciiname":"Akba Safra",
    "gn:country_code":"DZ",
    "gn:dem":785,
    "gn:feature_class":"P",
    "gn:feature_code":"PPL",
    "gn:name":"Akba Safra",
    "gn:population":0,
    "gn:timezone":"Africa/Algiers",
    "iso:country":"DZ",
    "wof:name":"Akba Safra",
    "wof:placetype":"locality"
},
  "geometry": {"coordinates":[3.81667,35.36667],"type":"Point"}
}