{
  "type": "Feature",
  "properties": {
    "gn:admin1_code":"19.0",
    "gn:asciiname":"Gueddila",
    "gn:country_code":"DZ",
    "gn:dem":444,
    "gn:feature_class":"P",
    "gn:feature_code":"PPL",
    "gn:name":"Gueddila",
    "gn:population":0,
    "gn:timezone":"Africa/Algiers",
    "iso:country":"DZ",
    "wof:name":"Gueddila",
    "wof:placetype":"locality"
},
  "geometry": {"coordinates":[5.79771,35.06343],"type":"Point"}
}