{
  "type": "Feature",
  "properties": {
    "gn:admin1_code":"14.0",
    "gn:asciiname":"Tagounits",
    "gn:country_code":"DZ",
    "gn:dem":702,
    "gn:feature_class":"P",
    "gn:feature_code":"PPL",
    "gn:name":"Tagounits",
    "gn:population":0,
    "gn:timezone":"Africa/Algiers",
    "iso:country":"DZ",
    "wof:name":"Tagounits",
    "wof:placetype":"locality"
},
  "geometry": {"coordinates":[4.36724,36.59622],"type":"Point"}
}