{
  "type": "Feature",
  "properties": {
    "gn:admin1_code":"41.0",
    "gn:asciiname":"El Mdainia",
    "gn:country_code":"DZ",
    "gn:dem":179,
    "gn:feature_class":"P",
    "gn:feature_code":"PPL",
    "gn:name":"El Mda\u00efnia",
    "gn:population":0,
    "gn:timezone":"Africa/Algiers",
    "iso:country":"DZ",
    "wof:name":"El Mdainia",
    "wof:placetype":"locality"
},
  "geometry": {"coordinates":[1.3368,36.11881],"type":"Point"}
}