{
  "type": "Feature",
  "properties": {
    "gn:admin1_code":"35.0",
    "gn:asciiname":"Ain Defla Seghira",
    "gn:country_code":"DZ",
    "gn:dem":337,
    "gn:feature_class":"P",
    "gn:feature_code":"PPL",
    "gn:name":"A\u00efn Defla Seghira",
    "gn:population":0,
    "gn:timezone":"Africa/Algiers",
    "iso:country":"DZ",
    "wof:name":"Ain Defla Seghira",
    "wof:placetype":"locality"
},
  "geometry": {"coordinates":[2.02775,36.21138],"type":"Point"}
}