{
  "type": "Feature",
  "properties": {
    "gn:admin1_code":"41.0",
    "gn:asciiname":"Beni Haoua",
    "gn:country_code":"DZ",
    "gn:dem":23,
    "gn:feature_class":"P",
    "gn:feature_code":"PPL",
    "gn:name":"Beni Haoua",
    "gn:population":0,
    "gn:timezone":"Africa/Algiers",
    "iso:country":"DZ",
    "name:ara_x_preferred":[
        "\u0628\u0646\u0649 \u062d\u0648\u0627\u0621"
    ],
    "name:fra_x_historical":[
        "Francis",
        "Francis-Garnier",
        "Port Brierer"
    ],
    "name:fra_x_preferred":[
        "Francis"
    ],
    "name:fra_x_variant":[
        "Francis-Garnier",
        "Port Brierer"
    ],
    "name:und_x_variant":[
        "B\u00e9ni Haoua"
    ],
    "wof:name":"Beni Haoua",
    "wof:placetype":"locality"
},
  "geometry": {"coordinates":[1.56891,36.5311],"type":"Point"}
}