{
  "type": "Feature",
  "properties": {
    "gn:admin1_code":"41.0",
    "gn:asciiname":"Beni Haoua",
    "gn:country_code":"DZ",
    "gn:dem":23,
    "gn:feature_class":"P",
    "gn:feature_code":"PPL",
    "gn:name":"Beni Haoua",
    "gn:population":0,
    "gn:timezone":"Africa/Algiers",
    "iso:country":"DZ",
    "name:ara_x_preferred":[
        "\u0628\u0646\u0649 \u062d\u0648\u0627\u0621"
    ],
    "name:ara_x_variant":[
        "\u0628\u0646\u064a \u062d\u0648\u0627\u0621"
    ],
    "name:azb_x_preferred":[
        "\u0628\u0646\u06cc \u062d\u0648\u0627\u0621"
    ],
    "name:fas_x_preferred":[
        "\u0628\u0646\u06cc \u062d\u0648\u0627\u0621"
    ],
    "name:fra_x_historical":[
        "Francis",
        "Francis-Garnier",
        "Port Brierer"
    ],
    "name:fra_x_preferred":[
        "Francis"
    ],
    "name:fra_x_variant":[
        "Francis-Garnier",
        "Port Brierer",
        "Beni Haoua"
    ],
    "name:ita_x_preferred":[
        "Beni Haoua"
    ],
    "name:kab_x_preferred":[
        "Ayt \u1e24ewwa"
    ],
    "name:msa_x_preferred":[
        "Beni Haoua"
    ],
    "name:por_x_preferred":[
        "Beni Haoua"
    ],
    "name:ron_x_preferred":[
        "Beni Haoua"
    ],
    "name:und_x_variant":[
        "B\u00e9ni Haoua"
    ],
    "name:urd_x_preferred":[
        "\u0628\u0646\u06cc \u062d\u0648\u0627\u0621"
    ],
    "name:vie_x_preferred":[
        "Beni Haoua"
    ],
    "name:zho_x_preferred":[
        "\u8c9d\u5c3c\u54c8\u74e6"
    ],
    "wof:name":"Beni Haoua",
    "wof:placetype":"locality"
},
  "geometry": {"coordinates":[1.56891,36.5311],"type":"Point"}
}