{
  "type": "Feature",
  "properties": {
    "gn:admin1_code":"26.0",
    "gn:asciiname":"Douar el Hadj el Arbi",
    "gn:country_code":"DZ",
    "gn:dem":616,
    "gn:feature_class":"P",
    "gn:feature_code":"PPL",
    "gn:name":"Douar el Hadj el Arbi",
    "gn:population":0,
    "gn:timezone":"Africa/Algiers",
    "iso:country":"DZ",
    "wof:name":"Douar el Hadj el Arbi",
    "wof:placetype":"locality"
},
  "geometry": {"coordinates":[0.29639,35.56083],"type":"Point"}
}