{
  "type": "Feature",
  "properties": {
    "gn:admin1_code":"35.0",
    "gn:asciiname":"Hellil",
    "gn:country_code":"DZ",
    "gn:dem":301,
    "gn:feature_class":"P",
    "gn:feature_code":"PPL",
    "gn:name":"Hellil",
    "gn:population":0,
    "gn:timezone":"Africa/Algiers",
    "iso:country":"DZ",
    "wof:name":"Hellil",
    "wof:placetype":"locality"
},
  "geometry": {"coordinates":[2.33877,36.22897],"type":"Point"}
}