{
  "type": "Feature",
  "properties": {
    "gn:admin1_code":"12.0",
    "gn:asciiname":"Bir el Arche",
    "gn:country_code":"DZ",
    "gn:dem":951,
    "gn:feature_class":"P",
    "gn:feature_code":"PPL",
    "gn:name":"Bir el Arche",
    "gn:population":0,
    "gn:timezone":"Africa/Algiers",
    "iso:country":"DZ",
    "name:ara_x_preferred":[
        "\u0628\u0626\u0631 \u0627\u0644\u0639\u0631\u0634"
    ],
    "name:azb_x_preferred":[
        "\u0628\u0626\u0631 \u0639\u0631\u0634"
    ],
    "name:fas_x_preferred":[
        "\u0628\u0626\u0631 \u0639\u0631\u0634"
    ],
    "name:fra_x_preferred":[
        "Bir El Arch"
    ],
    "name:ita_x_preferred":[
        "Bir El Arch"
    ],
    "name:msa_x_preferred":[
        "Bir El Arch"
    ],
    "name:por_x_preferred":[
        "Bir El Arch"
    ],
    "name:ron_x_preferred":[
        "Bir El Arch"
    ],
    "name:spa_x_preferred":[
        "Bir El Arch"
    ],
    "name:und_x_variant":[
        "Navarin",
        "Bir-Lahrech",
        "Bir el Arch",
        "Bir el Arche"
    ],
    "name:vie_x_preferred":[
        "Bir El Arch"
    ],
    "wof:name":"Bir el Arche",
    "wof:placetype":"locality"
},
  "geometry": {"coordinates":[5.83904,36.13083],"type":"Point"}
}