{
  "type": "Feature",
  "properties": {
    "gn:admin1_code":"53.0",
    "gn:asciiname":"Dunqulah",
    "gn:country_code":"DZ",
    "gn:dem":464,
    "gn:feature_class":"P",
    "gn:feature_code":"PPL",
    "gn:name":"Dunqulah",
    "gn:population":0,
    "gn:timezone":"Africa/Algiers",
    "iso:country":"DZ",
    "wof:name":"Dunqulah",
    "wof:placetype":"locality"
},
  "geometry": {"coordinates":[3.48333,19.16667],"type":"Point"}
}