{
  "type": "Feature",
  "properties": {
    "gn:admin1_code":"0.0",
    "gn:asciiname":"El Aouainia",
    "gn:country_code":"DZ",
    "gn:dem":713,
    "gn:feature_class":"P",
    "gn:feature_code":"PPL",
    "gn:name":"El Aoua\u00efnia",
    "gn:population":0,
    "gn:timezone":"Africa/Algiers",
    "iso:country":"DZ",
    "wof:name":"El Aouainia",
    "wof:placetype":"locality"
},
  "geometry": {"coordinates":[2.43333,36.08333],"type":"Point"}
}