{
  "type": "Feature",
  "properties": {
    "gn:admin1_code":"34.0",
    "gn:asciiname":"Allamellal Sidi Cherif",
    "gn:country_code":"DZ",
    "gn:dem":256,
    "gn:feature_class":"P",
    "gn:feature_code":"PPL",
    "gn:name":"Allamellal Sidi Cherif",
    "gn:population":0,
    "gn:timezone":"Africa/Algiers",
    "iso:country":"DZ",
    "wof:name":"Allamellal Sidi Cherif",
    "wof:placetype":"locality"
},
  "geometry": {"coordinates":[0.2655,29.29587],"type":"Point"}
}