{
  "type": "Feature",
  "properties": {
    "gn:admin1_code":"14.0",
    "gn:asciiname":"Taourirt Mimoun",
    "gn:country_code":"DZ",
    "gn:dem":713,
    "gn:feature_class":"P",
    "gn:feature_code":"PPL",
    "gn:name":"Taourirt Mimoun",
    "gn:population":0,
    "gn:timezone":"Africa/Algiers",
    "iso:country":"DZ",
    "wof:name":"Taourirt Mimoun",
    "wof:placetype":"locality"
},
  "geometry": {"coordinates":[4.20172,36.57028],"type":"Point"}
}