{
  "type": "Feature",
  "properties": {
    "gn:admin1_code":"29.0",
    "gn:asciiname":"Mechta Mdareg Narou",
    "gn:country_code":"DZ",
    "gn:dem":869,
    "gn:feature_class":"P",
    "gn:feature_code":"PPL",
    "gn:name":"Mechta Mdareg Narou",
    "gn:population":0,
    "gn:timezone":"Africa/Algiers",
    "iso:country":"DZ",
    "wof:name":"Mechta Mdareg Narou",
    "wof:placetype":"locality"
},
  "geometry": {"coordinates":[7.29572,35.717],"type":"Point"}
}