{
  "type": "Feature",
  "properties": {
    "gn:admin1_code":"27.0",
    "gn:asciiname":"Bou Amoud",
    "gn:country_code":"DZ",
    "gn:dem":555,
    "gn:feature_class":"P",
    "gn:feature_code":"PPL",
    "gn:name":"Bou Amoud",
    "gn:population":0,
    "gn:timezone":"Africa/Algiers",
    "iso:country":"DZ",
    "wof:name":"Bou Amoud",
    "wof:placetype":"locality"
},
  "geometry": {"coordinates":[3.9081,35.77985],"type":"Point"}
}