{
  "type": "Feature",
  "properties": {
    "gn:admin1_code":"52.0",
    "gn:asciiname":"Mechta Sidi Ameur",
    "gn:country_code":"DZ",
    "gn:dem":993,
    "gn:feature_class":"P",
    "gn:feature_code":"PPL",
    "gn:name":"Mechta Sidi Ameur",
    "gn:population":0,
    "gn:timezone":"Africa/Algiers",
    "iso:country":"DZ",
    "wof:name":"Mechta Sidi Ameur",
    "wof:placetype":"locality"
},
  "geometry": {"coordinates":[7.64833,36.16757],"type":"Point"}
}