{
  "type": "Feature",
  "properties": {
    "gn:admin1_code":"6.0",
    "gn:asciiname":"Bled el Hamadia",
    "gn:country_code":"DZ",
    "gn:dem":1050,
    "gn:feature_class":"P",
    "gn:feature_code":"PPL",
    "gn:name":"Bled el Hamadia",
    "gn:population":0,
    "gn:timezone":"Africa/Algiers",
    "iso:country":"DZ",
    "wof:name":"Bled el Hamadia",
    "wof:placetype":"locality"
},
  "geometry": {"coordinates":[3.48931,36.13922],"type":"Point"}
}