{
  "type": "Feature",
  "properties": {
    "gn:admin1_code":"40.0",
    "gn:asciiname":"Ait Slimane",
    "gn:country_code":"DZ",
    "gn:dem":479,
    "gn:feature_class":"P",
    "gn:feature_code":"PPL",
    "gn:name":"A\u00eft Slimane",
    "gn:population":0,
    "gn:timezone":"Africa/Algiers",
    "iso:country":"DZ",
    "wof:name":"Ait Slimane",
    "wof:placetype":"locality"
},
  "geometry": {"coordinates":[3.85805,36.6784],"type":"Point"}
}