{
  "type": "Feature",
  "properties": {
    "gn:admin1_code":"15.0",
    "gn:asciiname":"Douar Chaib Rasso",
    "gn:country_code":"DZ",
    "gn:dem":267,
    "gn:feature_class":"P",
    "gn:feature_code":"PPL",
    "gn:name":"Douar Cha\u00efb Rasso",
    "gn:population":0,
    "gn:timezone":"Africa/Algiers",
    "iso:country":"DZ",
    "wof:name":"Douar Chaib Rasso",
    "wof:placetype":"locality"
},
  "geometry": {"coordinates":[-2.15,35.06667],"type":"Point"}
}