{
  "type": "Feature",
  "properties": {
    "gn:admin1_code":"35.0",
    "gn:asciiname":"Kouesmia",
    "gn:country_code":"DZ",
    "gn:dem":326,
    "gn:feature_class":"P",
    "gn:feature_code":"PPL",
    "gn:name":"Kouesmia",
    "gn:population":0,
    "gn:timezone":"Africa/Algiers",
    "iso:country":"DZ",
    "wof:name":"Kouesmia",
    "wof:placetype":"locality"
},
  "geometry": {"coordinates":[2.14777,36.19208],"type":"Point"}
}