{
  "type": "Feature",
  "properties": {
    "gn:admin1_code":"12.0",
    "gn:asciiname":"Mechta Teksra",
    "gn:country_code":"DZ",
    "gn:dem":811,
    "gn:feature_class":"P",
    "gn:feature_code":"PPL",
    "gn:name":"Mechta Teksra",
    "gn:population":0,
    "gn:timezone":"Africa/Algiers",
    "iso:country":"DZ",
    "name:und_x_variant":[
        "Mechtat Teksra",
        "Mechta Teksra"
    ],
    "wof:name":"Mechta Teksra",
    "wof:placetype":"locality"
},
  "geometry": {"coordinates":[5.01265,36.32932],"type":"Point"}
}