{
  "type": "Feature",
  "properties": {
    "gn:admin1_code":"12.0",
    "gn:asciiname":"Djemmana",
    "gn:country_code":"DZ",
    "gn:dem":1052,
    "gn:feature_class":"P",
    "gn:feature_code":"PPL",
    "gn:name":"Djemmana",
    "gn:population":0,
    "gn:timezone":"Africa/Algiers",
    "iso:country":"DZ",
    "wof:name":"Djemmana",
    "wof:placetype":"locality"
},
  "geometry": {"coordinates":[5.42962,35.79896],"type":"Point"}
}