{
  "type": "Feature",
  "properties": {
    "gn:admin1_code":"26.0",
    "gn:asciiname":"Douar Stayta",
    "gn:country_code":"DZ",
    "gn:dem":460,
    "gn:feature_class":"P",
    "gn:feature_code":"PPLL",
    "gn:name":"Douar Stayta",
    "gn:population":0,
    "gn:timezone":"Africa/Algiers",
    "iso:country":"DZ",
    "wof:name":"Douar Stayta",
    "wof:placetype":"locality"
},
  "geometry": {"coordinates":[0.06707,35.29163],"type":"Point"}
}