{
  "type": "Feature",
  "properties": {
    "gn:admin1_code":"12.0",
    "gn:asciiname":"Takendoukt",
    "gn:country_code":"DZ",
    "gn:dem":730,
    "gn:feature_class":"P",
    "gn:feature_code":"PPL",
    "gn:name":"Takendoukt",
    "gn:population":0,
    "gn:timezone":"Africa/Algiers",
    "iso:country":"DZ",
    "wof:name":"Takendoukt",
    "wof:placetype":"locality"
},
  "geometry": {"coordinates":[5.18333,36.45],"type":"Point"}
}