{
  "type": "Feature",
  "properties": {
    "gn:admin1_code":"13.0",
    "gn:asciiname":"Douar Ouled el Hadj",
    "gn:country_code":"DZ",
    "gn:dem":917,
    "gn:feature_class":"P",
    "gn:feature_code":"PPL",
    "gn:name":"Douar Ouled el Hadj",
    "gn:population":0,
    "gn:timezone":"Africa/Algiers",
    "iso:country":"DZ",
    "name:und_x_variant":[
        "Oulad Hadj",
        "Douar Oulad Hadj",
        "Douar Ouled el Hadj"
    ],
    "wof:name":"Douar Ouled el Hadj",
    "wof:placetype":"locality"
},
  "geometry": {"coordinates":[0.95698,35.00996],"type":"Point"}
}