{
  "type": "Feature",
  "properties": {
    "gn:admin1_code":"55.0",
    "gn:asciiname":"Oued Sidi Slimane",
    "gn:country_code":"DZ",
    "gn:dem":136,
    "gn:feature_class":"P",
    "gn:feature_code":"PPL",
    "gn:name":"Oued Sidi Slimane",
    "gn:population":0,
    "gn:timezone":"Africa/Algiers",
    "iso:country":"DZ",
    "wof:name":"Oued Sidi Slimane",
    "wof:placetype":"locality"
},
  "geometry": {"coordinates":[3.00172,36.66278],"type":"Point"}
}