{
  "type": "Feature",
  "properties": {
    "gn:admin1_code":"14.0",
    "gn:asciiname":"Maraghna",
    "gn:country_code":"DZ",
    "gn:dem":888,
    "gn:feature_class":"P",
    "gn:feature_code":"PPL",
    "gn:name":"Maraghna",
    "gn:population":0,
    "gn:timezone":"Africa/Algiers",
    "iso:country":"DZ",
    "wof:name":"Maraghna",
    "wof:placetype":"locality"
},
  "geometry": {"coordinates":[4.43255,36.56146],"type":"Point"}
}