{
  "type": "Feature",
  "properties": {
    "gn:admin1_code":"30.0",
    "gn:asciiname":"Sidi Ali Boussidi",
    "gn:country_code":"DZ",
    "gn:dem":608,
    "gn:feature_class":"P",
    "gn:feature_code":"PPL",
    "gn:name":"Sidi Ali Boussidi",
    "gn:population":0,
    "gn:timezone":"Africa/Algiers",
    "iso:country":"DZ",
    "name:und_x_variant":[
        "Parmentier",
        "A\u00efne el Hadjar",
        "Sidi Ali Boussidi"
    ],
    "wof:name":"Sidi Ali Boussidi",
    "wof:placetype":"locality"
},
  "geometry": {"coordinates":[-0.83034,35.1028],"type":"Point"}
}