{
  "type": "Feature",
  "properties": {
    "gn:admin1_code":"30.0",
    "gn:asciiname":"Sidi Ali Boussidi",
    "gn:country_code":"DZ",
    "gn:dem":608,
    "gn:feature_class":"P",
    "gn:feature_code":"PPL",
    "gn:name":"Sidi Ali Boussidi",
    "gn:population":0,
    "gn:timezone":"Africa/Algiers",
    "iso:country":"DZ",
    "name:ara_x_preferred":[
        "\u0633\u064a\u062f\u064a \u0639\u0644\u064a \u0628\u0648\u0633\u064a\u062f\u064a"
    ],
    "name:azb_x_preferred":[
        "\u0633\u06cc\u062f\u06cc \u0639\u0644\u06cc \u0628\u0648\u0633\u06cc\u062f\u06cc"
    ],
    "name:fas_x_preferred":[
        "\u0633\u06cc\u062f\u06cc \u0639\u0644\u06cc \u0628\u0648\u0633\u06cc\u062f\u06cc"
    ],
    "name:fra_x_preferred":[
        "Sidi Ali Boussidi"
    ],
    "name:ita_x_preferred":[
        "Sidi Ali Boussidi"
    ],
    "name:kab_x_preferred":[
        "Sidi \u0190li Busidi"
    ],
    "name:msa_x_preferred":[
        "Sidi Ali Boussidi"
    ],
    "name:pol_x_preferred":[
        "Sidi Ali Bu Sidi"
    ],
    "name:por_x_preferred":[
        "Sidi Ali Boussidi"
    ],
    "name:ron_x_preferred":[
        "Sidi Ali Boussidi"
    ],
    "name:spa_x_preferred":[
        "Sidi Ali Boussidi"
    ],
    "name:und_x_variant":[
        "Parmentier",
        "A\u00efne el Hadjar",
        "Sidi Ali Boussidi"
    ],
    "name:vie_x_preferred":[
        "Sidi Ali Boussidi"
    ],
    "wof:name":"Sidi Ali Boussidi",
    "wof:placetype":"locality"
},
  "geometry": {"coordinates":[-0.83034,35.1028],"type":"Point"}
}