{
  "type": "Feature",
  "properties": {
    "gn:admin1_code":"26.0",
    "gn:asciiname":"Slatna",
    "gn:country_code":"DZ",
    "gn:dem":642,
    "gn:feature_class":"P",
    "gn:feature_code":"PPL",
    "gn:name":"Slatna",
    "gn:population":0,
    "gn:timezone":"Africa/Algiers",
    "iso:country":"DZ",
    "name:und_x_variant":[
        "Douar Lezra",
        "Slatna",
        "Dar Hadj el Mokhtar"
    ],
    "wof:name":"Slatna",
    "wof:placetype":"locality"
},
  "geometry": {"coordinates":[0.18663,35.40641],"type":"Point"}
}