{
  "type": "Feature",
  "properties": {
    "gn:admin1_code":"26.0",
    "gn:asciiname":"Slatna",
    "gn:country_code":"DZ",
    "gn:dem":642,
    "gn:feature_class":"P",
    "gn:feature_code":"PPL",
    "gn:name":"Slatna",
    "gn:population":0,
    "gn:timezone":"Africa/Algiers",
    "iso:country":"DZ",
    "name:bos_x_preferred":[
        "Slatna"
    ],
    "name:hrv_x_preferred":[
        "Slatna"
    ],
    "name:nld_x_preferred":[
        "Slatna"
    ],
    "name:pol_x_preferred":[
        "Slatna"
    ],
    "name:ron_x_preferred":[
        "Slatna"
    ],
    "name:slv_x_preferred":[
        "Slatna"
    ],
    "name:ukr_x_preferred":[
        "\u0421\u043b\u0430\u0442\u043d\u0430"
    ],
    "name:und_x_variant":[
        "Douar Lezra",
        "Slatna",
        "Dar Hadj el Mokhtar"
    ],
    "wof:name":"Slatna",
    "wof:placetype":"locality"
},
  "geometry": {"coordinates":[0.18663,35.40641],"type":"Point"}
}