{
  "type": "Feature",
  "properties": {
    "gn:admin1_code":"18.0",
    "gn:asciiname":"Oulad Aied",
    "gn:country_code":"DZ",
    "gn:dem":806,
    "gn:feature_class":"P",
    "gn:feature_code":"PPL",
    "gn:name":"Oulad A\u00efed",
    "gn:population":0,
    "gn:timezone":"Africa/Algiers",
    "iso:country":"DZ",
    "name:und_x_variant":[
        "Ouled A\u00efed",
        "Oulad A\u00efed"
    ],
    "wof:name":"Oulad Aied",
    "wof:placetype":"locality"
},
  "geometry": {"coordinates":[5.4154,36.49172],"type":"Point"}
}