{
  "type": "Feature",
  "properties": {
    "gn:admin1_code":"35.0",
    "gn:asciiname":"Tarik Ibn Ziad",
    "gn:country_code":"DZ",
    "gn:dem":648,
    "gn:feature_class":"P",
    "gn:feature_code":"PPL",
    "gn:name":"Tarik Ibn Ziad",
    "gn:population":0,
    "gn:timezone":"Africa/Algiers",
    "iso:country":"DZ",
    "name:und_x_variant":[
        "Marbot",
        "Tarik Ibn Ziyad",
        "Tarik Ibn Zayad",
        "Tarik Ibn Zyad",
        "Tarik Ibn Ziad"
    ],
    "wof:name":"Tarik Ibn Ziad",
    "wof:placetype":"locality"
},
  "geometry": {"coordinates":[2.14558,35.99377],"type":"Point"}
}