{
  "type": "Feature",
  "properties": {
    "gn:admin1_code":"3.0",
    "gn:asciiname":"Oulad Abed",
    "gn:country_code":"DZ",
    "gn:dem":728,
    "gn:feature_class":"P",
    "gn:feature_code":"PPL",
    "gn:name":"Oulad Abed",
    "gn:population":0,
    "gn:timezone":"Africa/Algiers",
    "iso:country":"DZ",
    "wof:name":"Oulad Abed",
    "wof:placetype":"locality"
},
  "geometry": {"coordinates":[6.20608,35.08161],"type":"Point"}
}