{
  "type": "Feature",
  "properties": {
    "iso:country":"DZ",
    "name:ara_x_preferred":[
        "\u0627\u0644\u0639\u0637\u0641"
    ],
    "name:arz_x_preferred":[
        "\u0627\u0644\u0639\u0637\u0641"
    ],
    "name:azb_x_preferred":[
        "\u0639\u0637\u0641"
    ],
    "name:deu_x_preferred":[
        "El Atteuf"
    ],
    "name:eng_x_preferred":[
        "El Atteuf"
    ],
    "name:fas_x_preferred":[
        "\u0639\u0637\u0641"
    ],
    "name:fra_x_preferred":[
        "El Atteuf"
    ],
    "name:ind_x_preferred":[
        "El Atteuf"
    ],
    "name:ita_x_preferred":[
        "El Atteuf"
    ],
    "name:jpn_x_preferred":[
        "\u30a8\u30eb\uff1d\u30a2\u30c3\u30c8\u30a5\u30d5"
    ],
    "name:kab_x_preferred":[
        "L\u025ba\u1e6def"
    ],
    "name:msa_x_preferred":[
        "El Atteuf"
    ],
    "name:nan_x_preferred":[
        "El Atteuf"
    ],
    "name:nld_x_preferred":[
        "El Atteuf"
    ],
    "name:por_x_preferred":[
        "El Atteuf"
    ],
    "name:ron_x_preferred":[
        "El Atteuf"
    ],
    "name:spa_x_preferred":[
        "El Atteuf"
    ],
    "name:vie_x_preferred":[
        "El Atteuf"
    ],
    "name:zho_x_preferred":[
        "\u963f\u63a8\u592b"
    ],
    "qs:gn_country":"DZ",
    "qs:gn_fcode":"PPL",
    "qs:gn_pop":0,
    "qs:name":"El Ateuf",
    "qs:name_adm0":"\u0627\u0644\u062c\u0632\u0627\u0626\u0631",
    "qs:name_adm1":"Ghardaia",
    "qs:photos":8,
    "qs:photos_1k":2,
    "qs:photos_9k":1,
    "qs:photos_9r":1,
    "qs:photos_all":8,
    "qs:photos_sr":1,
    "qs:placetype":"Town",
    "qs:pop_sr":"0",
    "qs:woe_adm0":23424740,
    "wd:wordcount":346,
    "wof:name":"El Ateuf",
    "wof:placetype":"locality"
},
  "geometry": {"coordinates":[3.74923,32.47523],"type":"Point"}
}