{
  "type": "Feature",
  "properties": {
    "gn:admin1_code":"43.0",
    "gn:asciiname":"El Berd",
    "gn:country_code":"DZ",
    "gn:dem":19,
    "gn:feature_class":"P",
    "gn:feature_code":"PPL",
    "gn:name":"El Berd",
    "gn:population":0,
    "gn:timezone":"Africa/Algiers",
    "iso:country":"DZ",
    "wof:name":"El Berd",
    "wof:placetype":"locality"
},
  "geometry": {"coordinates":[6.02072,33.68755],"type":"Point"}
}