{
  "type": "Feature",
  "properties": {
    "gn:admin1_code":"31.0",
    "gn:asciiname":"Oumm Toub",
    "gn:country_code":"DZ",
    "gn:dem":239,
    "gn:feature_class":"P",
    "gn:feature_code":"PPL",
    "gn:name":"Oumm To\u00fbb",
    "gn:population":0,
    "gn:timezone":"Africa/Algiers",
    "iso:country":"DZ",
    "name:und_x_variant":[
        "Souk el Metoub",
        "Oum Toub",
        "Oumm To\u00fbb"
    ],
    "wof:name":"Oumm Toub",
    "wof:placetype":"locality"
},
  "geometry": {"coordinates":[6.57201,36.68878],"type":"Point"}
}