{
  "type": "Feature",
  "properties": {
    "gn:admin1_code":"31.0",
    "gn:asciiname":"Oumm Toub",
    "gn:country_code":"DZ",
    "gn:dem":239,
    "gn:feature_class":"P",
    "gn:feature_code":"PPL",
    "gn:name":"Oumm To\u00fbb",
    "gn:population":0,
    "gn:timezone":"Africa/Algiers",
    "iso:country":"DZ",
    "name:ara_x_preferred":[
        "\u0623\u0645 \u0627\u0644\u0637\u0648\u0628"
    ],
    "name:azb_x_preferred":[
        "\u0627\u0645 \u0637\u0648\u0628"
    ],
    "name:fas_x_preferred":[
        "\u0627\u0645 \u0637\u0648\u0628"
    ],
    "name:fra_x_preferred":[
        "Oum Toub"
    ],
    "name:ita_x_preferred":[
        "Oum Toub"
    ],
    "name:kab_x_preferred":[
        "Um \u1e6c\u1e6dub"
    ],
    "name:msa_x_preferred":[
        "Oum Toub"
    ],
    "name:por_x_preferred":[
        "Oum Toub"
    ],
    "name:ron_x_preferred":[
        "Oum Toub"
    ],
    "name:spa_x_preferred":[
        "Oum Toub"
    ],
    "name:und_x_variant":[
        "Souk el Metoub",
        "Oum Toub",
        "Oumm To\u00fbb"
    ],
    "name:vie_x_preferred":[
        "Oum Toub"
    ],
    "name:zho_x_preferred":[
        "\u70cf\u59c6\u5716\u535c"
    ],
    "wof:name":"Oumm Toub",
    "wof:placetype":"locality"
},
  "geometry": {"coordinates":[6.57201,36.68878],"type":"Point"}
}