{
  "type": "Feature",
  "properties": {
    "gn:admin1_code":"45.0",
    "gn:asciiname":"At Isguen",
    "gn:country_code":"DZ",
    "gn:dem":524,
    "gn:feature_class":"P",
    "gn:feature_code":"PPL",
    "gn:name":"At Isguen",
    "gn:population":0,
    "gn:timezone":"Africa/Algiers",
    "iso:country":"DZ",
    "wof:name":"At Isguen",
    "wof:placetype":"locality"
},
  "geometry": {"coordinates":[3.41,32.28],"type":"Point"}
}