{
  "type": "Feature",
  "properties": {
    "gn:admin1_code":"6.0",
    "gn:asciiname":"Nahmine et Tahta",
    "gn:country_code":"DZ",
    "gn:dem":566,
    "gn:feature_class":"P",
    "gn:feature_code":"PPL",
    "gn:name":"Nahmine et Tahta",
    "gn:population":0,
    "gn:timezone":"Africa/Algiers",
    "iso:country":"DZ",
    "wof:name":"Nahmine et Tahta",
    "wof:placetype":"locality"
},
  "geometry": {"coordinates":[3.3275,36.42953],"type":"Point"}
}