{
  "type": "Feature",
  "properties": {
    "gn:admin1_code":"13.0",
    "gn:asciiname":"Douar Ouled Mohamed",
    "gn:country_code":"DZ",
    "gn:dem":1028,
    "gn:feature_class":"P",
    "gn:feature_code":"PPL",
    "gn:name":"Douar Ouled Mohamed",
    "gn:population":0,
    "gn:timezone":"Africa/Algiers",
    "iso:country":"DZ",
    "wof:name":"Douar Ouled Mohamed",
    "wof:placetype":"locality"
},
  "geometry": {"coordinates":[0.94362,35.19815],"type":"Point"}
}