{
  "type": "Feature",
  "properties": {
    "gn:admin1_code":"13.0",
    "gn:asciiname":"El M'Razig",
    "gn:country_code":"DZ",
    "gn:dem":647,
    "gn:feature_class":"P",
    "gn:feature_code":"PPL",
    "gn:name":"El M\u2019Razig",
    "gn:population":0,
    "gn:timezone":"Africa/Algiers",
    "iso:country":"DZ",
    "wof:name":"El M'Razig",
    "wof:placetype":"locality"
},
  "geometry": {"coordinates":[0.72623,35.23011],"type":"Point"}
}