{
  "type": "Feature",
  "properties": {
    "gn:admin1_code":"6.0",
    "gn:asciiname":"Dar Ben Saha Zine",
    "gn:country_code":"DZ",
    "gn:dem":723,
    "gn:feature_class":"P",
    "gn:feature_code":"PPL",
    "gn:name":"Dar Ben Saha Zine",
    "gn:population":0,
    "gn:timezone":"Africa/Algiers",
    "iso:country":"DZ",
    "wof:name":"Dar Ben Saha Zine",
    "wof:placetype":"locality"
},
  "geometry": {"coordinates":[2.44136,35.51634],"type":"Point"}
}