{
  "type": "Feature",
  "properties": {
    "gn:admin1_code":"51.0",
    "gn:asciiname":"Douar Ouled Abed",
    "gn:country_code":"DZ",
    "gn:dem":99,
    "gn:feature_class":"P",
    "gn:feature_code":"PPL",
    "gn:name":"Douar Ouled Abed",
    "gn:population":0,
    "gn:timezone":"Africa/Algiers",
    "iso:country":"DZ",
    "name:und_x_variant":[
        "Mechtat Oulad Habed"
    ],
    "wof:name":"Douar Ouled Abed",
    "wof:placetype":"locality"
},
  "geometry": {"coordinates":[0.7236,35.85878],"type":"Point"}
}