{
  "type": "Feature",
  "properties": {
    "gn:admin1_code":"3.0",
    "gn:asciiname":"Hammam Sidi el Hadj",
    "gn:country_code":"DZ",
    "gn:dem":391,
    "gn:feature_class":"P",
    "gn:feature_code":"PPL",
    "gn:name":"Hammam Sidi el Hadj",
    "gn:population":0,
    "gn:timezone":"Africa/Algiers",
    "iso:country":"DZ",
    "wof:name":"Hammam Sidi el Hadj",
    "wof:placetype":"locality"
},
  "geometry": {"coordinates":[5.61772,35.10264],"type":"Point"}
}