{
  "type": "Feature",
  "properties": {
    "gn:admin1_code":"51.0",
    "gn:asciiname":"Douar Gueithana",
    "gn:country_code":"DZ",
    "gn:dem":267,
    "gn:feature_class":"P",
    "gn:feature_code":"PPLL",
    "gn:name":"Douar Gueithana",
    "gn:population":0,
    "gn:timezone":"Africa/Algiers",
    "iso:country":"DZ",
    "wof:name":"Douar Gueithana",
    "wof:placetype":"locality"
},
  "geometry": {"coordinates":[0.2775,35.65777999999999],"type":"Point"}
}