{
  "type": "Feature",
  "properties": {
    "gn:admin1_code":"51.0",
    "gn:asciiname":"Douar Ouled Allel",
    "gn:country_code":"DZ",
    "gn:dem":144,
    "gn:feature_class":"P",
    "gn:feature_code":"PPL",
    "gn:name":"Douar Ouled Allel",
    "gn:population":0,
    "gn:timezone":"Africa/Algiers",
    "iso:country":"DZ",
    "name:und_x_variant":[
        "Oulad Allal",
        "Douar Oulad Allal",
        "Douar Ouled Allel"
    ],
    "wof:name":"Douar Ouled Allel",
    "wof:placetype":"locality"
},
  "geometry": {"coordinates":[0.63065,35.71406],"type":"Point"}
}