{
  "type": "Feature",
  "properties": {
    "gn:admin1_code":"35.0",
    "gn:asciiname":"Ouled Khaled",
    "gn:country_code":"DZ",
    "gn:dem":431,
    "gn:feature_class":"P",
    "gn:feature_code":"PPL",
    "gn:name":"Ouled Khaled",
    "gn:population":0,
    "gn:timezone":"Africa/Algiers",
    "iso:country":"DZ",
    "name:ara_x_preferred":[
        "\u0623\u0648\u0644\u0627\u062f \u062e\u0627\u0644\u062f"
    ],
    "name:azb_x_preferred":[
        "\u0627\u0648\u0644\u0627\u062f \u062e\u0627\u0644\u062f"
    ],
    "name:fas_x_preferred":[
        "\u0627\u0648\u0644\u0627\u062f \u062e\u0627\u0644\u062f"
    ],
    "name:fra_x_preferred":[
        "Ouled Khaled"
    ],
    "name:ita_x_preferred":[
        "Ouled Khaled"
    ],
    "name:kab_x_preferred":[
        "Wlad Xaled"
    ],
    "name:msa_x_preferred":[
        "Ouled Khaled"
    ],
    "name:por_x_preferred":[
        "Ouled Khaled"
    ],
    "name:ron_x_preferred":[
        "Ouled Khaled"
    ],
    "name:spa_x_preferred":[
        "Ouled Khaled"
    ],
    "name:vie_x_preferred":[
        "Ouled Khaled"
    ],
    "wof:name":"Ouled Khaled",
    "wof:placetype":"locality"
},
  "geometry": {"coordinates":[2.31984,36.13541],"type":"Point"}
}