{
  "type": "Feature",
  "properties": {
    "gn:admin1_code":"41.0",
    "gn:asciiname":"Douar Ouled Henni",
    "gn:country_code":"DZ",
    "gn:dem":342,
    "gn:feature_class":"P",
    "gn:feature_code":"PPL",
    "gn:name":"Douar Ouled Henni",
    "gn:population":0,
    "gn:timezone":"Africa/Algiers",
    "iso:country":"DZ",
    "wof:name":"Douar Ouled Henni",
    "wof:placetype":"locality"
},
  "geometry": {"coordinates":[1.16808,36.23618],"type":"Point"}
}