{
  "type": "Feature",
  "properties": {
    "gn:admin1_code":"18.0",
    "gn:asciiname":"Tiksarine",
    "gn:country_code":"DZ",
    "gn:dem":776,
    "gn:feature_class":"P",
    "gn:feature_code":"PPL",
    "gn:name":"Tiksarine",
    "gn:population":0,
    "gn:timezone":"Africa/Algiers",
    "iso:country":"DZ",
    "name:und_x_variant":[
        "Tikssarine",
        "Tiksarine"
    ],
    "wof:name":"Tiksarine",
    "wof:placetype":"locality"
},
  "geometry": {"coordinates":[4.80944,36.52517],"type":"Point"}
}