{
  "type": "Feature",
  "properties": {
    "gn:admin1_code":"51.0",
    "gn:asciiname":"Douar Draissia",
    "gn:country_code":"DZ",
    "gn:dem":28,
    "gn:feature_class":"P",
    "gn:feature_code":"PPL",
    "gn:name":"Douar Dra\u00efssia",
    "gn:population":0,
    "gn:timezone":"Africa/Algiers",
    "iso:country":"DZ",
    "wof:name":"Douar Draissia",
    "wof:placetype":"locality"
},
  "geometry": {"coordinates":[0.62917,35.83333],"type":"Point"}
}