{
  "type": "Feature",
  "properties": {
    "gn:admin1_code":"3.0",
    "gn:asciiname":"Oulad Mannsour",
    "gn:country_code":"DZ",
    "gn:dem":763,
    "gn:feature_class":"P",
    "gn:feature_code":"PPL",
    "gn:name":"Oulad Mannsour",
    "gn:population":0,
    "gn:timezone":"Africa/Algiers",
    "iso:country":"DZ",
    "wof:name":"Oulad Mannsour",
    "wof:placetype":"locality"
},
  "geometry": {"coordinates":[6.15875,35.04266],"type":"Point"}
}