{
  "type": "Feature",
  "properties": {
    "gn:admin1_code":"24.0",
    "gn:asciiname":"Mechta Bou Nabel",
    "gn:country_code":"DZ",
    "gn:dem":381,
    "gn:feature_class":"P",
    "gn:feature_code":"PPL",
    "gn:name":"Mechta Bo\u00fb N\u00e2bel",
    "gn:population":0,
    "gn:timezone":"Africa/Algiers",
    "iso:country":"DZ",
    "name:und_x_variant":[
        "Mechtat Bou Nabel",
        "Mechta Bo\u00fb N\u00e2bel"
    ],
    "wof:name":"Mechta Bou Nabel",
    "wof:placetype":"locality"
},
  "geometry": {"coordinates":[6.11172,36.75395],"type":"Point"}
}