{
  "type": "Feature",
  "properties": {
    "gn:admin1_code":"35.0",
    "gn:asciiname":"Theniet es Smar",
    "gn:country_code":"DZ",
    "gn:dem":840,
    "gn:feature_class":"P",
    "gn:feature_code":"PPL",
    "gn:name":"Theniet es Smar",
    "gn:population":0,
    "gn:timezone":"Africa/Algiers",
    "iso:country":"DZ",
    "wof:name":"Theniet es Smar",
    "wof:placetype":"locality"
},
  "geometry": {"coordinates":[2.67347,36.16451],"type":"Point"}
}