{
  "type": "Feature",
  "properties": {
    "gn:admin1_code":"26.0",
    "gn:asciiname":"Douar Bakhaitia",
    "gn:country_code":"DZ",
    "gn:dem":62,
    "gn:feature_class":"P",
    "gn:feature_code":"PPL",
    "gn:name":"Douar Bakha\u00eftia",
    "gn:population":0,
    "gn:timezone":"Africa/Algiers",
    "iso:country":"DZ",
    "wof:name":"Douar Bakhaitia",
    "wof:placetype":"locality"
},
  "geometry": {"coordinates":[0.091,35.59158],"type":"Point"}
}