{
  "type": "Feature",
  "properties": {
    "gn:admin1_code":"14.0",
    "gn:asciiname":"Bou Djelil",
    "gn:country_code":"DZ",
    "gn:dem":541,
    "gn:feature_class":"P",
    "gn:feature_code":"PPL",
    "gn:name":"Bou Djelil",
    "gn:population":0,
    "gn:timezone":"Africa/Algiers",
    "iso:country":"DZ",
    "wof:name":"Bou Djelil",
    "wof:placetype":"locality"
},
  "geometry": {"coordinates":[4.16375,36.65266],"type":"Point"}
}