{
  "type": "Feature",
  "properties": {
    "gn:admin1_code":"52.0",
    "gn:asciiname":"Gambetta",
    "gn:country_code":"DZ",
    "gn:dem":854,
    "gn:feature_class":"P",
    "gn:feature_code":"PPL",
    "gn:name":"Gambetta",
    "gn:population":0,
    "gn:timezone":"Africa/Algiers",
    "iso:country":"DZ",
    "wof:name":"Gambetta",
    "wof:placetype":"locality"
},
  "geometry": {"coordinates":[8.04278,36.1725],"type":"Point"}
}