{
  "type": "Feature",
  "properties": {
    "gn:admin1_code":"52.0",
    "gn:asciiname":"Gambetta",
    "gn:country_code":"DZ",
    "gn:dem":854,
    "gn:feature_class":"P",
    "gn:feature_code":"PPL",
    "gn:name":"Gambetta",
    "gn:population":0,
    "gn:timezone":"Africa/Algiers",
    "iso:country":"DZ",
    "name:bel_x_preferred":[
        "\u0413\u0430\u043c\u0431\u0435\u0442\u0430"
    ],
    "name:deu_x_preferred":[
        "Gambetta"
    ],
    "name:fra_x_preferred":[
        "Gambetta"
    ],
    "name:ita_x_preferred":[
        "Gambetta"
    ],
    "name:nld_x_preferred":[
        "Gambetta"
    ],
    "name:pol_x_preferred":[
        "Gambetta"
    ],
    "name:rus_x_preferred":[
        "\u0413\u0430\u043c\u0431\u0435\u0442\u0442\u0430"
    ],
    "name:spa_x_preferred":[
        "Gambetta"
    ],
    "name:swe_x_preferred":[
        "Gambetta"
    ],
    "wof:name":"Gambetta",
    "wof:placetype":"locality"
},
  "geometry": {"coordinates":[8.04278,36.1725],"type":"Point"}
}