{
  "type": "Feature",
  "properties": {
    "gn:admin1_code":"6.0",
    "gn:asciiname":"El Kouazet",
    "gn:country_code":"DZ",
    "gn:dem":595,
    "gn:feature_class":"P",
    "gn:feature_code":"PPL",
    "gn:name":"El Kouazet",
    "gn:population":0,
    "gn:timezone":"Africa/Algiers",
    "iso:country":"DZ",
    "wof:name":"El Kouazet",
    "wof:placetype":"locality"
},
  "geometry": {"coordinates":[3.34264,36.20903],"type":"Point"}
}