{
  "type": "Feature",
  "properties": {
    "gn:admin1_code":"7.0",
    "gn:asciiname":"Dhamchia",
    "gn:country_code":"DZ",
    "gn:dem":161,
    "gn:feature_class":"P",
    "gn:feature_code":"PPL",
    "gn:name":"Dhamchia",
    "gn:population":0,
    "gn:timezone":"Africa/Algiers",
    "iso:country":"DZ",
    "wof:name":"Dhamchia",
    "wof:placetype":"locality"
},
  "geometry": {"coordinates":[0.03567,35.83062],"type":"Point"}
}