{
  "type": "Feature",
  "properties": {
    "gn:admin1_code":"51.0",
    "gn:asciiname":"Mechta Khalifia",
    "gn:country_code":"DZ",
    "gn:dem":362,
    "gn:feature_class":"P",
    "gn:feature_code":"PPLL",
    "gn:name":"Mechta Khalifia",
    "gn:population":0,
    "gn:timezone":"Africa/Algiers",
    "iso:country":"DZ",
    "wof:name":"Mechta Khalifia",
    "wof:placetype":"locality"
},
  "geometry": {"coordinates":[1.16052,35.71252],"type":"Point"}
}