{
  "type": "Feature",
  "properties": {
    "gn:admin1_code":"40.0",
    "gn:asciiname":"Azerou Bahar",
    "gn:country_code":"DZ",
    "gn:dem":799,
    "gn:feature_class":"P",
    "gn:feature_code":"PPL",
    "gn:name":"Azerou Bahar",
    "gn:population":0,
    "gn:timezone":"Africa/Algiers",
    "iso:country":"DZ",
    "wof:name":"Azerou Bahar",
    "wof:placetype":"locality"
},
  "geometry": {"coordinates":[4.07239,36.83736],"type":"Point"}
}