{
  "type": "Feature",
  "properties": {
    "gn:admin1_code":"30.0",
    "gn:asciiname":"Douar Rhelalda",
    "gn:country_code":"DZ",
    "gn:dem":518,
    "gn:feature_class":"P",
    "gn:feature_code":"PPL",
    "gn:name":"Douar Rhelalda",
    "gn:population":0,
    "gn:timezone":"Africa/Algiers",
    "iso:country":"DZ",
    "name:und_x_variant":[
        "Rhelalda",
        "Douar Rhelalda"
    ],
    "wof:name":"Douar Rhelalda",
    "wof:placetype":"locality"
},
  "geometry": {"coordinates":[-0.47425,35.18244],"type":"Point"}
}