{
  "type": "Feature",
  "properties": {
    "gn:admin1_code":"30.0",
    "gn:asciiname":"Douar el Khleifia",
    "gn:country_code":"DZ",
    "gn:dem":521,
    "gn:feature_class":"P",
    "gn:feature_code":"PPL",
    "gn:name":"Douar el Khle\u00effia",
    "gn:population":0,
    "gn:timezone":"Africa/Algiers",
    "iso:country":"DZ",
    "name:und_x_variant":[
        "Khalefia",
        "Douar el Khle\u00effia"
    ],
    "wof:name":"Douar el Khleifia",
    "wof:placetype":"locality"
},
  "geometry": {"coordinates":[-0.55011,35.1951],"type":"Point"}
}