{
  "type": "Feature",
  "properties": {
    "gn:admin1_code":"23.0",
    "gn:asciiname":"Hammam M'Bails",
    "gn:country_code":"DZ",
    "gn:dem":458,
    "gn:feature_class":"P",
    "gn:feature_code":"PPL",
    "gn:name":"Hammam M\u2019Ba\u00efls",
    "gn:population":0,
    "gn:timezone":"Africa/Algiers",
    "iso:country":"DZ",
    "name:und_x_variant":[
        "Hammon N\u2019Bails",
        "Hammam N\u2019Ba\u00efls",
        "Hammam M\u2019Ba\u00efls"
    ],
    "wof:name":"Hammam M'Bails",
    "wof:placetype":"locality"
},
  "geometry": {"coordinates":[7.64459,36.32307],"type":"Point"}
}