{
  "type": "Feature",
  "properties": {
    "gn:admin1_code":"26.0",
    "gn:asciiname":"Douar Ouled Belkacem",
    "gn:country_code":"DZ",
    "gn:dem":640,
    "gn:feature_class":"P",
    "gn:feature_code":"PPL",
    "gn:name":"Douar Ouled Belkacem",
    "gn:population":0,
    "gn:timezone":"Africa/Algiers",
    "iso:country":"DZ",
    "name:und_x_variant":[
        "Douar Oulad Belkassem"
    ],
    "wof:name":"Douar Ouled Belkacem",
    "wof:placetype":"locality"
},
  "geometry": {"coordinates":[0.60192,35.35672],"type":"Point"}
}