{
  "type": "Feature",
  "properties": {
    "gn:admin1_code":"14.0",
    "gn:asciiname":"Taourirt Amokrane",
    "gn:country_code":"DZ",
    "gn:dem":643,
    "gn:feature_class":"P",
    "gn:feature_code":"PPL",
    "gn:name":"Taourirt Amokrane",
    "gn:population":0,
    "gn:timezone":"Africa/Algiers",
    "iso:country":"DZ",
    "name:und_x_variant":[
        "Taourirt-Amokhane",
        "Taourirt Amokrane"
    ],
    "wof:name":"Taourirt Amokrane",
    "wof:placetype":"locality"
},
  "geometry": {"coordinates":[4.20055,36.61317],"type":"Point"}
}