{
  "type": "Feature",
  "properties": {
    "gn:admin1_code":"51.0",
    "gn:asciiname":"Ouled Mohammed",
    "gn:country_code":"DZ",
    "gn:dem":291,
    "gn:feature_class":"P",
    "gn:feature_code":"PPL",
    "gn:name":"Ouled Mohammed",
    "gn:population":0,
    "gn:timezone":"Africa/Algiers",
    "iso:country":"DZ",
    "name:und_x_variant":[
        "Douar Ouled Mohammed",
        "Ouled Mohammed"
    ],
    "wof:name":"Ouled Mohammed",
    "wof:placetype":"locality"
},
  "geometry": {"coordinates":[0.44429,35.59502],"type":"Point"}
}