{
  "type": "Feature",
  "properties": {
    "gn:admin1_code":"25.0",
    "gn:asciiname":"Mkam Sidi Mabrouk",
    "gn:country_code":"DZ",
    "gn:dem":1409,
    "gn:feature_class":"P",
    "gn:feature_code":"PPL",
    "gn:name":"Mkam Sidi Mabrouk",
    "gn:population":0,
    "gn:timezone":"Africa/Algiers",
    "iso:country":"DZ",
    "wof:name":"Mkam Sidi Mabrouk",
    "wof:placetype":"locality"
},
  "geometry": {"coordinates":[2.21813,34.23506],"type":"Point"}
}