{
  "type": "Feature",
  "properties": {
    "gn:admin1_code":"29.0",
    "gn:asciiname":"Mechta Cheikh Raba",
    "gn:country_code":"DZ",
    "gn:dem":871,
    "gn:feature_class":"P",
    "gn:feature_code":"PPL",
    "gn:name":"Mechta Che\u00efkh Raba",
    "gn:population":0,
    "gn:timezone":"Africa/Algiers",
    "iso:country":"DZ",
    "name:und_x_variant":[
        "Mechtat Che\u00efkh Raba",
        "Mechta Che\u00efkh Raba"
    ],
    "wof:name":"Mechta Cheikh Raba",
    "wof:placetype":"locality"
},
  "geometry": {"coordinates":[7.40708,35.98938],"type":"Point"}
}