{
  "type": "Feature",
  "properties": {
    "gn:admin1_code":"41.0",
    "gn:asciiname":"Douar el Kdadir",
    "gn:country_code":"DZ",
    "gn:dem":513,
    "gn:feature_class":"P",
    "gn:feature_code":"PPL",
    "gn:name":"Douar el Kdadir",
    "gn:population":0,
    "gn:timezone":"Africa/Algiers",
    "iso:country":"DZ",
    "wof:name":"Douar el Kdadir",
    "wof:placetype":"locality"
},
  "geometry": {"coordinates":[1.52116,36.46513],"type":"Point"}
}