{
  "type": "Feature",
  "properties": {
    "gn:admin1_code":"35.0",
    "gn:asciiname":"Le Pont de l'Oued Djer",
    "gn:country_code":"DZ",
    "gn:dem":269,
    "gn:feature_class":"P",
    "gn:feature_code":"PPL",
    "gn:name":"Le Pont de l\u2019Oued Djer",
    "gn:population":0,
    "gn:timezone":"Africa/Algiers",
    "iso:country":"DZ",
    "wof:name":"Le Pont de l'Oued Djer",
    "wof:placetype":"locality"
},
  "geometry": {"coordinates":[2.43851,36.37524000000001],"type":"Point"}
}