{
  "type": "Feature",
  "properties": {
    "gn:admin1_code":"7.0",
    "gn:asciiname":"El Kessara",
    "gn:country_code":"DZ",
    "gn:dem":35,
    "gn:feature_class":"P",
    "gn:feature_code":"PPLL",
    "gn:name":"El Kessara",
    "gn:population":0,
    "gn:timezone":"Africa/Algiers",
    "iso:country":"DZ",
    "name:und_x_variant":[
        "Mechtat el Ksara"
    ],
    "wof:name":"El Kessara",
    "wof:placetype":"locality"
},
  "geometry": {"coordinates":[0.57653,35.95797],"type":"Point"}
}