{
  "type": "Feature",
  "properties": {
    "gn:admin1_code":"21.0",
    "gn:asciiname":"Mechta Ferraha",
    "gn:country_code":"DZ",
    "gn:dem":723,
    "gn:feature_class":"P",
    "gn:feature_code":"PPL",
    "gn:name":"Mechta Ferraha",
    "gn:population":0,
    "gn:timezone":"Africa/Algiers",
    "iso:country":"DZ",
    "wof:name":"Mechta Ferraha",
    "wof:placetype":"locality"
},
  "geometry": {"coordinates":[3.85503,35.92493],"type":"Point"}
}