{
  "type": "Feature",
  "properties": {
    "gn:admin1_code":"6.0",
    "gn:asciiname":"Zeaikia",
    "gn:country_code":"DZ",
    "gn:dem":678,
    "gn:feature_class":"P",
    "gn:feature_code":"PPL",
    "gn:name":"Zea\u00efkia",
    "gn:population":0,
    "gn:timezone":"Africa/Algiers",
    "iso:country":"DZ",
    "wof:name":"Zeaikia",
    "wof:placetype":"locality"
},
  "geometry": {"coordinates":[3.31515,36.18587],"type":"Point"}
}