{
  "type": "Feature",
  "properties": {
    "gn:admin1_code":"51.0",
    "gn:asciiname":"Kehailia",
    "gn:country_code":"DZ",
    "gn:dem":271,
    "gn:feature_class":"P",
    "gn:feature_code":"PPL",
    "gn:name":"Keha\u00eflia",
    "gn:population":0,
    "gn:timezone":"Africa/Algiers",
    "iso:country":"DZ",
    "wof:name":"Kehailia",
    "wof:placetype":"locality"
},
  "geometry": {"coordinates":[0.80766,35.77154],"type":"Point"}
}