{
  "type": "Feature",
  "properties": {
    "gn:admin1_code":"27.0",
    "gn:asciiname":"El Aouinat",
    "gn:country_code":"DZ",
    "gn:dem":540,
    "gn:feature_class":"P",
    "gn:feature_code":"PPL",
    "gn:name":"El Aouinat",
    "gn:population":0,
    "gn:timezone":"Africa/Algiers",
    "iso:country":"DZ",
    "wof:name":"El Aouinat",
    "wof:placetype":"locality"
},
  "geometry": {"coordinates":[4.18363,35.29237],"type":"Point"}
}