{
  "type": "Feature",
  "properties": {
    "gn:admin1_code":"27.0",
    "gn:asciiname":"'Ain Zia",
    "gn:country_code":"DZ",
    "gn:dem":794,
    "gn:feature_class":"P",
    "gn:feature_code":"PPL",
    "gn:name":"\u2019A\u00efn Zia",
    "gn:population":0,
    "gn:timezone":"Africa/Algiers",
    "iso:country":"DZ",
    "wof:name":"'Ain Zia",
    "wof:placetype":"locality"
},
  "geometry": {"coordinates":[4.37852,35.1205],"type":"Point"}
}