{
  "type": "Feature",
  "properties": {
    "gn:admin1_code":"35.0",
    "gn:asciiname":"Bouazine",
    "gn:country_code":"DZ",
    "gn:dem":509,
    "gn:feature_class":"P",
    "gn:feature_code":"PPL",
    "gn:name":"Bouazine",
    "gn:population":0,
    "gn:timezone":"Africa/Algiers",
    "iso:country":"DZ",
    "wof:name":"Bouazine",
    "wof:placetype":"locality"
},
  "geometry": {"coordinates":[1.98606,36.17104000000001],"type":"Point"}
}