{
  "type": "Feature",
  "properties": {
    "iso:country":"DZ",
    "name:ara_x_preferred":[
        "\u0627\u0644\u0639\u0628\u0627\u062f\u064a\u0629"
    ],
    "name:ceb_x_preferred":[
        "El Abadia"
    ],
    "name:eng_x_preferred":[
        "El Abadia"
    ],
    "name:fas_x_preferred":[
        "\u0639\u0628\u0627\u062f\u06cc\u0647"
    ],
    "name:fra_x_preferred":[
        "El Abadia"
    ],
    "name:ita_x_preferred":[
        "El Abadia"
    ],
    "name:kab_x_preferred":[
        "L\u025bebbadeyya"
    ],
    "name:msa_x_preferred":[
        "El Abadia"
    ],
    "name:nld_x_preferred":[
        "El Abadia"
    ],
    "name:por_x_preferred":[
        "El Abadia"
    ],
    "name:ron_x_preferred":[
        "El Abadia"
    ],
    "name:swe_x_preferred":[
        "El Abadia"
    ],
    "name:unk_x_variant":[
        "Carnot"
    ],
    "name:vie_x_preferred":[
        "El Abadia"
    ],
    "name:zho_min_nan_x_preferred":[
        "El Abadia"
    ],
    "qs:gn_country":"DZ",
    "qs:gn_fcode":"PPL",
    "qs:gn_pop":28724,
    "qs:name":"El Abadia",
    "qs:name_adm0":"\u0627\u0644\u062c\u0632\u0627\u0626\u0631",
    "qs:name_adm1":"Ain Defla",
    "qs:photos":0,
    "qs:photos_1k":0,
    "qs:photos_9k":0,
    "qs:photos_9r":0,
    "qs:photos_all":0,
    "qs:photos_sr":0,
    "qs:placetype":"Town",
    "qs:pop_sr":"7",
    "qs:woe_adm0":23424740,
    "wd:wordcount":25,
    "wof:name":"El Abadia",
    "wof:placetype":"locality",
    "wof:population":28724
},
  "geometry": {"coordinates":[1.68609,36.26951],"type":"Point"}
}