{
  "type": "Feature",
  "properties": {
    "gn:admin1_code":"51.0",
    "gn:asciiname":"Douar Fraihia",
    "gn:country_code":"DZ",
    "gn:dem":357,
    "gn:feature_class":"P",
    "gn:feature_code":"PPL",
    "gn:name":"Douar Fra\u00efhia",
    "gn:population":0,
    "gn:timezone":"Africa/Algiers",
    "iso:country":"DZ",
    "wof:name":"Douar Fraihia",
    "wof:placetype":"locality"
},
  "geometry": {"coordinates":[0.729,35.52745],"type":"Point"}
}