{
  "type": "Feature",
  "properties": {
    "gn:admin1_code":"30.0",
    "gn:asciiname":"Bedrabine",
    "gn:country_code":"DZ",
    "gn:dem":632,
    "gn:feature_class":"P",
    "gn:feature_code":"PPL",
    "gn:name":"Bedrabine",
    "gn:population":0,
    "gn:timezone":"Africa/Algiers",
    "iso:country":"DZ",
    "wof:name":"Bedrabine",
    "wof:placetype":"locality"
},
  "geometry": {"coordinates":[-0.85039,35.0095],"type":"Point"}
}