{
  "type": "Feature",
  "properties": {
    "iso:country":"DZ",
    "name:ara_x_preferred":[
        "\u0633\u0628\u062f\u0648"
    ],
    "name:azb_x_preferred":[
        "\u0633\u0628\u062f\u0648"
    ],
    "name:ceb_x_preferred":[
        "Sebdou"
    ],
    "name:deu_x_preferred":[
        "Sebdou"
    ],
    "name:eng_x_preferred":[
        "Sebdou"
    ],
    "name:fas_x_preferred":[
        "\u0633\u0628\u062f\u0648"
    ],
    "name:fra_x_preferred":[
        "Sebdou"
    ],
    "name:ita_x_preferred":[
        "Sebdou"
    ],
    "name:kab_x_preferred":[
        "Sebdu"
    ],
    "name:msa_x_preferred":[
        "Sebdou"
    ],
    "name:nan_x_preferred":[
        "Sebdou"
    ],
    "name:nld_x_preferred":[
        "Sebdou"
    ],
    "name:pol_x_preferred":[
        "Sabdu"
    ],
    "name:por_x_preferred":[
        "Sebdou"
    ],
    "name:ron_x_preferred":[
        "Sebdou"
    ],
    "name:spa_x_preferred":[
        "Sebdou"
    ],
    "name:swe_x_preferred":[
        "Sebdou"
    ],
    "name:vie_x_preferred":[
        "Sebdou"
    ],
    "name:zho_min_nan_x_preferred":[
        "Sebdou"
    ],
    "qs:gn_country":"DZ",
    "qs:gn_fcode":"PPL",
    "qs:gn_pop":41146,
    "qs:name":"Debdou",
    "qs:name_adm0":"\u0627\u0644\u0645\u063a\u0631\u0628",
    "qs:name_adm1":"\u0627\u0644\u062c\u0647\u0629 \u0627\u0644\u0634\u0631\u0642\u064a\u0629",
    "qs:photos":0,
    "qs:photos_1k":0,
    "qs:photos_9k":1,
    "qs:photos_9r":1,
    "qs:photos_all":2,
    "qs:photos_sr":0,
    "qs:placetype":"Town",
    "qs:pop_sr":"7",
    "qs:woe_adm0":23424893,
    "wd:wordcount":38,
    "wof:name":"Debdou",
    "wof:placetype":"locality",
    "wof:population":41146
},
  "geometry": {"coordinates":[-1.33143,34.63703],"type":"Point"}
}