{
  "type": "Feature",
  "properties": {
    "gn:admin1_code":"18.0",
    "gn:asciiname":"Chouarikh",
    "gn:country_code":"DZ",
    "gn:dem":935,
    "gn:feature_class":"P",
    "gn:feature_code":"PPL",
    "gn:name":"Chouarikh",
    "gn:population":0,
    "gn:timezone":"Africa/Algiers",
    "iso:country":"DZ",
    "wof:name":"Chouarikh",
    "wof:placetype":"locality"
},
  "geometry": {"coordinates":[4.51667,36.26667],"type":"Point"}
}