{
  "type": "Feature",
  "properties": {
    "gn:admin1_code":"35.0",
    "gn:asciiname":"El Khama",
    "gn:country_code":"DZ",
    "gn:dem":363,
    "gn:feature_class":"P",
    "gn:feature_code":"PPL",
    "gn:name":"El Khama",
    "gn:population":0,
    "gn:timezone":"Africa/Algiers",
    "iso:country":"DZ",
    "wof:name":"El Khama",
    "wof:placetype":"locality"
},
  "geometry": {"coordinates":[1.69592,36.13061],"type":"Point"}
}