{
  "type": "Feature",
  "properties": {
    "gn:admin1_code":"12.0",
    "gn:asciiname":"Oulad Ali Ben Athmane",
    "gn:country_code":"DZ",
    "gn:dem":715,
    "gn:feature_class":"P",
    "gn:feature_code":"PPL",
    "gn:name":"Oulad Ali Ben Athmane",
    "gn:population":0,
    "gn:timezone":"Africa/Algiers",
    "iso:country":"DZ",
    "name:und_x_variant":[
        "Oulad Ali Ben Athman",
        "Oulad Ali Ben Athmane"
    ],
    "wof:name":"Oulad Ali Ben Athmane",
    "wof:placetype":"locality"
},
  "geometry": {"coordinates":[4.99496,36.43631],"type":"Point"}
}