{
  "type": "Feature",
  "properties": {
    "gn:admin1_code":"12.0",
    "gn:asciiname":"Fitchou",
    "gn:country_code":"DZ",
    "gn:dem":699,
    "gn:feature_class":"P",
    "gn:feature_code":"PPL",
    "gn:name":"Fitchou",
    "gn:population":0,
    "gn:timezone":"Africa/Algiers",
    "iso:country":"DZ",
    "wof:name":"Fitchou",
    "wof:placetype":"locality"
},
  "geometry": {"coordinates":[5.20782,36.44973],"type":"Point"}
}