{
  "type": "Feature",
  "properties": {
    "gn:admin1_code":"33.0",
    "gn:asciiname":"Ouled Mehania",
    "gn:country_code":"DZ",
    "gn:dem":756,
    "gn:feature_class":"P",
    "gn:feature_code":"PPL",
    "gn:name":"Ouled Mehania",
    "gn:population":0,
    "gn:timezone":"Africa/Algiers",
    "iso:country":"DZ",
    "wof:name":"Ouled Mehania",
    "wof:placetype":"locality"
},
  "geometry": {"coordinates":[8.04699,35.61071],"type":"Point"}
}