{
  "type": "Feature",
  "properties": {
    "gn:admin1_code":"13.0",
    "gn:asciiname":"Douar Boukennar",
    "gn:country_code":"DZ",
    "gn:dem":576,
    "gn:feature_class":"P",
    "gn:feature_code":"PPL",
    "gn:name":"Douar Boukennar",
    "gn:population":0,
    "gn:timezone":"Africa/Algiers",
    "iso:country":"DZ",
    "wof:name":"Douar Boukennar",
    "wof:placetype":"locality"
},
  "geometry": {"coordinates":[0.67707,35.19529],"type":"Point"}
}