{
  "type": "Feature",
  "properties": {
    "gn:admin1_code":"6.0",
    "gn:asciiname":"Oulad Dahmane",
    "gn:country_code":"DZ",
    "gn:dem":701,
    "gn:feature_class":"P",
    "gn:feature_code":"PPL",
    "gn:name":"Oulad Dahmane",
    "gn:population":0,
    "gn:timezone":"Africa/Algiers",
    "iso:country":"DZ",
    "name:und_x_variant":[
        "Ouled Dahmane",
        "Oulad Dahmane"
    ],
    "wof:name":"Oulad Dahmane",
    "wof:placetype":"locality"
},
  "geometry": {"coordinates":[3.46006,36.36192],"type":"Point"}
}