{
  "type": "Feature",
  "properties": {
    "gn:admin1_code":"13.0",
    "gn:asciiname":"Douar Ouled Ali",
    "gn:country_code":"DZ",
    "gn:dem":498,
    "gn:feature_class":"P",
    "gn:feature_code":"PPL",
    "gn:name":"Douar Ouled Ali",
    "gn:population":0,
    "gn:timezone":"Africa/Algiers",
    "iso:country":"DZ",
    "wof:name":"Douar Ouled Ali",
    "wof:placetype":"locality"
},
  "geometry": {"coordinates":[0.91845,35.40859000000001],"type":"Point"}
}