{
  "type": "Feature",
  "properties": {
    "gn:admin1_code":"13.0",
    "gn:asciiname":"Mechtat Gouchgal",
    "gn:country_code":"DZ",
    "gn:dem":1132,
    "gn:feature_class":"P",
    "gn:feature_code":"PPL",
    "gn:name":"Mechtat Gouchgal",
    "gn:population":0,
    "gn:timezone":"Africa/Algiers",
    "iso:country":"DZ",
    "wof:name":"Mechtat Gouchgal",
    "wof:placetype":"locality"
},
  "geometry": {"coordinates":[1.12662,35.09968],"type":"Point"}
}