{
  "type": "Feature",
  "properties": {
    "gn:admin1_code":"29.0",
    "gn:asciiname":"Mechta Oulad Djelila",
    "gn:country_code":"DZ",
    "gn:dem":850,
    "gn:feature_class":"P",
    "gn:feature_code":"PPL",
    "gn:name":"Mechta Oulad Djelila",
    "gn:population":0,
    "gn:timezone":"Africa/Algiers",
    "iso:country":"DZ",
    "name:und_x_variant":[
        "Mechtat Oulad Djelila",
        "Mechta Oulad Djelila"
    ],
    "wof:name":"Mechta Oulad Djelila",
    "wof:placetype":"locality"
},
  "geometry": {"coordinates":[6.90888,36.11185],"type":"Point"}
}