{
  "type": "Feature",
  "properties": {
    "gn:admin1_code":"36.0",
    "gn:asciiname":"La Pierre du Chat",
    "gn:country_code":"DZ",
    "gn:dem":68,
    "gn:feature_class":"P",
    "gn:feature_code":"PPL",
    "gn:name":"La Pierre du Chat",
    "gn:population":0,
    "gn:timezone":"Africa/Algiers",
    "iso:country":"DZ",
    "name:und_x_variant":[
        "Pierre du Chat",
        "La Pierre du Chat"
    ],
    "wof:name":"La Pierre du Chat",
    "wof:placetype":"locality"
},
  "geometry": {"coordinates":[-1.45176,35.14937],"type":"Point"}
}