{
  "type": "Feature",
  "properties": {
    "gn:admin1_code":"3.0",
    "gn:asciiname":"Ayallalaoun",
    "gn:country_code":"DZ",
    "gn:dem":1172,
    "gn:feature_class":"P",
    "gn:feature_code":"PPL",
    "gn:name":"Ayallalaoun",
    "gn:population":0,
    "gn:timezone":"Africa/Algiers",
    "iso:country":"DZ",
    "name:und_x_variant":[
        "Ayllalaoun",
        "Ayallalaoun"
    ],
    "wof:name":"Ayallalaoun",
    "wof:placetype":"locality"
},
  "geometry": {"coordinates":[6.08333,35.20279],"type":"Point"}
}