{
  "type": "Feature",
  "properties": {
    "gn:admin1_code":"14.0",
    "gn:asciiname":"Ibkarene",
    "gn:country_code":"DZ",
    "gn:dem":1047,
    "gn:feature_class":"P",
    "gn:feature_code":"PPL",
    "gn:name":"Ibkarene",
    "gn:population":0,
    "gn:timezone":"Africa/Algiers",
    "iso:country":"DZ",
    "wof:name":"Ibkarene",
    "wof:placetype":"locality"
},
  "geometry": {"coordinates":[4.48333,36.63333],"type":"Point"}
}