{
  "type": "Feature",
  "properties": {
    "gn:admin1_code":"9.0",
    "gn:asciiname":"Douar Sidi Ma'achou",
    "gn:country_code":"DZ",
    "gn:dem":493,
    "gn:feature_class":"P",
    "gn:feature_code":"PPL",
    "gn:name":"Douar Sidi Ma\u2019\u00e2chou",
    "gn:population":0,
    "gn:timezone":"Africa/Algiers",
    "iso:country":"DZ",
    "wof:name":"Douar Sidi Ma'achou",
    "wof:placetype":"locality"
},
  "geometry": {"coordinates":[-0.51667,35.36667],"type":"Point"}
}