{
  "type": "Feature",
  "properties": {
    "gn:admin1_code":"21.0",
    "gn:asciiname":"Mechta des Rouaba",
    "gn:country_code":"DZ",
    "gn:dem":988,
    "gn:feature_class":"P",
    "gn:feature_code":"PPL",
    "gn:name":"Mechta des Rouaba",
    "gn:population":0,
    "gn:timezone":"Africa/Algiers",
    "iso:country":"DZ",
    "name:und_x_variant":[
        "Mechtas des Rouaba",
        "Mechta des Rouaba"
    ],
    "wof:name":"Mechta des Rouaba",
    "wof:placetype":"locality"
},
  "geometry": {"coordinates":[3.91114,36.12072],"type":"Point"}
}