{
  "type": "Feature",
  "properties": {
    "gn:admin1_code":"55.0",
    "gn:asciiname":"Bains Romains",
    "gn:country_code":"DZ",
    "gn:dem":20,
    "gn:feature_class":"P",
    "gn:feature_code":"PPL",
    "gn:name":"Bains Romains",
    "gn:population":0,
    "gn:timezone":"Africa/Algiers",
    "iso:country":"DZ",
    "wof:name":"Bains Romains",
    "wof:placetype":"locality"
},
  "geometry": {"coordinates":[2.99072,36.81322],"type":"Point"}
}