{
  "type": "Feature",
  "properties": {
    "gn:admin1_code":"51.0",
    "gn:asciiname":"Mechta Moussa Beloufa",
    "gn:country_code":"DZ",
    "gn:dem":545,
    "gn:feature_class":"P",
    "gn:feature_code":"PPL",
    "gn:name":"Mechta Moussa Beloufa",
    "gn:population":0,
    "gn:timezone":"Africa/Algiers",
    "iso:country":"DZ",
    "name:und_x_variant":[
        "Mechtat Moussa Beloufa",
        "Mechta Moussa Beloufa"
    ],
    "wof:name":"Mechta Moussa Beloufa",
    "wof:placetype":"locality"
},
  "geometry": {"coordinates":[0.78953,36.11375],"type":"Point"}
}