{
  "type": "Feature",
  "properties": {
    "gn:admin1_code":"18.0",
    "gn:asciiname":"El Meroudj",
    "gn:country_code":"DZ",
    "gn:dem":800,
    "gn:feature_class":"P",
    "gn:feature_code":"PPL",
    "gn:name":"El Meroudj",
    "gn:population":0,
    "gn:timezone":"Africa/Algiers",
    "iso:country":"DZ",
    "wof:name":"El Meroudj",
    "wof:placetype":"locality"
},
  "geometry": {"coordinates":[5.03795,36.63283],"type":"Point"}
}