{
  "type": "Feature",
  "properties": {
    "gn:admin1_code":"24.0",
    "gn:asciiname":"El Habal",
    "gn:country_code":"DZ",
    "gn:dem":613,
    "gn:feature_class":"P",
    "gn:feature_code":"PPL",
    "gn:name":"El Habal",
    "gn:population":0,
    "gn:timezone":"Africa/Algiers",
    "iso:country":"DZ",
    "wof:name":"El Habal",
    "wof:placetype":"locality"
},
  "geometry": {"coordinates":[5.6425,36.59028],"type":"Point"}
}