{
  "type": "Feature",
  "properties": {
    "gn:admin1_code":"50.0",
    "gn:asciiname":"Ed Dlilia",
    "gn:country_code":"DZ",
    "gn:dem":98,
    "gn:feature_class":"P",
    "gn:feature_code":"PPL",
    "gn:name":"Ed Dlilia",
    "gn:population":0,
    "gn:timezone":"Africa/Algiers",
    "iso:country":"DZ",
    "wof:name":"Ed Dlilia",
    "wof:placetype":"locality"
},
  "geometry": {"coordinates":[6.39528,33.16417],"type":"Point"}
}