{
  "type": "Feature",
  "properties": {
    "gn:admin1_code":"51.0",
    "gn:asciiname":"Douar Krenansa",
    "gn:country_code":"DZ",
    "gn:dem":246,
    "gn:feature_class":"P",
    "gn:feature_code":"PPLL",
    "gn:name":"Douar Krenansa",
    "gn:population":0,
    "gn:timezone":"Africa/Algiers",
    "iso:country":"DZ",
    "wof:name":"Douar Krenansa",
    "wof:placetype":"locality"
},
  "geometry": {"coordinates":[0.69556,35.49722],"type":"Point"}
}