{
  "type": "Feature",
  "properties": {
    "gn:admin1_code":"42.0",
    "gn:asciiname":"Chellala Gueblia",
    "gn:country_code":"DZ",
    "gn:dem":1131,
    "gn:feature_class":"P",
    "gn:feature_code":"PPL",
    "gn:name":"Chellala Gueblia",
    "gn:population":0,
    "gn:timezone":"Africa/Algiers",
    "iso:country":"DZ",
    "wof:name":"Chellala Gueblia",
    "wof:placetype":"locality"
},
  "geometry": {"coordinates":[0.10844,33.0132],"type":"Point"}
}