{
  "type": "Feature",
  "properties": {
    "gn:admin1_code":"18.0",
    "gn:asciiname":"Amadene Foukam",
    "gn:country_code":"DZ",
    "gn:dem":36,
    "gn:feature_class":"P",
    "gn:feature_code":"PPL",
    "gn:name":"Amadene Foukam",
    "gn:population":0,
    "gn:timezone":"Africa/Algiers",
    "iso:country":"DZ",
    "wof:name":"Amadene Foukam",
    "wof:placetype":"locality"
},
  "geometry": {"coordinates":[4.94003,36.69866],"type":"Point"}
}