{
  "type": "Feature",
  "properties": {
    "gn:admin1_code":"14.0",
    "gn:asciiname":"Irhil Imoula",
    "gn:country_code":"DZ",
    "gn:dem":665,
    "gn:feature_class":"P",
    "gn:feature_code":"PPL",
    "gn:name":"Irhil Imoula",
    "gn:population":0,
    "gn:timezone":"Africa/Algiers",
    "iso:country":"DZ",
    "wof:name":"Irhil Imoula",
    "wof:placetype":"locality"
},
  "geometry": {"coordinates":[4.04295,36.55281],"type":"Point"}
}