{
  "type": "Feature",
  "properties": {
    "gn:admin1_code":"27.0",
    "gn:asciiname":"Mechta Loudani",
    "gn:country_code":"DZ",
    "gn:dem":431,
    "gn:feature_class":"P",
    "gn:feature_code":"PPL",
    "gn:name":"Mechta Loudani",
    "gn:population":0,
    "gn:timezone":"Africa/Algiers",
    "iso:country":"DZ",
    "name:und_x_variant":[
        "Mechtat Loudani",
        "Mechta Loudani"
    ],
    "wof:name":"Mechta Loudani",
    "wof:placetype":"locality"
},
  "geometry": {"coordinates":[4.76047,35.58255],"type":"Point"}
}