{
  "type": "Feature",
  "properties": {
    "gn:admin1_code":"14.0",
    "gn:asciiname":"Ichtouanene",
    "gn:country_code":"DZ",
    "gn:dem":330,
    "gn:feature_class":"P",
    "gn:feature_code":"PPL",
    "gn:name":"Ichtouanene",
    "gn:population":0,
    "gn:timezone":"Africa/Algiers",
    "iso:country":"DZ",
    "wof:name":"Ichtouanene",
    "wof:placetype":"locality"
},
  "geometry": {"coordinates":[4.14167,36.81145],"type":"Point"}
}