{
  "type": "Feature",
  "properties": {
    "gn:admin1_code":"26.0",
    "gn:asciiname":"Douar Ouled Sidi el Bachir",
    "gn:country_code":"DZ",
    "gn:dem":559,
    "gn:feature_class":"P",
    "gn:feature_code":"PPL",
    "gn:name":"Douar Ouled Sidi el Bachir",
    "gn:population":0,
    "gn:timezone":"Africa/Algiers",
    "iso:country":"DZ",
    "wof:name":"Douar Ouled Sidi el Bachir",
    "wof:placetype":"locality"
},
  "geometry": {"coordinates":[0.38528,35.48056],"type":"Point"}
}