{
  "type": "Feature",
  "properties": {
    "gn:admin1_code":"7.0",
    "gn:asciiname":"Hadj Mohammed Meda",
    "gn:country_code":"DZ",
    "gn:dem":34,
    "gn:feature_class":"P",
    "gn:feature_code":"PPL",
    "gn:name":"Hadj Mohammed Meda",
    "gn:population":0,
    "gn:timezone":"Africa/Algiers",
    "iso:country":"DZ",
    "wof:name":"Hadj Mohammed Meda",
    "wof:placetype":"locality"
},
  "geometry": {"coordinates":[0.52667,35.95333],"type":"Point"}
}