{
  "type": "Feature",
  "properties": {
    "gn:admin1_code":"41.0",
    "gn:asciiname":"Ouled Adda",
    "gn:country_code":"DZ",
    "gn:dem":548,
    "gn:feature_class":"P",
    "gn:feature_code":"PPL",
    "gn:name":"Ouled Adda",
    "gn:population":0,
    "gn:timezone":"Africa/Algiers",
    "iso:country":"DZ",
    "wof:name":"Ouled Adda",
    "wof:placetype":"locality"
},
  "geometry": {"coordinates":[1.51389,36.02361],"type":"Point"}
}