{
  "type": "Feature",
  "properties": {
    "gn:admin1_code":"3.0",
    "gn:asciiname":"Tine Tarine",
    "gn:country_code":"DZ",
    "gn:dem":1300,
    "gn:feature_class":"P",
    "gn:feature_code":"PPL",
    "gn:name":"Tine Tarine",
    "gn:population":0,
    "gn:timezone":"Africa/Algiers",
    "iso:country":"DZ",
    "wof:name":"Tine Tarine",
    "wof:placetype":"locality"
},
  "geometry": {"coordinates":[6.08461,35.13814],"type":"Point"}
}