{
  "type": "Feature",
  "properties": {
    "gn:admin1_code":"51.0",
    "gn:asciiname":"Douar D'Bala",
    "gn:country_code":"DZ",
    "gn:dem":599,
    "gn:feature_class":"P",
    "gn:feature_code":"PPLL",
    "gn:name":"Douar D\u2019Bala",
    "gn:population":0,
    "gn:timezone":"Africa/Algiers",
    "iso:country":"DZ",
    "wof:name":"Douar D'Bala",
    "wof:placetype":"locality"
},
  "geometry": {"coordinates":[0.93442,35.49816],"type":"Point"}
}