{
  "type": "Feature",
  "properties": {
    "gn:admin1_code":"26.0",
    "gn:asciiname":"Douar Rguib",
    "gn:country_code":"DZ",
    "gn:dem":565,
    "gn:feature_class":"P",
    "gn:feature_code":"PPL",
    "gn:name":"Douar Rguib",
    "gn:population":0,
    "gn:timezone":"Africa/Algiers",
    "iso:country":"DZ",
    "wof:name":"Douar Rguib",
    "wof:placetype":"locality"
},
  "geometry": {"coordinates":[0.39121,35.49274000000001],"type":"Point"}
}