{
  "type": "Feature",
  "properties": {
    "gn:admin1_code":"7.0",
    "gn:asciiname":"Douar Sidi Tahar",
    "gn:country_code":"DZ",
    "gn:dem":83,
    "gn:feature_class":"P",
    "gn:feature_code":"PPL",
    "gn:name":"Douar Sidi Tahar",
    "gn:population":0,
    "gn:timezone":"Africa/Algiers",
    "iso:country":"DZ",
    "wof:name":"Douar Sidi Tahar",
    "wof:placetype":"locality"
},
  "geometry": {"coordinates":[0.41066,35.79154000000001],"type":"Point"}
}