{
  "type": "Feature",
  "properties": {
    "gn:admin1_code":"41.0",
    "gn:asciiname":"El Attatou",
    "gn:country_code":"DZ",
    "gn:dem":403,
    "gn:feature_class":"P",
    "gn:feature_code":"PPL",
    "gn:name":"El Attatou",
    "gn:population":0,
    "gn:timezone":"Africa/Algiers",
    "iso:country":"DZ",
    "wof:name":"El Attatou",
    "wof:placetype":"locality"
},
  "geometry": {"coordinates":[1.48537,36.08229],"type":"Point"}
}