{
  "type": "Feature",
  "properties": {
    "gn:admin1_code":"41.0",
    "gn:asciiname":"Karaa Chira",
    "gn:country_code":"DZ",
    "gn:dem":229,
    "gn:feature_class":"P",
    "gn:feature_code":"PPL",
    "gn:name":"Kara\u00e2 Chira",
    "gn:population":0,
    "gn:timezone":"Africa/Algiers",
    "iso:country":"DZ",
    "name:und_x_variant":[
        "Kara\u00e2 Chira",
        "Ben Allel"
    ],
    "wof:name":"Karaa Chira",
    "wof:placetype":"locality"
},
  "geometry": {"coordinates":[1.50505,36.14726],"type":"Point"}
}