{
  "type": "Feature",
  "properties": {
    "gn:admin1_code":"52.0",
    "gn:asciiname":"Mechta 'Ain Beida",
    "gn:country_code":"DZ",
    "gn:dem":821,
    "gn:feature_class":"P",
    "gn:feature_code":"PPL",
    "gn:name":"Mechta \u2019A\u00efn Be\u00efda",
    "gn:population":0,
    "gn:timezone":"Africa/Algiers",
    "iso:country":"DZ",
    "wof:name":"Mechta 'Ain Beida",
    "wof:placetype":"locality"
},
  "geometry": {"coordinates":[7.85279,36.03784],"type":"Point"}
}