{
  "type": "Feature",
  "properties": {
    "gn:admin1_code":"41.0",
    "gn:asciiname":"Bouchikha",
    "gn:country_code":"DZ",
    "gn:dem":645,
    "gn:feature_class":"P",
    "gn:feature_code":"PPL",
    "gn:name":"Bouchikha",
    "gn:population":0,
    "gn:timezone":"Africa/Algiers",
    "iso:country":"DZ",
    "wof:name":"Bouchikha",
    "wof:placetype":"locality"
},
  "geometry": {"coordinates":[1.62537,36.38432],"type":"Point"}
}