{
  "type": "Feature",
  "properties": {
    "gn:admin1_code":"3.0",
    "gn:asciiname":"Mechta Kannda",
    "gn:country_code":"DZ",
    "gn:dem":992,
    "gn:feature_class":"P",
    "gn:feature_code":"PPL",
    "gn:name":"Mechta Kannda",
    "gn:population":0,
    "gn:timezone":"Africa/Algiers",
    "iso:country":"DZ",
    "wof:name":"Mechta Kannda",
    "wof:placetype":"locality"
},
  "geometry": {"coordinates":[5.57122,35.6544],"type":"Point"}
}