{
  "type": "Feature",
  "properties": {
    "gn:admin1_code":"26.0",
    "gn:asciiname":"Doaur Nbabcha",
    "gn:country_code":"DZ",
    "gn:dem":260,
    "gn:feature_class":"P",
    "gn:feature_code":"PPL",
    "gn:name":"Doaur Nbabcha",
    "gn:population":0,
    "gn:timezone":"Africa/Algiers",
    "iso:country":"DZ",
    "wof:name":"Doaur Nbabcha",
    "wof:placetype":"locality"
},
  "geometry": {"coordinates":[0.77502,35.43043],"type":"Point"}
}