{
  "type": "Feature",
  "properties": {
    "gn:admin1_code":"48.0",
    "gn:asciiname":"Siliana",
    "gn:country_code":"DZ",
    "gn:dem":277,
    "gn:feature_class":"P",
    "gn:feature_code":"PPL",
    "gn:name":"Siliana",
    "gn:population":0,
    "gn:timezone":"Africa/Algiers",
    "iso:country":"DZ",
    "wof:name":"Siliana",
    "wof:placetype":"locality"
},
  "geometry": {"coordinates":[6.29204,36.53972],"type":"Point"}
}