{
  "type": "Feature",
  "properties": {
    "gn:admin1_code":"48.0",
    "gn:asciiname":"Siliana",
    "gn:country_code":"DZ",
    "gn:dem":277,
    "gn:feature_class":"P",
    "gn:feature_code":"PPL",
    "gn:name":"Siliana",
    "gn:population":0,
    "gn:timezone":"Africa/Algiers",
    "iso:country":"DZ",
    "name:ara_x_preferred":[
        "\u0633\u0644\u064a\u0627\u0646\u0629"
    ],
    "name:ben_x_preferred":[
        "\u09b8\u09bf\u09b2\u09bf\u099c\u09be\u09a8\u09be"
    ],
    "name:cat_x_preferred":[
        "Siliana"
    ],
    "name:ceb_x_preferred":[
        "Siliana"
    ],
    "name:cym_x_preferred":[
        "Siliana"
    ],
    "name:deu_x_preferred":[
        "Siliana"
    ],
    "name:ell_x_preferred":[
        "\u03a3\u03b9\u03bb\u03b3\u03b9\u03ac\u03bd\u03b1"
    ],
    "name:fra_x_preferred":[
        "Siliana"
    ],
    "name:gle_x_preferred":[
        "Siliana"
    ],
    "name:heb_x_preferred":[
        "\u05e1\u05d9\u05dc\u05d9\u05d0\u05e0\u05d4"
    ],
    "name:hin_x_preferred":[
        "\u0938\u093f\u0932\u093f\u0906\u0928\u093e"
    ],
    "name:hun_x_preferred":[
        "Siliana"
    ],
    "name:ind_x_preferred":[
        "Siliana"
    ],
    "name:ita_x_preferred":[
        "Siliana"
    ],
    "name:jpn_x_preferred":[
        "\u30b7\u30ea\u30a2\u30ca"
    ],
    "name:kab_x_preferred":[
        "Silyana"
    ],
    "name:kor_x_preferred":[
        "\uc2e4\ub9ac\uc544\ub098"
    ],
    "name:nld_x_preferred":[
        "Siliana"
    ],
    "name:pol_x_preferred":[
        "Siljana"
    ],
    "name:por_x_preferred":[
        "Siliana"
    ],
    "name:ron_x_preferred":[
        "Siliana"
    ],
    "name:sco_x_preferred":[
        "Siliana"
    ],
    "name:spa_x_preferred":[
        "Siliana"
    ],
    "name:swe_x_preferred":[
        "Siliana"
    ],
    "name:tur_x_preferred":[
        "Silyana"
    ],
    "name:ukr_x_preferred":[
        "\u0421\u0456\u043b\u044c\u044f\u043d\u0430"
    ],
    "name:urd_x_preferred":[
        "\u0633\u0644\u06cc\u0627\u0646\u06c1"
    ],
    "name:vie_x_preferred":[
        "Siliana"
    ],
    "name:zho_x_preferred":[
        "\u932b\u52d2\u4e9e\u5948"
    ],
    "wof:name":"Siliana",
    "wof:placetype":"locality"
},
  "geometry": {"coordinates":[6.29204,36.53972],"type":"Point"}
}