{
  "type": "Feature",
  "properties": {
    "gn:admin1_code":"39.0",
    "gn:asciiname":"El Ach",
    "gn:country_code":"DZ",
    "gn:dem":742,
    "gn:feature_class":"P",
    "gn:feature_code":"PPL",
    "gn:name":"El Ach",
    "gn:population":0,
    "gn:timezone":"Africa/Algiers",
    "iso:country":"DZ",
    "name:ara_x_preferred":[
        "\u0627\u0644\u0639\u0634"
    ],
    "name:fra_x_preferred":[
        "El Ach"
    ],
    "name:ita_x_preferred":[
        "El Ach"
    ],
    "name:msa_x_preferred":[
        "El Ach"
    ],
    "name:por_x_preferred":[
        "El Ach"
    ],
    "name:ron_x_preferred":[
        "El Ach"
    ],
    "name:spa_x_preferred":[
        "El Ach"
    ],
    "name:vie_x_preferred":[
        "El Ach"
    ],
    "wof:name":"El Ach",
    "wof:placetype":"locality"
},
  "geometry": {"coordinates":[4.68203,35.94548],"type":"Point"}
}