{
  "type": "Feature",
  "properties": {
    "gn:admin1_code":"48.0",
    "gn:asciiname":"Ferdoua",
    "gn:cc2":"DZ",
    "gn:country_code":"DZ",
    "gn:dem":283,
    "gn:feature_class":"P",
    "gn:feature_code":"PPL",
    "gn:name":"Ferdoua",
    "gn:population":0,
    "gn:timezone":"Africa/Algiers",
    "iso:country":"DZ",
    "name:und_x_variant":[
        "Douar Ferdoua",
        "Ferdoua"
    ],
    "wof:name":"Ferdoua",
    "wof:placetype":"locality"
},
  "geometry": {"coordinates":[6.29,36.50833],"type":"Point"}
}