{
  "type": "Feature",
  "properties": {
    "gn:admin1_code":"19.0",
    "gn:asciiname":"Yaouda",
    "gn:country_code":"DZ",
    "gn:dem":229,
    "gn:feature_class":"P",
    "gn:feature_code":"PPL",
    "gn:name":"Yaouda",
    "gn:population":0,
    "gn:timezone":"Africa/Algiers",
    "iso:country":"DZ",
    "wof:name":"Yaouda",
    "wof:placetype":"locality"
},
  "geometry": {"coordinates":[5.62977,34.99448],"type":"Point"}
}