{
  "type": "Feature",
  "properties": {
    "gn:admin1_code":"15.0",
    "gn:asciiname":"Magdad",
    "gn:country_code":"DZ",
    "gn:dem":149,
    "gn:feature_class":"P",
    "gn:feature_code":"PPL",
    "gn:name":"Magdad",
    "gn:population":0,
    "gn:timezone":"Africa/Algiers",
    "iso:country":"DZ",
    "name:und_x_variant":[
        "Douar Magdad",
        "Magdad"
    ],
    "wof:name":"Magdad",
    "wof:placetype":"locality"
},
  "geometry": {"coordinates":[-1.86465,35.07175],"type":"Point"}
}