{
  "type": "Feature",
  "properties": {
    "gn:admin1_code":"41.0",
    "gn:asciiname":"El Hamr",
    "gn:country_code":"DZ",
    "gn:dem":288,
    "gn:feature_class":"P",
    "gn:feature_code":"PPL",
    "gn:name":"El Hamr",
    "gn:population":0,
    "gn:timezone":"Africa/Algiers",
    "iso:country":"DZ",
    "wof:name":"El Hamr",
    "wof:placetype":"locality"
},
  "geometry": {"coordinates":[1.43085,36.14497],"type":"Point"}
}