{
  "type": "Feature",
  "properties": {
    "gn:admin1_code":"21.0",
    "gn:asciiname":"Mechta Sidi Kherouf",
    "gn:country_code":"DZ",
    "gn:dem":906,
    "gn:feature_class":"P",
    "gn:feature_code":"PPL",
    "gn:name":"Mechta Sidi Kherouf",
    "gn:population":0,
    "gn:timezone":"Africa/Algiers",
    "iso:country":"DZ",
    "name:und_x_variant":[
        "Mechta Sidi Krerouf",
        "Mechta Sidi Kherouf"
    ],
    "wof:name":"Mechta Sidi Kherouf",
    "wof:placetype":"locality"
},
  "geometry": {"coordinates":[3.93143,35.99142],"type":"Point"}
}