{
  "type": "Feature",
  "properties": {
    "gn:admin1_code":"12.0",
    "gn:asciiname":"Mechta Hannech",
    "gn:country_code":"DZ",
    "gn:dem":910,
    "gn:feature_class":"P",
    "gn:feature_code":"PPL",
    "gn:name":"Mechta Hannech",
    "gn:population":0,
    "gn:timezone":"Africa/Algiers",
    "iso:country":"DZ",
    "wof:name":"Mechta Hannech",
    "wof:placetype":"locality"
},
  "geometry": {"coordinates":[5.67964,36.27481],"type":"Point"}
}