{
  "type": "Feature",
  "properties": {
    "gn:admin1_code":"6.0",
    "gn:asciiname":"Douar Hassi Debboub",
    "gn:country_code":"DZ",
    "gn:dem":834,
    "gn:feature_class":"P",
    "gn:feature_code":"PPL",
    "gn:name":"Douar Hassi Debboub",
    "gn:population":0,
    "gn:timezone":"Africa/Algiers",
    "iso:country":"DZ",
    "wof:name":"Douar Hassi Debboub",
    "wof:placetype":"locality"
},
  "geometry": {"coordinates":[2.3661,35.69754000000001],"type":"Point"}
}