{
  "type": "Feature",
  "properties": {
    "gn:admin1_code":"41.0",
    "gn:asciiname":"Douar Charia",
    "gn:country_code":"DZ",
    "gn:dem":614,
    "gn:feature_class":"P",
    "gn:feature_code":"PPL",
    "gn:name":"Douar Charia",
    "gn:population":0,
    "gn:timezone":"Africa/Algiers",
    "iso:country":"DZ",
    "wof:name":"Douar Charia",
    "wof:placetype":"locality"
},
  "geometry": {"coordinates":[1.47362,36.32733],"type":"Point"}
}