{
  "type": "Feature",
  "properties": {
    "gn:admin1_code":"6.0",
    "gn:asciiname":"Ferkat el M'haidia",
    "gn:country_code":"DZ",
    "gn:dem":645,
    "gn:feature_class":"P",
    "gn:feature_code":"PPL",
    "gn:name":"Ferkat el M\u2019ha\u00efdia",
    "gn:population":0,
    "gn:timezone":"Africa/Algiers",
    "iso:country":"DZ",
    "wof:name":"Ferkat el M'haidia",
    "wof:placetype":"locality"
},
  "geometry": {"coordinates":[3.3986,36.19419],"type":"Point"}
}