{
  "type": "Feature",
  "properties": {
    "gn:admin1_code":"26.0",
    "gn:asciiname":"Fergoug",
    "gn:country_code":"DZ",
    "gn:dem":95,
    "gn:feature_class":"P",
    "gn:feature_code":"PPL",
    "gn:name":"Fergo\u00fbg",
    "gn:population":0,
    "gn:timezone":"Africa/Algiers",
    "iso:country":"DZ",
    "name:und_x_variant":[
        "Douar Fergo\u00fbg",
        "Oued Fergoug",
        "Fergo\u00fbg"
    ],
    "wof:name":"Fergoug",
    "wof:placetype":"locality"
},
  "geometry": {"coordinates":[0.04066,35.52284],"type":"Point"}
}