{
  "type": "Feature",
  "properties": {
    "gn:admin1_code":"51.0",
    "gn:asciiname":"Bou Aker",
    "gn:country_code":"DZ",
    "gn:dem":699,
    "gn:feature_class":"P",
    "gn:feature_code":"PPL",
    "gn:name":"Bou Aker",
    "gn:population":0,
    "gn:timezone":"Africa/Algiers",
    "iso:country":"DZ",
    "name:und_x_variant":[
        "Douar Bou Aker",
        "Bou Aker"
    ],
    "wof:name":"Bou Aker",
    "wof:placetype":"locality"
},
  "geometry": {"coordinates":[1.0092,35.61852000000001],"type":"Point"}
}