{
  "type": "Feature",
  "properties": {
    "gn:admin1_code":"51.0",
    "gn:asciiname":"Ouled Abed",
    "gn:country_code":"DZ",
    "gn:dem":39,
    "gn:feature_class":"P",
    "gn:feature_code":"PPL",
    "gn:name":"Ouled Abed",
    "gn:population":0,
    "gn:timezone":"Africa/Algiers",
    "iso:country":"DZ",
    "name:und_x_variant":[
        "Mechtat Oulad Abed"
    ],
    "wof:name":"Ouled Abed",
    "wof:placetype":"locality"
},
  "geometry": {"coordinates":[0.6196,35.91500999999999],"type":"Point"}
}