{
  "type": "Feature",
  "properties": {
    "gn:admin1_code":"44.0",
    "gn:asciiname":"Toustain",
    "gn:country_code":"DZ",
    "gn:dem":136,
    "gn:feature_class":"P",
    "gn:feature_code":"PPL",
    "gn:name":"Toustain",
    "gn:population":0,
    "gn:timezone":"Africa/Algiers",
    "iso:country":"DZ",
    "name:und_x_variant":[
        "Zitouna",
        "Toustain"
    ],
    "wof:name":"Toustain",
    "wof:placetype":"locality"
},
  "geometry": {"coordinates":[8.23366,36.66783],"type":"Point"}
}