{
  "type": "Feature",
  "properties": {
    "gn:admin1_code":"14.0",
    "gn:asciiname":"Akaoudj",
    "gn:country_code":"DZ",
    "gn:dem":185,
    "gn:feature_class":"P",
    "gn:feature_code":"PPL",
    "gn:name":"Akaoudj",
    "gn:population":0,
    "gn:timezone":"Africa/Algiers",
    "iso:country":"DZ",
    "name:azb_x_preferred":[
        "\u0627\u06a9\u0648\u062c"
    ],
    "name:ceb_x_preferred":[
        "Akaoudj"
    ],
    "name:fas_x_preferred":[
        "\u0627\u06a9\u0648\u062c"
    ],
    "name:swe_x_preferred":[
        "Akaoudj"
    ],
    "wof:name":"Akaoudj",
    "wof:placetype":"locality"
},
  "geometry": {"coordinates":[4.07378,36.74009],"type":"Point"}
}