{
  "type": "Feature",
  "properties": {
    "gn:admin1_code":"41.0",
    "gn:asciiname":"Sobha",
    "gn:country_code":"DZ",
    "gn:dem":109,
    "gn:feature_class":"P",
    "gn:feature_code":"PPL",
    "gn:name":"Sobha",
    "gn:population":0,
    "gn:timezone":"Africa/Algiers",
    "iso:country":"DZ",
    "name:ara_x_preferred":[
        "\u0635\u0628\u062d\u0629"
    ],
    "name:azb_x_preferred":[
        "\u0635\u0628\u062d\u0647"
    ],
    "name:fas_x_preferred":[
        "\u0635\u0628\u062d\u0647"
    ],
    "name:fra_x_preferred":[
        "Sobha"
    ],
    "name:ita_x_preferred":[
        "Sobha"
    ],
    "name:kab_x_preferred":[
        "\u1e62ub\u1e25a"
    ],
    "name:msa_x_preferred":[
        "Sobha"
    ],
    "name:por_x_preferred":[
        "Sobha"
    ],
    "name:ron_x_preferred":[
        "Sobha"
    ],
    "name:spa_x_preferred":[
        "Sobha"
    ],
    "name:urd_x_preferred":[
        "\u0635\u0628\u062d\u06c1"
    ],
    "name:vie_x_preferred":[
        "Sobha"
    ],
    "wof:name":"Sobha",
    "wof:placetype":"locality"
},
  "geometry": {"coordinates":[1.10845,36.10998],"type":"Point"}
}