{
  "type": "Feature",
  "properties": {
    "gn:admin1_code":"41.0",
    "gn:asciiname":"Sobha",
    "gn:country_code":"DZ",
    "gn:dem":109,
    "gn:feature_class":"P",
    "gn:feature_code":"PPL",
    "gn:name":"Sobha",
    "gn:population":0,
    "gn:timezone":"Africa/Algiers",
    "iso:country":"DZ",
    "wof:name":"Sobha",
    "wof:placetype":"locality"
},
  "geometry": {"coordinates":[1.10845,36.10998],"type":"Point"}
}