{
  "type": "Feature",
  "properties": {
    "gn:admin1_code":"30.0",
    "gn:asciiname":"Douar Djebairia",
    "gn:country_code":"DZ",
    "gn:dem":570,
    "gn:feature_class":"P",
    "gn:feature_code":"PPL",
    "gn:name":"Douar Djeba\u00efria",
    "gn:population":0,
    "gn:timezone":"Africa/Algiers",
    "iso:country":"DZ",
    "name:und_x_variant":[
        "Sully",
        "Douar Djeba\u00efria"
    ],
    "wof:name":"Douar Djebairia",
    "wof:placetype":"locality"
},
  "geometry": {"coordinates":[-0.57811,35.11002],"type":"Point"}
}