{
  "type": "Feature",
  "properties": {
    "gn:admin1_code":"35.0",
    "gn:asciiname":"Douar Ababda",
    "gn:country_code":"DZ",
    "gn:dem":716,
    "gn:feature_class":"P",
    "gn:feature_code":"PPL",
    "gn:name":"Douar Ababda",
    "gn:population":0,
    "gn:timezone":"Africa/Algiers",
    "iso:country":"DZ",
    "wof:name":"Douar Ababda",
    "wof:placetype":"locality"
},
  "geometry": {"coordinates":[2.43413,36.08212],"type":"Point"}
}