{
  "type": "Feature",
  "properties": {
    "gn:admin1_code":"21.0",
    "gn:asciiname":"Mechta Marouf",
    "gn:country_code":"DZ",
    "gn:dem":913,
    "gn:feature_class":"P",
    "gn:feature_code":"PPL",
    "gn:name":"Mechta Marouf",
    "gn:population":0,
    "gn:timezone":"Africa/Algiers",
    "iso:country":"DZ",
    "wof:name":"Mechta Marouf",
    "wof:placetype":"locality"
},
  "geometry": {"coordinates":[4.0205,35.98408],"type":"Point"}
}