{
  "type": "Feature",
  "properties": {
    "gn:admin1_code":"27.0",
    "gn:asciiname":"Ouled Bedira",
    "gn:country_code":"DZ",
    "gn:dem":498,
    "gn:feature_class":"P",
    "gn:feature_code":"PPL",
    "gn:name":"Ouled Bedira",
    "gn:population":0,
    "gn:timezone":"Africa/Algiers",
    "iso:country":"DZ",
    "wof:name":"Ouled Bedira",
    "wof:placetype":"locality"
},
  "geometry": {"coordinates":[4.56005,35.74416],"type":"Point"}
}