{
  "type": "Feature",
  "properties": {
    "gn:admin1_code":"35.0",
    "gn:asciiname":"El Meraimia",
    "gn:country_code":"DZ",
    "gn:dem":305,
    "gn:feature_class":"P",
    "gn:feature_code":"PPL",
    "gn:name":"El Mera\u00efmia",
    "gn:population":0,
    "gn:timezone":"Africa/Algiers",
    "iso:country":"DZ",
    "wof:name":"El Meraimia",
    "wof:placetype":"locality"
},
  "geometry": {"coordinates":[1.88938,36.15754],"type":"Point"}
}