{
  "type": "Feature",
  "properties": {
    "iso:country":"DZ",
    "name:ara_x_preferred":[
        "\u0628\u0646\u064a \u0648\u0646\u064a\u0641"
    ],
    "name:dut_x_preferred":[
        "B\u00e9ni Ounif"
    ],
    "name:eng_x_preferred":[
        "B\u00e9ni Ounif"
    ],
    "name:fre_x_preferred":[
        "Beni Ounif"
    ],
    "name:ger_x_preferred":[
        "Beni Ounif"
    ],
    "name:ita_x_preferred":[
        "Beni Ounif"
    ],
    "name:kab_x_preferred":[
        "Bni Wnif"
    ],
    "name:may_x_preferred":[
        "Beni Ounif"
    ],
    "name:per_x_preferred":[
        "\u0628\u0646\u06cc \u0648\u0646\u06cc\u0641"
    ],
    "name:por_x_preferred":[
        "B\u00e9ni Ounif"
    ],
    "name:rum_x_preferred":[
        "Beni Ounif"
    ],
    "name:vie_x_preferred":[
        "Beni Ounif"
    ],
    "ne:ADM0CAP":0.0,
    "ne:ADM0NAME":"Algeria",
    "ne:ADM0_A3":"DZA",
    "ne:ADM1NAME":"BZchar",
    "ne:ADMIN1_COD":0,
    "ne:CAPALT":0,
    "ne:CHANGED":0,
    "ne:CHECKME":0,
    "ne:COMPARE":0,
    "ne:DIFFASCII":0,
    "ne:ELEVATION":0.0,
    "ne:FEATURECLA":"Populated place",
    "ne:GEONAMEID":-1,
    "ne:GN_POP":0,
    "ne:GTOPO30":0.0,
    "ne:ISO_A2":"DZ",
    "ne:LABELRANK":5,
    "ne:LATITUDE":32.04927,
    "ne:LONGITUDE":-1.251381,
    "ne:LS_MATCH":1,
    "ne:LS_NAME":"Beni Ounif",
    "ne:MAX_AREAKM":4.0,
    "ne:MAX_AREAMI":1.0,
    "ne:MAX_BBXMAX":-1.233333,
    "ne:MAX_BBXMIN":-1.258333,
    "ne:MAX_BBYMAX":32.058333,
    "ne:MAX_BBYMIN":32.041667,
    "ne:MAX_NATSCA":20.0,
    "ne:MAX_PERKM":9.0,
    "ne:MAX_PERMI":5.0,
    "ne:MAX_POP10":5628,
    "ne:MAX_POP20":5628,
    "ne:MAX_POP300":0,
    "ne:MAX_POP310":0,
    "ne:MAX_POP50":0,
    "ne:MEAN_BBXC":-1.2475,
    "ne:MEAN_BBYC":32.049167,
    "ne:MEGACITY":0,
    "ne:MIN_AREAKM":4.0,
    "ne:MIN_AREAMI":1.0,
    "ne:MIN_BBXMAX":-1.233333,
    "ne:MIN_BBXMIN":-1.258333,
    "ne:MIN_BBYMAX":32.058333,
    "ne:MIN_BBYMIN":32.041667,
    "ne:MIN_PERKM":9.0,
    "ne:MIN_PERMI":5.0,
    "ne:NAME":"Beni Ounif",
    "ne:NAMEASCII":"Beni Ounif",
    "ne:NAMEDIFF":0,
    "ne:NATSCALE":20,
    "ne:POP1950":0,
    "ne:POP1955":0,
    "ne:POP1960":0,
    "ne:POP1965":0,
    "ne:POP1970":0,
    "ne:POP1975":0,
    "ne:POP1980":0,
    "ne:POP1985":0,
    "ne:POP1990":0,
    "ne:POP1995":0,
    "ne:POP2000":0,
    "ne:POP2005":0,
    "ne:POP2010":0,
    "ne:POP2015":0,
    "ne:POP2020":0,
    "ne:POP2025":0,
    "ne:POP2050":0,
    "ne:POP_MAX":5628,
    "ne:POP_MIN":5628,
    "ne:POP_OTHER":5628,
    "ne:RANK_MAX":5,
    "ne:RANK_MIN":5,
    "ne:SCALERANK":7,
    "ne:SOV0NAME":"Algeria",
    "ne:SOV_A3":"DZA",
    "ne:UN_FID":0,
    "ne:UN_LAT":0.0,
    "ne:UN_LONG":0.0,
    "ne:WORLDCITY":0,
    "ne:min_zoom":6.1,
    "wof:name":"Beni Ounif",
    "wof:placetype":"locality"
},
  "geometry": {"coordinates":[-1.25138126769571,32.04926983543101],"type":"Point"}
}