{
  "type": "Feature",
  "properties": {
    "iso:country":"DZ",
    "name:ara_x_preferred":[
        "\u0633\u0641\u064a\u0632\u0641"
    ],
    "name:ceb_x_preferred":[
        "Sfizef"
    ],
    "name:dut_x_preferred":[
        "Sfissef"
    ],
    "name:eng_x_preferred":[
        "Sfissef"
    ],
    "name:fra_x_preferred":[
        "Sfisef"
    ],
    "name:fre_x_preferred":[
        "Sfisef"
    ],
    "name:ita_x_preferred":[
        "Sfisef"
    ],
    "name:kab_x_preferred":[
        "Sfisef"
    ],
    "name:may_x_preferred":[
        "Sfissef"
    ],
    "name:msa_x_preferred":[
        "Sfissef"
    ],
    "name:per_x_preferred":[
        "\u0633\u0641\u06cc\u0632\u0641"
    ],
    "name:pol_x_preferred":[
        "Sufajzif"
    ],
    "name:por_x_preferred":[
        "Sfissef"
    ],
    "name:ron_x_preferred":[
        "Sfisef"
    ],
    "name:rum_x_preferred":[
        "Sfisef"
    ],
    "name:swe_x_preferred":[
        "Sfizef"
    ],
    "name:unk_x_variant":[
        "Mercier-Lacombe"
    ],
    "name:zho_min_nan_x_preferred":[
        "Sfisef"
    ],
    "qs:gn_country":"DZ",
    "qs:gn_fcode":"PPL",
    "qs:gn_pop":31081,
    "qs:name":"Sfizef",
    "qs:name_adm0":"\u0627\u0644\u062c\u0632\u0627\u0626\u0631",
    "qs:name_adm1":"\u0648\u0644\u0627\u064a\u0629 \u0633\u064a\u062f\u064a \u0628\u0644\u0639\u0628\u0627\u0633",
    "qs:photos":0,
    "qs:photos_1k":0,
    "qs:photos_9k":0,
    "qs:photos_9r":0,
    "qs:photos_all":0,
    "qs:photos_sr":0,
    "qs:placetype":"Town",
    "qs:pop_sr":"7",
    "qs:woe_adm0":23424740,
    "wd:wordcount":40,
    "wof:name":"Sfizef",
    "wof:placetype":"locality",
    "wof:population":31081
},
  "geometry": {"coordinates":[-0.24435,35.23464],"type":"Point"}
}