{
  "type": "Feature",
  "properties": {
    "gn:admin1_code":"7.0",
    "gn:asciiname":"Chnegliah",
    "gn:country_code":"DZ",
    "gn:dem":54,
    "gn:feature_class":"P",
    "gn:feature_code":"PPL",
    "gn:name":"Chnegliah",
    "gn:population":0,
    "gn:timezone":"Africa/Algiers",
    "iso:country":"DZ",
    "name:und_x_variant":[
        "Douar Chenaghia",
        "Douar Chnegliah",
        "Chnegliah"
    ],
    "wof:name":"Chnegliah",
    "wof:placetype":"locality"
},
  "geometry": {"coordinates":[0.12824,35.64599000000001],"type":"Point"}
}