{
  "type": "Feature",
  "properties": {
    "gn:admin1_code":"7.0",
    "gn:asciiname":"Douar N'djajra",
    "gn:country_code":"DZ",
    "gn:dem":204,
    "gn:feature_class":"P",
    "gn:feature_code":"PPL",
    "gn:name":"Douar N\u2019djajra",
    "gn:population":0,
    "gn:timezone":"Africa/Algiers",
    "iso:country":"DZ",
    "name:und_x_variant":[
        "Douar Nedjedjra",
        "Dou\u00e2r Medjazera",
        "Douar N\u2019djajra",
        "Medjazera"
    ],
    "wof:name":"Douar N'djajra",
    "wof:placetype":"locality"
},
  "geometry": {"coordinates":[0.2163,35.85955],"type":"Point"}
}