{
  "type": "Feature",
  "properties": {
    "gn:admin1_code":"13.0",
    "gn:asciiname":"Oulad Ben Chaib",
    "gn:country_code":"DZ",
    "gn:dem":732,
    "gn:feature_class":"P",
    "gn:feature_code":"PPL",
    "gn:name":"Oulad Ben Cha\u00efb",
    "gn:population":0,
    "gn:timezone":"Africa/Algiers",
    "iso:country":"DZ",
    "wof:name":"Oulad Ben Chaib",
    "wof:placetype":"locality"
},
  "geometry": {"coordinates":[1.35827,35.58434000000001],"type":"Point"}
}