{
  "type": "Feature",
  "properties": {
    "gn:admin1_code":"14.0",
    "gn:asciiname":"Tifera",
    "gn:country_code":"DZ",
    "gn:dem":529,
    "gn:feature_class":"P",
    "gn:feature_code":"PPL",
    "gn:name":"Tifera",
    "gn:population":0,
    "gn:timezone":"Africa/Algiers",
    "iso:country":"DZ",
    "wof:name":"Tifera",
    "wof:placetype":"locality"
},
  "geometry": {"coordinates":[4.14534,36.84112],"type":"Point"}
}