{
  "type": "Feature",
  "properties": {
    "gn:admin1_code":"26.0",
    "gn:asciiname":"Ouled Aissa",
    "gn:country_code":"DZ",
    "gn:dem":766,
    "gn:feature_class":"P",
    "gn:feature_code":"PPL",
    "gn:name":"Ouled Aissa",
    "gn:population":0,
    "gn:timezone":"Africa/Algiers",
    "iso:country":"DZ",
    "name:ara_x_preferred":[
        "\u0623\u0648\u0644\u0627\u062f \u0639\u064a\u0633\u0649"
    ],
    "name:fra_x_preferred":[
        "Ouled A\u00efssa"
    ],
    "name:ita_x_preferred":[
        "Ouled A\u00efssa"
    ],
    "name:msa_x_preferred":[
        "Ouled Aissa"
    ],
    "name:ron_x_preferred":[
        "Ouled A\u00efssa"
    ],
    "name:und_x_variant":[
        "Douar Oulad A\u00efssa"
    ],
    "wof:name":"Ouled Aissa",
    "wof:placetype":"locality"
},
  "geometry": {"coordinates":[0.60914,35.34443],"type":"Point"}
}