{
  "type": "Feature",
  "properties": {
    "gn:admin1_code":"26.0",
    "gn:asciiname":"Ouled Aissa",
    "gn:country_code":"DZ",
    "gn:dem":766,
    "gn:feature_class":"P",
    "gn:feature_code":"PPL",
    "gn:name":"Ouled Aissa",
    "gn:population":0,
    "gn:timezone":"Africa/Algiers",
    "iso:country":"DZ",
    "name:und_x_variant":[
        "Douar Oulad A\u00efssa"
    ],
    "wof:name":"Ouled Aissa",
    "wof:placetype":"locality"
},
  "geometry": {"coordinates":[0.60914,35.34443],"type":"Point"}
}