{
  "type": "Feature",
  "properties": {
    "gn:admin1_code":"27.0",
    "gn:asciiname":"Chellal",
    "gn:country_code":"DZ",
    "gn:dem":409,
    "gn:feature_class":"P",
    "gn:feature_code":"PPL",
    "gn:name":"Chellal",
    "gn:population":0,
    "gn:timezone":"Africa/Algiers",
    "iso:country":"DZ",
    "name:und_x_variant":[
        "Hodnet Oued M\u2019Sila",
        "Bordj Chellal",
        "Chellal"
    ],
    "wof:name":"Chellal",
    "wof:placetype":"locality"
},
  "geometry": {"coordinates":[4.3853,35.51768],"type":"Point"}
}