{
  "type": "Feature",
  "properties": {
    "gn:admin1_code":"27.0",
    "gn:asciiname":"Chellal",
    "gn:country_code":"DZ",
    "gn:dem":409,
    "gn:feature_class":"P",
    "gn:feature_code":"PPL",
    "gn:name":"Chellal",
    "gn:population":0,
    "gn:timezone":"Africa/Algiers",
    "iso:country":"DZ",
    "name:ara_x_preferred":[
        "\u0634\u0644\u0627\u0644"
    ],
    "name:azb_x_preferred":[
        "\u0634\u0644\u0627\u0644"
    ],
    "name:fas_x_preferred":[
        "\u0634\u0644\u0627\u0644"
    ],
    "name:fra_x_preferred":[
        "Chellal"
    ],
    "name:ita_x_preferred":[
        "Chellal"
    ],
    "name:msa_x_preferred":[
        "Chellal"
    ],
    "name:por_x_preferred":[
        "Chellal"
    ],
    "name:ron_x_preferred":[
        "Chellal"
    ],
    "name:spa_x_preferred":[
        "Chellal"
    ],
    "name:und_x_variant":[
        "Hodnet Oued M\u2019Sila",
        "Bordj Chellal"
    ],
    "name:vie_x_preferred":[
        "Chellal"
    ],
    "wof:name":"Chellal",
    "wof:placetype":"locality"
},
  "geometry": {"coordinates":[4.3853,35.51768],"type":"Point"}
}