{
  "type": "Feature",
  "properties": {
    "gn:admin1_code":"21.0",
    "gn:asciiname":"Lahguiat",
    "gn:country_code":"DZ",
    "gn:dem":436,
    "gn:feature_class":"P",
    "gn:feature_code":"PPL",
    "gn:name":"Lahguiat",
    "gn:population":0,
    "gn:timezone":"Africa/Algiers",
    "iso:country":"DZ",
    "name:und_x_variant":[
        "Dechra Lahguiat",
        "Lahguiat"
    ],
    "wof:name":"Lahguiat",
    "wof:placetype":"locality"
},
  "geometry": {"coordinates":[3.68605,36.4761],"type":"Point"}
}