{
  "type": "Feature",
  "properties": {
    "gn:admin1_code":"38.0",
    "gn:asciiname":"Ben Zireg",
    "gn:country_code":"DZ",
    "gn:dem":949,
    "gn:feature_class":"P",
    "gn:feature_code":"PPL",
    "gn:name":"Ben Zireg",
    "gn:population":0,
    "gn:timezone":"Africa/Algiers",
    "iso:country":"DZ",
    "wof:name":"Ben Zireg",
    "wof:placetype":"locality"
},
  "geometry": {"coordinates":[-1.83848,31.91914],"type":"Point"}
}