{
  "type": "Feature",
  "properties": {
    "gn:admin1_code":"43.0",
    "gn:asciiname":"Ouzitene",
    "gn:country_code":"DZ",
    "gn:dem":79,
    "gn:feature_class":"P",
    "gn:feature_code":"PPL",
    "gn:name":"Ouzit\u00e8ne",
    "gn:population":0,
    "gn:timezone":"Africa/Algiers",
    "iso:country":"DZ",
    "wof:name":"Ouzitene",
    "wof:placetype":"locality"
},
  "geometry": {"coordinates":[6.83333,33.35],"type":"Point"}
}