{
  "type": "Feature",
  "properties": {
    "gn:admin1_code":"6.0",
    "gn:asciiname":"Draa Mamiounet",
    "gn:country_code":"DZ",
    "gn:dem":796,
    "gn:feature_class":"P",
    "gn:feature_code":"PPL",
    "gn:name":"Draa Mamiounet",
    "gn:population":0,
    "gn:timezone":"Africa/Algiers",
    "iso:country":"DZ",
    "wof:name":"Draa Mamiounet",
    "wof:placetype":"locality"
},
  "geometry": {"coordinates":[3.3065,36.13019],"type":"Point"}
}