{
  "type": "Feature",
  "properties": {
    "gn:admin1_code":"35.0",
    "gn:asciiname":"Lemraoubia",
    "gn:country_code":"DZ",
    "gn:dem":469,
    "gn:feature_class":"P",
    "gn:feature_code":"PPL",
    "gn:name":"Lemraoubia",
    "gn:population":0,
    "gn:timezone":"Africa/Algiers",
    "iso:country":"DZ",
    "wof:name":"Lemraoubia",
    "wof:placetype":"locality"
},
  "geometry": {"coordinates":[1.97565,36.31873],"type":"Point"}
}