{
  "type": "Feature",
  "properties": {
    "gn:country":"DZ",
    "gn:fcode":"PPL",
    "gn:pop":28029,
    "iso:country":"DZ",
    "name:ara_x_preferred":[
        "\u0639\u064a\u0646 \u0627\u0644\u062d\u0645\u0627\u0645"
    ],
    "name:azb_x_preferred":[
        "\u0639\u06cc\u0646 \u0627\u0644\u062d\u0645\u0627\u0645"
    ],
    "name:cat_x_preferred":[
        "Ain El Hammam"
    ],
    "name:deu_x_preferred":[
        "A\u00efn El Hammam"
    ],
    "name:eng_x_preferred":[
        "A\u00efn El Hammam"
    ],
    "name:fas_x_preferred":[
        "\u0639\u06cc\u0646 \u0627\u0644\u062d\u0645\u0627\u0645"
    ],
    "name:fra_x_preferred":[
        "A\u00efn El Hammam"
    ],
    "name:ita_x_preferred":[
        "A\u00efn El Hammam"
    ],
    "name:kab_x_preferred":[
        "A\u1e63qif n \u1e6cmana"
    ],
    "name:msa_x_preferred":[
        "Ain El Hammam"
    ],
    "name:nan_x_preferred":[
        "A\u00efn El Hammam"
    ],
    "name:nld_x_preferred":[
        "Ain El Hammam"
    ],
    "name:por_x_preferred":[
        "A\u00efn El Hammam"
    ],
    "name:ron_x_preferred":[
        "A\u00efn El Hammam"
    ],
    "name:rus_x_preferred":[
        "\u0410\u0439\u043d-\u044d\u043b\u044c-\u0425\u0430\u043c\u043c\u0430\u043c"
    ],
    "name:sco_x_preferred":[
        "A\u00efn El Hammam"
    ],
    "name:spa_x_preferred":[
        "A\u00efn El Hammam"
    ],
    "name:swe_x_preferred":[
        "A\u00efn El Hammam"
    ],
    "name:unk_x_variant":[
        "Michelet"
    ],
    "name:vie_x_preferred":[
        "Ain-El-Hammam"
    ],
    "name:zho_x_preferred":[
        "\u827e\u56e0\u54c8\u99ac\u59c6"
    ],
    "qs:name":"\u2019A\u00efn el Hammam",
    "qs:photos_9r":0,
    "qs:photos_sr":0,
    "qs:pop_sr":"7",
    "wd:wordcount":31,
    "wof:name":"\u2019A\u00efn el Hammam",
    "wof:placetype":"locality",
    "wof:population":28029
},
  "geometry": {"coordinates":[4.30619,36.56471],"type":"Point"}
}