{
  "type": "Feature",
  "properties": {
    "gn:admin1_code":"35.0",
    "gn:asciiname":"El Halailia",
    "gn:country_code":"DZ",
    "gn:dem":342,
    "gn:feature_class":"P",
    "gn:feature_code":"PPL",
    "gn:name":"El Hala\u00eflia",
    "gn:population":0,
    "gn:timezone":"Africa/Algiers",
    "iso:country":"DZ",
    "wof:name":"El Halailia",
    "wof:placetype":"locality"
},
  "geometry": {"coordinates":[1.78734,36.18809],"type":"Point"}
}