{
  "type": "Feature",
  "properties": {
    "gn:admin1_code":"51.0",
    "gn:asciiname":"Douar el Abaidia",
    "gn:country_code":"DZ",
    "gn:dem":91,
    "gn:feature_class":"P",
    "gn:feature_code":"PPL",
    "gn:name":"Douar el Aba\u00efdia",
    "gn:population":0,
    "gn:timezone":"Africa/Algiers",
    "iso:country":"DZ",
    "name:und_x_variant":[
        "Douar el Aba\u00efdia",
        "Douar el Abe\u00efdia"
    ],
    "wof:name":"Douar el Abaidia",
    "wof:placetype":"locality"
},
  "geometry": {"coordinates":[0.37375,35.75556],"type":"Point"}
}