{
  "type": "Feature",
  "properties": {
    "gn:admin1_code":"27.0",
    "gn:asciiname":"Roumana",
    "gn:country_code":"DZ",
    "gn:dem":534,
    "gn:feature_class":"P",
    "gn:feature_code":"PPL",
    "gn:name":"Roumana",
    "gn:population":0,
    "gn:timezone":"Africa/Algiers",
    "iso:country":"DZ",
    "wof:name":"Roumana",
    "wof:placetype":"locality"
},
  "geometry": {"coordinates":[4.30007,35.21538],"type":"Point"}
}