{
  "type": "Feature",
  "properties": {
    "gn:admin1_code":"12.0",
    "gn:asciiname":"Mechtet Bou Medjou",
    "gn:country_code":"DZ",
    "gn:dem":900,
    "gn:feature_class":"P",
    "gn:feature_code":"PPL",
    "gn:name":"Mechtet Bou Medjou",
    "gn:population":0,
    "gn:timezone":"Africa/Algiers",
    "iso:country":"DZ",
    "wof:name":"Mechtet Bou Medjou",
    "wof:placetype":"locality"
},
  "geometry": {"coordinates":[5.88889,35.98444],"type":"Point"}
}