{
  "type": "Feature",
  "properties": {
    "gn:admin1_code":"24.0",
    "gn:asciiname":"Zaouia el Hadjria",
    "gn:country_code":"DZ",
    "gn:dem":241,
    "gn:feature_class":"P",
    "gn:feature_code":"PPL",
    "gn:name":"Zaouia el Hadjria",
    "gn:population":0,
    "gn:timezone":"Africa/Algiers",
    "iso:country":"DZ",
    "name:und_x_variant":[
        "El Hadjr\u00eeya",
        "Zaouia el Hadjria"
    ],
    "wof:name":"Zaouia el Hadjria",
    "wof:placetype":"locality"
},
  "geometry": {"coordinates":[6.25892,36.88951],"type":"Point"}
}