{
  "type": "Feature",
  "properties": {
    "gn:admin1_code":"6.0",
    "gn:asciiname":"Douar Lakhail",
    "gn:country_code":"DZ",
    "gn:dem":793,
    "gn:feature_class":"P",
    "gn:feature_code":"PPL",
    "gn:name":"Douar Lakhail",
    "gn:population":0,
    "gn:timezone":"Africa/Algiers",
    "iso:country":"DZ",
    "wof:name":"Douar Lakhail",
    "wof:placetype":"locality"
},
  "geometry": {"coordinates":[2.87348,36.0841],"type":"Point"}
}