{
  "type": "Feature",
  "properties": {
    "gn:admin1_code":"13.0",
    "gn:asciiname":"El Hatatba",
    "gn:country_code":"DZ",
    "gn:dem":767,
    "gn:feature_class":"P",
    "gn:feature_code":"PPL",
    "gn:name":"El Hatatba",
    "gn:population":0,
    "gn:timezone":"Africa/Algiers",
    "iso:country":"DZ",
    "name:und_x_variant":[
        "Douar el Hatatba",
        "El Hatatba"
    ],
    "wof:name":"El Hatatba",
    "wof:placetype":"locality"
},
  "geometry": {"coordinates":[1.16254,35.26385],"type":"Point"}
}