{
  "type": "Feature",
  "properties": {
    "gn:admin1_code":"47.0",
    "gn:asciiname":"Taberdga",
    "gn:country_code":"DZ",
    "gn:dem":1159,
    "gn:feature_class":"P",
    "gn:feature_code":"PPL",
    "gn:name":"Taberdga",
    "gn:population":0,
    "gn:timezone":"Africa/Algiers",
    "iso:country":"DZ",
    "name:und_x_variant":[
        "Talberdga",
        "Tabendga",
        "Taberdga"
    ],
    "wof:name":"Taberdga",
    "wof:placetype":"locality"
},
  "geometry": {"coordinates":[7.00477,35.03836],"type":"Point"}
}