{
  "type": "Feature",
  "properties": {
    "gn:admin1_code":"9.0",
    "gn:asciiname":"Assi Bou Nif",
    "gn:cc2":"DZ",
    "gn:country_code":"DZ",
    "gn:dem":121,
    "gn:feature_class":"P",
    "gn:feature_code":"PPL",
    "gn:name":"Assi Bou Nif",
    "gn:population":0,
    "gn:timezone":"Africa/Algiers",
    "iso:country":"DZ",
    "name:und_x_variant":[
        "Hassi Bou Nif",
        "Assi Bou Nif"
    ],
    "wof:name":"Assi Bou Nif",
    "wof:placetype":"locality"
},
  "geometry": {"coordinates":[-0.49944,35.69222],"type":"Point"}
}