{
  "type": "Feature",
  "properties": {
    "gn:admin1_code":"6.0",
    "gn:asciiname":"Ouled Thabet",
    "gn:country_code":"DZ",
    "gn:dem":1044,
    "gn:feature_class":"P",
    "gn:feature_code":"PPL",
    "gn:name":"Ouled Thabet",
    "gn:population":0,
    "gn:timezone":"Africa/Algiers",
    "iso:country":"DZ",
    "wof:name":"Ouled Thabet",
    "wof:placetype":"locality"
},
  "geometry": {"coordinates":[3.30819,36.04789],"type":"Point"}
}