{
  "type": "Feature",
  "properties": {
    "gn:admin1_code":"6.0",
    "gn:asciiname":"Ben Attali",
    "gn:country_code":"DZ",
    "gn:dem":768,
    "gn:feature_class":"P",
    "gn:feature_code":"PPL",
    "gn:name":"Ben Attali",
    "gn:population":0,
    "gn:timezone":"Africa/Algiers",
    "iso:country":"DZ",
    "wof:name":"Ben Attali",
    "wof:placetype":"locality"
},
  "geometry": {"coordinates":[2.75082,36.31348],"type":"Point"}
}