{
  "type": "Feature",
  "properties": {
    "gn:admin1_code":"35.0",
    "gn:asciiname":"Hadj el Djelani",
    "gn:country_code":"DZ",
    "gn:dem":515,
    "gn:feature_class":"P",
    "gn:feature_code":"PPL",
    "gn:name":"Hadj el Djelani",
    "gn:population":0,
    "gn:timezone":"Africa/Algiers",
    "iso:country":"DZ",
    "wof:name":"Hadj el Djelani",
    "wof:placetype":"locality"
},
  "geometry": {"coordinates":[2.61667,36.11667],"type":"Point"}
}