{
  "type": "Feature",
  "properties": {
    "gn:admin1_code":"13.0",
    "gn:asciiname":"Kaddour Bel Hadj",
    "gn:country_code":"DZ",
    "gn:dem":925,
    "gn:feature_class":"P",
    "gn:feature_code":"PPL",
    "gn:name":"Kaddour Bel Hadj",
    "gn:population":0,
    "gn:timezone":"Africa/Algiers",
    "iso:country":"DZ",
    "wof:name":"Kaddour Bel Hadj",
    "wof:placetype":"locality"
},
  "geometry": {"coordinates":[1.83702,35.29307],"type":"Point"}
}