{
  "type": "Feature",
  "properties": {
    "gn:admin1_code":"52.0",
    "gn:asciiname":"Mechta Oulad Rajah",
    "gn:country_code":"DZ",
    "gn:dem":843,
    "gn:feature_class":"P",
    "gn:feature_code":"PPL",
    "gn:name":"Mechta Oulad Rajah",
    "gn:population":0,
    "gn:timezone":"Africa/Algiers",
    "iso:country":"DZ",
    "wof:name":"Mechta Oulad Rajah",
    "wof:placetype":"locality"
},
  "geometry": {"coordinates":[7.57924,36.16555],"type":"Point"}
}