{
  "type": "Feature",
  "properties": {
    "gn:admin1_code":"18.0",
    "gn:asciiname":"Adeyane",
    "gn:country_code":"DZ",
    "gn:dem":969,
    "gn:feature_class":"P",
    "gn:feature_code":"PPL",
    "gn:name":"Adeyane",
    "gn:population":0,
    "gn:timezone":"Africa/Algiers",
    "iso:country":"DZ",
    "name:und_x_variant":[
        "Ayedan",
        "Adeyane"
    ],
    "wof:name":"Adeyane",
    "wof:placetype":"locality"
},
  "geometry": {"coordinates":[5.48168,36.59537],"type":"Point"}
}