{
  "type": "Feature",
  "properties": {
    "iso:country":"DZ",
    "name:ara_x_preferred":[
        "\u0628\u0631\u062c \u0632\u0645\u0648\u0631\u0629"
    ],
    "name:ceb_x_preferred":[
        "Bordj Zemoura"
    ],
    "name:eng_x_preferred":[
        "Bordj Zemoura"
    ],
    "name:fas_x_preferred":[
        "\u0628\u0631\u062c \u0632\u0645\u0648\u0631\u0647"
    ],
    "name:fra_x_preferred":[
        "Bordj Zemoura"
    ],
    "name:ita_x_preferred":[
        "Bordj Zemoura"
    ],
    "name:msa_x_preferred":[
        "Bordj Zemoura"
    ],
    "name:nld_x_preferred":[
        "Bordj Zemoura"
    ],
    "name:por_x_preferred":[
        "Bordj Zemoura"
    ],
    "name:ron_x_preferred":[
        "Bordj Zemoura"
    ],
    "name:swe_x_preferred":[
        "Bordj Zemoura"
    ],
    "name:unk_x_variant":[
        "Zemmoura"
    ],
    "name:vie_x_preferred":[
        "Bordj Zemoura"
    ],
    "name:zho_min_nan_x_preferred":[
        "Bordj Zemoura"
    ],
    "qs:gn_country":"DZ",
    "qs:gn_fcode":"PPL",
    "qs:gn_pop":19782,
    "qs:name":"Bordj Zemoura",
    "qs:name_adm0":"\u0627\u0644\u062c\u0632\u0627\u0626\u0631",
    "qs:name_adm1":"Setif",
    "qs:photos":0,
    "qs:photos_1k":0,
    "qs:photos_9k":0,
    "qs:photos_9r":0,
    "qs:photos_all":0,
    "qs:photos_sr":0,
    "qs:placetype":"Town",
    "qs:pop_sr":"6",
    "qs:woe_adm0":23424740,
    "wd:wordcount":42,
    "wof:name":"Bordj Zemoura",
    "wof:placetype":"locality",
    "wof:population":19782
},
  "geometry": {"coordinates":[4.85668,36.27462],"type":"Point"}
}