{
  "type": "Feature",
  "properties": {
    "gn:admin1_code":"50.0",
    "gn:asciiname":"Ourhlana",
    "gn:country_code":"DZ",
    "gn:dem":47,
    "gn:feature_class":"P",
    "gn:feature_code":"PPL",
    "gn:name":"Ourhlana",
    "gn:population":0,
    "gn:timezone":"Africa/Algiers",
    "iso:country":"DZ",
    "name:und_x_variant":[
        "Ourlhana",
        "Ourhlana"
    ],
    "wof:name":"Ourhlana",
    "wof:placetype":"locality"
},
  "geometry": {"coordinates":[5.99389,33.55429],"type":"Point"}
}