{
  "type": "Feature",
  "properties": {
    "gn:admin1_code":"50.0",
    "gn:asciiname":"Taibine",
    "gn:country_code":"DZ",
    "gn:dem":109,
    "gn:feature_class":"P",
    "gn:feature_code":"PPL",
    "gn:name":"Ta\u00efbine",
    "gn:population":0,
    "gn:timezone":"Africa/Algiers",
    "iso:country":"DZ",
    "wof:name":"Taibine",
    "wof:placetype":"locality"
},
  "geometry": {"coordinates":[5.45351,32.64278],"type":"Point"}
}