{
  "type": "Feature",
  "properties": {
    "gn:admin1_code":"6.0",
    "gn:asciiname":"El Arba",
    "gn:country_code":"DZ",
    "gn:dem":503,
    "gn:feature_class":"P",
    "gn:feature_code":"PPL",
    "gn:name":"El Arba",
    "gn:population":0,
    "gn:timezone":"Africa/Algiers",
    "iso:country":"DZ",
    "name:und_x_variant":[
        "Souk el Arba",
        "El Arba"
    ],
    "wof:name":"El Arba",
    "wof:placetype":"locality"
},
  "geometry": {"coordinates":[3.38213,36.26168],"type":"Point"}
}