{
  "type": "Feature",
  "properties": {
    "gn:admin1_code":"30.0",
    "gn:asciiname":"Boutin",
    "gn:country_code":"DZ",
    "gn:dem":656,
    "gn:feature_class":"P",
    "gn:feature_code":"PPL",
    "gn:name":"Boutin",
    "gn:population":0,
    "gn:timezone":"Africa/Algiers",
    "iso:country":"DZ",
    "name:deu_x_preferred":[
        "Boutin"
    ],
    "name:fra_x_preferred":[
        "Boutin"
    ],
    "name:und_x_variant":[
        "Hassi Daho",
        "Hassi Daha"
    ],
    "wof:name":"Boutin",
    "wof:placetype":"locality"
},
  "geometry": {"coordinates":[-0.5452,35.07238],"type":"Point"}
}