{
  "type": "Feature",
  "properties": {
    "gn:admin1_code":"33.0",
    "gn:asciiname":"Mechtat el Meharzia",
    "gn:country_code":"DZ",
    "gn:dem":1002,
    "gn:feature_class":"P",
    "gn:feature_code":"PPLL",
    "gn:name":"Mechtat el Meharzia",
    "gn:population":0,
    "gn:timezone":"Africa/Algiers",
    "iso:country":"DZ",
    "name:und_x_variant":[
        "Mechtet el Meharzia",
        "Mechtat el Meharzia"
    ],
    "wof:name":"Mechtat el Meharzia",
    "wof:placetype":"locality"
},
  "geometry": {"coordinates":[8.26296,35.59648],"type":"Point"}
}