{
  "type": "Feature",
  "properties": {
    "gn:country":"DZ",
    "gn:fcode":"PPLL",
    "gn:population":4930,
    "iso:country":"DZ",
    "name:ara_x_preferred":[
        "\u062c\u0628\u064a\u0644\u0629 \u0627\u0644\u0631\u0635\u0641\u0627\u0621"
    ],
    "name:azb_x_preferred":[
        "\u062c\u0628\u06cc\u0644\u0647 \u0631\u0635\u0641\u0627\u0621"
    ],
    "name:ceb_x_preferred":[
        "Djebilet Rosfa"
    ],
    "name:eng_x_preferred":[
        "Djebilet Rosfa"
    ],
    "name:fas_x_preferred":[
        "\u062c\u0628\u06cc\u0644\u0647 \u0631\u0635\u0641\u0627\u0621"
    ],
    "name:fra_x_preferred":[
        "Djebilet Rosfa"
    ],
    "name:ita_x_preferred":[
        "Djebilet Rosfa"
    ],
    "name:msa_x_preferred":[
        "Djebilet Rosfa"
    ],
    "name:nan_x_preferred":[
        "Djebilet Rosfa"
    ],
    "name:nld_x_preferred":[
        "Djebilet Rosfa"
    ],
    "name:por_x_preferred":[
        "Djebilet Rosfa"
    ],
    "name:ron_x_preferred":[
        "Djebilet Rosfa"
    ],
    "name:spa_x_preferred":[
        "Djebilet Rosfa"
    ],
    "name:swe_x_preferred":[
        "Djebilet Rosfa"
    ],
    "name:vie_x_preferred":[
        "Djebilet Rosfa"
    ],
    "name:zho_x_preferred":[
        "\u5091\u6bd4\u840a\u7279\u7f85\u65af\u6cd5"
    ],
    "qs:name":"Djebilet Rosfa",
    "qs:photos_9r":0,
    "qs:photos_sr":0,
    "qs:pop_sr":"4",
    "wd:wordcount":40,
    "wof:name":"Djebilet Rosfa",
    "wof:placetype":"locality",
    "wof:population":4930
},
  "geometry": {"coordinates":[0.83496,34.86375],"type":"Point"}
}