{
  "type": "Feature",
  "properties": {
    "gn:country":"DZ",
    "gn:fcode":"PPLL",
    "gn:pop":4930,
    "iso:country":"DZ",
    "name:ara_x_preferred":[
        "\u062c\u0628\u064a\u0644\u0629 \u0627\u0644\u0631\u0635\u0641\u0627\u0621"
    ],
    "name:dut_x_preferred":[
        "Djebilet Rosfa"
    ],
    "name:eng_x_preferred":[
        "Djebilet Rosfa"
    ],
    "name:fre_x_preferred":[
        "Djebilet Rosfa"
    ],
    "name:ita_x_preferred":[
        "Djebilet Rosfa"
    ],
    "name:may_x_preferred":[
        "Djebilet Rosfa"
    ],
    "name:per_x_preferred":[
        "\u062c\u0628\u06cc\u0644\u0647 \u0631\u0635\u0641\u0627\u0621"
    ],
    "name:por_x_preferred":[
        "Djebilet Rosfa"
    ],
    "name:rum_x_preferred":[
        "Djebilet Rosfa"
    ],
    "name:swe_x_preferred":[
        "Djebilet Rosfa"
    ],
    "name:vie_x_preferred":[
        "Djebilet Rosfa"
    ],
    "qs:name":"Djebilet Rosfa",
    "qs:photos_9r":0,
    "qs:photos_sr":0,
    "qs:pop_sr":"4",
    "wd:wordcount":40,
    "wof:name":"Djebilet Rosfa",
    "wof:placetype":"locality",
    "wof:population":4930
},
  "geometry": {"coordinates":[0.83496,34.86375],"type":"Point"}
}