{
  "type": "Feature",
  "properties": {
    "gn:admin1_code":"14.0",
    "gn:asciiname":"El Hadoud",
    "gn:country_code":"DZ",
    "gn:dem":281,
    "gn:feature_class":"P",
    "gn:feature_code":"PPL",
    "gn:name":"El Hadoud",
    "gn:population":0,
    "gn:timezone":"Africa/Algiers",
    "iso:country":"DZ",
    "wof:name":"El Hadoud",
    "wof:placetype":"locality"
},
  "geometry": {"coordinates":[4.36475,36.78634],"type":"Point"}
}