{
  "type": "Feature",
  "properties": {
    "gn:admin1_code":"48.0",
    "gn:asciiname":"Mechta Ramdane",
    "gn:country_code":"DZ",
    "gn:dem":1031,
    "gn:feature_class":"P",
    "gn:feature_code":"PPL",
    "gn:name":"Mechta Ramdane",
    "gn:population":0,
    "gn:timezone":"Africa/Algiers",
    "iso:country":"DZ",
    "name:und_x_variant":[
        "Mechtat Rammdane",
        "Mechta Ramdane"
    ],
    "wof:name":"Mechta Ramdane",
    "wof:placetype":"locality"
},
  "geometry": {"coordinates":[6.18198,36.32066],"type":"Point"}
}