{
  "type": "Feature",
  "properties": {
    "gn:admin1_code":"21.0",
    "gn:asciiname":"Mechta Bou Said Lakhdar",
    "gn:country_code":"DZ",
    "gn:dem":825,
    "gn:feature_class":"P",
    "gn:feature_code":"PPL",
    "gn:name":"Mechta Bou Sa\u00efd Lakhdar",
    "gn:population":0,
    "gn:timezone":"Africa/Algiers",
    "iso:country":"DZ",
    "wof:name":"Mechta Bou Said Lakhdar",
    "wof:placetype":"locality"
},
  "geometry": {"coordinates":[3.86695,35.96517],"type":"Point"}
}