{
  "type": "Feature",
  "properties": {
    "gn:admin1_code":"3.0",
    "gn:asciiname":"Mechta Ouled Djeich",
    "gn:country_code":"DZ",
    "gn:dem":823,
    "gn:feature_class":"P",
    "gn:feature_code":"PPL",
    "gn:name":"Mechta Ouled Dje\u00efch",
    "gn:population":0,
    "gn:timezone":"Africa/Algiers",
    "iso:country":"DZ",
    "wof:name":"Mechta Ouled Djeich",
    "wof:placetype":"locality"
},
  "geometry": {"coordinates":[6.10296,35.81401],"type":"Point"}
}