{
  "type": "Feature",
  "properties": {
    "gn:admin1_code":"51.0",
    "gn:asciiname":"Douar Aoumria",
    "gn:country_code":"DZ",
    "gn:dem":131,
    "gn:feature_class":"P",
    "gn:feature_code":"PPL",
    "gn:name":"Douar Aoumria",
    "gn:population":0,
    "gn:timezone":"Africa/Algiers",
    "iso:country":"DZ",
    "wof:name":"Douar Aoumria",
    "wof:placetype":"locality"
},
  "geometry": {"coordinates":[0.53056,35.61917000000001],"type":"Point"}
}