{
  "type": "Feature",
  "properties": {
    "gn:admin1_code":"6.0",
    "gn:asciiname":"Douar Titri",
    "gn:country_code":"DZ",
    "gn:dem":848,
    "gn:feature_class":"P",
    "gn:feature_code":"PPL",
    "gn:name":"Douar Titri",
    "gn:population":0,
    "gn:timezone":"Africa/Algiers",
    "iso:country":"DZ",
    "wof:name":"Douar Titri",
    "wof:placetype":"locality"
},
  "geometry": {"coordinates":[2.97804,36.01855],"type":"Point"}
}