{
  "type": "Feature",
  "properties": {
    "gn:admin1_code":"55.0",
    "gn:asciiname":"Oued Sebt",
    "gn:country_code":"DZ",
    "gn:dem":12,
    "gn:feature_class":"P",
    "gn:feature_code":"PPL",
    "gn:name":"Oued Sebt",
    "gn:population":0,
    "gn:timezone":"Africa/Algiers",
    "iso:country":"DZ",
    "name:fra_x_preferred":[
        "Oued Sebt"
    ],
    "wof:name":"Oued Sebt",
    "wof:placetype":"locality"
},
  "geometry": {"coordinates":[1.96353,36.5642],"type":"Point"}
}