{
  "type": "Feature",
  "properties": {
    "iso:country":"DZ",
    "name:ara_x_preferred":[
        "\u0637\u0648\u0644\u0642\u0629"
    ],
    "name:arz_x_preferred":[
        "\u0637\u0648\u0644\u0642\u0647"
    ],
    "name:cat_x_preferred":[
        "Tolga"
    ],
    "name:ceb_x_preferred":[
        "Tolga"
    ],
    "name:deu_x_preferred":[
        "Tolga"
    ],
    "name:eng_x_preferred":[
        "Tolga"
    ],
    "name:fra_x_preferred":[
        "Tolga"
    ],
    "name:hun_x_preferred":[
        "Tolga"
    ],
    "name:ita_x_preferred":[
        "Tolga"
    ],
    "name:kab_x_preferred":[
        "\u1e6culga"
    ],
    "name:msa_x_preferred":[
        "Tolga"
    ],
    "name:nan_x_preferred":[
        "Tolga"
    ],
    "name:nld_x_preferred":[
        "Tolga"
    ],
    "name:por_x_preferred":[
        "Tolga"
    ],
    "name:ron_x_preferred":[
        "Tolga"
    ],
    "name:rus_x_preferred":[
        "\u0422\u043e\u043b\u0433\u0430"
    ],
    "name:spa_x_preferred":[
        "Tolga"
    ],
    "name:swe_x_preferred":[
        "Tolga"
    ],
    "name:vie_x_preferred":[
        "Tolga"
    ],
    "name:zho_min_nan_x_preferred":[
        "Tolga"
    ],
    "name:zul_x_preferred":[
        "Tolga"
    ],
    "qs:gn_country":"DZ",
    "qs:gn_fcode":"PPL",
    "qs:gn_pop":68246,
    "qs:name":"Tolga",
    "qs:name_adm0":"\u0627\u0644\u062c\u0632\u0627\u0626\u0631",
    "qs:name_adm1":"\u0648\u0644\u0627\u064a\u0629 \u0628\u0633\u0643\u0631\u0629",
    "qs:photos":0,
    "qs:photos_1k":0,
    "qs:photos_9k":1,
    "qs:photos_9r":1,
    "qs:photos_all":1,
    "qs:photos_sr":0,
    "qs:placetype":"Town",
    "qs:pop_sr":"8",
    "qs:woe_adm0":23424740,
    "wd:wordcount":62,
    "wof:name":"Tolga",
    "wof:placetype":"locality",
    "wof:population":68246
},
  "geometry": {"coordinates":[5.37845,34.72224],"type":"Point"}
}