{
  "type": "Feature",
  "properties": {
    "gn:admin1_code":"51.0",
    "gn:asciiname":"Ben Daoud",
    "gn:country_code":"DZ",
    "gn:dem":94,
    "gn:feature_class":"P",
    "gn:feature_code":"PPL",
    "gn:name":"Ben Daoud",
    "gn:population":0,
    "gn:timezone":"Africa/Algiers",
    "iso:country":"DZ",
    "name:ara_x_preferred":[
        "\u0628\u0646 \u062f\u0627\u0648\u062f"
    ],
    "name:azb_x_preferred":[
        "\u0628\u0646 \u062f\u0627\u0648\u062f"
    ],
    "name:fas_x_preferred":[
        "\u0628\u0646 \u062f\u0627\u0648\u062f"
    ],
    "name:fra_x_preferred":[
        "Ben Daoud"
    ],
    "name:ita_x_preferred":[
        "Ben Daoud"
    ],
    "name:msa_x_preferred":[
        "Ben Daoud"
    ],
    "name:por_x_preferred":[
        "Ben Daoud"
    ],
    "name:ron_x_preferred":[
        "Ben Daoud"
    ],
    "name:spa_x_preferred":[
        "Ben Daoud"
    ],
    "name:und_x_variant":[
        "Douar Ben Daoud"
    ],
    "name:vie_x_preferred":[
        "Ben Daoud"
    ],
    "wof:name":"Ben Daoud",
    "wof:placetype":"locality"
},
  "geometry": {"coordinates":[0.52024,35.71914],"type":"Point"}
}