{
  "type": "Feature",
  "properties": {
    "gn:admin1_code":"51.0",
    "gn:asciiname":"Ben Daoud",
    "gn:country_code":"DZ",
    "gn:dem":94,
    "gn:feature_class":"P",
    "gn:feature_code":"PPL",
    "gn:name":"Ben Daoud",
    "gn:population":0,
    "gn:timezone":"Africa/Algiers",
    "iso:country":"DZ",
    "name:und_x_variant":[
        "Douar Ben Daoud",
        "Ben Daoud"
    ],
    "wof:name":"Ben Daoud",
    "wof:placetype":"locality"
},
  "geometry": {"coordinates":[0.52024,35.71914],"type":"Point"}
}