{
  "type": "Feature",
  "properties": {
    "gn:admin1_code":"15.0",
    "gn:asciiname":"El Kelssaine",
    "gn:country_code":"DZ",
    "gn:dem":615,
    "gn:feature_class":"P",
    "gn:feature_code":"PPL",
    "gn:name":"El Kelssa\u00efne",
    "gn:population":0,
    "gn:timezone":"Africa/Algiers",
    "iso:country":"DZ",
    "name:und_x_variant":[
        "El Kessa\u00efne",
        "El Kelssa\u00efne"
    ],
    "wof:name":"El Kelssaine",
    "wof:placetype":"locality"
},
  "geometry": {"coordinates":[-1.61562,35.14092],"type":"Point"}
}