{
  "type": "Feature",
  "properties": {
    "gn:admin1_code":"7.0",
    "gn:asciiname":"El Ghomri",
    "gn:country_code":"DZ",
    "gn:dem":61,
    "gn:feature_class":"P",
    "gn:feature_code":"PPL",
    "gn:name":"El Ghomri",
    "gn:population":0,
    "gn:timezone":"Africa/Algiers",
    "iso:country":"DZ",
    "name:ara_x_preferred":[
        "\u0627\u0644\u063a\u0645\u0631\u064a"
    ],
    "name:azb_x_preferred":[
        "\u063a\u0645\u0631\u06cc"
    ],
    "name:fas_x_preferred":[
        "\u063a\u0645\u0631\u06cc"
    ],
    "name:fra_x_preferred":[
        "El Ghomri"
    ],
    "name:ita_x_preferred":[
        "El Ghomri"
    ],
    "name:msa_x_preferred":[
        "El Ghomri"
    ],
    "name:por_x_preferred":[
        "El Ghomri"
    ],
    "name:ron_x_preferred":[
        "El Ghomri"
    ],
    "name:spa_x_preferred":[
        "El Ghomri"
    ],
    "name:und_x_variant":[
        "Er Romri",
        "Nouvion",
        "El Ghomri"
    ],
    "name:vie_x_preferred":[
        "El Ghomri"
    ],
    "wof:name":"El Ghomri",
    "wof:placetype":"locality"
},
  "geometry": {"coordinates":[0.20724,35.68688],"type":"Point"}
}