{
  "type": "Feature",
  "properties": {
    "gn:admin1_code":"40.0",
    "gn:asciiname":"El Oued",
    "gn:country_code":"DZ",
    "gn:dem":241,
    "gn:feature_class":"P",
    "gn:feature_code":"PPL",
    "gn:name":"El Oued",
    "gn:population":0,
    "gn:timezone":"Africa/Algiers",
    "iso:country":"DZ",
    "wof:name":"El Oued",
    "wof:placetype":"locality"
},
  "geometry": {"coordinates":[3.75333,36.81833],"type":"Point"}
}