{
  "type": "Feature",
  "properties": {
    "gn:admin1_code":"33.0",
    "gn:asciiname":"Oum Ali",
    "gn:country_code":"DZ",
    "gn:dem":916,
    "gn:feature_class":"P",
    "gn:feature_code":"PPL",
    "gn:name":"Oum Ali",
    "gn:population":0,
    "gn:timezone":"Africa/Algiers",
    "iso:country":"DZ",
    "name:ara_x_preferred":[
        "\u0623\u0645 \u0639\u0644\u064a"
    ],
    "name:azb_x_preferred":[
        "\u0627\u0645 \u0639\u0644\u06cc"
    ],
    "name:fas_x_preferred":[
        "\u0627\u0645 \u0639\u0644\u06cc"
    ],
    "name:fra_x_preferred":[
        "Oum Ali"
    ],
    "name:ita_x_preferred":[
        "Oum Ali"
    ],
    "name:msa_x_preferred":[
        "Oum Ali"
    ],
    "name:por_x_preferred":[
        "Oum Ali"
    ],
    "name:ron_x_preferred":[
        "Oum Ali"
    ],
    "name:spa_x_preferred":[
        "Oum Ali"
    ],
    "name:und_x_variant":[
        "Bordj Oum Ali",
        "Bir Oum Ali",
        "Oum Ali"
    ],
    "name:vie_x_preferred":[
        "Oum Ali"
    ],
    "name:zho_x_preferred":[
        "\u70cf\u59c6\u963f\u5229"
    ],
    "wof:name":"Oum Ali",
    "wof:placetype":"locality"
},
  "geometry": {"coordinates":[8.30112,35.00982],"type":"Point"}
}