{
  "type": "Feature",
  "properties": {
    "gn:admin1_code":"33.0",
    "gn:asciiname":"Oum Ali",
    "gn:country_code":"DZ",
    "gn:dem":916,
    "gn:feature_class":"P",
    "gn:feature_code":"PPL",
    "gn:name":"Oum Ali",
    "gn:population":0,
    "gn:timezone":"Africa/Algiers",
    "iso:country":"DZ",
    "name:und_x_variant":[
        "Bordj Oum Ali",
        "Bir Oum Ali",
        "Oum Ali"
    ],
    "wof:name":"Oum Ali",
    "wof:placetype":"locality"
},
  "geometry": {"coordinates":[8.30112,35.00982],"type":"Point"}
}