{
  "type": "Feature",
  "properties": {
    "gn:admin1_code":"48.0",
    "gn:asciiname":"Mechtat el Kef",
    "gn:country_code":"DZ",
    "gn:dem":1114,
    "gn:feature_class":"P",
    "gn:feature_code":"PPL",
    "gn:name":"Mechtat el Kef",
    "gn:population":0,
    "gn:timezone":"Africa/Algiers",
    "iso:country":"DZ",
    "wof:name":"Mechtat el Kef",
    "wof:placetype":"locality"
},
  "geometry": {"coordinates":[6.08028,36.34333],"type":"Point"}
}