{
  "type": "Feature",
  "properties": {
    "gn:admin1_code":"35.0",
    "gn:asciiname":"Guezazna",
    "gn:country_code":"DZ",
    "gn:dem":200,
    "gn:feature_class":"P",
    "gn:feature_code":"PPL",
    "gn:name":"Guezazna",
    "gn:population":0,
    "gn:timezone":"Africa/Algiers",
    "iso:country":"DZ",
    "wof:name":"Guezazna",
    "wof:placetype":"locality"
},
  "geometry": {"coordinates":[1.77212,36.2678],"type":"Point"}
}