{
  "type": "Feature",
  "properties": {
    "gn:admin1_code":"15.0",
    "gn:asciiname":"El Kolla",
    "gn:country_code":"DZ",
    "gn:dem":77,
    "gn:feature_class":"P",
    "gn:feature_code":"PPL",
    "gn:name":"El Kolla",
    "gn:population":0,
    "gn:timezone":"Africa/Algiers",
    "iso:country":"DZ",
    "wof:name":"El Kolla",
    "wof:placetype":"locality"
},
  "geometry": {"coordinates":[-1.84431,35.07621],"type":"Point"}
}