{
  "type": "Feature",
  "properties": {
    "gn:admin1_code":"26.0",
    "gn:asciiname":"Dar Ouled Ahmed",
    "gn:country_code":"DZ",
    "gn:dem":560,
    "gn:feature_class":"P",
    "gn:feature_code":"PPL",
    "gn:name":"Dar Ouled Ahmed",
    "gn:population":0,
    "gn:timezone":"Africa/Algiers",
    "iso:country":"DZ",
    "wof:name":"Dar Ouled Ahmed",
    "wof:placetype":"locality"
},
  "geometry": {"coordinates":[0.40917,35.5175],"type":"Point"}
}