{
  "type": "Feature",
  "properties": {
    "gn:admin1_code":"6.0",
    "gn:asciiname":"Dechra",
    "gn:country_code":"DZ",
    "gn:dem":864,
    "gn:feature_class":"P",
    "gn:feature_code":"PPL",
    "gn:name":"Dechra",
    "gn:population":0,
    "gn:timezone":"Africa/Algiers",
    "iso:country":"DZ",
    "wof:name":"Dechra",
    "wof:placetype":"locality"
},
  "geometry": {"coordinates":[2.87306,36.13194],"type":"Point"}
}