{
  "type": "Feature",
  "properties": {
    "gn:admin1_code":"41.0",
    "gn:asciiname":"Douar el M'Hane",
    "gn:country_code":"DZ",
    "gn:dem":276,
    "gn:feature_class":"P",
    "gn:feature_code":"PPL",
    "gn:name":"Douar el M\u2019Hane",
    "gn:population":0,
    "gn:timezone":"Africa/Algiers",
    "iso:country":"DZ",
    "name:und_x_variant":[
        "Douar el M\u2019Hane",
        "Douar el Mh\u00e2ne"
    ],
    "wof:name":"Douar el M'Hane",
    "wof:placetype":"locality"
},
  "geometry": {"coordinates":[1.17809,36.22542],"type":"Point"}
}