{
  "type": "Feature",
  "properties": {
    "gn:admin1_code":"31.0",
    "gn:asciiname":"Mechtet Ch'ab Ben Hadid",
    "gn:country_code":"DZ",
    "gn:dem":216,
    "gn:feature_class":"P",
    "gn:feature_code":"PPL",
    "gn:name":"Mechtet Ch\u2019\u00e2b Ben Had\u00eed",
    "gn:population":0,
    "gn:timezone":"Africa/Algiers",
    "iso:country":"DZ",
    "name:und_x_variant":[
        "Mechta Ben Addid",
        "Mechtat Ben Addid",
        "Mechtet Ch\u2019\u00e2b Ben Had\u00eed"
    ],
    "wof:name":"Mechtet Ch'ab Ben Hadid",
    "wof:placetype":"locality"
},
  "geometry": {"coordinates":[6.7638,36.65901],"type":"Point"}
}