{
  "type": "Feature",
  "properties": {
    "gn:admin1_code":"21.0",
    "gn:asciiname":"Mechta Kamria",
    "gn:country_code":"DZ",
    "gn:dem":815,
    "gn:feature_class":"P",
    "gn:feature_code":"PPL",
    "gn:name":"Mechta Kamria",
    "gn:population":0,
    "gn:timezone":"Africa/Algiers",
    "iso:country":"DZ",
    "name:und_x_variant":[
        "Mechta Kamira",
        "Mechta Kamria"
    ],
    "wof:name":"Mechta Kamria",
    "wof:placetype":"locality"
},
  "geometry": {"coordinates":[3.76021,36.01818],"type":"Point"}
}