{
  "type": "Feature",
  "properties": {
    "gn:admin1_code":"6.0",
    "gn:asciiname":"El Menched",
    "gn:country_code":"DZ",
    "gn:dem":1188,
    "gn:feature_class":"P",
    "gn:feature_code":"PPL",
    "gn:name":"El Menched",
    "gn:population":0,
    "gn:timezone":"Africa/Algiers",
    "iso:country":"DZ",
    "wof:name":"El Menched",
    "wof:placetype":"locality"
},
  "geometry": {"coordinates":[3.43083,36.08767],"type":"Point"}
}