{
  "type": "Feature",
  "properties": {
    "gn:admin1_code":"26.0",
    "gn:asciiname":"Douar Ghraibia",
    "gn:country_code":"DZ",
    "gn:dem":587,
    "gn:feature_class":"P",
    "gn:feature_code":"PPL",
    "gn:name":"Douar Ghra\u00efbia",
    "gn:population":0,
    "gn:timezone":"Africa/Algiers",
    "iso:country":"DZ",
    "wof:name":"Douar Ghraibia",
    "wof:placetype":"locality"
},
  "geometry": {"coordinates":[0.2691,35.45875],"type":"Point"}
}