{
  "type": "Feature",
  "properties": {
    "gn:admin1_code":"31.0",
    "gn:asciiname":"Mechta Kermat",
    "gn:country_code":"DZ",
    "gn:dem":85,
    "gn:feature_class":"P",
    "gn:feature_code":"PPL",
    "gn:name":"Mechta Kermat",
    "gn:population":0,
    "gn:timezone":"Africa/Algiers",
    "iso:country":"DZ",
    "wof:name":"Mechta Kermat",
    "wof:placetype":"locality"
},
  "geometry": {"coordinates":[7.20944,36.76389],"type":"Point"}
}