{
  "type": "Feature",
  "properties": {
    "gn:admin1_code":"34.0",
    "gn:asciiname":"Irhzer",
    "gn:country_code":"DZ",
    "gn:dem":242,
    "gn:feature_class":"P",
    "gn:feature_code":"PPL",
    "gn:name":"Irhzer",
    "gn:population":0,
    "gn:timezone":"Africa/Algiers",
    "iso:country":"DZ",
    "wof:name":"Irhzer",
    "wof:placetype":"locality"
},
  "geometry": {"coordinates":[0.32521,29.37559000000001],"type":"Point"}
}