{
  "type": "Feature",
  "properties": {
    "gn:admin1_code":"23.0",
    "gn:asciiname":"Moumna",
    "gn:country_code":"DZ",
    "gn:dem":87,
    "gn:feature_class":"P",
    "gn:feature_code":"PPL",
    "gn:name":"Mo\u00fbmna",
    "gn:population":0,
    "gn:timezone":"Africa/Algiers",
    "iso:country":"DZ",
    "wof:name":"Moumna",
    "wof:placetype":"locality"
},
  "geometry": {"coordinates":[7.78333,36.58333],"type":"Point"}
}