{
  "type": "Feature",
  "properties": {
    "gn:admin1_code":"55.0",
    "gn:asciiname":"Sidi Ahmed Bel Hassene",
    "gn:country_code":"DZ",
    "gn:dem":797,
    "gn:feature_class":"P",
    "gn:feature_code":"PPL",
    "gn:name":"Sidi Ahmed Bel Hassene",
    "gn:population":0,
    "gn:timezone":"Africa/Algiers",
    "iso:country":"DZ",
    "wof:name":"Sidi Ahmed Bel Hassene",
    "wof:placetype":"locality"
},
  "geometry": {"coordinates":[1.987,36.42038],"type":"Point"}
}