{
  "type": "Feature",
  "properties": {
    "gn:admin1_code":"51.0",
    "gn:asciiname":"Tiliouane",
    "gn:country_code":"DZ",
    "gn:dem":128,
    "gn:feature_class":"P",
    "gn:feature_code":"PPL",
    "gn:name":"Tiliouane",
    "gn:population":0,
    "gn:timezone":"Africa/Algiers",
    "iso:country":"DZ",
    "wof:name":"Tiliouane",
    "wof:placetype":"locality"
},
  "geometry": {"coordinates":[0.52203,35.6336],"type":"Point"}
}