{
  "type": "Feature",
  "properties": {
    "gn:admin1_code":"4.0",
    "gn:asciiname":"Mechta Chaab Serradj",
    "gn:country_code":"DZ",
    "gn:dem":818,
    "gn:feature_class":"P",
    "gn:feature_code":"PPL",
    "gn:name":"Mechta Chaab Serradj",
    "gn:population":0,
    "gn:timezone":"Africa/Algiers",
    "iso:country":"DZ",
    "wof:name":"Mechta Chaab Serradj",
    "wof:placetype":"locality"
},
  "geometry": {"coordinates":[7.07746,36.15878],"type":"Point"}
}