{
  "type": "Feature",
  "properties": {
    "gn:admin1_code":"6.0",
    "gn:asciiname":"Oulad Said",
    "gn:country_code":"DZ",
    "gn:dem":718,
    "gn:feature_class":"P",
    "gn:feature_code":"PPL",
    "gn:name":"Oulad Sa\u00efd",
    "gn:population":0,
    "gn:timezone":"Africa/Algiers",
    "iso:country":"DZ",
    "wof:name":"Oulad Said",
    "wof:placetype":"locality"
},
  "geometry": {"coordinates":[3.41019,35.81701],"type":"Point"}
}