{
  "type": "Feature",
  "properties": {
    "gn:admin1_code":"6.0",
    "gn:asciiname":"Oulad Said",
    "gn:country_code":"DZ",
    "gn:dem":718,
    "gn:feature_class":"P",
    "gn:feature_code":"PPL",
    "gn:name":"Oulad Sa\u00efd",
    "gn:population":0,
    "gn:timezone":"Africa/Algiers",
    "iso:country":"DZ",
    "name:ara_x_preferred":[
        "\u0623\u0648\u0644\u0627\u062f \u0633\u0639\u064a\u062f"
    ],
    "name:cat_x_preferred":[
        "Oulad Said"
    ],
    "name:ceb_x_preferred":[
        "Oulad Sa\u00efd"
    ],
    "name:fra_x_preferred":[
        "Oulad Sa\u00efd"
    ],
    "name:ita_x_preferred":[
        "Oulad Said"
    ],
    "name:swe_x_preferred":[
        "Oulad Sa\u00efd"
    ],
    "wof:name":"Oulad Said",
    "wof:placetype":"locality"
},
  "geometry": {"coordinates":[3.41019,35.81701],"type":"Point"}
}