{
  "type": "Feature",
  "properties": {
    "gn:admin1_code":"27.0",
    "gn:asciiname":"Eddis",
    "gn:country_code":"DZ",
    "gn:dem":549,
    "gn:feature_class":"P",
    "gn:feature_code":"PPL",
    "gn:name":"Eddis",
    "gn:population":0,
    "gn:timezone":"Africa/Algiers",
    "iso:country":"DZ",
    "name:und_x_variant":[
        "Belkassem",
        "Eddis"
    ],
    "wof:name":"Eddis",
    "wof:placetype":"locality"
},
  "geometry": {"coordinates":[4.1696,35.30248],"type":"Point"}
}