{
  "type": "Feature",
  "properties": {
    "gn:country":"DZ",
    "gn:fcode":"PPL",
    "gn:pop":35512,
    "iso:country":"DZ",
    "name:ara_x_preferred":[
        "\u0633\u064a\u062f\u064a \u0627\u0644\u0634\u062d\u0645\u064a"
    ],
    "name:dut_x_preferred":[
        "Sidi Chami"
    ],
    "name:eng_x_preferred":[
        "Sidi Chami"
    ],
    "name:fre_x_preferred":[
        "Sidi Chami"
    ],
    "name:ita_x_preferred":[
        "Sidi Chami"
    ],
    "name:may_x_preferred":[
        "Sidi Chami"
    ],
    "name:per_x_preferred":[
        "\u0633\u06cc\u062f\u06cc \u0634\u062d\u0645\u06cc"
    ],
    "name:por_x_preferred":[
        "Sidi Chami"
    ],
    "name:rum_x_preferred":[
        "Sidi Chami"
    ],
    "name:rus_x_preferred":[
        "\u0421\u0438\u0434\u0438-\u0428\u0430\u043c\u0438"
    ],
    "name:swe_x_preferred":[
        "Sidi Chami"
    ],
    "name:unk_x_variant":[
        "Sidi Chamy"
    ],
    "name:vie_x_preferred":[
        "Sidi Chahmi"
    ],
    "qs:name":"Sidi ech Chahmi",
    "qs:photos_9r":0,
    "qs:photos_sr":0,
    "qs:pop_sr":"7",
    "wof:name":"Sidi ech Chahmi",
    "wof:placetype":"locality",
    "wof:population":35512
},
  "geometry": {"coordinates":[-0.52168,35.65903],"type":"Point"}
}