{
  "type": "Feature",
  "properties": {
    "gn:country":"DZ",
    "gn:fcode":"PPL",
    "gn:population":35512,
    "iso:country":"DZ",
    "name:ara_x_preferred":[
        "\u0633\u064a\u062f\u064a \u0627\u0644\u0634\u062d\u0645\u064a"
    ],
    "name:arz_x_preferred":[
        "\u0633\u064a\u062f\u0649 \u0627\u0644\u0634\u062d\u0645\u0649"
    ],
    "name:azb_x_preferred":[
        "\u0633\u06cc\u062f\u06cc \u0634\u062d\u0645\u06cc"
    ],
    "name:aze_x_preferred":[
        "Sidi-\u015e\u0259mi"
    ],
    "name:ceb_x_preferred":[
        "Sidi ech Chahmi"
    ],
    "name:eng_x_preferred":[
        "Sidi Chami"
    ],
    "name:fas_x_preferred":[
        "\u0633\u06cc\u062f\u06cc \u0634\u062d\u0645\u06cc"
    ],
    "name:fra_x_preferred":[
        "Sidi Chami"
    ],
    "name:ita_x_preferred":[
        "Sidi Chami"
    ],
    "name:kab_x_preferred":[
        "Sidi Cce\u1e25mi"
    ],
    "name:msa_x_preferred":[
        "Sidi Chami"
    ],
    "name:nan_x_preferred":[
        "Sidi Chami"
    ],
    "name:nld_x_preferred":[
        "Sidi Chami"
    ],
    "name:por_x_preferred":[
        "Sidi Chami"
    ],
    "name:ron_x_preferred":[
        "Sidi Chami"
    ],
    "name:rus_x_preferred":[
        "\u0421\u0438\u0434\u0438-\u0428\u0430\u043c\u0438"
    ],
    "name:spa_x_preferred":[
        "Sidi Chami"
    ],
    "name:swe_x_preferred":[
        "Sidi Chami"
    ],
    "name:und_x_variant":[
        "Sidi Chamy"
    ],
    "name:vie_x_preferred":[
        "Sidi Chahmi"
    ],
    "name:zho_x_preferred":[
        "\u897f\u8fea\u6c99\u7c73"
    ],
    "qs:name":"Sidi ech Chahmi",
    "qs:photos_9r":0,
    "qs:photos_sr":0,
    "qs:pop_sr":"7",
    "wof:name":"Sidi ech Chahmi",
    "wof:placetype":"locality",
    "wof:population":35512
},
  "geometry": {"coordinates":[-0.52168,35.65903],"type":"Point"}
}