{
  "type": "Feature",
  "properties": {
    "gn:admin1_code":"13.0",
    "gn:asciiname":"Djemlet el Assa",
    "gn:country_code":"DZ",
    "gn:dem":745,
    "gn:feature_class":"P",
    "gn:feature_code":"PPL",
    "gn:name":"Djemlet el Assa",
    "gn:population":0,
    "gn:timezone":"Africa/Algiers",
    "iso:country":"DZ",
    "wof:name":"Djemlet el Assa",
    "wof:placetype":"locality"
},
  "geometry": {"coordinates":[2.36746,35.50277],"type":"Point"}
}