{
  "type": "Feature",
  "properties": {
    "gn:admin1_code":"9.0",
    "gn:asciiname":"Benfreha",
    "gn:country_code":"DZ",
    "gn:dem":93,
    "gn:feature_class":"P",
    "gn:feature_code":"PPL",
    "gn:name":"Benfreha",
    "gn:population":0,
    "gn:timezone":"Africa/Algiers",
    "iso:country":"DZ",
    "name:und_x_variant":[
        "Legrand",
        "Assi Ben Fereah",
        "Benfreha"
    ],
    "wof:name":"Benfreha",
    "wof:placetype":"locality"
},
  "geometry": {"coordinates":[-0.41847,35.69337],"type":"Point"}
}