{
  "type": "Feature",
  "properties": {
    "gn:admin1_code":"15.0",
    "gn:asciiname":"Settout",
    "gn:country_code":"DZ",
    "gn:dem":148,
    "gn:feature_class":"P",
    "gn:feature_code":"PPL",
    "gn:name":"Settout",
    "gn:population":0,
    "gn:timezone":"Africa/Algiers",
    "iso:country":"DZ",
    "name:und_x_variant":[
        "Douar Settout",
        "Settout"
    ],
    "wof:name":"Settout",
    "wof:placetype":"locality"
},
  "geometry": {"coordinates":[-1.78605,35.0643],"type":"Point"}
}