{
  "type": "Feature",
  "properties": {
    "gn:admin1_code":"55.0",
    "gn:asciiname":"Messelmoun",
    "gn:country_code":"DZ",
    "gn:dem":33,
    "gn:feature_class":"P",
    "gn:feature_code":"PPL",
    "gn:name":"Messelmoun",
    "gn:population":0,
    "gn:timezone":"Africa/Algiers",
    "iso:country":"DZ",
    "name:und_x_variant":[
        "Messlmo\u00fbn"
    ],
    "wof:name":"Messelmoun",
    "wof:placetype":"locality"
},
  "geometry": {"coordinates":[1.99938,36.56382],"type":"Point"}
}