{
  "type": "Feature",
  "properties": {
    "gn:admin1_code":"39.0",
    "gn:asciiname":"Oulad Hamdane",
    "gn:country_code":"DZ",
    "gn:dem":1163,
    "gn:feature_class":"P",
    "gn:feature_code":"PPL",
    "gn:name":"Oulad Hamdane",
    "gn:population":0,
    "gn:timezone":"Africa/Algiers",
    "iso:country":"DZ",
    "name:ara_x_preferred":[
        "\u0623\u0648\u0644\u0627\u062f \u062d\u0645\u062f\u0627\u0646"
    ],
    "name:cat_x_preferred":[
        "Oulad Hamdane"
    ],
    "name:ceb_x_preferred":[
        "Oulad Hamdane"
    ],
    "name:ita_x_preferred":[
        "Oulad Hamdane"
    ],
    "name:swe_x_preferred":[
        "Oulad Hamdane"
    ],
    "wof:name":"Oulad Hamdane",
    "wof:placetype":"locality"
},
  "geometry": {"coordinates":[4.94272,35.89288],"type":"Point"}
}