{
  "type": "Feature",
  "properties": {
    "gn:admin1_code":"39.0",
    "gn:asciiname":"Oulad Hamdane",
    "gn:country_code":"DZ",
    "gn:dem":1163,
    "gn:feature_class":"P",
    "gn:feature_code":"PPL",
    "gn:name":"Oulad Hamdane",
    "gn:population":0,
    "gn:timezone":"Africa/Algiers",
    "iso:country":"DZ",
    "wof:name":"Oulad Hamdane",
    "wof:placetype":"locality"
},
  "geometry": {"coordinates":[4.94272,35.89288],"type":"Point"}
}