{
  "type": "Feature",
  "properties": {
    "gn:admin1_code":"55.0",
    "gn:asciiname":"Rardous",
    "gn:country_code":"DZ",
    "gn:dem":419,
    "gn:feature_class":"P",
    "gn:feature_code":"PPL",
    "gn:name":"Rardous",
    "gn:population":0,
    "gn:timezone":"Africa/Algiers",
    "iso:country":"DZ",
    "wof:name":"Rardous",
    "wof:placetype":"locality"
},
  "geometry": {"coordinates":[2.14601,36.51945],"type":"Point"}
}