{
  "type": "Feature",
  "properties": {
    "gn:admin1_code":"39.0",
    "gn:asciiname":"Blondel",
    "gn:country_code":"DZ",
    "gn:dem":1041,
    "gn:feature_class":"P",
    "gn:feature_code":"PPL",
    "gn:name":"Blondel",
    "gn:population":0,
    "gn:timezone":"Africa/Algiers",
    "iso:country":"DZ",
    "name:ces_x_preferred":[
        "Blondel"
    ],
    "name:deu_x_preferred":[
        "Blondel"
    ],
    "name:fra_x_preferred":[
        "Blondel"
    ],
    "name:ita_x_preferred":[
        "Blondel"
    ],
    "name:nld_x_preferred":[
        "Blondel"
    ],
    "name:pol_x_preferred":[
        "Blondel"
    ],
    "name:rus_x_preferred":[
        "\u0411\u043b\u043e\u043d\u0434\u0435\u043b\u044c"
    ],
    "name:swe_x_preferred":[
        "Blondel"
    ],
    "name:ukr_x_preferred":[
        "\u0411\u043b\u043e\u043d\u0434\u0435\u043b\u044c"
    ],
    "name:und_x_variant":[
        "A\u00efne Soltane"
    ],
    "wof:name":"Blondel",
    "wof:placetype":"locality"
},
  "geometry": {"coordinates":[4.73333,36.13333],"type":"Point"}
}