{
  "type": "Feature",
  "properties": {
    "gn:admin1_code":"53.0",
    "gn:asciiname":"Ideles",
    "gn:country_code":"DZ",
    "gn:dem":1391,
    "gn:feature_class":"P",
    "gn:feature_code":"PPL",
    "gn:name":"Idel\u00e8s",
    "gn:population":0,
    "gn:timezone":"Africa/Algiers",
    "iso:country":"DZ",
    "name:und_x_variant":[
        "Arrem Ideles",
        "Idel\u00e8s"
    ],
    "wof:name":"Ideles",
    "wof:placetype":"locality"
},
  "geometry": {"coordinates":[5.93306,23.82364],"type":"Point"}
}