{
  "type": "Feature",
  "properties": {
    "gn:admin1_code":"53.0",
    "gn:asciiname":"Ideles",
    "gn:country_code":"DZ",
    "gn:dem":1391,
    "gn:feature_class":"P",
    "gn:feature_code":"PPL",
    "gn:name":"Idel\u00e8s",
    "gn:population":0,
    "gn:timezone":"Africa/Algiers",
    "iso:country":"DZ",
    "name:ara_x_preferred":[
        "\u0623\u062f\u0644\u0633"
    ],
    "name:azb_x_preferred":[
        "\u0627\u062f\u0644\u0633"
    ],
    "name:fas_x_preferred":[
        "\u0627\u062f\u0644\u0633"
    ],
    "name:fin_x_preferred":[
        "Idles"
    ],
    "name:fra_x_preferred":[
        "Idles"
    ],
    "name:ita_x_preferred":[
        "Idles"
    ],
    "name:kab_x_preferred":[
        "Idelles"
    ],
    "name:msa_x_preferred":[
        "Idl\u00e8s"
    ],
    "name:pol_x_preferred":[
        "Idalas"
    ],
    "name:por_x_preferred":[
        "Idl\u00e8s"
    ],
    "name:ron_x_preferred":[
        "Idles"
    ],
    "name:rus_x_preferred":[
        "\u0418\u0434\u043b\u0435\u0441"
    ],
    "name:spa_x_preferred":[
        "Idles"
    ],
    "name:und_x_variant":[
        "Arrem Ideles",
        "Idel\u00e8s"
    ],
    "name:vie_x_preferred":[
        "Idles"
    ],
    "name:zho_x_preferred":[
        "\u4f0a\u5fb7\u840a\u65af"
    ],
    "wof:name":"Ideles",
    "wof:placetype":"locality"
},
  "geometry": {"coordinates":[5.93306,23.82364],"type":"Point"}
}