{
  "type": "Feature",
  "properties": {
    "gn:admin1_code":"26.0",
    "gn:asciiname":"Douar el Araissia",
    "gn:country_code":"DZ",
    "gn:dem":605,
    "gn:feature_class":"P",
    "gn:feature_code":"PPLL",
    "gn:name":"Douar el Araissia",
    "gn:population":0,
    "gn:timezone":"Africa/Algiers",
    "iso:country":"DZ",
    "name:und_x_variant":[
        "Douar Kada Ould el Hachemi"
    ],
    "wof:name":"Douar el Araissia",
    "wof:placetype":"locality"
},
  "geometry": {"coordinates":[0.50773,35.33669000000001],"type":"Point"}
}