{
  "type": "Feature",
  "properties": {
    "gn:admin1_code":"26.0",
    "gn:asciiname":"Douar Ben Salah",
    "gn:country_code":"DZ",
    "gn:dem":505,
    "gn:feature_class":"P",
    "gn:feature_code":"PPL",
    "gn:name":"Douar Ben Salah",
    "gn:population":0,
    "gn:timezone":"Africa/Algiers",
    "iso:country":"DZ",
    "wof:name":"Douar Ben Salah",
    "wof:placetype":"locality"
},
  "geometry": {"coordinates":[0.11294,35.26936],"type":"Point"}
}