{
  "type": "Feature",
  "properties": {
    "gn:admin1_code":"12.0",
    "gn:asciiname":"Mechtat Kef el Hammam",
    "gn:country_code":"DZ",
    "gn:dem":996,
    "gn:feature_class":"P",
    "gn:feature_code":"PPL",
    "gn:name":"Mechtat Kef el Hammam",
    "gn:population":0,
    "gn:timezone":"Africa/Algiers",
    "iso:country":"DZ",
    "name:und_x_variant":[
        "Mechtat Kef el Hamam",
        "Mechtat Kef el Hammam"
    ],
    "wof:name":"Mechtat Kef el Hammam",
    "wof:placetype":"locality"
},
  "geometry": {"coordinates":[5.50287,35.64243],"type":"Point"}
}