{
  "type": "Feature",
  "properties": {
    "gn:admin1_code":"41.0",
    "gn:asciiname":"Ech Chegga",
    "gn:country_code":"DZ",
    "gn:dem":107,
    "gn:feature_class":"P",
    "gn:feature_code":"PPL",
    "gn:name":"Ech Chegga",
    "gn:population":0,
    "gn:timezone":"Africa/Algiers",
    "iso:country":"DZ",
    "wof:name":"Ech Chegga",
    "wof:placetype":"locality"
},
  "geometry": {"coordinates":[1.34768,36.19336],"type":"Point"}
}