{
  "type": "Feature",
  "properties": {
    "iso:country":"DZ",
    "name:ara_x_preferred":[
        "\u062e\u0645\u064a\u0633 \u0645\u0644\u064a\u0627\u0646\u0629"
    ],
    "name:azb_x_preferred":[
        "\u062e\u0645\u06cc\u0633 \u0645\u0644\u06cc\u0627\u0646\u0647"
    ],
    "name:ceb_x_preferred":[
        "Khemis Miliana"
    ],
    "name:deu_x_preferred":[
        "Khemis Miliana"
    ],
    "name:deu_x_variant":[
        "Malliana"
    ],
    "name:eng_x_preferred":[
        "Khemis Miliana"
    ],
    "name:fas_x_preferred":[
        "\u062e\u0645\u06cc\u0633 \u0645\u0644\u06cc\u0627\u0646\u0647"
    ],
    "name:fra_x_preferred":[
        "Khemis Miliana"
    ],
    "name:fra_x_variant":[
        "Affreville"
    ],
    "name:ita_x_preferred":[
        "Khemis Miliana"
    ],
    "name:kab_x_preferred":[
        "Lexmis n Tmelyant"
    ],
    "name:msa_x_preferred":[
        "Khemis Miliana"
    ],
    "name:nan_x_preferred":[
        "Khemis Miliana"
    ],
    "name:nld_x_preferred":[
        "Khemis Miliana"
    ],
    "name:pol_x_preferred":[
        "Chamis Miljana"
    ],
    "name:por_x_preferred":[
        "Khemis Miliana"
    ],
    "name:ron_x_preferred":[
        "Khemis Miliana"
    ],
    "name:spa_x_preferred":[
        "Khemis Miliana"
    ],
    "name:swe_x_preferred":[
        "Khemis Miliana"
    ],
    "name:unk_x_variant":[
        "El Khemis Miliana"
    ],
    "name:vie_x_preferred":[
        "Khemis Miliana"
    ],
    "name:zho_min_nan_x_preferred":[
        "Khemis Miliana"
    ],
    "name:zho_x_preferred":[
        "\u6d77\u7c73\u65af\u7c73\u5229\u4e9e\u7d0d"
    ],
    "qs:gn_country":"DZ",
    "qs:gn_fcode":"PPL",
    "qs:gn_pop":75865,
    "qs:name":"Khemis Miliana",
    "qs:name_adm0":"\u0627\u0644\u062c\u0632\u0627\u0626\u0631",
    "qs:name_adm1":"Ain Defla",
    "qs:photos":32,
    "qs:photos_1k":6,
    "qs:photos_9k":1,
    "qs:photos_9r":2,
    "qs:photos_all":32,
    "qs:photos_sr":2,
    "qs:placetype":"Town",
    "qs:pop_sr":"8",
    "qs:woe_adm0":23424740,
    "wd:wordcount":410,
    "wof:name":"Khemis Miliana",
    "wof:placetype":"locality",
    "wof:population":75865
},
  "geometry": {"coordinates":[2.22015,36.26104],"type":"Point"}
}