{
  "type": "Feature",
  "properties": {
    "gn:admin1_code":"24.0",
    "gn:asciiname":"Bou Adjem",
    "gn:country_code":"DZ",
    "gn:dem":142,
    "gn:feature_class":"P",
    "gn:feature_code":"PPL",
    "gn:name":"Bou Adjem",
    "gn:population":0,
    "gn:timezone":"Africa/Algiers",
    "iso:country":"DZ",
    "name:und_x_variant":[
        "Mechtat Bou Ajem",
        "Bou Hdjem",
        "Mechta Bou Adjem",
        "Bou Adjem"
    ],
    "wof:name":"Bou Adjem",
    "wof:placetype":"locality"
},
  "geometry": {"coordinates":[5.57316,36.71623],"type":"Point"}
}