{
  "type": "Feature",
  "properties": {
    "gn:admin1_code":"14.0",
    "gn:asciiname":"Taguercif",
    "gn:country_code":"DZ",
    "gn:dem":282,
    "gn:feature_class":"P",
    "gn:feature_code":"PPL",
    "gn:name":"Taguercif",
    "gn:population":0,
    "gn:timezone":"Africa/Algiers",
    "iso:country":"DZ",
    "name:und_x_variant":[
        "Taguersift",
        "Taguercif"
    ],
    "wof:name":"Taguercif",
    "wof:placetype":"locality"
},
  "geometry": {"coordinates":[4.30335,36.78792],"type":"Point"}
}