{
  "type": "Feature",
  "properties": {
    "gn:admin1_code":"18.0",
    "gn:asciiname":"Bou Mraou",
    "gn:country_code":"DZ",
    "gn:dem":674,
    "gn:feature_class":"P",
    "gn:feature_code":"PPL",
    "gn:name":"Bou Mraou",
    "gn:population":0,
    "gn:timezone":"Africa/Algiers",
    "iso:country":"DZ",
    "name:und_x_variant":[
        "Bou Meraou",
        "Bou Mraou"
    ],
    "wof:name":"Bou Mraou",
    "wof:placetype":"locality"
},
  "geometry": {"coordinates":[4.98333,36.63333],"type":"Point"}
}