{
  "type": "Feature",
  "properties": {
    "gn:admin1_code":"18.0",
    "gn:asciiname":"Tiahmaine",
    "gn:country_code":"DZ",
    "gn:dem":340,
    "gn:feature_class":"P",
    "gn:feature_code":"PPL",
    "gn:name":"Tiahma\u00efne",
    "gn:population":0,
    "gn:timezone":"Africa/Algiers",
    "iso:country":"DZ",
    "wof:name":"Tiahmaine",
    "wof:placetype":"locality"
},
  "geometry": {"coordinates":[4.91458,36.76294],"type":"Point"}
}