{
  "type": "Feature",
  "properties": {
    "gn:admin1_code":"14.0",
    "gn:asciiname":"Ait Abid",
    "gn:country_code":"DZ",
    "gn:dem":462,
    "gn:feature_class":"P",
    "gn:feature_code":"PPL",
    "gn:name":"A\u00eft Abid",
    "gn:population":0,
    "gn:timezone":"Africa/Algiers",
    "iso:country":"DZ",
    "wof:name":"Ait Abid",
    "wof:placetype":"locality"
},
  "geometry": {"coordinates":[4.05744,36.55805],"type":"Point"}
}