{
  "type": "Feature",
  "properties": {
    "gn:admin1_code":"24.0",
    "gn:asciiname":"Tizmat",
    "gn:country_code":"DZ",
    "gn:dem":738,
    "gn:feature_class":"P",
    "gn:feature_code":"PPL",
    "gn:name":"Tizmat",
    "gn:population":0,
    "gn:timezone":"Africa/Algiers",
    "iso:country":"DZ",
    "wof:name":"Tizmat",
    "wof:placetype":"locality"
},
  "geometry": {"coordinates":[5.75295,36.60227],"type":"Point"}
}