{
  "type": "Feature",
  "properties": {
    "gn:admin1_code":"26.0",
    "gn:asciiname":"Dar Ben el Hassine",
    "gn:country_code":"DZ",
    "gn:dem":653,
    "gn:feature_class":"P",
    "gn:feature_code":"PPL",
    "gn:name":"Dar Ben el Hassine",
    "gn:population":0,
    "gn:timezone":"Africa/Algiers",
    "iso:country":"DZ",
    "wof:name":"Dar Ben el Hassine",
    "wof:placetype":"locality"
},
  "geometry": {"coordinates":[0.245,35.44333],"type":"Point"}
}