{
  "type": "Feature",
  "properties": {
    "gn:admin1_code":"7.0",
    "gn:asciiname":"Douar Ouled Ben Abdallah",
    "gn:country_code":"DZ",
    "gn:dem":206,
    "gn:feature_class":"P",
    "gn:feature_code":"PPL",
    "gn:name":"Douar Ouled Ben Abdallah",
    "gn:population":0,
    "gn:timezone":"Africa/Algiers",
    "iso:country":"DZ",
    "wof:name":"Douar Ouled Ben Abdallah",
    "wof:placetype":"locality"
},
  "geometry": {"coordinates":[0.26443,35.72473],"type":"Point"}
}