{
  "type": "Feature",
  "properties": {
    "gn:admin1_code":"21.0",
    "gn:asciiname":"Mechta Makha Mala",
    "gn:country_code":"DZ",
    "gn:dem":756,
    "gn:feature_class":"P",
    "gn:feature_code":"PPL",
    "gn:name":"Mechta Makha Mala",
    "gn:population":0,
    "gn:timezone":"Africa/Algiers",
    "iso:country":"DZ",
    "name:und_x_variant":[
        "Mechta Makra Mala",
        "Mechta Makha Mala"
    ],
    "wof:name":"Mechta Makha Mala",
    "wof:placetype":"locality"
},
  "geometry": {"coordinates":[4.02757,35.94968],"type":"Point"}
}