{
  "type": "Feature",
  "properties": {
    "gn:admin1_code":"31.0",
    "gn:asciiname":"Mechtat es Serdouk",
    "gn:country_code":"DZ",
    "gn:dem":532,
    "gn:feature_class":"P",
    "gn:feature_code":"PPL",
    "gn:name":"Mechtat es Serdouk",
    "gn:population":0,
    "gn:timezone":"Africa/Algiers",
    "iso:country":"DZ",
    "wof:name":"Mechtat es Serdouk",
    "wof:placetype":"locality"
},
  "geometry": {"coordinates":[6.61472,36.54194],"type":"Point"}
}