{
  "type": "Feature",
  "properties": {
    "gn:admin1_code":"39.0",
    "gn:asciiname":"Portes de Fer",
    "gn:country_code":"DZ",
    "gn:dem":426,
    "gn:feature_class":"P",
    "gn:feature_code":"PPL",
    "gn:name":"Portes de Fer",
    "gn:population":0,
    "gn:timezone":"Africa/Algiers",
    "iso:country":"DZ",
    "wof:name":"Portes de Fer",
    "wof:placetype":"locality"
},
  "geometry": {"coordinates":[4.37464,36.21119],"type":"Point"}
}