{
  "type": "Feature",
  "properties": {
    "gn:admin1_code":"14.0",
    "gn:asciiname":"Feldene",
    "gn:country_code":"DZ",
    "gn:dem":669,
    "gn:feature_class":"P",
    "gn:feature_code":"PPL",
    "gn:name":"Feldene",
    "gn:population":0,
    "gn:timezone":"Africa/Algiers",
    "iso:country":"DZ",
    "name:und_x_variant":[
        "Felden",
        "Feldene"
    ],
    "wof:name":"Feldene",
    "wof:placetype":"locality"
},
  "geometry": {"coordinates":[4.52761,36.49799],"type":"Point"}
}