{
  "type": "Feature",
  "properties": {
    "gn:admin1_code":"14.0",
    "gn:asciiname":"Ait Abbas",
    "gn:country_code":"DZ",
    "gn:dem":479,
    "gn:feature_class":"P",
    "gn:feature_code":"PPL",
    "gn:name":"A\u00eft Abbas",
    "gn:population":0,
    "gn:timezone":"Africa/Algiers",
    "iso:country":"DZ",
    "name:ara_x_preferred":[
        "\u0622\u064a\u062a \u0639\u0628\u0627\u0633"
    ],
    "name:cat_x_preferred":[
        "Ait Abbas"
    ],
    "name:fas_x_preferred":[
        "\u0622\u06cc\u062a \u0639\u0628\u0627\u0633"
    ],
    "name:ita_x_preferred":[
        "Ait Abbas"
    ],
    "wof:name":"Ait Abbas",
    "wof:placetype":"locality"
},
  "geometry": {"coordinates":[4.2108,36.54001],"type":"Point"}
}