{
  "type": "Feature",
  "properties": {
    "gn:admin1_code":"35.0",
    "gn:asciiname":"Beni Nasseur",
    "gn:country_code":"DZ",
    "gn:dem":834,
    "gn:feature_class":"P",
    "gn:feature_code":"PPLL",
    "gn:name":"Beni Nasseur",
    "gn:population":0,
    "gn:timezone":"Africa/Algiers",
    "iso:country":"DZ",
    "wof:name":"Beni Nasseur",
    "wof:placetype":"locality"
},
  "geometry": {"coordinates":[1.8565,36.40964],"type":"Point"}
}