{
  "type": "Feature",
  "properties": {
    "gn:admin1_code":"39.0",
    "gn:asciiname":"Mechta 'Ain Meriout",
    "gn:country_code":"DZ",
    "gn:dem":964,
    "gn:feature_class":"P",
    "gn:feature_code":"PPL",
    "gn:name":"Mechta \u2019A\u00efn Meriout",
    "gn:population":0,
    "gn:timezone":"Africa/Algiers",
    "iso:country":"DZ",
    "name:und_x_variant":[
        "Mechtat A\u00efne Meriout",
        "Mechta \u2019A\u00efn Meriout"
    ],
    "wof:name":"Mechta 'Ain Meriout",
    "wof:placetype":"locality"
},
  "geometry": {"coordinates":[5.0504,36.17641],"type":"Point"}
}