{
  "type": "Feature",
  "properties": {
    "gn:admin1_code":"31.0",
    "gn:asciiname":"Sedrata",
    "gn:country_code":"DZ",
    "gn:dem":763,
    "gn:feature_class":"P",
    "gn:feature_code":"PPL",
    "gn:name":"Sedrata",
    "gn:population":0,
    "gn:timezone":"Africa/Algiers",
    "iso:country":"DZ",
    "name:und_x_variant":[
        "Douar Sedrata",
        "Sedrata"
    ],
    "wof:name":"Sedrata",
    "wof:placetype":"locality"
},
  "geometry": {"coordinates":[6.90948,36.44267],"type":"Point"}
}