{
  "type": "Feature",
  "properties": {
    "gn:admin1_code":"31.0",
    "gn:asciiname":"Sedrata",
    "gn:country_code":"DZ",
    "gn:dem":763,
    "gn:feature_class":"P",
    "gn:feature_code":"PPL",
    "gn:name":"Sedrata",
    "gn:population":0,
    "gn:timezone":"Africa/Algiers",
    "iso:country":"DZ",
    "name:ara_x_preferred":[
        "\u0633\u062f\u0631\u0627\u062a\u0629"
    ],
    "name:azb_x_preferred":[
        "\u0633\u062f\u0631\u0627\u062a\u0647"
    ],
    "name:ceb_x_preferred":[
        "Sedrata"
    ],
    "name:epo_x_preferred":[
        "Sedrata"
    ],
    "name:fas_x_preferred":[
        "\u0633\u062f\u0631\u0627\u062a\u0647"
    ],
    "name:fin_x_preferred":[
        "Sedrata"
    ],
    "name:fra_x_preferred":[
        "Sedrata"
    ],
    "name:ita_x_preferred":[
        "Sedrata"
    ],
    "name:kab_x_preferred":[
        "Isedraten"
    ],
    "name:msa_x_preferred":[
        "Sedrata"
    ],
    "name:por_x_preferred":[
        "Sedrata"
    ],
    "name:ron_x_preferred":[
        "Sedrata"
    ],
    "name:spa_x_preferred":[
        "Sedrata"
    ],
    "name:swe_x_preferred":[
        "Sedrata"
    ],
    "name:und_x_variant":[
        "Douar Sedrata"
    ],
    "name:vie_x_preferred":[
        "Sedrata"
    ],
    "wof:name":"Sedrata",
    "wof:placetype":"locality"
},
  "geometry": {"coordinates":[6.90948,36.44267],"type":"Point"}
}