{
  "type": "Feature",
  "properties": {
    "gn:admin1_code":"31.0",
    "gn:asciiname":"Bekkouche Lakhdar",
    "gn:country_code":"DZ",
    "gn:dem":75,
    "gn:feature_class":"P",
    "gn:feature_code":"PPL",
    "gn:name":"Bekkouche Lakhdar",
    "gn:population":0,
    "gn:timezone":"Africa/Algiers",
    "iso:country":"DZ",
    "name:und_x_variant":[
        "Gastu",
        "Zit Emba",
        "Bekkouche La\u00efd",
        "Bekkouche Lakhdar"
    ],
    "wof:name":"Bekkouche Lakhdar",
    "wof:placetype":"locality"
},
  "geometry": {"coordinates":[7.30667,36.69861],"type":"Point"}
}