{
  "type": "Feature",
  "properties": {
    "gn:admin1_code":"31.0",
    "gn:asciiname":"Bekkouche Lakhdar",
    "gn:country_code":"DZ",
    "gn:dem":75,
    "gn:feature_class":"P",
    "gn:feature_code":"PPL",
    "gn:name":"Bekkouche Lakhdar",
    "gn:population":0,
    "gn:timezone":"Africa/Algiers",
    "iso:country":"DZ",
    "name:ara_x_preferred":[
        "\u0628\u0643\u0648\u0634 \u0644\u062e\u0636\u0631"
    ],
    "name:azb_x_preferred":[
        "\u0628\u06a9\u0648\u0634 \u0644\u062e\u0636\u0631"
    ],
    "name:fas_x_preferred":[
        "\u0628\u06a9\u0648\u0634 \u0644\u062e\u0636\u0631"
    ],
    "name:fra_x_preferred":[
        "Bekkouche Lakhdar"
    ],
    "name:ita_x_preferred":[
        "Bekkouche Lakhdar"
    ],
    "name:kab_x_preferred":[
        "Bekkuc Lex\u1e0der"
    ],
    "name:msa_x_preferred":[
        "Bekkouche Lakhdar"
    ],
    "name:por_x_preferred":[
        "Bekkouche Lakhdar"
    ],
    "name:ron_x_preferred":[
        "Bekkouche Lakhdar"
    ],
    "name:spa_x_preferred":[
        "Bekkouche Lakhdar"
    ],
    "name:und_x_variant":[
        "Gastu",
        "Zit Emba",
        "Bekkouche La\u00efd"
    ],
    "name:vie_x_preferred":[
        "Bekkouche Lakhdar"
    ],
    "name:zho_x_preferred":[
        "\u62dc\u5eab\u4ec0\u840a\u5fb7"
    ],
    "wof:name":"Bekkouche Lakhdar",
    "wof:placetype":"locality"
},
  "geometry": {"coordinates":[7.30667,36.69861],"type":"Point"}
}