{
  "type": "Feature",
  "properties": {
    "iso:country":"DZ",
    "name:ara_x_preferred":[
        "\u0627\u0644\u0631\u0648\u064a\u0628\u0629"
    ],
    "name:ara_x_variant":[
        "\u0628\u0644\u062f\u064a\u0629 \u0627\u0644\u0631\u0648\u064a\u0628\u0629"
    ],
    "name:arz_x_preferred":[
        "\u0627\u0644\u0631\u0648\u064a\u0628\u0647"
    ],
    "name:azb_x_preferred":[
        "\u0631\u0648\u06cc\u0628\u0647"
    ],
    "name:cat_x_preferred":[
        "Rou\u00efba"
    ],
    "name:ceb_x_preferred":[
        "Rouiba"
    ],
    "name:ces_x_preferred":[
        "Rou\u00efba"
    ],
    "name:eng_x_preferred":[
        "Rou\u00efba"
    ],
    "name:eng_x_variant":[
        "Rouiba"
    ],
    "name:fas_x_preferred":[
        "\u0631\u0648\u06cc\u0628\u0647"
    ],
    "name:fra_x_preferred":[
        "Rou\u00efba"
    ],
    "name:ita_x_preferred":[
        "Rou\u00efba"
    ],
    "name:jpn_x_preferred":[
        "\u30eb\u30a4\u30d0"
    ],
    "name:kab_x_preferred":[
        "Rrwiba"
    ],
    "name:msa_x_preferred":[
        "Rouiba"
    ],
    "name:nan_x_preferred":[
        "Rou\u00efba"
    ],
    "name:nld_x_preferred":[
        "Rou\u00efba"
    ],
    "name:pol_x_preferred":[
        "Ar-Ruwajba"
    ],
    "name:por_x_preferred":[
        "Rou\u00efba"
    ],
    "name:ron_x_preferred":[
        "Rou\u00efba"
    ],
    "name:ron_x_variant":[
        "Rouiba"
    ],
    "name:spa_x_preferred":[
        "Rou\u00efba"
    ],
    "name:swe_x_preferred":[
        "Rouiba"
    ],
    "name:tur_x_preferred":[
        "Ruveybe"
    ],
    "name:ukr_x_preferred":[
        "\u0420\u0443\u0457\u0431\u0430"
    ],
    "name:urd_x_preferred":[
        "\u0631\u0648\u0628\u06cc\u06c1"
    ],
    "name:vie_x_preferred":[
        "Rouiba"
    ],
    "qs:gn_country":"DZ",
    "qs:gn_fcode":"PPL",
    "qs:gn_pop":20742,
    "qs:name":"Rouiba",
    "qs:name_adm0":"\u0627\u0644\u062c\u0632\u0627\u0626\u0631",
    "qs:name_adm1":"Boumerdes",
    "qs:photos":0,
    "qs:photos_1k":0,
    "qs:photos_9k":0,
    "qs:photos_9r":0,
    "qs:photos_all":0,
    "qs:photos_sr":0,
    "qs:placetype":"Town",
    "qs:pop_sr":"7",
    "qs:woe_adm0":23424740,
    "wd:wordcount":149,
    "wof:name":"Rouiba",
    "wof:placetype":"locality",
    "wof:population":20742
},
  "geometry": {"coordinates":[3.28079,36.73829],"type":"Point"}
}