{
  "type": "Feature",
  "properties": {
    "gn:admin1_code":"40.0",
    "gn:asciiname":"Oulad Taleb",
    "gn:country_code":"DZ",
    "gn:dem":57,
    "gn:feature_class":"P",
    "gn:feature_code":"PPL",
    "gn:name":"Oulad Taleb",
    "gn:population":0,
    "gn:timezone":"Africa/Algiers",
    "iso:country":"DZ",
    "name:und_x_variant":[
        "Ouled Taleb",
        "Oulad Taleb"
    ],
    "wof:name":"Oulad Taleb",
    "wof:placetype":"locality"
},
  "geometry": {"coordinates":[3.83478,36.89934],"type":"Point"}
}