{
  "type": "Feature",
  "properties": {
    "gn:admin1_code":"26.0",
    "gn:asciiname":"Douar el Habib Oued Kadda",
    "gn:country_code":"DZ",
    "gn:dem":417,
    "gn:feature_class":"P",
    "gn:feature_code":"PPLL",
    "gn:name":"Douar el Habib Oued Kadda",
    "gn:population":0,
    "gn:timezone":"Africa/Algiers",
    "iso:country":"DZ",
    "wof:name":"Douar el Habib Oued Kadda",
    "wof:placetype":"locality"
},
  "geometry": {"coordinates":[0.50056,35.50360999999999],"type":"Point"}
}