{
  "type": "Feature",
  "properties": {
    "gn:admin1_code":"48.0",
    "gn:asciiname":"Bordj Ben Zeggouta",
    "gn:country_code":"DZ",
    "gn:dem":788,
    "gn:feature_class":"P",
    "gn:feature_code":"PPL",
    "gn:name":"Bordj Ben Zeggouta",
    "gn:population":0,
    "gn:timezone":"Africa/Algiers",
    "iso:country":"DZ",
    "wof:name":"Bordj Ben Zeggouta",
    "wof:placetype":"locality"
},
  "geometry": {"coordinates":[6.2697,36.30166],"type":"Point"}
}