{
  "type": "Feature",
  "properties": {
    "gn:admin1_code":"7.0",
    "gn:asciiname":"Soltane Ben Allou",
    "gn:country_code":"DZ",
    "gn:dem":199,
    "gn:feature_class":"P",
    "gn:feature_code":"PPLL",
    "gn:name":"Soltane Ben Allou",
    "gn:population":0,
    "gn:timezone":"Africa/Algiers",
    "iso:country":"DZ",
    "wof:name":"Soltane Ben Allou",
    "wof:placetype":"locality"
},
  "geometry": {"coordinates":[0.14766,35.86419],"type":"Point"}
}