{
  "type": "Feature",
  "properties": {
    "gn:admin1_code":"26.0",
    "gn:asciiname":"Mohammadia",
    "gn:cc2":"DZ",
    "gn:country_code":"DZ",
    "gn:dem":43,
    "gn:feature_class":"P",
    "gn:feature_code":"PPL",
    "gn:name":"Mohammadia",
    "gn:population":0,
    "gn:timezone":"Africa/Algiers",
    "iso:country":"DZ",
    "name:und_x_variant":[
        "Perr\u00e9gaux",
        "Mohammadia"
    ],
    "wof:name":"Mohammadia",
    "wof:placetype":"locality"
},
  "geometry": {"coordinates":[0.06861,35.58861],"type":"Point"}
}