{
  "type": "Feature",
  "properties": {
    "gn:admin1_code":"39.0",
    "gn:asciiname":"Mechta Ouled Mehenni",
    "gn:country_code":"DZ",
    "gn:dem":966,
    "gn:feature_class":"P",
    "gn:feature_code":"PPL",
    "gn:name":"Mechta Ouled Mehenni",
    "gn:population":0,
    "gn:timezone":"Africa/Algiers",
    "iso:country":"DZ",
    "name:und_x_variant":[
        "Mechtat Ouled Mehenni",
        "Mechta Ouled Mehenni"
    ],
    "wof:name":"Mechta Ouled Mehenni",
    "wof:placetype":"locality"
},
  "geometry": {"coordinates":[4.80568,36.14309],"type":"Point"}
}