{
  "type": "Feature",
  "properties": {
    "gn:admin1_code":"9.0",
    "gn:asciiname":"Oulad Bou Heia",
    "gn:country_code":"DZ",
    "gn:dem":356,
    "gn:feature_class":"P",
    "gn:feature_code":"PPL",
    "gn:name":"Oulad Bou He\u00efa",
    "gn:population":0,
    "gn:timezone":"Africa/Algiers",
    "iso:country":"DZ",
    "wof:name":"Oulad Bou Heia",
    "wof:placetype":"locality"
},
  "geometry": {"coordinates":[-0.94947,35.65507],"type":"Point"}
}