{
  "type": "Feature",
  "properties": {
    "gn:admin1_code":"26.0",
    "gn:asciiname":"Douar es Sahilia",
    "gn:country_code":"DZ",
    "gn:dem":230,
    "gn:feature_class":"P",
    "gn:feature_code":"PPL",
    "gn:name":"Douar es Sah\u00eelia",
    "gn:population":0,
    "gn:timezone":"Africa/Algiers",
    "iso:country":"DZ",
    "name:und_x_variant":[
        "Sahilia",
        "Douar es Sah\u00eelia"
    ],
    "wof:name":"Douar es Sahilia",
    "wof:placetype":"locality"
},
  "geometry": {"coordinates":[-0.36038,35.49953],"type":"Point"}
}