{
  "type": "Feature",
  "properties": {
    "gn:admin1_code":"1.0",
    "gn:asciiname":"Alger Plage",
    "gn:country_code":"DZ",
    "gn:dem":1,
    "gn:feature_class":"P",
    "gn:feature_code":"PPL",
    "gn:name":"Alger Plage",
    "gn:population":0,
    "gn:timezone":"Africa/Algiers",
    "iso:country":"DZ",
    "wof:name":"Alger Plage",
    "wof:placetype":"locality"
},
  "geometry": {"coordinates":[3.23569,36.78567],"type":"Point"}
}