{
  "type": "Feature",
  "properties": {
    "gn:admin1_code":"22.0",
    "gn:asciiname":"Hassi Bahbah",
    "gn:country_code":"DZ",
    "gn:dem":886,
    "gn:feature_class":"P",
    "gn:feature_code":"PPL",
    "gn:name":"Hassi Bahbah",
    "gn:population":0,
    "gn:timezone":"Africa/Algiers",
    "iso:country":"DZ",
    "name:ara_x_preferred":[
        "\u062d\u0627\u0633\u064a \u0628\u062d\u0628\u062d"
    ],
    "name:azb_x_preferred":[
        "\u062d\u0627\u0633\u06cc \u0628\u062d\u0628\u062d"
    ],
    "name:ceb_x_preferred":[
        "Hassi Bahbah"
    ],
    "name:fas_x_preferred":[
        "\u062d\u0627\u0633\u06cc \u0628\u062d\u0628\u062d"
    ],
    "name:fra_x_preferred":[
        "Hassi Bahbah"
    ],
    "name:ita_x_preferred":[
        "Hassi Bahbah"
    ],
    "name:kab_x_preferred":[
        "\u1e24asi Be\u1e25ba\u1e25"
    ],
    "name:msa_x_preferred":[
        "Hassi Bahbah"
    ],
    "name:pol_x_preferred":[
        "Hasi Bahbah"
    ],
    "name:por_x_preferred":[
        "Hassi Bahbah"
    ],
    "name:ron_x_preferred":[
        "Hassi Bahbah"
    ],
    "name:rus_x_preferred":[
        "\u0425\u0430\u0441\u0441\u0438-\u0411\u0430\u0445\u0431\u0430\u0445"
    ],
    "name:spa_x_preferred":[
        "Hassi Bahbah"
    ],
    "name:swe_x_preferred":[
        "Hassi Bahbah"
    ],
    "name:urd_x_preferred":[
        "\u062d\u0627\u0633\u06cc \u0628\u062d\u0628\u062d"
    ],
    "name:vie_x_preferred":[
        "Hassi Bahbah"
    ],
    "wof:name":"Hassi Bahbah",
    "wof:placetype":"locality"
},
  "geometry": {"coordinates":[3.0299,35.07109000000001],"type":"Point"}
}