{
  "type": "Feature",
  "properties": {
    "gn:admin1_code":"22.0",
    "gn:asciiname":"Hassi Bahbah",
    "gn:country_code":"DZ",
    "gn:dem":886,
    "gn:feature_class":"P",
    "gn:feature_code":"PPL",
    "gn:name":"Hassi Bahbah",
    "gn:population":0,
    "gn:timezone":"Africa/Algiers",
    "iso:country":"DZ",
    "wof:name":"Hassi Bahbah",
    "wof:placetype":"locality"
},
  "geometry": {"coordinates":[3.0299,35.07109000000001],"type":"Point"}
}