{
  "type": "Feature",
  "properties": {
    "gn:admin1_code":"34.0",
    "gn:asciiname":"Noum en Nass",
    "gn:country_code":"DZ",
    "gn:dem":258,
    "gn:feature_class":"P",
    "gn:feature_code":"PPL",
    "gn:name":"Noum en Nass",
    "gn:population":0,
    "gn:timezone":"Africa/Algiers",
    "iso:country":"DZ",
    "name:und_x_variant":[
        "Noum en Nas",
        "Noum en Nass"
    ],
    "wof:name":"Noum en Nass",
    "wof:placetype":"locality"
},
  "geometry": {"coordinates":[-0.20669,27.64403],"type":"Point"}
}