{
  "type": "Feature",
  "properties": {
    "gn:admin1_code":"26.0",
    "gn:asciiname":"Matemore",
    "gn:country_code":"DZ",
    "gn:dem":476,
    "gn:feature_class":"P",
    "gn:feature_code":"PPL",
    "gn:name":"Matemore",
    "gn:population":0,
    "gn:timezone":"Africa/Algiers",
    "iso:country":"DZ",
    "name:und_x_variant":[
        "Matmore",
        "Matemore"
    ],
    "wof:name":"Matemore",
    "wof:placetype":"locality"
},
  "geometry": {"coordinates":[0.21269,35.32539000000001],"type":"Point"}
}