{
  "type": "Feature",
  "properties": {
    "gn:admin1_code":"14.0",
    "gn:asciiname":"Ait Ahmed",
    "gn:country_code":"DZ",
    "gn:dem":718,
    "gn:feature_class":"P",
    "gn:feature_code":"PPL",
    "gn:name":"A\u00eft Ahmed",
    "gn:population":0,
    "gn:timezone":"Africa/Algiers",
    "iso:country":"DZ",
    "wof:name":"Ait Ahmed",
    "wof:placetype":"locality"
},
  "geometry": {"coordinates":[4.5237,36.79679],"type":"Point"}
}