{
  "type": "Feature",
  "properties": {
    "gn:admin1_code":"3.0",
    "gn:asciiname":"Ouled Amar",
    "gn:country_code":"DZ",
    "gn:dem":431,
    "gn:feature_class":"P",
    "gn:feature_code":"PPL",
    "gn:name":"Ouled Amar",
    "gn:population":0,
    "gn:timezone":"Africa/Algiers",
    "iso:country":"DZ",
    "name:und_x_variant":[
        "Ouled Ahmar",
        "Ouled Amar"
    ],
    "wof:name":"Ouled Amar",
    "wof:placetype":"locality"
},
  "geometry": {"coordinates":[5.14101,35.45407],"type":"Point"}
}