{
  "type": "Feature",
  "properties": {
    "gn:admin1_code":"19.0",
    "gn:asciiname":"Amentane",
    "gn:country_code":"DZ",
    "gn:dem":704,
    "gn:feature_class":"P",
    "gn:feature_code":"PPL",
    "gn:name":"Amentane",
    "gn:population":0,
    "gn:timezone":"Africa/Algiers",
    "iso:country":"DZ",
    "name:fra_x_preferred":[
        "Amentane"
    ],
    "name:ita_x_preferred":[
        "Amentane"
    ],
    "name:msa_x_preferred":[
        "Amantan"
    ],
    "name:und_x_variant":[
        "Amenntane",
        "Amentane"
    ],
    "wof:name":"Amentane",
    "wof:placetype":"locality"
},
  "geometry": {"coordinates":[5.94004,35.11794],"type":"Point"}
}