{
  "type": "Feature",
  "properties": {
    "gn:admin1_code":"14.0",
    "gn:asciiname":"Issoumatene",
    "gn:country_code":"DZ",
    "gn:dem":92,
    "gn:feature_class":"P",
    "gn:feature_code":"PPL",
    "gn:name":"Issoumatene",
    "gn:population":0,
    "gn:timezone":"Africa/Algiers",
    "iso:country":"DZ",
    "wof:name":"Issoumatene",
    "wof:placetype":"locality"
},
  "geometry": {"coordinates":[4.34423,36.86537],"type":"Point"}
}