{
  "type": "Feature",
  "properties": {
    "gn:admin1_code":"27.0",
    "gn:asciiname":"Mechtat ed Dir",
    "gn:country_code":"DZ",
    "gn:dem":777,
    "gn:feature_class":"P",
    "gn:feature_code":"PPL",
    "gn:name":"Mechtat ed Dir",
    "gn:population":0,
    "gn:timezone":"Africa/Algiers",
    "iso:country":"DZ",
    "wof:name":"Mechtat ed Dir",
    "wof:placetype":"locality"
},
  "geometry": {"coordinates":[4.85969,35.75909],"type":"Point"}
}