{
  "type": "Feature",
  "properties": {
    "gn:admin1_code":"29.0",
    "gn:asciiname":"Mechta Bazina",
    "gn:country_code":"DZ",
    "gn:dem":877,
    "gn:feature_class":"P",
    "gn:feature_code":"PPL",
    "gn:name":"Mechta Bazina",
    "gn:population":0,
    "gn:timezone":"Africa/Algiers",
    "iso:country":"DZ",
    "name:und_x_variant":[
        "Mechtat Bazina",
        "Mechta Bazina"
    ],
    "wof:name":"Mechta Bazina",
    "wof:placetype":"locality"
},
  "geometry": {"coordinates":[7.63772,35.58996],"type":"Point"}
}