{
  "type": "Feature",
  "properties": {
    "gn:admin1_code":"26.0",
    "gn:asciiname":"Douar Mgadiche",
    "gn:country_code":"DZ",
    "gn:dem":501,
    "gn:feature_class":"P",
    "gn:feature_code":"PPL",
    "gn:name":"Douar Mgadiche",
    "gn:population":0,
    "gn:timezone":"Africa/Algiers",
    "iso:country":"DZ",
    "wof:name":"Douar Mgadiche",
    "wof:placetype":"locality"
},
  "geometry": {"coordinates":[0.38706,35.42079000000001],"type":"Point"}
}