{
  "type": "Feature",
  "properties": {
    "gn:admin1_code":"27.0",
    "gn:asciiname":"El Biada",
    "gn:country_code":"DZ",
    "gn:dem":428,
    "gn:feature_class":"P",
    "gn:feature_code":"PPL",
    "gn:name":"El Biada",
    "gn:population":0,
    "gn:timezone":"Africa/Algiers",
    "iso:country":"DZ",
    "name:und_x_variant":[
        "Douar el Biada",
        "El Biada"
    ],
    "wof:name":"El Biada",
    "wof:placetype":"locality"
},
  "geometry": {"coordinates":[4.47236,35.62708],"type":"Point"}
}