{
  "type": "Feature",
  "properties": {
    "gn:admin1_code":"23.0",
    "gn:asciiname":"Bouchegout",
    "gn:country_code":"DZ",
    "gn:dem":146,
    "gn:feature_class":"P",
    "gn:feature_code":"PPL",
    "gn:name":"Bouchegout",
    "gn:population":0,
    "gn:timezone":"Africa/Algiers",
    "iso:country":"DZ",
    "wof:name":"Bouchegout",
    "wof:placetype":"locality"
},
  "geometry": {"coordinates":[7.73333,36.47222],"type":"Point"}
}